Workbook

Sheet Projects_OLD
A1: Timestamp | B1: კონტრაგენტი : | C1: პროექტის დასახელება : | D1: შემოსავლის კოდი : | E1: თარიღი : | F1: თანხა : | G1: ვალუტა : | H1: პროექტის სტატუსი : | I1: თანამშრომელი : | J1: ORIS 1630 : | K1: კონტრაქტის # - | L1: პროექტი_GUID/ | M1: პროექტი// | N1: შემოსავლის კოდი_GUID | O1: კონტრაგენტი_GUID | P1: თანამშრომელი_GUID | Q1: [Collateral] | S1: Name1
A2: 44342.728 | B2: ოლიმპ ჯორჯია (ს.კ. 405231011) - შპს | C2: Biota Park | D2: 1.1.1. (+) შემოსავალი ლიფტების რეალიზაციიდან | E2: 43767 | F2: 350000 | G2: USD | H2: მიმდინარე | J2: 1 6 30 1270 | K2: 405231011/43767/1.1.1./1 | L2: 26A47FBE-6B71-4D89-B27B-4629DEEA1D34 | M2: Biota Park | 1.1.1. (+) შემოსავალი ლიფტების რეალიზაციიდან | ოლიმპ ჯორჯია (ს.კ. 405231011) - შპს | N2: B59170EC-16CC-499A-9FF7-0428DCB8F727 | O2: 6DECD64D-60DA-49AE-A9B3-49D7E02F2D62 | Q2: gio.nikabadze@gmail.com | S2: {=if(A2:A465<>"",left(M2:M465,iferror(search("(+)",M2:M465),search("(-)",M2:M465))-2)&" "&MID(M2:M465,SEARCH("|",M2:M465),1)&" "&left(B2:B465,SEARCH("(ს.კ.",B2:B465)-1)&" "&MID(M2:M465,SEARCH("|",M2:M465),1)&" "&TEXT(F2:F465,"#,##0.00")&" "&G2:G465&" "&MID(M2:M465,SEARCH("|",M2:M465),1)&" "&TEXT(E2:E465,"DD.MM.YYYY"),"")} -> Biota Park | 1.1.1. | ოლიმპ ჯორჯია | 350,000.00 USD | 29.10.2019
A3: 44342.729 | B3: ინდეკო (ს.კ. 202376133) - შპს | C3: Chakhrukhadze | D3: 1.1.1. (+) შემოსავალი ლიფტების რეალიზაციიდან | E3: 43762 | F3: 23100 | G3: USD | H3: მიმდინარე | J3: 1 6 30 541 4 | K3: 202376133/43762/1.1.1./1 | L3: BFCA9047-3C75-4EEB-9FE8-82617FFD3965 | M3: Chakhrukhadze | 1.1.1. (+) შემოსავალი ლიფტების რეალიზაციიდან | ინდეკო (ს.კ. 202376133) - შპს | N3: B59170EC-16CC-499A-9FF7-0428DCB8F727 | O3: 8E8E99BE-75FC-49EC-9D89-960E30E7CB06 | Q3: gio.nikabadze@gmail.com | S3: Chakhrukhadze | 1.1.1. | ინდეკო | 23,100.00 USD | 24.10.2019
A4: 44342.729 | B4: ბეტა ჯგუფი (ს.კ. 405171996) - შპს | C4: Med. University | D4: 1.1.1. (+) შემოსავალი ლიფტების რეალიზაციიდან | E4: 43767 | F4: 42500 | G4: USD | H4: მიმდინარე | K4: 405171996/43767/1.1.1./1 | L4: 00664103-FB2D-4EA7-A2B7-28064D745999 | M4: Med. University | 1.1.1. (+) შემოსავალი ლიფტების რეალიზაციიდან | ბეტა ჯგუფი (ს.კ. 405171996) - შპს | N4: B59170EC-16CC-499A-9FF7-0428DCB8F727 | O4: 3029E0C5-9337-4596-87DB-0A677D44A180 | Q4: gio.nikabadze@gmail.com | S4: Med. University | 1.1.1. | ბეტა ჯგუფი | 42,500.00 USD | 29.10.2019
A5: 44342.729 | B5: გიოკაპიტალი (ს.კ. 406155841) - შპს | C5: Varketili | D5: 1.1.1. (+) შემოსავალი ლიფტების რეალიზაციიდან | E5: 43724 | F5: 48500 | G5: USD | H5: მიმდინარე | J5: 1 6 30 1252 | K5: 406155841/43724/1.1.1./1 | L5: 80851DA9-84C4-4C2C-95FE-D6A0282F7B22 | M5: Varketili | 1.1.1. (+) შემოსავალი ლიფტების რეალიზაციიდან | გიოკაპიტალი (ს.კ. 406155841) - შპს | N5: B59170EC-16CC-499A-9FF7-0428DCB8F727 | O5: 97BEEA92-7829-4A09-8B1C-D0FE871340D4 | Q5: gio.nikabadze@gmail.com | S5: Varketili | 1.1.1. | გიოკაპიტალი | 48,500.00 USD | 16.09.2019
A6: 44342.729 | B6: რედ-კო (ს.კ. 405148415) - შპს | C6: Gudauri Redco Parking | D6: 1.1.1. (+) შემოსავალი ლიფტების რეალიზაციიდან | E6: 43734 | F6: 28000 | G6: USD | H6: მიმდინარე | K6: 405148415/43734/1.1.1./1 | L6: 2E1DDD27-332A-4E4A-B571-52B4DE3B8E04 | M6: Gudauri Redco Parking | 1.1.1. (+) შემოსავალი ლიფტების რეალიზაციიდან | რედ-კო (ს.კ. 405148415) - შპს | N6: B59170EC-16CC-499A-9FF7-0428DCB8F727 | O6: DA9D440B-CACD-4076-8B91-BFFCA46814B6 | Q6: gio.nikabadze@gmail.com | S6: Gudauri Redco Parking | 1.1.1. | რედ-კო | 28,000.00 USD | 26.09.2019
A7: 44342.729 | B7: მაია კვიჭიძე (ს.კ. 01008011243) - ფიზ. პირი | C7: Ortachala | D7: 1.1.1. (+) შემოსავალი ლიფტების რეალიზაციიდან | E7: 43672 | F7: 24000 | G7: USD | H7: მიმდინარე | K7: 01008011243/43672/1.1.1./1 | L7: 83FEC832-A4EA-4380-B5E9-85BEEECE8FA4 | M7: Ortachala | 1.1.1. (+) შემოსავალი ლიფტების რეალიზაციიდან | მაია კვიჭიძე (ს.კ. 01008011243) - ფიზ. პირი | N7: B59170EC-16CC-499A-9FF7-0428DCB8F727 | O7: D5136DB7-C17A-4DDB-9797-D1B10612D28C | Q7: gio.nikabadze@gmail.com | S7: Ortachala | 1.1.1. | მაია კვიჭიძე | 24,000.00 USD | 26.07.2019
A8: 44342.729 | B8: მოდუსი (ს.კ. 245565669) - შპს | C8: Modus Agladze | D8: 1.1.1. (+) შემოსავალი ლიფტების რეალიზაციიდან | E8: 43633 | F8: 57000 | G8: USD | H8: მიმდინარე | K8: 245565669/43633/1.1.1./1 | L8: ABDEF9CC-F0E1-4950-B30C-D46A8A8A912C | M8: Modus Agladze | 1.1.1. (+) შემოსავალი ლიფტების რეალიზაციიდან | მოდუსი (ს.კ. 245565669) - შპს | N8: B59170EC-16CC-499A-9FF7-0428DCB8F727 | O8: 9729C88B-F3C5-441A-8782-0656302A37F2 | Q8: gio.nikabadze@gmail.com | S8: Modus Agladze | 1.1.1. | მოდუსი | 57,000.00 USD | 17.06.2019
A9: 44342.729 | B9: ჰომბეი (ს.კ. 405255815) - შპს | C9: Crystal Bakuriani | D9: 1.1.1. (+) შემოსავალი ლიფტების რეალიზაციიდან | E9: 43608 | F9: 104500 | G9: USD | H9: მიმდინარე | K9: 405255815/43608/1.1.1./1 | L9: 230FCB1B-1310-4C49-9D2C-9CD5F9A792A3 | M9: Crystal Bakuriani | 1.1.1. (+) შემოსავალი ლიფტების რეალიზაციიდან | ჰომბეი (ს.კ. 405255815) - შპს | N9: B59170EC-16CC-499A-9FF7-0428DCB8F727 | O9: AAFC235A-2BBF-4CEC-A2AE-F1AEBABC12E4 | Q9: gio.nikabadze@gmail.com | S9: Crystal Bakuriani | 1.1.1. | ჰომბეი | 104,500.00 USD | 23.05.2019
A10: 44342.729 | B10: ანა აბუსერიძე (ს.კ. 61001051501) - ფიზ. პირი | C10: Abuseridze - Batumi | D10: 1.1.1. (+) შემოსავალი ლიფტების რეალიზაციიდან | E10: 43622 | F10: 31000 | G10: USD | H10: მიმდინარე | J10: 1 6 30 1179 | K10: 61001051501/43622/1.1.1./1 | L10: 4E89F135-A0AD-4622-97BD-7B68EF6062F8 | M10: Abuseridze - Batumi | 1.1.1. (+) შემოსავალი ლიფტების რეალიზაციიდან | ანა აბუსერიძე (ს.კ. 61001051501) - ფიზ. პირი | N10: B59170EC-16CC-499A-9FF7-0428DCB8F727 | O10: 15F35EBB-5A28-4C1B-B7CC-45FF3F31D4D6 | Q10: gio.nikabadze@gmail.com | S10: Abuseridze - Batumi | 1.1.1. | ანა აბუსერიძე | 31,000.00 USD | 06.06.2019
A11: 44342.729 | B11: იუნიქს ქონსთრაქშენ კომპანი (ს.კ. 405133822) - შპს | C11: UNIX Marselle | D11: 1.1.1. (+) შემოსავალი ლიფტების რეალიზაციიდან | E11: 43607 | F11: 340000 | G11: USD | H11: მიმდინარე | K11: 405133822/43607/1.1.1./1 | L11: CFFC1C06-B78B-45A0-8A02-37A23706EAFC | M11: UNIX Marselle | 1.1.1. (+) შემოსავალი ლიფტების რეალიზაციიდან | იუნიქს ქონსთრაქშენ კომპანი (ს.კ. 405133822) - შპს | N11: B59170EC-16CC-499A-9FF7-0428DCB8F727 | O11: B4968862-3843-414D-9E73-1A7611618B41 | Q11: gio.nikabadze@gmail.com | S11: UNIX Marselle | 1.1.1. | იუნიქს ქონსთრაქშენ კომპანი | 340,000.00 USD | 22.05.2019
A12: 44342.729 | B12: თბილისი პალასი (ს.კ. 405253381) - შპს | C12: Tbilisi Palace | D12: 1.1.1. (+) შემოსავალი ლიფტების რეალიზაციიდან | E12: 43460 | F12: 160000 | G12: USD | H12: მიმდინარე | K12: 405253381/43460/1.1.1./1 | L12: 125722B7-4DB0-4817-B1A4-DBA0B1B893D4 | M12: Tbilisi Palace | 1.1.1. (+) შემოსავალი ლიფტების რეალიზაციიდან | თბილისი პალასი (ს.კ. 405253381) - შპს | N12: B59170EC-16CC-499A-9FF7-0428DCB8F727 | O12: 3F5B4217-38D4-4FB8-B3F3-E856A10FFF06 | Q12: gio.nikabadze@gmail.com | S12: Tbilisi Palace | 1.1.1. | თბილისი პალასი | 160,000.00 USD | 26.12.2018
A13: 44342.729 | B13: თეგეტა მოტორსი (ს.კ. 202177205) - შპს | C13: Tegeta Batumi | D13: 1.1.1. (+) შემოსავალი ლიფტების რეალიზაციიდან | E13: 43479 | F13: 28650 | G13: USD | H13: მიმდინარე | K13: 202177205/43479/1.1.1./1 | L13: 255604D7-5424-4548-9CAA-ECFF960BB6AE | M13: Tegeta Batumi | 1.1.1. (+) შემოსავალი ლიფტების რეალიზაციიდან | თეგეტა მოტორსი (ს.კ. 202177205) - შპს | N13: B59170EC-16CC-499A-9FF7-0428DCB8F727 | O13: 5A21C207-4868-4EA6-9B48-5D0F743D5535 | Q13: gio.nikabadze@gmail.com | S13: Tegeta Batumi | 1.1.1. | თეგეტა მოტორსი | 28,650.00 USD | 14.01.2019
A14: 44342.729 | B14: Dar Building (ს.კ. 445420875) - შპს | C14: DAR TOWER | D14: 1.1.1. (+) შემოსავალი ლიფტების რეალიზაციიდან | E14: 43363 | F14: 1046340 | G14: USD | H14: მიმდინარე | J14: 1 6 30 853 1 | K14: 445420875/43363/1.1.1./1 | L14: A4EE54E2-C9BC-44F8-8554-44B9037B38D2 | M14: DAR TOWER | 1.1.1. (+) შემოსავალი ლიფტების რეალიზაციიდან | Dar Building (ს.კ. 445420875) - შპს | N14: B59170EC-16CC-499A-9FF7-0428DCB8F727 | O14: 7BF4A039-29BC-44AC-A87D-E8832394B94E | Q14: gio.nikabadze@gmail.com | S14: DAR TOWER | 1.1.1. | Dar Building | 1,046,340.00 USD | 20.09.2018
A15: 44342.729 | B15: ბათბილდინგი (ს.კ. 445509334) - შპს | C15: BAT Tower | D15: 1.1.1. (+) შემოსავალი ლიფტების რეალიზაციიდან | E15: 43461 | F15: 73000 | G15: USD | H15: მიმდინარე | J15: 1 6 30 1039 | K15: 445509334/43461/1.1.1./1 | L15: A7AFCD4C-CA26-464C-8F1B-E9A5240DCB0F | M15: BAT Tower | 1.1.1. (+) შემოსავალი ლიფტების რეალიზაციიდან | ბათბილდინგი (ს.კ. 445509334) - შპს | N15: B59170EC-16CC-499A-9FF7-0428DCB8F727 | O15: DAE7B000-963F-42D9-AA35-8F3F2F8A3716 | Q15: gio.nikabadze@gmail.com | S15: BAT Tower | 1.1.1. | ბათბილდინგი | 73,000.00 USD | 27.12.2018
A16: 44342.729 | B16: რუმი (ს.კ. 445481853) - შპს | C16: Rumi - batumi | D16: 1.1.1. (+) შემოსავალი ლიფტების რეალიზაციიდან | E16: 43816 | F16: 114550 | G16: USD | H16: მიმდინარე | J16: 1 6 30 1335 | K16: 445481853/43816/1.1.1./1 | L16: E95274D6-921C-43D1-B7C4-4F99A71C4005 | M16: Rumi - batumi | 1.1.1. (+) შემოსავალი ლიფტების რეალიზაციიდან | რუმი (ს.კ. 445481853) - შპს | N16: B59170EC-16CC-499A-9FF7-0428DCB8F727 | O16: BFABDF11-34C8-4815-A840-47DD5AAB9F4F | Q16: gio.nikabadze@gmail.com | S16: Rumi - batumi | 1.1.1. | რუმი | 114,550.00 USD | 17.12.2019
A17: 44342.729 | B17: ფალიაშვილის 63 (ს.კ. ICE000034) - ამხანაგობა | C17: Domus Paliashviliს 63 | D17: 1.1.1. (+) შემოსავალი ლიფტების რეალიზაციიდან | E17: 42948 | F17: 97000 | G17: GEL | H17: მიმდინარე | K17: ICE000034/42948/1.1.1./1 | L17: C897938C-00C4-4220-BAF1-CA29F3237D16 | M17: Domus Paliashviliს 63 | 1.1.1. (+) შემოსავალი ლიფტების რეალიზაციიდან | ფალიაშვილის 63 (ს.კ. ICE000034) - ამხანაგობა | N17: B59170EC-16CC-499A-9FF7-0428DCB8F727 | O17: 7F0A41E4-FA68-43E7-A979-126560D14B58 | Q17: gio.nikabadze@gmail.com | S17: Domus Paliashviliს 63 | 1.1.1. | ფალიაშვილის 63 | 97,000.00 GEL | 01.08.2017
A18: 44342.729 | B18: ეკომეტრი (ს.კ. 404464030) - შპს | C18: Gelovani 52 | D18: 1.1.1. (+) შემოსავალი ლიფტების რეალიზაციიდან | E18: 42923 | F18: 161000 | G18: USD | H18: მიმდინარე | K18: 404464030/42923/1.1.1./1 | L18: 196F7BB2-781C-4FF2-BAEE-C30045DA8E1E | M18: Gelovani 52 | 1.1.1. (+) შემოსავალი ლიფტების რეალიზაციიდან | ეკომეტრი (ს.კ. 404464030) - შპს | N18: B59170EC-16CC-499A-9FF7-0428DCB8F727 | O18: B25EF46E-8022-4949-A1EB-E8A1256C7A3B | Q18: gio.nikabadze@gmail.com | S18: Gelovani 52 | 1.1.1. | ეკომეტრი | 161,000.00 USD | 07.07.2017
A19: 44342.729 | B19: ჩემპიონი 2 (ს.კ. 248416432) - შპს | C19: Chempioni | D19: 1.1.1. (+) შემოსავალი ლიფტების რეალიზაციიდან | E19: 42536 | F19: 23924 | G19: USD | H19: მიმდინარე | K19: 248416432/42536/1.1.1./1 | L19: 42197EB0-C73A-4679-8D11-1DD3BAC96135 | M19: Chempioni | 1.1.1. (+) შემოსავალი ლიფტების რეალიზაციიდან | ჩემპიონი 2 (ს.კ. 248416432) - შპს | N19: B59170EC-16CC-499A-9FF7-0428DCB8F727 | O19: 967EE73E-8B77-4A8F-9FD3-AA36FF0ECB17 | Q19: gio.nikabadze@gmail.com | S19: Chempioni | 1.1.1. | ჩემპიონი 2 | 23,924.00 USD | 15.06.2016
A20: 44342.729 | B20: ნიუ თაიმ (ს.კ. 445440577) - შპს | C20: New Time | D20: 1.1.1. (+) შემოსავალი ლიფტების რეალიზაციიდან | E20: 42885 | F20: 150000 | G20: USD | H20: მიმდინარე | K20: 445440577/42885/1.1.1./1 | L20: 7A83BC1F-C807-436E-9390-775B1D423BFD | M20: New Time | 1.1.1. (+) შემოსავალი ლიფტების რეალიზაციიდან | ნიუ თაიმ (ს.კ. 445440577) - შპს | N20: B59170EC-16CC-499A-9FF7-0428DCB8F727 | O20: EEF69DEA-9E1B-41C3-B563-3922DCE0A9BD | Q20: gio.nikabadze@gmail.com | S20: New Time | 1.1.1. | ნიუ თაიმ | 150,000.00 USD | 30.05.2017
A21: 44342.729 | B21: ელტური-2008 (ს.კ. 248434038) - შპს | C21: Green Cape | D21: 1.1.1. (+) შემოსავალი ლიფტების რეალიზაციიდან | E21: 43460 | F21: 70360 | G21: USD | H21: მიმდინარე | K21: 248434038/43460/1.1.1./1 | L21: D9285AF5-11A4-4764-B11B-745E9DAF1D34 | M21: Green Cape | 1.1.1. (+) შემოსავალი ლიფტების რეალიზაციიდან | ელტური-2008 (ს.კ. 248434038) - შპს | N21: B59170EC-16CC-499A-9FF7-0428DCB8F727 | O21: 0A7F5182-3B4F-4292-8569-FC31854BA5B4 | Q21: gio.nikabadze@gmail.com | S21: Green Cape | 1.1.1. | ელტური-2008 | 70,360.00 USD | 26.12.2018
A22: 44342.729 | B22: ინდეკო (ს.კ. 202376133) - შპს | C22: Indeko - shartava 39 | D22: 1.1.1. (+) შემოსავალი ლიფტების რეალიზაციიდან | E22: 43460 | F22: 155520 | G22: USD | H22: მიმდინარე | K22: 202376133/42345/1.1.1./1 | L22: C5E1547A-8529-495B-974D-92544D0F1C66 | M22: Indeko - shartava 39 | 1.1.1. (+) შემოსავალი ლიფტების რეალიზაციიდან | ინდეკო (ს.კ. 202376133) - შპს | N22: B59170EC-16CC-499A-9FF7-0428DCB8F727 | O22: 8E8E99BE-75FC-49EC-9D89-960E30E7CB06 | Q22: gio.nikabadze@gmail.com | S22: Indeko - shartava 39 | 1.1.1. | ინდეკო | 155,520.00 USD | 26.12.2018
A23: 44342.729 | B23: რედ-კო (ს.კ. 405148415) - შპს | C23: Redco 1 | D23: 1.1.1. (+) შემოსავალი ლიფტების რეალიზაციიდან | E23: 43248 | F23: 370000 | G23: USD | H23: მიმდინარე | J23: 1 6 30 917 2 | K23: 405148415/43248/1.1.1./1 | L23: D421D947-C097-4870-8EF1-C7F724377248 | M23: Redco 1 | 1.1.1. (+) შემოსავალი ლიფტების რეალიზაციიდან | რედ-კო (ს.კ. 405148415) - შპს | N23: B59170EC-16CC-499A-9FF7-0428DCB8F727 | O23: DA9D440B-CACD-4076-8B91-BFFCA46814B6 | Q23: gio.nikabadze@gmail.com | S23: Redco 1 | 1.1.1. | რედ-კო | 370,000.00 USD | 28.05.2018
A24: 44342.729 | B24: ბიზნეს ცენტრი დელისი (ს.კ. 204854014) - სს | C24: Delisi | D24: 1.1.1. (+) შემოსავალი ლიფტების რეალიზაციიდან | E24: 42598 | F24: 53454 | G24: USD | H24: მიმდინარე | K24: 204854014/42598/1.1.1./1 | L24: 2496A0E0-1118-49DC-8A82-539003DC1B23 | M24: Delisi | 1.1.1. (+) შემოსავალი ლიფტების რეალიზაციიდან | ბიზნეს ცენტრი დელისი (ს.კ. 204854014) - სს | N24: B59170EC-16CC-499A-9FF7-0428DCB8F727 | O24: 62F6C15C-8FCC-4A60-B37E-8A3DE9D20A48 | Q24: gio.nikabadze@gmail.com | S24: Delisi | 1.1.1. | ბიზნეს ცენტრი დელისი | 53,454.00 USD | 16.08.2016
A25: 44342.729 | B25: შველა (ს.კ. 448396021) - შპს | C25: Shvela | D25: 1.1.1. (+) შემოსავალი ლიფტების რეალიზაციიდან | E25: 42536 | F25: 50206 | G25: USD | H25: მიმდინარე | K25: 448396021/42536/1.1.1./1 | L25: 1C2CAB23-3967-41F9-AC61-62415AE0373C | M25: Shvela | 1.1.1. (+) შემოსავალი ლიფტების რეალიზაციიდან | შველა (ს.კ. 448396021) - შპს | N25: B59170EC-16CC-499A-9FF7-0428DCB8F727 | O25: A5C44F5D-1F9C-4BC1-BD39-C8B2E88BC49A | Q25: gio.nikabadze@gmail.com | S25: Shvela | 1.1.1. | შველა | 50,206.00 USD | 15.06.2016
A26: 44342.729 | B26: ბკ კაპიტალი (ს.კ. 205057123) - შპს | C26: Moxy Zaabruken Hotel 1 | D26: 1.1.1. (+) შემოსავალი ლიფტების რეალიზაციიდან | E26: 42647 | F26: 157608.67 | G26: USD | H26: მიმდინარე | K26: 205057123/42647/1.1.1./1 | L26: 202843CA-C5C3-4057-8040-234B6C369B5E | M26: Moxy Zaabruken Hotel | 1.1.1. (+) შემოსავალი ლიფტების რეალიზაციიდან | ბკ კაპიტალი (ს.კ. 205057123) - შპს | N26: B59170EC-16CC-499A-9FF7-0428DCB8F727 | O26: D57E2878-F57C-4B96-B89E-A8B81F35634A | Q26: gio.nikabadze@gmail.com | S26: Moxy Zaabruken Hotel | 1.1.1. | ბკ კაპიტალი | 157,608.67 USD | 04.10.2016
A27: 44342.729 | B27: ინჟინერთა ჯგუფი (ს.კ. 400101457) - შპს | C27: Tbilisi Gardens | D27: 1.1.1. (+) შემოსავალი ლიფტების რეალიზაციიდან | E27: 42723 | F27: 325000 | G27: USD | H27: მიმდინარე | K27: 400101457/42723/1.1.1./1 | L27: 8C8C52A5-1A7C-485F-9AC8-043862EF3D55 | M27: Tbilisi Gardens | 1.1.1. (+) შემოსავალი ლიფტების რეალიზაციიდან | ინჟინერთა ჯგუფი (ს.კ. 400101457) - შპს | N27: B59170EC-16CC-499A-9FF7-0428DCB8F727 | O27: 2ED6F730-5337-4222-94F9-284E801BCE61 | Q27: gio.nikabadze@gmail.com | S27: Tbilisi Gardens | 1.1.1. | ინჟინერთა ჯგუფი | 325,000.00 USD | 19.12.2016
A28: 44342.729 | B28: მოდუსი (ს.კ. 245565669) - შპს | C28: Modus Kakhety HW | D28: 1.1.1. (+) შემოსავალი ლიფტების რეალიზაციიდან | E28: 42641 | F28: 25000 | G28: USD | H28: მიმდინარე | K28: 245565669/42641/1.1.1./1 | L28: BFD4409A-7F01-4C7C-9F40-73A80C2E63A6 | M28: Modus Kakhety HW | 1.1.1. (+) შემოსავალი ლიფტების რეალიზაციიდან | მოდუსი (ს.კ. 245565669) - შპს | N28: B59170EC-16CC-499A-9FF7-0428DCB8F727 | O28: 9729C88B-F3C5-441A-8782-0656302A37F2 | Q28: gio.nikabadze@gmail.com | S28: Modus Kakhety HW | 1.1.1. | მოდუსი | 25,000.00 USD | 28.09.2016
A29: 44342.729 | B29: სითი დეველოპმენტ (ს.კ. 404481324) - შპს | C29: Kbuleti Str. - Khomeriki | D29: 1.1.1. (+) შემოსავალი ლიფტების რეალიზაციიდან | E29: 42485 | F29: 36577 | G29: USD | H29: მიმდინარე | K29: 404481324/42485/1.1.1./1 | L29: A53105CE-1BDB-4625-B775-A01DA1F6C8AD | M29: Kbuleti Str. - Khomeriki | 1.1.1. (+) შემოსავალი ლიფტების რეალიზაციიდან | სითი დეველოპმენტ (ს.კ. 404481324) - შპს | N29: B59170EC-16CC-499A-9FF7-0428DCB8F727 | O29: 57A60218-744B-4922-BF21-F9C52A01DAF6 | Q29: gio.nikabadze@gmail.com | S29: Kbuleti Str. - Khomeriki | 1.1.1. | სითი დეველოპმენტ | 36,577.00 USD | 25.04.2016
A30: 44342.729 | B30: დომუს დეველოპმენტ (ს.კ. 205210261) - შპს | C30: Domus | D30: 1.1.1. (+) შემოსავალი ლიფტების რეალიზაციიდან | E30: 42355 | F30: 527700 | G30: USD | H30: მიმდინარე | K30: 205210261/42355/1.1.1./1 | L30: F154242F-E028-49D8-B7BE-42EB31281CD5 | M30: Domus | 1.1.1. (+) შემოსავალი ლიფტების რეალიზაციიდან | დომუს დეველოპმენტ (ს.კ. 205210261) - შპს | N30: B59170EC-16CC-499A-9FF7-0428DCB8F727 | O30: A3C5943B-D1C3-4CB2-946C-86BF678B6183 | Q30: gio.nikabadze@gmail.com | S30: Domus | 1.1.1. | დომუს დეველოპმენტ | 527,700.00 USD | 17.12.2015
A31: 44342.729 | B31: ირაკლი კაციტაძე (ს.კ. 01008004604) - ფიზ. პირი | C31: Paliashvili 23 | D31: 1.1.2. (+) შემოსავალი ლიფტების სერვისიდან - გეგმიური | E31: 43831 | F31: 1 | G31: GEL | H31: მიმდინარე | K31: 01008004604/43831/1.1.2./1 | L31: 6D999F5B-2199-4578-A47D-FDC2DF179273 | M31: Paliashvili 23 | 1.1.2. (+) შემოსავალი ლიფტების სერვისიდან - გეგმიური | ირაკლი კაციტაძე (ს.კ. 01008004604) - ფიზ. პირი | N31: 12238130-9D12-4099-A48B-9EB5A085E0F8 | O31: 9AE0C821-91FF-44A4-90E6-F71F98BC044C | Q31: gio.nikabadze@gmail.com | S31: Paliashvili 23 | 1.1.2. | ირაკლი კაციტაძე | 1.00 GEL | 01.01.2020
A32: 44342.729 | B32: ბკ კაპიტალი (ს.კ. 205057123) - შპს | C32: Moxy Zabruken Restaurant | D32: 1.1.1. (+) შემოსავალი ლიფტების რეალიზაციიდან | E32: 43742 | F32: 78804.33 | G32: USD | H32: მიმდინარე | K32: 205057123/43742/1.1.1./1 | L32: 5E543EA8-4A6A-4F8C-9F72-071B61F85EEB | M32: Moxy Zabruken Restaurant | 1.1.1. (+) შემოსავალი ლიფტების რეალიზაციიდან | ბკ კაპიტალი (ს.კ. 205057123) - შპს | N32: B59170EC-16CC-499A-9FF7-0428DCB8F727 | O32: D57E2878-F57C-4B96-B89E-A8B81F35634A | Q32: gio.nikabadze@gmail.com | S32: Moxy Zabruken Restaurant | 1.1.1. | ბკ კაპიტალი | 78,804.33 USD | 04.10.2019
A33: 44342.729 | B33: ორბი ჯგუფი ბათუმი (ს.კ. 445468798) - შპს | C33: TWIN TOWER | D33: 1.1.1. (+) შემოსავალი ლიფტების რეალიზაციიდან | E33: 43059 | F33: 3273908 | G33: USD | H33: მიმდინარე | J33: 1 6 30 773 1 | K33: 445468798/43059/1.1.1./1 | L33: C35D9FF1-3A09-4634-9BFA-87C709266063 | M33: TWIN TOWER | 1.1.1. (+) შემოსავალი ლიფტების რეალიზაციიდან | ორბი ჯგუფი ბათუმი (ს.კ. 445468798) - შპს | N33: B59170EC-16CC-499A-9FF7-0428DCB8F727 | O33: E284E0FD-A2B7-4D93-8E91-006FF0A8A4CE | Q33: gio.nikabadze@gmail.com | S33: TWIN TOWER | 1.1.1. | ორბი ჯგუფი ბათუმი | 3,273,908.00 USD | 20.11.2017
A34: 44342.729 | B34: აი ჯი დეველოფმენტ ჯორჯია (ს.კ. 404851503) - შპს | C34: City Mall | D34: 1.1.1. (+) შემოსავალი ლიფტების რეალიზაციიდან | E34: 43354 | F34: 1194345 | G34: USD | H34: მიმდინარე | J34: 1 6 30 971 | K34: 404851503/43354/1.1.1./1 | L34: EA15EDA6-F906-4932-87BA-DDB8898D4EBC | M34: City Mall | 1.1.1. (+) შემოსავალი ლიფტების რეალიზაციიდან | აი ჯი დეველოფმენტ ჯორჯია (ს.კ. 404851503) - შპს | N34: B59170EC-16CC-499A-9FF7-0428DCB8F727 | O34: DDFBBDF4-5DA2-4BD2-918A-77AAF121BF72 | Q34: gio.nikabadze@gmail.com | S34: City Mall | 1.1.1. | აი ჯი დეველოფმენტ ჯორჯია | 1,194,345.00 USD | 11.09.2018
A35: 44342.729 | B35: რენთინგ ბიენბი (ს.კ. 404564244) - სს | C35: Renting BNB | D35: 1.1.1. (+) შემოსავალი ლიფტების რეალიზაციიდან | E35: 43886 | F35: 26000 | G35: USD | H35: მიმდინარე | J35: 1 6 30 1429 | K35: 404564244/43886/1.1.1./1 | L35: 55F53FA9-CDDE-4FBA-91A1-FEAFA51B29A0 | M35: Renting BNB | 1.1.1. (+) შემოსავალი ლიფტების რეალიზაციიდან | რენთინგ ბიენბი (ს.კ. 404564244) - სს | N35: B59170EC-16CC-499A-9FF7-0428DCB8F727 | O35: 9B349A17-7CE1-4232-98C6-02C565C3642C | Q35: gio.nikabadze@gmail.com | S35: Renting BNB | 1.1.1. | რენთინგ ბიენბი | 26,000.00 USD | 25.02.2020
A36: 44342.729 | B36: ტრანსმშენი (ს.კ. 212274812) - სს | C36: Aeroporti | D36: 1.1.1. (+) შემოსავალი ლიფტების რეალიზაციიდან | E36: 43699 | F36: 20000 | G36: USD | H36: მიმდინარე | K36: 212274812/43699/1.1.1./1 | L36: 44F2F4A0-908E-42D1-B73F-04859CACCB08 | M36: Aeroporti | 1.1.1. (+) შემოსავალი ლიფტების რეალიზაციიდან | ტრანსმშენი (ს.კ. 212274812) - სს | N36: B59170EC-16CC-499A-9FF7-0428DCB8F727 | O36: 9B21D54A-56D8-405D-95E2-A05872C7C1E9 | Q36: gio.nikabadze@gmail.com | S36: Aeroporti | 1.1.1. | ტრანსმშენი | 20,000.00 USD | 22.08.2019
A37: 44342.729 | B37: ბეტა ჯგუფი (ს.კ. 405171996) - შპს | C37: Dividers Med Uni | D37: 1.1.1. (+) შემოსავალი ლიფტების რეალიზაციიდან | E37: 43477 | F37: 11000 | G37: GEL | H37: მიმდინარე | K37: 405171996/43477/1.1.1./1 | L37: 2F958FC8-AC98-416D-BEAC-E4C6006FCCB3 | M37: Dividers Med Uni | 1.1.1. (+) შემოსავალი ლიფტების რეალიზაციიდან | ბეტა ჯგუფი (ს.კ. 405171996) - შპს | N37: B59170EC-16CC-499A-9FF7-0428DCB8F727 | O37: 3029E0C5-9337-4596-87DB-0A677D44A180 | Q37: gio.nikabadze@gmail.com | S37: Dividers Med Uni | 1.1.1. | ბეტა ჯგუფი | 11,000.00 GEL | 12.01.2019
A38: 44342.729 | B38: ლუდსახარში ორი კათხა (ს.კ. 406283338) - შპს | C38: Brewery 1 (300KG) | D38: 1.1.1. (+) შემოსავალი ლიფტების რეალიზაციიდან | E38: 43896 | F38: 10610 | G38: USD | H38: მიმდინარე | K38: 406283338/43896/1.1.1./1 | L38: 4DB7E760-9ECD-4426-BB50-E293E58D2B02 | M38: Brewery 1 (300KG) | 1.1.1. (+) შემოსავალი ლიფტების რეალიზაციიდან | ლუდსახარში ორი კათხა (ს.კ. 406283338) - შპს | N38: B59170EC-16CC-499A-9FF7-0428DCB8F727 | O38: 1C2A10A9-FA2F-437B-8C70-F109D1C009EE | Q38: gio.nikabadze@gmail.com | S38: Brewery 1 (300KG) | 1.1.1. | ლუდსახარში ორი კათხა | 10,610.00 USD | 06.03.2020
A39: 44342.729 | B39: ახალშენი 2016 (ს.კ. 405136758) - შპს | C39: Khiliani | D39: 1.1.1. (+) შემოსავალი ლიფტების რეალიზაციიდან | E39: 43677 | F39: 26400 | G39: USD | H39: მიმდინარე | K39: 405136758/43677/1.1.1./1 | L39: E136ACFA-DBED-49EE-B224-24513754542C | M39: Khiliani | 1.1.1. (+) შემოსავალი ლიფტების რეალიზაციიდან | ახალშენი 2016 (ს.კ. 405136758) - შპს | N39: B59170EC-16CC-499A-9FF7-0428DCB8F727 | O39: 04FB28EA-5501-4B01-BA1D-C2955C0E1213 | Q39: gio.nikabadze@gmail.com | S39: Khiliani | 1.1.1. | ახალშენი 2016 | 26,400.00 USD | 31.07.2019
A40: 44342.729 | B40: ორბი ჯგუფი ბათუმი (ს.კ. 445468798) - შპს | C40: ORBI Office Lift | D40: 1.1.1. (+) შემოსავალი ლიფტების რეალიზაციიდან | E40: 43788 | F40: 30000 | G40: USD | H40: მიმდინარე | K40: 445468798/43788/1.1.1./1 | L40: 5B0BA252-1105-4374-8654-430AE04E8A64 | M40: ORBI Office Lift | 1.1.1. (+) შემოსავალი ლიფტების რეალიზაციიდან | ორბი ჯგუფი ბათუმი (ს.კ. 445468798) - შპს | N40: B59170EC-16CC-499A-9FF7-0428DCB8F727 | O40: E284E0FD-A2B7-4D93-8E91-006FF0A8A4CE | Q40: gio.nikabadze@gmail.com | S40: ORBI Office Lift | 1.1.1. | ორბი ჯგუფი ბათუმი | 30,000.00 USD | 19.11.2019
A41: 44342.729 | B41: ბეტა ჯგუფი (ს.კ. 405171996) - შპს | C41: IBIS Perovi | D41: 1.1.1. (+) შემოსავალი ლიფტების რეალიზაციიდან | E41: 43719 | F41: 83750 | G41: USD | H41: მიმდინარე | J41: 1 6 30 1257 1 | K41: 405171996/43719/1.1.1./1 | L41: 3619FEF3-250F-43C1-93C3-B77FEADECC84 | M41: IBIS Perovi | 1.1.1. (+) შემოსავალი ლიფტების რეალიზაციიდან | ბეტა ჯგუფი (ს.კ. 405171996) - შპს | N41: B59170EC-16CC-499A-9FF7-0428DCB8F727 | O41: 3029E0C5-9337-4596-87DB-0A677D44A180 | Q41: gio.nikabadze@gmail.com | S41: IBIS Perovi | 1.1.1. | ბეტა ჯგუფი | 83,750.00 USD | 11.09.2019
A42: 44342.729 | B42: კანოპუსი (ს.კ. 405229881) - შპს | C42: Sololaki | D42: 1.1.1. (+) შემოსავალი ლიფტების რეალიზაციიდან | E42: 43769 | F42: 24000 | G42: USD | H42: მიმდინარე | K42: 405229881/43769/1.1.1./1 | L42: 0159D5F2-86A6-4D6F-87C4-D563AB9AA860 | M42: Sololaki | 1.1.1. (+) შემოსავალი ლიფტების რეალიზაციიდან | კანოპუსი (ს.კ. 405229881) - შპს | N42: B59170EC-16CC-499A-9FF7-0428DCB8F727 | O42: F43C8D9B-B556-4114-B404-AEEFA8C31B20 | Q42: gio.nikabadze@gmail.com | S42: Sololaki | 1.1.1. | კანოპუსი | 24,000.00 USD | 31.10.2019
A43: 44342.73 | B43: ბეტა ჯგუფი (ს.კ. 405171996) - შპს | C43: IBIS Perov Dumbwaiter | D43: 1.1.1. (+) შემოსავალი ლიფტების რეალიზაციიდან | E43: 43804 | F43: 16300 | G43: USD | H43: მიმდინარე | K43: 405171996/43804/1.1.1./1 | L43: B9668B49-46F2-4E2F-B183-F802279CAA6C | M43: IBIS Perov Dumbwaiter | 1.1.1. (+) შემოსავალი ლიფტების რეალიზაციიდან | ბეტა ჯგუფი (ს.კ. 405171996) - შპს | N43: B59170EC-16CC-499A-9FF7-0428DCB8F727 | O43: 3029E0C5-9337-4596-87DB-0A677D44A180 | Q43: gio.nikabadze@gmail.com | S43: IBIS Perov Dumbwaiter | 1.1.1. | ბეტა ჯგუფი | 16,300.00 USD | 05.12.2019
A44: 44342.73 | B44: სითი რეალ ისთეით (ს.კ. 406067410) - შპს | C44: Kleemann Pekini | D44: 1.1.1. (+) შემოსავალი ლიფტების რეალიზაციიდან | E44: 43228 | F44: 353218 | G44: USD | H44: მიმდინარე | K44: 406067410/43228/1.1.1./1 | L44: 7BF69DE1-9EA3-4EAE-9713-910380F15356 | M44: Kleemann Pekini | 1.1.1. (+) შემოსავალი ლიფტების რეალიზაციიდან | სითი რეალ ისთეით (ს.კ. 406067410) - შპს | N44: B59170EC-16CC-499A-9FF7-0428DCB8F727 | O44: 04B265BA-02B2-4620-87C1-1D9CA09C8962 | Q44: gio.nikabadze@gmail.com | S44: Kleemann Pekini | 1.1.1. | სითი რეალ ისთეით | 353,218.00 USD | 08.05.2018
A45: 44342.73 | B45: ანაგი (ს.კ. 245416401) - შპს | C45: Gudauri Alpic | D45: 1.1.1. (+) შემოსავალი ლიფტების რეალიზაციიდან | E45: 43732 | F45: 81000 | G45: USD | H45: მიმდინარე | K45: 245416401/43732/1.1.1./1 | L45: 56B157A4-78FF-42DD-B032-B267792BBED8 | M45: Gudauri Alpic | 1.1.1. (+) შემოსავალი ლიფტების რეალიზაციიდან | ანაგი (ს.კ. 245416401) - შპს | N45: B59170EC-16CC-499A-9FF7-0428DCB8F727 | O45: 7DDF7E55-92EE-4E47-9E16-F1D4D3FABF60 | Q45: gio.nikabadze@gmail.com | S45: Gudauri Alpic | 1.1.1. | ანაგი | 81,000.00 USD | 24.09.2019
A46: 44342.73 | B46: ანაგი (ს.კ. 245416401) - შპს | C46: Batumi Stadium | D46: 1.1.1. (+) შემოსავალი ლიფტების რეალიზაციიდან | E46: 43589 | F46: 139932.66 | G46: USD | H46: მიმდინარე | K46: 245416401/43589/1.1.1./1 | L46: 8A712C8E-EE09-4385-8E22-3C7E70676923 | M46: Batumi Stadium | 1.1.1. (+) შემოსავალი ლიფტების რეალიზაციიდან | ანაგი (ს.კ. 245416401) - შპს | N46: B59170EC-16CC-499A-9FF7-0428DCB8F727 | O46: 7DDF7E55-92EE-4E47-9E16-F1D4D3FABF60 | Q46: gio.nikabadze@gmail.com | S46: Batumi Stadium | 1.1.1. | ანაგი | 139,932.66 USD | 04.05.2019
A47: 44342.73 | B47: დეველოპერული კომპანია მც კვადრატი (ს.კ. 404474403) - შპს | C47: Gazapkhuli | D47: 1.1.2. (+) შემოსავალი ლიფტების სერვისიდან - გეგმიური | E47: 43831 | F47: 100 | G47: GEL | H47: მიმდინარე | K47: 404474403/43831/1.1.2./1 | L47: F487D937-85D8-43B1-8D4D-27757BC0BE36 | M47: Gazapkhuli | 1.1.2. (+) შემოსავალი ლიფტების სერვისიდან - გეგმიური | დეველოპერული კომპანია მც კვადრატი (ს.კ. 404474403) - შპს | N47: 12238130-9D12-4099-A48B-9EB5A085E0F8 | O47: EC22924D-9707-4BC1-9814-FD45570D704B | Q47: gio.nikabadze@gmail.com | S47: Gazapkhuli | 1.1.2. | დეველოპერული კომპანია მც კვადრატი | 100.00 GEL | 01.01.2020
A48: 44342.73 | B48: თერმორუმი (ს.კ. 405134448) - შპს | C48: Thermoroom | D48: 1.1.1. (+) შემოსავალი ლიფტების რეალიზაციიდან | E48: 43546 | F48: 82900 | G48: USD | H48: მიმდინარე | K48: 405134448/43546/1.1.1./1 | L48: 554B8399-3687-4503-A8C9-12E3BBDE60E9 | M48: Thermoroom | 1.1.1. (+) შემოსავალი ლიფტების რეალიზაციიდან | თერმორუმი (ს.კ. 405134448) - შპს | N48: B59170EC-16CC-499A-9FF7-0428DCB8F727 | O48: A71E107A-D0C2-4155-83C0-22DCD22BD19F | Q48: gio.nikabadze@gmail.com | S48: Thermoroom | 1.1.1. | თერმორუმი | 82,900.00 USD | 22.03.2019
A49: 44342.73 | B49: ტექნოკლიმა (ს.კ. 402009857) - შპს | C49: ENCORE Gudauri | D49: 1.1.1. (+) შემოსავალი ლიფტების რეალიზაციიდან | E49: 43711 | F49: 180540 | G49: EUR | H49: მიმდინარე | K49: 402009857/43711/1.1.1./1 | L49: 165277AE-3A0C-494C-8C92-CC3A68C15375 | M49: ENCORE Gudauri | 1.1.1. (+) შემოსავალი ლიფტების რეალიზაციიდან | ტექნოკლიმა (ს.კ. 402009857) - შპს | N49: B59170EC-16CC-499A-9FF7-0428DCB8F727 | O49: 967D325E-9818-4D9E-8716-3D66A117AF42 | Q49: gio.nikabadze@gmail.com | S49: ENCORE Gudauri | 1.1.1. | ტექნოკლიმა | 180,540.00 EUR | 03.09.2019
A50: 44342.73 | B50: ჯი-ემ-თი სასტუმროები (ს.კ. 203842333) - შპს | C50: MOXY HVAC | D50: 1.2.1. (+) შემოსავალი MEP დანადგარების რეალიზაციიდან | E50: 43124 | F50: 416156.43 | G50: USD | H50: მიმდინარე | K50: 203842333/43124/1.2.1./1 | L50: C78D3D45-B3FB-4533-AE2E-53D8A5FA6C34 | M50: MOXY HVAC | 1.2.1. (+) შემოსავალი MEP დანადგარების რეალიზაციიდან | ჯი-ემ-თი სასტუმროები (ს.კ. 203842333) - შპს | N50: FEA4B88F-633F-4422-B3D6-250792A2DA80 | O50: 9E3145B1-F47E-49C3-BF51-BCB9055ABC20 | Q50: gio.nikabadze@gmail.com | S50: MOXY HVAC | 1.2.1. | ჯი-ემ-თი სასტუმროები | 416,156.43 USD | 24.01.2018
A51: 44342.73 | B51: 1920 (ს.კ. 400247899) - შპს | C51: Paster Hostel | D51: 1.1.1. (+) შემოსავალი ლიფტების რეალიზაციიდან | E51: 43571 | F51: 36200 | G51: USD | H51: მიმდინარე | K51: 400247899/43571/1.1.1./1 | L51: 59251EDF-2EEC-4871-ADAA-D7901FD7C84E | M51: Paster Hostel | 1.1.1. (+) შემოსავალი ლიფტების რეალიზაციიდან | 1920 (ს.კ. 400247899) - შპს | N51: B59170EC-16CC-499A-9FF7-0428DCB8F727 | O51: 30D1E20E-3889-4EAC-883A-6509ABFFA5D7 | Q51: gio.nikabadze@gmail.com | S51: Paster Hostel | 1.1.1. | 1920 | 36,200.00 USD | 16.04.2019
A52: 44342.73 | B52: გოჩა ჩხაიძე (ს.კ. 65002012107) - ფიზ. პირი | C52: Kaklebi | D52: 1.1.1. (+) შემოსავალი ლიფტების რეალიზაციიდან | E52: 43566 | F52: 37760 | G52: USD | H52: მიმდინარე | K52: 65002012107/43566/1.1.1./1 | L52: BCE7664A-F047-41AD-8D93-756E595D21F6 | M52: Kaklebi | 1.1.1. (+) შემოსავალი ლიფტების რეალიზაციიდან | გოჩა ჩხაიძე (ს.კ. 65002012107) - ფიზ. პირი | N52: B59170EC-16CC-499A-9FF7-0428DCB8F727 | O52: B658F42E-3F0A-44A3-B4ED-A7B4C1D8DEAE | Q52: gio.nikabadze@gmail.com | S52: Kaklebi | 1.1.1. | გოჩა ჩხაიძე | 37,760.00 USD | 11.04.2019
A53: 44342.73 | B53: სვირი + (ს.კ. 212916932) - შპს | C53: 156-ე საჯარო სკოლა | D53: 1.1.1. (+) შემოსავალი ლიფტების რეალიზაციიდან | E53: 43861 | F53: 8900 | G53: USD | H53: მიმდინარე | K53: 212916932/43861/1.1.1./1 | L53: 6E5F6760-7CEF-41CD-B373-B0F3B4EABCCA | M53: 156-ე საჯარო სკოლა | 1.1.1. (+) შემოსავალი ლიფტების რეალიზაციიდან | სვირი + (ს.კ. 212916932) - შპს | N53: B59170EC-16CC-499A-9FF7-0428DCB8F727 | O53: E0680301-116E-4D99-93F4-7C694EC80172 | Q53: gio.nikabadze@gmail.com | S53: 156-ე საჯარო სკოლა | 1.1.1. | სვირი + | 8,900.00 USD | 31.01.2020
... A66: 44342.73 | B66: Dar Building (ს.კ. 445420875) - შპს | C66: OFFICE Dar Building | D66: 1.1.1. (+) შემოსავალი ლიფტების რეალიზაციიდან | E66: 44170 | F66: 20800 | G66: USD | H66: მიმდინარე | K66: 445420875/44170/1.1.1./1 | L66: E3FEF6DB-0C48-4832-A5CF-868EF7B591A4 | M66: OFFICE Dar Building | 1.1.1. (+) შემოსავალი ლიფტების რეალიზაციიდან | Dar Building (ს.კ. 445420875) - შპს | N66: B59170EC-16CC-499A-9FF7-0428DCB8F727 | O66: 7BF4A039-29BC-44AC-A87D-E8832394B94E | Q66: gio.nikabadze@gmail.com | S66: OFFICE Dar Building | 1.1.1. | Dar Building | 20,800.00 USD | 05.12.2020
A67: 44342.73 | B67: ანაგი (ს.კ. 245416401) - შპს | C67: Archi Digomi | D67: 1.1.1. (+) შემოსავალი ლიფტების რეალიზაციიდან | E67: 43955 | F67: 107760 | G67: USD | H67: მიმდინარე | J67: 1 6 30 1132 3 | K67: 245416401/43955/1.1.1./1 | L67: A68BEF97-923B-4D3C-8A08-9CF9311578B7 | M67: Archi Digomi | 1.1.1. (+) შემოსავალი ლიფტების რეალიზაციიდან | ანაგი (ს.კ. 245416401) - შპს | N67: B59170EC-16CC-499A-9FF7-0428DCB8F727 | O67: 7DDF7E55-92EE-4E47-9E16-F1D4D3FABF60 | Q67: gio.nikabadze@gmail.com | S67: Archi Digomi | 1.1.1. | ანაგი | 107,760.00 USD | 04.05.2020
A68: 44342.73 | B68: Spanish Retail Georgia (ს.კ. 404404774) - შპს | C68: Zara City Mall | D68: 1.1.2. (+) შემოსავალი ლიფტების სერვისიდან - გეგმიური | E68: 43800 | F68: 1800 | G68: GEL | H68: მიმდინარე | K68: 404404774/43800/1.1.2./1 | L68: 5D93EA98-C1B5-460B-B2FB-C526651B3F64 | M68: Zara City Mall | 1.1.2. (+) შემოსავალი ლიფტების სერვისიდან - გეგმიური | Spanish Retail Georgia (ს.კ. 404404774) - შპს | N68: 12238130-9D12-4099-A48B-9EB5A085E0F8 | O68: 6DF25574-2F03-43D0-AEC4-2CD26A4A0C3A | Q68: gio.nikabadze@gmail.com | S68: Zara City Mall | 1.1.2. | Spanish Retail Georgia | 1,800.00 GEL | 01.12.2019
A69: 44342.73 | B69: გალერია ჰოტელ მენეჯმენტი (ს.კ. 404567508) - შპს | C69: Galleria Hotel | D69: 1.1.2. (+) შემოსავალი ლიფტების სერვისიდან - გეგმიური | E69: 43617 | F69: 300 | G69: USD | H69: მიმდინარე | K69: 404567508/43617/1.1.2./1 | L69: 7A62FB55-149C-4A13-B506-1117D0761263 | M69: Galleria Hotel | 1.1.2. (+) შემოსავალი ლიფტების სერვისიდან - გეგმიური | გალერია ჰოტელ მენეჯმენტი (ს.კ. 404567508) - შპს | N69: 12238130-9D12-4099-A48B-9EB5A085E0F8 | O69: 75C62470-4093-4FB3-8DB7-F700FEC2C222 | Q69: gio.nikabadze@gmail.com | S69: Galleria Hotel | 1.1.2. | გალერია ჰოტელ მენეჯმენტი | 300.00 USD | 01.06.2019
A70: 44342.73 | B70: ერა პალასი (ს.კ. 245619807) - შპს | C70: Era Palace | D70: 1.1.2. (+) შემოსავალი ლიფტების სერვისიდან - გეგმიური | E70: 43586 | F70: 200 | G70: GEL | H70: მიმდინარე | K70: 245619807/43586/1.1.2./1 | L70: 75411B5D-3913-49E0-B5A6-48ED0D4EEBB6 | M70: Era Palace | 1.1.2. (+) შემოსავალი ლიფტების სერვისიდან - გეგმიური | ერა პალასი (ს.კ. 245619807) - შპს | N70: 12238130-9D12-4099-A48B-9EB5A085E0F8 | O70: 71A96223-5CD1-4DA9-9617-A85A565B4669 | Q70: gio.nikabadze@gmail.com | S70: Era Palace | 1.1.2. | ერა პალასი | 200.00 GEL | 01.05.2019
A71: 44342.73 | B71: თბილი სახლი (ს.კ. 204976179) - შპს | C71: Muzeums | D71: 1.1.2. (+) შემოსავალი ლიფტების სერვისიდან - გეგმიური | E71: 43497 | F71: 750 | G71: GEL | H71: მიმდინარე | K71: 204976179/43497/1.1.2./1 | L71: 9D27243C-D81D-4430-90C4-5F8CCBF5809F | M71: Muzeums | 1.1.2. (+) შემოსავალი ლიფტების სერვისიდან - გეგმიური | თბილი სახლი (ს.კ. 204976179) - შპს | N71: 12238130-9D12-4099-A48B-9EB5A085E0F8 | O71: 726D9023-53A2-435E-8A5B-8BCEA9625E08 | Q71: gio.nikabadze@gmail.com | S71: Muzeums | 1.1.2. | თბილი სახლი | 750.00 GEL | 01.02.2019
A72: 44342.73 | B72: იუნიქს ქონსთრაქშენ კომპანი (ს.კ. 405133822) - შპს | C72: UNIX Ipolit Ivanov | D72: 1.1.2. (+) შემოსავალი ლიფტების სერვისიდან - გეგმიური | E72: 43539 | F72: 1500 | G72: GEL | H72: მიმდინარე | J72: 1 6 31 902 | K72: 405133822/43539/1.1.2./1 | L72: 4C7A7F0C-187C-4D2B-857D-A522EE632F24 | M72: UNIX Ipolit Ivanov | 1.1.2. (+) შემოსავალი ლიფტების სერვისიდან - გეგმიური | იუნიქს ქონსთრაქშენ კომპანი (ს.კ. 405133822) - შპს | N72: 12238130-9D12-4099-A48B-9EB5A085E0F8 | O72: B4968862-3843-414D-9E73-1A7611618B41 | Q72: gio.nikabadze@gmail.com | S72: UNIX Ipolit Ivanov | 1.1.2. | იუნიქს ქონსთრაქშენ კომპანი | 1,500.00 GEL | 15.03.2019
A73: 44342.73 | B73: პიქსელ მენეჯმენტი (ს.კ. 404862314) - შპს | C73: PIXEL | D73: 1.1.2. (+) შემოსავალი ლიფტების სერვისიდან - გეგმიური | E73: 43435 | F73: 1645 | G73: USD | H73: მიმდინარე | J73: 1 6 31 1044 | K73: 404862314/43435/1.1.2./1 | L73: 5485535C-2F61-456A-9548-E6F7EE885A7B | M73: PIXEL | 1.1.2. (+) შემოსავალი ლიფტების სერვისიდან - გეგმიური | პიქსელ მენეჯმენტი (ს.კ. 404862314) - შპს | N73: 12238130-9D12-4099-A48B-9EB5A085E0F8 | O73: 42A1D3CC-F7CD-4EC1-A425-6E261EB22EBC | Q73: gio.nikabadze@gmail.com | S73: PIXEL | 1.1.2. | პიქსელ მენეჯმენტი | 1,645.00 USD | 01.12.2018
A74: 44342.73 | B74: დავუდ (ს.კ. 404438417) - სს | C74: Khetagurov Office | D74: 1.1.2. (+) შემოსავალი ლიფტების სერვისიდან - გეგმიური | E74: 43462 | F74: 1000 | G74: GEL | H74: მიმდინარე | K74: 404438417/43462/1.1.2./1 | L74: 1937421D-0C5D-47B3-84E7-F06B2CECE212 | M74: Khetagurov Office | 1.1.2. (+) შემოსავალი ლიფტების სერვისიდან - გეგმიური | დავუდ (ს.კ. 404438417) - სს | N74: 12238130-9D12-4099-A48B-9EB5A085E0F8 | O74: 059C7B48-86B5-4FB3-AF87-564E29C595E9 | Q74: gio.nikabadze@gmail.com | S74: Khetagurov Office | 1.1.2. | დავუდ | 1,000.00 GEL | 28.12.2018
A75: 44342.73 | B75: თბილი სახლი (ს.კ. 204976179) - შპს | C75: Galleria Tbilisi | D75: 1.1.2. (+) შემოსავალი ლიფტების სერვისიდან - გეგმიური | E75: 43862 | F75: 1 | G75: GEL | H75: მიმდინარე | J75: 1 6 31 4 1 | K75: 204976179/43862/1.1.2./1 | L75: 0ABCF801-1738-4393-BF70-87C1FA8C9F0D | M75: Galleria Tbilisi | 1.1.2. (+) შემოსავალი ლიფტების სერვისიდან - გეგმიური | თბილი სახლი (ს.კ. 204976179) - შპს | N75: 12238130-9D12-4099-A48B-9EB5A085E0F8 | O75: 726D9023-53A2-435E-8A5B-8BCEA9625E08 | Q75: gio.nikabadze@gmail.com | S75: Galleria Tbilisi | 1.1.2. | თბილი სახლი | 1.00 GEL | 01.02.2020
A76: 44342.73 | B76: თბილისი ცენტრალი (ს.კ. 205129653) - სს | C76: Tbilisi Central HVAC Service | D76: 1.2.2. (+) შემოსავალი MEP დანადგარების სერვისიდან - გეგმიური | E76: 44075 | F76: 1 | G76: GEL | H76: მიმდინარე | J76: 1 6 31 1371 | K76: 205129653/44075/1.2.2./1 | L76: F2EB27A3-4AED-4096-AF24-4B7A9C4512A7 | M76: Tbilisi Central HVAC Service | 1.2.2. (+) შემოსავალი MEP დანადგარების სერვისიდან - გეგმიური | თბილისი ცენტრალი (ს.კ. 205129653) - სს | N76: 31562B13-85C8-472E-8D02-01D802D635C1 | O76: 3D0B2E19-A7F7-45A1-A329-05C7D5F99C8A | Q76: gio.nikabadze@gmail.com | S76: Tbilisi Central HVAC Service | 1.2.2. | თბილისი ცენტრალი | 1.00 GEL | 01.09.2020
A77: 44342.73 | B77: ნინო კირცხალია (ს.კ. 01031005362) - ფიზ. პირი | C77: Mziuri | D77: 1.1.2. (+) შემოსავალი ლიფტების სერვისიდან - გეგმიური | E77: 43831 | F77: 1 | G77: GEL | H77: მიმდინარე | K77: 01031005362/43831/1.1.2./1 | L77: 7D93AE81-A3AA-4EF2-A79C-0DE309E1B402 | M77: Mziuri | 1.1.2. (+) შემოსავალი ლიფტების სერვისიდან - გეგმიური | ნინო კირცხალია (ს.კ. 01031005362) - ფიზ. პირი | N77: 12238130-9D12-4099-A48B-9EB5A085E0F8 | O77: A5C53B51-103C-4B24-B833-6653108CDE4E | Q77: gio.nikabadze@gmail.com | S77: Mziuri | 1.1.2. | ნინო კირცხალია | 1.00 GEL | 01.01.2020
A78: 44342.73 | B78: ორბი ჯგუფი ბათუმი (ს.კ. 445468798) - შპს | C78: Orbi Other | D78: 1.1.2. (+) შემოსავალი ლიფტების სერვისიდან - გეგმიური | E78: 43831 | F78: 1 | G78: GEL | H78: მიმდინარე | K78: 445468798/43831/1.1.2./1 | L78: DCE1FBA2-AC1D-4481-B551-0D2215188884 | M78: Orbi Other | 1.1.2. (+) შემოსავალი ლიფტების სერვისიდან - გეგმიური | ორბი ჯგუფი ბათუმი (ს.კ. 445468798) - შპს | N78: 12238130-9D12-4099-A48B-9EB5A085E0F8 | O78: E284E0FD-A2B7-4D93-8E91-006FF0A8A4CE | Q78: gio.nikabadze@gmail.com | S78: Orbi Other | 1.1.2. | ორბი ჯგუფი ბათუმი | 1.00 GEL | 01.01.2020
A79: 44342.73 | B79: ნირან პროპერტის დეველოპმენტი (ს.კ. 204564729) - შპს | C79: Bagebi | D79: 1.1.1. (+) შემოსავალი ლიფტების რეალიზაციიდან | E79: 43122 | F79: 132998 | G79: USD | H79: მიმდინარე | K79: 204564729/43122/1.1.1./1 | L79: DA0DFA6D-FB59-42CC-A78F-D211EFD8F169 | M79: Bagebi | 1.1.1. (+) შემოსავალი ლიფტების რეალიზაციიდან | ნირან პროპერტის დეველოპმენტი (ს.კ. 204564729) - შპს | N79: B59170EC-16CC-499A-9FF7-0428DCB8F727 | O79: ADBD14C7-72E2-4703-84A5-B47EC0ACB641 | Q79: gio.nikabadze@gmail.com | S79: Bagebi | 1.1.1. | ნირან პროპერტის დეველოპმენტი | 132,998.00 USD | 22.01.2018
A80: 44342.73 | B80: ეიჩ ენდ ემ ჰენეს ენდ მაურიც ჯორჯია (ს.კ. 405164192) - შპს | C80: H&M | D80: 1.1.2. (+) შემოსავალი ლიფტების სერვისიდან - გეგმიური | E80: 43831 | F80: 1 | G80: GEL | H80: მიმდინარე | K80: 405164192/43831/1.1.2./1 | L80: BF531404-15D2-4F83-B5B6-88709B6ADBF6 | M80: H&M | 1.1.2. (+) შემოსავალი ლიფტების სერვისიდან - გეგმიური | ეიჩ ენდ ემ ჰენეს ენდ მაურიც ჯორჯია (ს.კ. 405164192) - შპს | N80: 12238130-9D12-4099-A48B-9EB5A085E0F8 | O80: 5569F396-B588-4816-B115-348127388797 | Q80: gio.nikabadze@gmail.com | S80: H&M | 1.1.2. | ეიჩ ენდ ემ ჰენეს ენდ მაურიც ჯორჯია | 1.00 GEL | 01.01.2020
A81: 44342.73 | B81: ჯი ემ ემ (ს.კ. 405115174) - შპს | C81: Marshal Gelovanis 52 | D81: 1.1.2. (+) შემოსავალი ლიფტების სერვისიდან - გეგმიური | E81: 43831 | F81: 1 | G81: GEL | H81: მიმდინარე | K81: 405115174/43831/1.1.2./1 | L81: 96631073-7C4A-4C6C-B52A-4318B544C05B | M81: Marshal Gelovanis 52 | 1.1.2. (+) შემოსავალი ლიფტების სერვისიდან - გეგმიური | ჯი ემ ემ (ს.კ. 405115174) - შპს | N81: 12238130-9D12-4099-A48B-9EB5A085E0F8 | O81: E6DBF0EF-BE8A-403C-B757-246FDF95B244 | Q81: gio.nikabadze@gmail.com | S81: Marshal Gelovanis 52 | 1.1.2. | ჯი ემ ემ | 1.00 GEL | 01.01.2020
A82: 44342.73 | B82: ოლსერვისგრუპ (ს.კ. 406233552) - შპს | C82: Marshal Gelovani 52 | D82: 1.1.2. (+) შემოსავალი ლიფტების სერვისიდან - გეგმიური | E82: 43466 | F82: 1200 | G82: GEL | H82: მიმდინარე | K82: 406233552/43466/1.1.2./1 | L82: 46C2E29A-C8A7-4F32-BAC6-1FA5D9731A7D | M82: Marshal Gelovani 52 | 1.1.2. (+) შემოსავალი ლიფტების სერვისიდან - გეგმიური | ოლსერვისგრუპ (ს.კ. 406233552) - შპს | N82: 12238130-9D12-4099-A48B-9EB5A085E0F8 | O82: C08C6F90-5808-41D5-A1CC-2A1CCFAF531B | Q82: gio.nikabadze@gmail.com | S82: Marshal Gelovani 52 | 1.1.2. | ოლსერვისგრუპ | 1,200.00 GEL | 01.01.2019
A83: 44342.731 | B83: ოლსერვისჯგუფი (ს.კ. 406269041) - შპს | C83: Marshal Gelovani 52 | D83: 1.1.2. (+) შემოსავალი ლიფტების სერვისიდან - გეგმიური | E83: 43471 | F83: 10 | G83: GEL | H83: მიმდინარე | K83: 406269041/43471/1.1.2./1 | L83: 4DE1AF55-BD4D-49EA-9CC2-7254972C4832 | M83: Marshal Gelovani 52 | 1.1.2. (+) შემოსავალი ლიფტების სერვისიდან - გეგმიური | ოლსერვისჯგუფი (ს.კ. 406269041) - შპს | N83: 12238130-9D12-4099-A48B-9EB5A085E0F8 | O83: F830C37E-1BED-416F-996D-C3C709C5F339 | Q83: gio.nikabadze@gmail.com | S83: Marshal Gelovani 52 | 1.1.2. | ოლსერვისჯგუფი | 10.00 GEL | 06.01.2019
A84: 44342.731 | B84: არქი საბურთალო (ს.კ. 405176982) - შპს | C84: Archi Jikia Block C | D84: 1.1.1. (+) შემოსავალი ლიფტების რეალიზაციიდან | E84: 44170 | F84: 136600 | G84: USD | H84: მიმდინარე | J84: 1 6 30 1453 | K84: 405176982/44170/1.1.1./1 | L84: 7F8895E0-BD86-4959-A763-AD1CD0F7FC77 | M84: Archi Jikia Block C | 1.1.1. (+) შემოსავალი ლიფტების რეალიზაციიდან | არქი საბურთალო (ს.კ. 405176982) - შპს | N84: B59170EC-16CC-499A-9FF7-0428DCB8F727 | O84: 25CECFAB-615A-4A1E-AC57-B18B8A92799B | Q84: gio.nikabadze@gmail.com | S84: Archi Jikia Block C | 1.1.1. | არქი საბურთალო | 136,600.00 USD | 05.12.2020
A85: 44342.731 | B85: შატო მუხრანი (ს.კ. 205000381) - სს | C85: Shato Mukhrani Gen-Set 2020 | D85: 1.2.1. (+) შემოსავალი MEP დანადგარების რეალიზაციიდან | E85: 43990 | F85: 55680 | G85: EUR | H85: მიმდინარე | K85: 205000381/43990/1.2.1./1 | L85: 798DCBA8-C0CF-4CAA-83E5-397FD911AAF0 | M85: Shato Mukhrani Gen-Set 2020 | 1.2.1. (+) შემოსავალი MEP დანადგარების რეალიზაციიდან | შატო მუხრანი (ს.კ. 205000381) - სს | N85: FEA4B88F-633F-4422-B3D6-250792A2DA80 | O85: 0E3C8876-D73B-417A-A61E-5FD08F98EDCB | Q85: gio.nikabadze@gmail.com | S85: Shato Mukhrani Gen-Set 2020 | 1.2.1. | შატო მუხრანი | 55,680.00 EUR | 08.06.2020
A86: 44342.731 | B86: ენსოლი (ს.კ. 205236190) - შპს | C86: Galleria Tbilisi | D86: 1.1.2. (+) შემოსავალი ლიფტების სერვისიდან - გეგმიური | E86: 43497 | F86: 3500 | G86: USD | H86: მიმდინარე | K86: 205236190/43497/1.1.2./1 | L86: 1BF0C1A7-EC4F-48F6-B5F1-6257BAB8D882 | M86: Galleria Tbilisi | 1.1.2. (+) შემოსავალი ლიფტების სერვისიდან - გეგმიური | ენსოლი (ს.კ. 205236190) - შპს | N86: 12238130-9D12-4099-A48B-9EB5A085E0F8 | O86: E13FA661-3B3D-437A-A26D-FB16D4C0D1C1 | Q86: gio.nikabadze@gmail.com | S86: Galleria Tbilisi | 1.1.2. | ენსოლი | 3,500.00 USD | 01.02.2019
A87: 44342.731 | B87: დომუსი (ს.კ. 404908864) - შპს | C87: Domus | D87: 1.1.2. (+) შემოსავალი ლიფტების სერვისიდან - გეგმიური | E87: 43146 | F87: 1400 | G87: USD | H87: მიმდინარე | K87: 404908864/43146/1.1.2./1 | L87: 4E9E5103-4BE9-4B72-838F-7CCF0A771578 | M87: Domus | 1.1.2. (+) შემოსავალი ლიფტების სერვისიდან - გეგმიური | დომუსი (ს.კ. 404908864) - შპს | N87: 12238130-9D12-4099-A48B-9EB5A085E0F8 | O87: B6B26BE3-174A-4141-A509-B6EE28D4677B | Q87: gio.nikabadze@gmail.com | S87: Domus | 1.1.2. | დომუსი | 1,400.00 USD | 15.02.2018
A88: 44342.731 | B88: როვშან მამადოვი (ს.კ. 67008001418) - ფიზ. პირი | C88: Rovshan Mamadovi | D88: 1.2.1. (+) შემოსავალი MEP დანადგარების რეალიზაციიდან | E88: 43999 | F88: 8214 | G88: USD | H88: მიმდინარე | K88: 67008001418/43999/1.2.1./1 | L88: 97C6ECBA-DA0F-4E2C-B8DB-26993DFCE122 | M88: Rovshan Mamadovi | 1.2.1. (+) შემოსავალი MEP დანადგარების რეალიზაციიდან | როვშან მამადოვი (ს.კ. 67008001418) - ფიზ. პირი | N88: FEA4B88F-633F-4422-B3D6-250792A2DA80 | O88: 3E3BB97B-230C-48D5-B6EF-41C9AE93AE61 | Q88: gio.nikabadze@gmail.com | S88: Rovshan Mamadovi | 1.2.1. | როვშან მამადოვი | 8,214.00 USD | 17.06.2020
A89: 44342.731 | B89: თბილი სახლი (ს.კ. 204976179) - შპს | C89: Sapatrulo | D89: 1.1.2. (+) შემოსავალი ლიფტების სერვისიდან - გეგმიური | E89: 43497 | F89: 250 | G89: GEL | H89: მიმდინარე | K89: 204976179/43497/1.1.2./1 | L89: 8BDDF5BD-4A6B-4C8E-942A-C62E20BCD667 | M89: Sapatrulo | 1.1.2. (+) შემოსავალი ლიფტების სერვისიდან - გეგმიური | თბილი სახლი (ს.კ. 204976179) - შპს | N89: 12238130-9D12-4099-A48B-9EB5A085E0F8 | O89: 726D9023-53A2-435E-8A5B-8BCEA9625E08 | Q89: gio.nikabadze@gmail.com | S89: Sapatrulo | 1.1.2. | თბილი სახლი | 250.00 GEL | 01.02.2019
A90: 44342.731 | B90: თბილი სახლი (ს.კ. 204976179) - შპს | C90: Erovnuli | D90: 1.1.2. (+) შემოსავალი ლიფტების სერვისიდან - გეგმიური | E90: 43497 | F90: 500 | G90: GEL | H90: მიმდინარე | K90: 204976179/43497/1.1.2./1 | L90: ED933289-CEA4-446C-99AC-B1B310C1ECB5 | M90: Erovnuli | 1.1.2. (+) შემოსავალი ლიფტების სერვისიდან - გეგმიური | თბილი სახლი (ს.კ. 204976179) - შპს | N90: 12238130-9D12-4099-A48B-9EB5A085E0F8 | O90: 726D9023-53A2-435E-8A5B-8BCEA9625E08 | Q90: gio.nikabadze@gmail.com | S90: Erovnuli | 1.1.2. | თბილი სახლი | 500.00 GEL | 01.02.2019
A91: 44342.731 | B91: ერა პალასი (ს.კ. 245619807) - შპს | C91: Gonio | D91: 1.1.2. (+) შემოსავალი ლიფტების სერვისიდან - გეგმიური | E91: 43617 | F91: 300 | G91: GEL | H91: მიმდინარე | K91: 245619807/43617/1.1.2./1 | L91: 3D3A6BA2-FC37-4C7B-9979-9C6C932BA9BF | M91: Gonio | 1.1.2. (+) შემოსავალი ლიფტების სერვისიდან - გეგმიური | ერა პალასი (ს.კ. 245619807) - შპს | N91: 12238130-9D12-4099-A48B-9EB5A085E0F8 | O91: 71A96223-5CD1-4DA9-9617-A85A565B4669 | Q91: gio.nikabadze@gmail.com | S91: Gonio | 1.1.2. | ერა პალასი | 300.00 GEL | 01.06.2019
A92: 44342.731 | B92: მოდუსი (ს.კ. 245565669) - შპს | C92: Modus batumi | D92: 1.1.2. (+) შემოსავალი ლიფტების სერვისიდან - გეგმიური | E92: 43592 | F92: 400 | G92: GEL | H92: მიმდინარე | K92: 245565669/43592/1.1.2./1 | L92: 07BBF564-E19D-46EA-8A32-44F28241B4B1 | M92: Modus batumi | 1.1.2. (+) შემოსავალი ლიფტების სერვისიდან - გეგმიური | მოდუსი (ს.კ. 245565669) - შპს | N92: 12238130-9D12-4099-A48B-9EB5A085E0F8 | O92: 9729C88B-F3C5-441A-8782-0656302A37F2 | Q92: gio.nikabadze@gmail.com | S92: Modus batumi | 1.1.2. | მოდუსი | 400.00 GEL | 07.05.2019
A93: 44342.731 | B93: ი. აბაშიძე 70 (ს.კ. ICE001082) - ამხანაგობა | C93: Abashidze 70 | D93: 1.1.2. (+) შემოსავალი ლიფტების სერვისიდან - გეგმიური | E93: 44013 | F93: 3000 | G93: GEL | H93: მიმდინარე | J93: 1 6 31 1485 | K93: ICE001082/44013/1.1.2./1 | L93: AFEF3A3A-0240-4773-9C5F-B7AC3C14711D | M93: Abashidze 70 | 1.1.2. (+) შემოსავალი ლიფტების სერვისიდან - გეგმიური | ი. აბაშიძე 70 (ს.კ. ICE001082) - ამხანაგობა | N93: 12238130-9D12-4099-A48B-9EB5A085E0F8 | O93: 3D0E73E0-0C40-467D-922F-74E3D4746FBD | Q93: gio.nikabadze@gmail.com | S93: Abashidze 70 | 1.1.2. | ი. აბაშიძე 70 | 3,000.00 GEL | 01.07.2020
A94: 44342.731 | B94: დელისი 2020 (ს.კ. ICE001083) - ამხანაგობა | C94: Epic gazapkhuli | D94: 1.1.2. (+) შემოსავალი ლიფტების სერვისიდან - გეგმიური | E94: 44014 | F94: 500 | G94: GEL | H94: მიმდინარე | J94: 1 6 31 1470 | K94: ICE001083/44014/1.1.2./1 | L94: F132898D-4C52-4676-8689-21E7C2709157 | M94: Epic gazapkhuli | 1.1.2. (+) შემოსავალი ლიფტების სერვისიდან - გეგმიური | დელისი 2020 (ს.კ. ICE001083) - ამხანაგობა | N94: 12238130-9D12-4099-A48B-9EB5A085E0F8 | O94: E18CBC98-9D65-4F4A-ADC0-B7350770D6F8 | Q94: gio.nikabadze@gmail.com | S94: Epic gazapkhuli | 1.1.2. | დელისი 2020 | 500.00 GEL | 02.07.2020
A95: 44342.731 | B95: ბაგები (ს.კ. 405330262) - შპს | C95: Epic Bagebi | D95: 1.1.1. (+) შემოსავალი ლიფტების რეალიზაციიდან | E95: 44013 | F95: 48000 | G95: USD | H95: მიმდინარე | J95: 1 6 30 1471 | K95: 405330262/44013/1.1.1./1 | L95: 6F71BE16-57C6-4634-B19B-DAD451C7CB11 | M95: Epic Bagebi | 1.1.1. (+) შემოსავალი ლიფტების რეალიზაციიდან | ბაგები (ს.კ. 405330262) - შპს | N95: B59170EC-16CC-499A-9FF7-0428DCB8F727 | O95: C270A903-5EB0-4E5A-8448-B4A637D5211F | Q95: gio.nikabadze@gmail.com | S95: Epic Bagebi | 1.1.1. | ბაგები | 48,000.00 USD | 01.07.2020
A96: 44342.731 | B96: მეპერსი (ს.კ. 402121887) - შპს | C96: Hilton Garden Inn Pipes 2 | D96: 1.2.1. (+) შემოსავალი MEP დანადგარების რეალიზაციიდან | E96: 43983 | F96: 4580.94 | G96: USD | H96: მიმდინარე | K96: 402121887/43983/1.2.1./1 | L96: 53D78126-348D-47EC-8E18-ACA366D918B3 | M96: Hilton Garden Inn Pipes 2 | 1.2.1. (+) შემოსავალი MEP დანადგარების რეალიზაციიდან | მეპერსი (ს.კ. 402121887) - შპს | N96: FEA4B88F-633F-4422-B3D6-250792A2DA80 | O96: 43EABC78-AF64-4C14-9FEF-C7E6A1B6F07E | Q96: gio.nikabadze@gmail.com | S96: Hilton Garden Inn Pipes 2 | 1.2.1. | მეპერსი | 4,580.94 USD | 01.06.2020
A97: 44342.731 | B97: თეგეტა მოტორსი (ს.კ. 202177205) - შპს | C97: Tegeta Batumi | D97: 1.1.2. (+) შემოსავალი ლიფტების სერვისიდან - გეგმიური | E97: 44013 | F97: 1 | G97: GEL | H97: მიმდინარე | K97: 202177205/44013/1.1.2./1 | L97: 065B3CAD-864E-4949-AE0A-9170B8973736 | M97: Tegeta Batumi | 1.1.2. (+) შემოსავალი ლიფტების სერვისიდან - გეგმიური | თეგეტა მოტორსი (ს.კ. 202177205) - შპს | N97: 12238130-9D12-4099-A48B-9EB5A085E0F8 | O97: 5A21C207-4868-4EA6-9B48-5D0F743D5535 | Q97: gio.nikabadze@gmail.com | S97: Tegeta Batumi | 1.1.2. | თეგეტა მოტორსი | 1.00 GEL | 01.07.2020
A98: 44342.731 | B98: საქ სამეცნიერო-საგანმანათ. კომპ ქსელების ასოციაცია გრენა (ს.კ. 204931654) - ასოციაცია | C98: Grena MEP 1 | D98: 1.2.1. (+) შემოსავალი MEP დანადგარების რეალიზაციიდან | E98: 44004 | F98: 9885 | G98: GEL | H98: მიმდინარე | K98: 204931654/44004/1.2.1./1 | L98: 67800432-96FF-489A-983A-99BD3F4C4954 | M98: Grena MEP 1 | 1.2.1. (+) შემოსავალი MEP დანადგარების რეალიზაციიდან | საქ სამეცნიერო-საგანმანათ. კომპ ქსელების ასოციაცია გრენა (ს.კ. 204931654) - ასოციაცია | N98: FEA4B88F-633F-4422-B3D6-250792A2DA80 | O98: 43A2E6CF-382D-45D9-9C82-D074B7CA8474 | Q98: gio.nikabadze@gmail.com | S98: Grena MEP 1 | 1.2.1. | საქ სამეცნიერო-საგანმანათ. კომპ ქსელების ასოციაცია გრენა | 9,885.00 GEL | 22.06.2020
A99: 44342.731 | B99: ახალშენი 2016 (ს.კ. 405136758) - შპს | C99: Khiliani | D99: 1.1.2. (+) შემოსავალი ლიფტების სერვისიდან - გეგმიური | E99: 43891 | F99: 1 | G99: GEL | H99: მიმდინარე | K99: 405136758/43891/1.1.2./1 | L99: AB270374-C6A2-4223-A667-ED4DD185CC7F | M99: Khiliani | 1.1.2. (+) შემოსავალი ლიფტების სერვისიდან - გეგმიური | ახალშენი 2016 (ს.კ. 405136758) - შპს | N99: 12238130-9D12-4099-A48B-9EB5A085E0F8 | O99: 04FB28EA-5501-4B01-BA1D-C2955C0E1213 | Q99: gio.nikabadze@gmail.com | S99: Khiliani | 1.1.2. | ახალშენი 2016 | 1.00 GEL | 01.03.2020
A100: 44342.731 | B100: ფალიაშვილის 63 (ს.კ. ICE000034) - ამხანაგობა | C100: Domus Paliashvilis 63 | D100: 1.1.2. (+) შემოსავალი ლიფტების სერვისიდან - გეგმიური | E100: 44019 | F100: 1 | G100: GEL | H100: მიმდინარე | K100: ICE000034/44019/1.1.2./1 | L100: D1923AD8-5716-4970-9AD0-37642D2C4B69 | M100: Domus Paliashvilis 63 | 1.1.2. (+) შემოსავალი ლიფტების სერვისიდან - გეგმიური | ფალიაშვილის 63 (ს.კ. ICE000034) - ამხანაგობა | N100: 12238130-9D12-4099-A48B-9EB5A085E0F8 | O100: 7F0A41E4-FA68-43E7-A979-126560D14B58 | Q100: gio.nikabadze@gmail.com | S100: Domus Paliashvilis 63 | 1.1.2. | ფალიაშვილის 63 | 1.00 GEL | 07.07.2020
A101: 44342.731 | B101: ინდეკო (ს.კ. 202376133) - შპს | C101: Indeko - shartava 39 | D101: 1.1.2. (+) შემოსავალი ლიფტების სერვისიდან - გეგმიური | E101: 43102 | F101: 1 | G101: GEL | H101: მიმდინარე | K101: 202376133/43102/1.1.2./1 | L101: 36DA9AC9-FD85-4E9B-B6AF-0CFCDD8E7D93 | M101: Indeko - shartava 39 | 1.1.2. (+) შემოსავალი ლიფტების სერვისიდან - გეგმიური | ინდეკო (ს.კ. 202376133) - შპს | N101: 12238130-9D12-4099-A48B-9EB5A085E0F8 | O101: 8E8E99BE-75FC-49EC-9D89-960E30E7CB06 | Q101: gio.nikabadze@gmail.com | S101: Indeko - shartava 39 | 1.1.2. | ინდეკო | 1.00 GEL | 02.01.2018
A102: 44342.731 | B102: დომუს სერვისი (ს.კ. 405311336) - შპს | C102: Domus | D102: 1.1.2. (+) შემოსავალი ლიფტების სერვისიდან - გეგმიური | E102: 43647 | F102: 1 | G102: USD | H102: მიმდინარე | K102: 405311336/43647/1.1.2./1 | L102: 576EC610-01F5-4D9B-9A18-3AE87057BAE9 | M102: Domus | 1.1.2. (+) შემოსავალი ლიფტების სერვისიდან - გეგმიური | დომუს სერვისი (ს.კ. 405311336) - შპს | N102: 12238130-9D12-4099-A48B-9EB5A085E0F8 | O102: 9B2B30F8-1FC4-427E-8478-DB1B57B48DDA | Q102: gio.nikabadze@gmail.com | S102: Domus | 1.1.2. | დომუს სერვისი | 1.00 USD | 01.07.2019
A103: 44342.731 | B103: იუნიქს ქონსთრაქშენ კომპანი (ს.კ. 405133822) - შპს | C103: UNIX Marselle 1 | D103: 1.1.2. (+) შემოსავალი ლიფტების სერვისიდან - გეგმიური | E103: 44013 | F103: 1 | G103: GEL | H103: მიმდინარე | K103: 405133822/44013/1.1.2./1 | L103: 91EE07CF-9713-420D-A132-7AEFD9A5F054 | M103: UNIX Marselle 1 | 1.1.2. (+) შემოსავალი ლიფტების სერვისიდან - გეგმიური | იუნიქს ქონსთრაქშენ კომპანი (ს.კ. 405133822) - შპს | N103: 12238130-9D12-4099-A48B-9EB5A085E0F8 | O103: B4968862-3843-414D-9E73-1A7611618B41 | Q103: gio.nikabadze@gmail.com | S103: UNIX Marselle 1 | 1.1.2. | იუნიქს ქონსთრაქშენ კომპანი | 1.00 GEL | 01.07.2020
A104: 44342.731 | B104: ბიზნეს ცენტრი დელისი (ს.კ. 204854014) - სს | C104: Delisi | D104: 1.1.2. (+) შემოსავალი ლიფტების სერვისიდან - გეგმიური | E104: 43831 | F104: 1 | G104: GEL | H104: მიმდინარე | K104: 204854014/43831/1.1.2./1 | L104: C01D4ADB-B292-4EAB-9036-EE74F4FB870D | M104: Delisi | 1.1.2. (+) შემოსავალი ლიფტების სერვისიდან - გეგმიური | ბიზნეს ცენტრი დელისი (ს.კ. 204854014) - სს | N104: 12238130-9D12-4099-A48B-9EB5A085E0F8 | O104: 62F6C15C-8FCC-4A60-B37E-8A3DE9D20A48 | Q104: gio.nikabadze@gmail.com | S104: Delisi | 1.1.2. | ბიზნეს ცენტრი დელისი | 1.00 GEL | 01.01.2020
A105: 44342.731 | B105: მოდუსი (ს.კ. 245565669) - შპს | C105: Modus Kakhety HW | D105: 1.1.2. (+) შემოსავალი ლიფტების სერვისიდან - გეგმიური | E105: 43586 | F105: 1 | G105: GEL | H105: მიმდინარე | J105: 1 6 30 642 2 | K105: 245565669/43586/1.1.2./1 | L105: 2A0A1CC3-2FD5-4F5A-BF97-52EE5BDDE144 | M105: Modus Kakhety HW | 1.1.2. (+) შემოსავალი ლიფტების სერვისიდან - გეგმიური | მოდუსი (ს.კ. 245565669) - შპს | N105: 12238130-9D12-4099-A48B-9EB5A085E0F8 | O105: 9729C88B-F3C5-441A-8782-0656302A37F2 | Q105: gio.nikabadze@gmail.com | S105: Modus Kakhety HW | 1.1.2. | მოდუსი | 1.00 GEL | 01.05.2019
A106: 44342.731 | B106: BD Property (ს.კ. 404390967) - შპს | C106: Tbilisi Gardens | D106: 1.1.2. (+) შემოსავალი ლიფტების სერვისიდან - გეგმიური | E106: 43466 | F106: 1 | G106: USD | H106: მიმდინარე | K106: 404390967/43466/1.1.2./1 | L106: D3F209CC-BD48-4729-87EA-24F29DD15FF4 | M106: Tbilisi Gardens | 1.1.2. (+) შემოსავალი ლიფტების სერვისიდან - გეგმიური | BD Property (ს.კ. 404390967) - შპს | N106: 12238130-9D12-4099-A48B-9EB5A085E0F8 | O106: 97275D0F-23EB-47CD-8A0F-C93649EE6164 | Q106: gio.nikabadze@gmail.com | S106: Tbilisi Gardens | 1.1.2. | BD Property | 1.00 USD | 01.01.2019
A107: 44342.731 | B107: გელა ხომერიკი (ს.კ. 33001011813) - ფიზ. პირი | C107: Kbuleti Str. - Khomeriki | D107: 1.1.2. (+) შემოსავალი ლიფტების სერვისიდან - გეგმიური | E107: 43132 | F107: 1 | G107: GEL | H107: მიმდინარე | K107: 33001011813/43132/1.1.2./1 | L107: 0172DB76-BF07-40C8-8007-921476501A04 | M107: Kbuleti Str. - Khomeriki | 1.1.2. (+) შემოსავალი ლიფტების სერვისიდან - გეგმიური | გელა ხომერიკი (ს.კ. 33001011813) - ფიზ. პირი | N107: 12238130-9D12-4099-A48B-9EB5A085E0F8 | O107: D92736A6-D9AA-4539-B5F8-0F34FACD5367 | Q107: gio.nikabadze@gmail.com | S107: Kbuleti Str. - Khomeriki | 1.1.2. | გელა ხომერიკი | 1.00 GEL | 01.02.2018
A108: 44342.731 | B108: თბილისი პალასი (ს.კ. 405253381) - შპს | C108: Tbilisi Palace | D108: 1.1.2. (+) შემოსავალი ლიფტების სერვისიდან - გეგმიური | E108: 43957 | F108: 1 | G108: GEL | H108: მიმდინარე | K108: 405253381/43957/1.1.2./1 | L108: 1322892A-5957-4D09-88EC-FC474E90B292 | M108: Tbilisi Palace | 1.1.2. (+) შემოსავალი ლიფტების სერვისიდან - გეგმიური | თბილისი პალასი (ს.კ. 405253381) - შპს | N108: 12238130-9D12-4099-A48B-9EB5A085E0F8 | O108: 3F5B4217-38D4-4FB8-B3F3-E856A10FFF06 | Q108: gio.nikabadze@gmail.com | S108: Tbilisi Palace | 1.1.2. | თბილისი პალასი | 1.00 GEL | 06.05.2020
A109: 44342.731 | B109: მოდუსი (ს.კ. 245565669) - შპს | C109: Modus Agladze | D109: 1.1.2. (+) შემოსავალი ლიფტების სერვისიდან - გეგმიური | E109: 43633 | F109: 1 | G109: GEL | H109: მიმდინარე | K109: 245565669/43633/1.1.2./1 | L109: 7F33E521-91AC-45E6-BEDC-038FF8B6F75A | M109: Modus Agladze | 1.1.2. (+) შემოსავალი ლიფტების სერვისიდან - გეგმიური | მოდუსი (ს.კ. 245565669) - შპს | N109: 12238130-9D12-4099-A48B-9EB5A085E0F8 | O109: 9729C88B-F3C5-441A-8782-0656302A37F2 | Q109: gio.nikabadze@gmail.com | S109: Modus Agladze | 1.1.2. | მოდუსი | 1.00 GEL | 17.06.2019
A110: 44342.731 | B110: ნიუ თაიმ (ს.კ. 445440577) - შპს | C110: New Time | D110: 1.1.2. (+) შემოსავალი ლიფტების სერვისიდან - გეგმიური | E110: 43311 | F110: 1 | G110: USD | H110: მიმდინარე | K110: 445440577/43311/1.1.2./1 | L110: 7E7F4F08-6722-4720-ADA7-30669A9837B9 | M110: New Time | 1.1.2. (+) შემოსავალი ლიფტების სერვისიდან - გეგმიური | ნიუ თაიმ (ს.კ. 445440577) - შპს | N110: 12238130-9D12-4099-A48B-9EB5A085E0F8 | O110: EEF69DEA-9E1B-41C3-B563-3922DCE0A9BD | Q110: gio.nikabadze@gmail.com | S110: New Time | 1.1.2. | ნიუ თაიმ | 1.00 USD | 30.07.2018
A111: 44342.731 | B111: ორბი ჯგუფი ბათუმი (ს.კ. 445468798) - შპს | C111: ORBI Office Lift | D111: 1.1.2. (+) შემოსავალი ლიფტების სერვისიდან - გეგმიური | E111: 43788 | F111: 1 | G111: USD | H111: მიმდინარე | K111: 445468798/43788/1.1.2./1 | L111: 5564FE9D-DA57-4C23-B925-E2D095D97D24 | M111: ORBI Office Lift | 1.1.2. (+) შემოსავალი ლიფტების სერვისიდან - გეგმიური | ორბი ჯგუფი ბათუმი (ს.კ. 445468798) - შპს | N111: 12238130-9D12-4099-A48B-9EB5A085E0F8 | O111: E284E0FD-A2B7-4D93-8E91-006FF0A8A4CE | Q111: gio.nikabadze@gmail.com | S111: ORBI Office Lift | 1.1.2. | ორბი ჯგუფი ბათუმი | 1.00 USD | 19.11.2019
A112: 44342.731 | B112: რედ-კო მენეჯმენტ გრუპი (ს.კ. 405198986) - შპს | C112: Redco 1 | D112: 1.1.2. (+) შემოსავალი ლიფტების სერვისიდან - გეგმიური | E112: 43879 | F112: 1 | G112: USD | H112: მიმდინარე | K112: 405198986/43879/1.1.2./1 | L112: A7C8AABE-B230-4454-A8DA-93EE74161089 | M112: Redco 1 | 1.1.2. (+) შემოსავალი ლიფტების სერვისიდან - გეგმიური | რედ-კო მენეჯმენტ გრუპი (ს.კ. 405198986) - შპს | N112: 12238130-9D12-4099-A48B-9EB5A085E0F8 | O112: 19F602E5-A978-4128-B38E-2D3540A8F675 | Q112: gio.nikabadze@gmail.com | S112: Redco 1 | 1.1.2. | რედ-კო მენეჯმენტ გრუპი | 1.00 USD | 18.02.2020
...

Sheet Old Info
A1: Timestamp | B1: კონტრაგენტი : | C1: პროექტის დასახელება : | D1: შემოსავლის კოდი : | E1: თარიღი : | F1: თანხა : | G1: ვალუტა : | H1: პროექტის სტატუსი : | I1: თანამშრომელი : | J1: ORIS 1630 : | K1: კონტრაქტის # - | L1: პროექტი_GUID/ | M1: პროექტი// | N1: შემოსავლის კოდი_GUID | O1: კონტრაგენტი_GUID | P1: თანამშრომელი_GUID | Q1: Collateral
A2: 44182.055 | B2: ოლიმპ ჯორჯია (ს.კ. 405231011) - შპს | C2: Biota Park | D2: 1.1.1. (+) შემოსავალი ლიფტების რეალიზაციიდან | E2: 43767 | F2: 350000 | G2: USD | H2: მიმდინარე | J2: 1 6 30 1270 | K2: 405231011/43767/1.1.1./1 | L2: 26A47FBE-6B71-4D89-B27B-4629DEEA1D34 | M2: Biota Park | 1.1.1. (+) შემოსავალი ლიფტების რეალიზაციიდან | ოლიმპ ჯორჯია (ს.კ. 405231011) - შპს | N2: B59170EC-16CC-499A-9FF7-0428DCB8F727 | O2: 6DECD64D-60DA-49AE-A9B3-49D7E02F2D62 | Q2: gio.nikabadze@gmail.com | T2: კონტრაგენტი :
A3: 44182.055 | B3: ინდეკო (ს.კ. 202376133) - შპს | C3: Chakhrukhadze | D3: 1.1.1. (+) შემოსავალი ლიფტების რეალიზაციიდან | E3: 43762 | F3: 23100 | G3: USD | H3: მიმდინარე | J3: 1 6 30 541 4 | K3: 202376133/43762/1.1.1./1 | L3: BFCA9047-3C75-4EEB-9FE8-82617FFD3965 | M3: Chakhrukhadze | 1.1.1. (+) შემოსავალი ლიფტების რეალიზაციიდან | ინდეკო (ს.კ. 202376133) - შპს | N3: B59170EC-16CC-499A-9FF7-0428DCB8F727 | O3: 8E8E99BE-75FC-49EC-9D89-960E30E7CB06 | Q3: gio.nikabadze@gmail.com | T3: პროექტის დასახელება :
A4: 44182.055 | B4: ბეტა ჯგუფი (ს.კ. 405171996) - შპს | C4: Med. University | D4: 1.1.1. (+) შემოსავალი ლიფტების რეალიზაციიდან | E4: 43767 | F4: 42500 | G4: USD | H4: მიმდინარე | K4: 405171996/43767/1.1.1./1 | L4: 00664103-FB2D-4EA7-A2B7-28064D745999 | M4: Med. University | 1.1.1. (+) შემოსავალი ლიფტების რეალიზაციიდან | ბეტა ჯგუფი (ს.კ. 405171996) - შპს | N4: B59170EC-16CC-499A-9FF7-0428DCB8F727 | O4: 3029E0C5-9337-4596-87DB-0A677D44A180 | Q4: gio.nikabadze@gmail.com | T4: შემოსავლის კოდი :
A5: 44182.055 | B5: გიოკაპიტალი (ს.კ. 406155841) - შპს | C5: Varketili | D5: 1.1.1. (+) შემოსავალი ლიფტების რეალიზაციიდან | E5: 43724 | F5: 48500 | G5: USD | H5: მიმდინარე | J5: 1 6 30 1252 | K5: 406155841/43724/1.1.1./1 | L5: 80851DA9-84C4-4C2C-95FE-D6A0282F7B22 | M5: Varketili | 1.1.1. (+) შემოსავალი ლიფტების რეალიზაციიდან | გიოკაპიტალი (ს.კ. 406155841) - შპს | N5: B59170EC-16CC-499A-9FF7-0428DCB8F727 | O5: 97BEEA92-7829-4A09-8B1C-D0FE871340D4 | Q5: gio.nikabadze@gmail.com | T5: თარიღი :
A6: 44182.055 | B6: რედ-კო (ს.კ. 405148415) - შპს | C6: Gudauri Redco Parking | D6: 1.1.1. (+) შემოსავალი ლიფტების რეალიზაციიდან | E6: 43734 | F6: 28000 | G6: USD | H6: მიმდინარე | K6: 405148415/43734/1.1.1./1 | L6: 2E1DDD27-332A-4E4A-B571-52B4DE3B8E04 | M6: Gudauri Redco Parking | 1.1.1. (+) შემოსავალი ლიფტების რეალიზაციიდან | რედ-კო (ს.კ. 405148415) - შპს | N6: B59170EC-16CC-499A-9FF7-0428DCB8F727 | O6: DA9D440B-CACD-4076-8B91-BFFCA46814B6 | Q6: gio.nikabadze@gmail.com | T6: თანხა :
A7: 44182.055 | B7: მაია კვიჭიძე (ს.კ. 01008011243) - ფიზ. პირი | C7: Ortachala | D7: 1.1.1. (+) შემოსავალი ლიფტების რეალიზაციიდან | E7: 43672 | F7: 24000 | G7: USD | H7: მიმდინარე | K7: 01008011243/43672/1.1.1./1 | L7: 83FEC832-A4EA-4380-B5E9-85BEEECE8FA4 | M7: Ortachala | 1.1.1. (+) შემოსავალი ლიფტების რეალიზაციიდან | მაია კვიჭიძე (ს.კ. 01008011243) - ფიზ. პირი | N7: B59170EC-16CC-499A-9FF7-0428DCB8F727 | O7: D5136DB7-C17A-4DDB-9797-D1B10612D28C | Q7: gio.nikabadze@gmail.com | T7: ვალუტა :
A8: 44182.056 | B8: მოდუსი (ს.კ. 245565669) - შპს | C8: Modus Agladze | D8: 1.1.1. (+) შემოსავალი ლიფტების რეალიზაციიდან | E8: 43633 | F8: 57000 | G8: USD | H8: მიმდინარე | K8: 245565669/43633/1.1.1./1 | L8: ABDEF9CC-F0E1-4950-B30C-D46A8A8A912C | M8: Modus Agladze | 1.1.1. (+) შემოსავალი ლიფტების რეალიზაციიდან | მოდუსი (ს.კ. 245565669) - შპს | N8: B59170EC-16CC-499A-9FF7-0428DCB8F727 | O8: 9729C88B-F3C5-441A-8782-0656302A37F2 | Q8: gio.nikabadze@gmail.com | T8: პროექტის სტატუსი : | W8: 1
A9: 44182.056 | B9: ჰომბეი (ს.კ. 405255815) - შპს | C9: Crystal Bakuriani | D9: 1.1.1. (+) შემოსავალი ლიფტების რეალიზაციიდან | E9: 43608 | F9: 104500 | G9: USD | H9: მიმდინარე | K9: 405255815/43608/1.1.1./1 | L9: 230FCB1B-1310-4C49-9D2C-9CD5F9A792A3 | M9: Crystal Bakuriani | 1.1.1. (+) შემოსავალი ლიფტების რეალიზაციიდან | ჰომბეი (ს.კ. 405255815) - შპს | N9: B59170EC-16CC-499A-9FF7-0428DCB8F727 | O9: AAFC235A-2BBF-4CEC-A2AE-F1AEBABC12E4 | Q9: gio.nikabadze@gmail.com | T9: თანამშრომელი : | W9: 1 | X9: 0
A10: 44182.056 | B10: ანა აბუსერიძე (ს.კ. 61001051501) - ფიზ. პირი | C10: Abuseridze - Batumi | D10: 1.1.1. (+) შემოსავალი ლიფტების რეალიზაციიდან | E10: 43622 | F10: 31000 | G10: USD | H10: მიმდინარე | J10: 1 6 30 1179 | K10: 61001051501/43622/1.1.1./1 | L10: 4E89F135-A0AD-4622-97BD-7B68EF6062F8 | M10: Abuseridze - Batumi | 1.1.1. (+) შემოსავალი ლიფტების რეალიზაციიდან | ანა აბუსერიძე (ს.კ. 61001051501) - ფიზ. პირი | N10: B59170EC-16CC-499A-9FF7-0428DCB8F727 | O10: 15F35EBB-5A28-4C1B-B7CC-45FF3F31D4D6 | Q10: gio.nikabadze@gmail.com | T10: ORIS 1630 :
A11: 44182.056 | B11: იუნიქს ქონსთრაქშენ კომპანი (ს.კ. 405133822) - შპს | C11: UNIX Marselle | D11: 1.1.1. (+) შემოსავალი ლიფტების რეალიზაციიდან | E11: 43607 | F11: 340000 | G11: USD | H11: მიმდინარე | K11: 405133822/43607/1.1.1./1 | L11: CFFC1C06-B78B-45A0-8A02-37A23706EAFC | M11: UNIX Marselle | 1.1.1. (+) შემოსავალი ლიფტების რეალიზაციიდან | იუნიქს ქონსთრაქშენ კომპანი (ს.კ. 405133822) - შპს | N11: B59170EC-16CC-499A-9FF7-0428DCB8F727 | O11: B4968862-3843-414D-9E73-1A7611618B41 | Q11: gio.nikabadze@gmail.com | T11: კონტრაქტის # -
A12: 44182.056 | B12: თბილისი პალასი (ს.კ. 405253381) - შპს | C12: Tbilisi Palace | D12: 1.1.1. (+) შემოსავალი ლიფტების რეალიზაციიდან | E12: 43460 | F12: 160000 | G12: USD | H12: მიმდინარე | K12: 405253381/43460/1.1.1./1 | L12: 125722B7-4DB0-4817-B1A4-DBA0B1B893D4 | M12: Tbilisi Palace | 1.1.1. (+) შემოსავალი ლიფტების რეალიზაციიდან | თბილისი პალასი (ს.კ. 405253381) - შპს | N12: B59170EC-16CC-499A-9FF7-0428DCB8F727 | O12: 3F5B4217-38D4-4FB8-B3F3-E856A10FFF06 | Q12: gio.nikabadze@gmail.com | T12: პროექტი_GUID/
A13: 44182.056 | B13: თეგეტა მოტორსი (ს.კ. 202177205) - შპს | C13: Tegeta Batumi | D13: 1.1.1. (+) შემოსავალი ლიფტების რეალიზაციიდან | E13: 43479 | F13: 28650 | G13: USD | H13: მიმდინარე | K13: 202177205/43479/1.1.1./1 | L13: 255604D7-5424-4548-9CAA-ECFF960BB6AE | M13: Tegeta Batumi | 1.1.1. (+) შემოსავალი ლიფტების რეალიზაციიდან | თეგეტა მოტორსი (ს.კ. 202177205) - შპს | N13: B59170EC-16CC-499A-9FF7-0428DCB8F727 | O13: 5A21C207-4868-4EA6-9B48-5D0F743D5535 | Q13: gio.nikabadze@gmail.com | T13: პროექტი//
A14: 44182.056 | B14: Dar Building (ს.კ. 445420875) - შპს | C14: DAR TOWER | D14: 1.1.1. (+) შემოსავალი ლიფტების რეალიზაციიდან | E14: 43363 | F14: 1046340 | G14: USD | H14: მიმდინარე | J14: 1 6 30 853 1 | K14: 445420875/43363/1.1.1./1 | L14: A4EE54E2-C9BC-44F8-8554-44B9037B38D2 | M14: DAR TOWER | 1.1.1. (+) შემოსავალი ლიფტების რეალიზაციიდან | Dar Building (ს.კ. 445420875) - შპს | N14: B59170EC-16CC-499A-9FF7-0428DCB8F727 | O14: 7BF4A039-29BC-44AC-A87D-E8832394B94E | Q14: gio.nikabadze@gmail.com | T14: შემოსავლის კოდი_GUID | W14: =38317.6666666666/365 -> 104.97991
A15: 44182.056 | B15: ბათბილდინგი (ს.კ. 445509334) - შპს | C15: BAT Tower | D15: 1.1.1. (+) შემოსავალი ლიფტების რეალიზაციიდან | E15: 43461 | F15: 73000 | G15: USD | H15: მიმდინარე | K15: 445509334/43461/1.1.1./1 | L15: A7AFCD4C-CA26-464C-8F1B-E9A5240DCB0F | M15: BAT Tower | 1.1.1. (+) შემოსავალი ლიფტების რეალიზაციიდან | ბათბილდინგი (ს.კ. 445509334) - შპს | N15: B59170EC-16CC-499A-9FF7-0428DCB8F727 | O15: DAE7B000-963F-42D9-AA35-8F3F2F8A3716 | Q15: gio.nikabadze@gmail.com | T15: კონტრაგენტი_GUID
A16: 44182.056 | B16: რუმი (ს.კ. 445481853) - შპს | C16: Rumi - batumi | D16: 1.1.1. (+) შემოსავალი ლიფტების რეალიზაციიდან | E16: 43816 | F16: 114550 | G16: USD | H16: მიმდინარე | J16: 1 6 30 1335 | K16: 445481853/43816/1.1.1./1 | L16: E95274D6-921C-43D1-B7C4-4F99A71C4005 | M16: Rumi - batumi | 1.1.1. (+) შემოსავალი ლიფტების რეალიზაციიდან | რუმი (ს.კ. 445481853) - შპს | N16: B59170EC-16CC-499A-9FF7-0428DCB8F727 | O16: BFABDF11-34C8-4815-A840-47DD5AAB9F4F | Q16: gio.nikabadze@gmail.com | T16: თანამშრომელი_GUID
A17: 44182.056 | B17: ფალიაშვილის 63 (ს.კ. ICE000034) - ამხანაგობა | C17: Domus Paliashviliს 63 | D17: 1.1.1. (+) შემოსავალი ლიფტების რეალიზაციიდან | E17: 42948 | F17: 97000 | G17: GEL | H17: მიმდინარე | K17: ICE000034/42948/1.1.1./1 | L17: C897938C-00C4-4220-BAF1-CA29F3237D16 | M17: Domus Paliashviliს 63 | 1.1.1. (+) შემოსავალი ლიფტების რეალიზაციიდან | ფალიაშვილის 63 (ს.კ. ICE000034) - ამხანაგობა | N17: B59170EC-16CC-499A-9FF7-0428DCB8F727 | O17: 7F0A41E4-FA68-43E7-A979-126560D14B58 | Q17: gio.nikabadze@gmail.com | T17: [Collateral]
A18: 44182.056 | B18: ეკომეტრი (ს.კ. 404464030) - შპს | C18: Gelovani 52 | D18: 1.1.1. (+) შემოსავალი ლიფტების რეალიზაციიდან | E18: 42923 | F18: 161000 | G18: USD | H18: მიმდინარე | K18: 404464030/42923/1.1.1./1 | L18: 196F7BB2-781C-4FF2-BAEE-C30045DA8E1E | M18: Gelovani 52 | 1.1.1. (+) შემოსავალი ლიფტების რეალიზაციიდან | ეკომეტრი (ს.კ. 404464030) - შპს | N18: B59170EC-16CC-499A-9FF7-0428DCB8F727 | O18: B25EF46E-8022-4949-A1EB-E8A1256C7A3B | Q18: gio.nikabadze@gmail.com
A19: 44182.056 | B19: ჩემპიონი 2 (ს.კ. 248416432) - შპს | C19: Chempioni | D19: 1.1.1. (+) შემოსავალი ლიფტების რეალიზაციიდან | E19: 42536 | F19: 23924 | G19: USD | H19: მიმდინარე | K19: 248416432/42536/1.1.1./1 | L19: 42197EB0-C73A-4679-8D11-1DD3BAC96135 | M19: Chempioni | 1.1.1. (+) შემოსავალი ლიფტების რეალიზაციიდან | ჩემპიონი 2 (ს.კ. 248416432) - შპს | N19: B59170EC-16CC-499A-9FF7-0428DCB8F727 | O19: 967EE73E-8B77-4A8F-9FD3-AA36FF0ECB17 | Q19: gio.nikabadze@gmail.com
A20: 44182.056 | B20: ნიუ თაიმ (ს.კ. 445440577) - შპს | C20: New Time | D20: 1.1.1. (+) შემოსავალი ლიფტების რეალიზაციიდან | E20: 42885 | F20: 150000 | G20: USD | H20: მიმდინარე | K20: 445440577/42885/1.1.1./1 | L20: 7A83BC1F-C807-436E-9390-775B1D423BFD | M20: New Time | 1.1.1. (+) შემოსავალი ლიფტების რეალიზაციიდან | ნიუ თაიმ (ს.კ. 445440577) - შპს | N20: B59170EC-16CC-499A-9FF7-0428DCB8F727 | O20: EEF69DEA-9E1B-41C3-B563-3922DCE0A9BD | Q20: gio.nikabadze@gmail.com
A21: 44182.056 | B21: ელტური-2008 (ს.კ. 248434038) - შპს | C21: Green Cape | D21: 1.1.1. (+) შემოსავალი ლიფტების რეალიზაციიდან | E21: 43460 | F21: 70360 | G21: USD | H21: მიმდინარე | K21: 248434038/43460/1.1.1./1 | L21: D9285AF5-11A4-4764-B11B-745E9DAF1D34 | M21: Green Cape | 1.1.1. (+) შემოსავალი ლიფტების რეალიზაციიდან | ელტური-2008 (ს.კ. 248434038) - შპს | N21: B59170EC-16CC-499A-9FF7-0428DCB8F727 | O21: 0A7F5182-3B4F-4292-8569-FC31854BA5B4 | Q21: gio.nikabadze@gmail.com | T21: =TEXTJOIN("','",TRUE,Projects!B1:Q1) -> კონტრაგენტი :','პროექტის დასახელება :','შემოსავლის კოდი :','თარიღი :','თანხა :','ვალუტა :','პროექტის სტატუსი :','თანამშრომელი :','ORIS 1630 :','კონტრაქტის # - ','პროექტი_GUID/','პროექტი//','შემოსავლის კოდი_GUID','კონტრაგენტი_GUID','თანამშრომელი_GUID','Collateral
A22: 44182.056 | B22: ინდეკო (ს.კ. 202376133) - შპს | C22: Indeko - shartava 39 | D22: 1.1.1. (+) შემოსავალი ლიფტების რეალიზაციიდან | E22: 43460 | F22: 155520 | G22: USD | H22: მიმდინარე | K22: 202376133/42345/1.1.1./1 | L22: C5E1547A-8529-495B-974D-92544D0F1C66 | M22: Indeko - shartava 39 | 1.1.1. (+) შემოსავალი ლიფტების რეალიზაციიდან | ინდეკო (ს.კ. 202376133) - შპს | N22: B59170EC-16CC-499A-9FF7-0428DCB8F727 | O22: 8E8E99BE-75FC-49EC-9D89-960E30E7CB06 | Q22: gio.nikabadze@gmail.com
A23: 44182.056 | B23: რედ-კო (ს.კ. 405148415) - შპს | C23: Redco 1 | D23: 1.1.1. (+) შემოსავალი ლიფტების რეალიზაციიდან | E23: 43248 | F23: 370000 | G23: USD | H23: მიმდინარე | J23: 1 6 30 917 2 | K23: 405148415/43248/1.1.1./1 | L23: D421D947-C097-4870-8EF1-C7F724377248 | M23: Redco 1 | 1.1.1. (+) შემოსავალი ლიფტების რეალიზაციიდან | რედ-კო (ს.კ. 405148415) - შპს | N23: B59170EC-16CC-499A-9FF7-0428DCB8F727 | O23: DA9D440B-CACD-4076-8B91-BFFCA46814B6 | Q23: gio.nikabadze@gmail.com
A24: 44182.056 | B24: ბიზნეს ცენტრი დელისი (ს.კ. 204854014) - სს | C24: Delisi | D24: 1.1.1. (+) შემოსავალი ლიფტების რეალიზაციიდან | E24: 42598 | F24: 53454 | G24: USD | H24: მიმდინარე | K24: 204854014/42598/1.1.1./1 | L24: 2496A0E0-1118-49DC-8A82-539003DC1B23 | M24: Delisi | 1.1.1. (+) შემოსავალი ლიფტების რეალიზაციიდან | ბიზნეს ცენტრი დელისი (ს.კ. 204854014) - სს | N24: B59170EC-16CC-499A-9FF7-0428DCB8F727 | O24: 62F6C15C-8FCC-4A60-B37E-8A3DE9D20A48 | Q24: gio.nikabadze@gmail.com
A25: 44182.056 | B25: შველა (ს.კ. 448396021) - შპს | C25: Shvela | D25: 1.1.1. (+) შემოსავალი ლიფტების რეალიზაციიდან | E25: 42536 | F25: 50206 | G25: USD | H25: მიმდინარე | K25: 448396021/42536/1.1.1./1 | L25: 1C2CAB23-3967-41F9-AC61-62415AE0373C | M25: Shvela | 1.1.1. (+) შემოსავალი ლიფტების რეალიზაციიდან | შველა (ს.კ. 448396021) - შპს | N25: B59170EC-16CC-499A-9FF7-0428DCB8F727 | O25: A5C44F5D-1F9C-4BC1-BD39-C8B2E88BC49A | Q25: gio.nikabadze@gmail.com
A26: 44182.056 | B26: ბკ კაპიტალი (ს.კ. 205057123) - შპს | C26: Moxy Zaabruken Hotel | D26: 1.1.1. (+) შემოსავალი ლიფტების რეალიზაციიდან | E26: 42647 | F26: 157608.67 | G26: USD | H26: მიმდინარე | K26: 205057123/42647/1.1.1./1 | L26: 202843CA-C5C3-4057-8040-234B6C369B5E | M26: Moxy Zaabruken Hotel | 1.1.1. (+) შემოსავალი ლიფტების რეალიზაციიდან | ბკ კაპიტალი (ს.კ. 205057123) - შპს | N26: B59170EC-16CC-499A-9FF7-0428DCB8F727 | O26: D57E2878-F57C-4B96-B89E-A8B81F35634A | Q26: gio.nikabadze@gmail.com
A27: 44182.056 | B27: ინჟინერთა ჯგუფი (ს.კ. 400101457) - შპს | C27: Tbilisi Gardens | D27: 1.1.1. (+) შემოსავალი ლიფტების რეალიზაციიდან | E27: 42723 | F27: 325000 | G27: USD | H27: მიმდინარე | K27: 400101457/42723/1.1.1./1 | L27: 8C8C52A5-1A7C-485F-9AC8-043862EF3D55 | M27: Tbilisi Gardens | 1.1.1. (+) შემოსავალი ლიფტების რეალიზაციიდან | ინჟინერთა ჯგუფი (ს.კ. 400101457) - შპს | N27: B59170EC-16CC-499A-9FF7-0428DCB8F727 | O27: 2ED6F730-5337-4222-94F9-284E801BCE61 | Q27: gio.nikabadze@gmail.com
A28: 44182.056 | B28: მოდუსი (ს.კ. 245565669) - შპს | C28: Modus Kakhety HW | D28: 1.1.1. (+) შემოსავალი ლიფტების რეალიზაციიდან | E28: 42641 | F28: 25000 | G28: USD | H28: მიმდინარე | K28: 245565669/42641/1.1.1./1 | L28: BFD4409A-7F01-4C7C-9F40-73A80C2E63A6 | M28: Modus Kakhety HW | 1.1.1. (+) შემოსავალი ლიფტების რეალიზაციიდან | მოდუსი (ს.კ. 245565669) - შპს | N28: B59170EC-16CC-499A-9FF7-0428DCB8F727 | O28: 9729C88B-F3C5-441A-8782-0656302A37F2 | Q28: gio.nikabadze@gmail.com
A29: 44182.056 | B29: სითი დეველოპმენტ (ს.კ. 404481324) - შპს | C29: Kbuleti Str. - Khomeriki | D29: 1.1.1. (+) შემოსავალი ლიფტების რეალიზაციიდან | E29: 42485 | F29: 36577 | G29: USD | H29: მიმდინარე | K29: 404481324/42485/1.1.1./1 | L29: A53105CE-1BDB-4625-B775-A01DA1F6C8AD | M29: Kbuleti Str. - Khomeriki | 1.1.1. (+) შემოსავალი ლიფტების რეალიზაციიდან | სითი დეველოპმენტ (ს.კ. 404481324) - შპს | N29: B59170EC-16CC-499A-9FF7-0428DCB8F727 | O29: 57A60218-744B-4922-BF21-F9C52A01DAF6 | Q29: gio.nikabadze@gmail.com
A30: 44182.056 | B30: დომუს დეველოპმენტ (ს.კ. 205210261) - შპს | C30: Domus | D30: 1.1.1. (+) შემოსავალი ლიფტების რეალიზაციიდან | E30: 42355 | F30: 527700 | G30: USD | H30: მიმდინარე | K30: 205210261/42355/1.1.1./1 | L30: F154242F-E028-49D8-B7BE-42EB31281CD5 | M30: Domus | 1.1.1. (+) შემოსავალი ლიფტების რეალიზაციიდან | დომუს დეველოპმენტ (ს.კ. 205210261) - შპს | N30: B59170EC-16CC-499A-9FF7-0428DCB8F727 | O30: A3C5943B-D1C3-4CB2-946C-86BF678B6183 | Q30: gio.nikabadze@gmail.com
A31: 44182.056 | B31: ირაკლი კაციტაძე (ს.კ. 01008004604) - ფიზ. პირი | C31: Paliashvili 23 | D31: 1.1.2. (+) შემოსავალი ლიფტების სერვისიდან - გეგმიური | E31: 43831 | F31: 1 | G31: GEL | H31: მიმდინარე | K31: 01008004604/43831/1.1.2./1 | L31: 6D999F5B-2199-4578-A47D-FDC2DF179273 | M31: Paliashvili 23 | 1.1.2. (+) შემოსავალი ლიფტების სერვისიდან - გეგმიური | ირაკლი კაციტაძე (ს.კ. 01008004604) - ფიზ. პირი | N31: 12238130-9D12-4099-A48B-9EB5A085E0F8 | O31: 9AE0C821-91FF-44A4-90E6-F71F98BC044C | Q31: gio.nikabadze@gmail.com
A32: 44182.056 | B32: ბკ კაპიტალი (ს.კ. 205057123) - შპს | C32: Moxy Zabruken Restaurant | D32: 1.1.1. (+) შემოსავალი ლიფტების რეალიზაციიდან | E32: 43742 | F32: 78804.33 | G32: USD | H32: მიმდინარე | K32: 205057123/43742/1.1.1./1 | L32: 5E543EA8-4A6A-4F8C-9F72-071B61F85EEB | M32: Moxy Zabruken Restaurant | 1.1.1. (+) შემოსავალი ლიფტების რეალიზაციიდან | ბკ კაპიტალი (ს.კ. 205057123) - შპს | N32: B59170EC-16CC-499A-9FF7-0428DCB8F727 | O32: D57E2878-F57C-4B96-B89E-A8B81F35634A | Q32: gio.nikabadze@gmail.com
A33: 44182.056 | B33: ორბი ჯგუფი ბათუმი (ს.კ. 445468798) - შპს | C33: TWIN TOWER | D33: 1.1.1. (+) შემოსავალი ლიფტების რეალიზაციიდან | E33: 43059 | F33: 3273908 | G33: USD | H33: მიმდინარე | J33: 1 6 30 773 1 | K33: 445468798/43059/1.1.1./1 | L33: C35D9FF1-3A09-4634-9BFA-87C709266063 | M33: TWIN TOWER | 1.1.1. (+) შემოსავალი ლიფტების რეალიზაციიდან | ორბი ჯგუფი ბათუმი (ს.კ. 445468798) - შპს | N33: B59170EC-16CC-499A-9FF7-0428DCB8F727 | O33: E284E0FD-A2B7-4D93-8E91-006FF0A8A4CE | Q33: gio.nikabadze@gmail.com
A34: 44182.056 | B34: აი ჯი დეველოფმენტ ჯორჯია (ს.კ. 404851503) - შპს | C34: City Mall | D34: 1.1.1. (+) შემოსავალი ლიფტების რეალიზაციიდან | E34: 43354 | F34: 1194345 | G34: USD | H34: მიმდინარე | J34: 1 6 30 971 | K34: 404851503/43354/1.1.1./1 | L34: EA15EDA6-F906-4932-87BA-DDB8898D4EBC | M34: City Mall | 1.1.1. (+) შემოსავალი ლიფტების რეალიზაციიდან | აი ჯი დეველოფმენტ ჯორჯია (ს.კ. 404851503) - შპს | N34: B59170EC-16CC-499A-9FF7-0428DCB8F727 | O34: DDFBBDF4-5DA2-4BD2-918A-77AAF121BF72 | Q34: gio.nikabadze@gmail.com
A35: 44182.056 | B35: რენთინგ ბიენბი (ს.კ. 404564244) - სს | C35: Renting BNB | D35: 1.1.1. (+) შემოსავალი ლიფტების რეალიზაციიდან | E35: 43886 | F35: 26000 | G35: USD | H35: მიმდინარე | K35: 404564244/43886/1.1.1./1 | L35: 55F53FA9-CDDE-4FBA-91A1-FEAFA51B29A0 | M35: Renting BNB | 1.1.1. (+) შემოსავალი ლიფტების რეალიზაციიდან | რენთინგ ბიენბი (ს.კ. 404564244) - სს | N35: B59170EC-16CC-499A-9FF7-0428DCB8F727 | O35: 9B349A17-7CE1-4232-98C6-02C565C3642C | Q35: gio.nikabadze@gmail.com
A36: 44182.056 | B36: ტრანსმშენი (ს.კ. 212274812) - სს | C36: Aeroporti | D36: 1.1.1. (+) შემოსავალი ლიფტების რეალიზაციიდან | E36: 43699 | F36: 20000 | G36: USD | H36: მიმდინარე | K36: 212274812/43699/1.1.1./1 | L36: 44F2F4A0-908E-42D1-B73F-04859CACCB08 | M36: Aeroporti | 1.1.1. (+) შემოსავალი ლიფტების რეალიზაციიდან | ტრანსმშენი (ს.კ. 212274812) - სს | N36: B59170EC-16CC-499A-9FF7-0428DCB8F727 | O36: 9B21D54A-56D8-405D-95E2-A05872C7C1E9 | Q36: gio.nikabadze@gmail.com
A37: 44182.056 | B37: ბეტა ჯგუფი (ს.კ. 405171996) - შპს | C37: Dividers Med Uni | D37: 1.1.1. (+) შემოსავალი ლიფტების რეალიზაციიდან | E37: 43477 | F37: 11000 | G37: GEL | H37: მიმდინარე | K37: 405171996/43477/1.1.1./1 | L37: 2F958FC8-AC98-416D-BEAC-E4C6006FCCB3 | M37: Dividers Med Uni | 1.1.1. (+) შემოსავალი ლიფტების რეალიზაციიდან | ბეტა ჯგუფი (ს.კ. 405171996) - შპს | N37: B59170EC-16CC-499A-9FF7-0428DCB8F727 | O37: 3029E0C5-9337-4596-87DB-0A677D44A180 | Q37: gio.nikabadze@gmail.com
A38: 44182.056 | B38: ლუდსახარში ორი კათხა (ს.კ. 406283338) - შპს | C38: Brewery 1 (300KG) | D38: 1.1.1. (+) შემოსავალი ლიფტების რეალიზაციიდან | E38: 43896 | F38: 10610 | G38: USD | H38: მიმდინარე | K38: 406283338/43896/1.1.1./1 | L38: 4DB7E760-9ECD-4426-BB50-E293E58D2B02 | M38: Brewery 1 (300KG) | 1.1.1. (+) შემოსავალი ლიფტების რეალიზაციიდან | ლუდსახარში ორი კათხა (ს.კ. 406283338) - შპს | N38: B59170EC-16CC-499A-9FF7-0428DCB8F727 | O38: 1C2A10A9-FA2F-437B-8C70-F109D1C009EE | Q38: gio.nikabadze@gmail.com
A39: 44182.056 | B39: ახალშენი 2016 (ს.კ. 405136758) - შპს | C39: Khiliani | D39: 1.1.1. (+) შემოსავალი ლიფტების რეალიზაციიდან | E39: 43677 | F39: 26400 | G39: USD | H39: მიმდინარე | K39: 405136758/43677/1.1.1./1 | L39: E136ACFA-DBED-49EE-B224-24513754542C | M39: Khiliani | 1.1.1. (+) შემოსავალი ლიფტების რეალიზაციიდან | ახალშენი 2016 (ს.კ. 405136758) - შპს | N39: B59170EC-16CC-499A-9FF7-0428DCB8F727 | O39: 04FB28EA-5501-4B01-BA1D-C2955C0E1213 | Q39: gio.nikabadze@gmail.com
A40: 44182.056 | B40: ორბი ჯგუფი ბათუმი (ს.კ. 445468798) - შპს | C40: ORBI Office Lift | D40: 1.1.1. (+) შემოსავალი ლიფტების რეალიზაციიდან | E40: 43788 | F40: 30000 | G40: USD | H40: მიმდინარე | K40: 445468798/43788/1.1.1./1 | L40: 5B0BA252-1105-4374-8654-430AE04E8A64 | M40: ORBI Office Lift | 1.1.1. (+) შემოსავალი ლიფტების რეალიზაციიდან | ორბი ჯგუფი ბათუმი (ს.კ. 445468798) - შპს | N40: B59170EC-16CC-499A-9FF7-0428DCB8F727 | O40: E284E0FD-A2B7-4D93-8E91-006FF0A8A4CE | Q40: gio.nikabadze@gmail.com
A41: 44182.056 | B41: ბეტა ჯგუფი (ს.კ. 405171996) - შპს | C41: IBIS Perovi | D41: 1.1.1. (+) შემოსავალი ლიფტების რეალიზაციიდან | E41: 43719 | F41: 83750 | G41: USD | H41: მიმდინარე | J41: 1 6 30 1257 1 | K41: 405171996/43719/1.1.1./1 | L41: 3619FEF3-250F-43C1-93C3-B77FEADECC84 | M41: IBIS Perovi | 1.1.1. (+) შემოსავალი ლიფტების რეალიზაციიდან | ბეტა ჯგუფი (ს.კ. 405171996) - შპს | N41: B59170EC-16CC-499A-9FF7-0428DCB8F727 | O41: 3029E0C5-9337-4596-87DB-0A677D44A180 | Q41: gio.nikabadze@gmail.com
A42: 44182.056 | B42: კანოპუსი (ს.კ. 405229881) - შპს | C42: Sololaki | D42: 1.1.1. (+) შემოსავალი ლიფტების რეალიზაციიდან | E42: 43769 | F42: 24000 | G42: USD | H42: მიმდინარე | K42: 405229881/43769/1.1.1./1 | L42: 0159D5F2-86A6-4D6F-87C4-D563AB9AA860 | M42: Sololaki | 1.1.1. (+) შემოსავალი ლიფტების რეალიზაციიდან | კანოპუსი (ს.კ. 405229881) - შპს | N42: B59170EC-16CC-499A-9FF7-0428DCB8F727 | O42: F43C8D9B-B556-4114-B404-AEEFA8C31B20 | Q42: gio.nikabadze@gmail.com
A43: 44182.056 | B43: ბეტა ჯგუფი (ს.კ. 405171996) - შპს | C43: IBIS Perov Dumbwaiter | D43: 1.1.1. (+) შემოსავალი ლიფტების რეალიზაციიდან | E43: 43804 | F43: 16300 | G43: USD | H43: მიმდინარე | K43: 405171996/43804/1.1.1./1 | L43: B9668B49-46F2-4E2F-B183-F802279CAA6C | M43: IBIS Perov Dumbwaiter | 1.1.1. (+) შემოსავალი ლიფტების რეალიზაციიდან | ბეტა ჯგუფი (ს.კ. 405171996) - შპს | N43: B59170EC-16CC-499A-9FF7-0428DCB8F727 | O43: 3029E0C5-9337-4596-87DB-0A677D44A180 | Q43: gio.nikabadze@gmail.com
A44: 44182.056 | B44: სითი რეალ ისთეით (ს.კ. 406067410) - შპს | C44: Kleemann Pekini | D44: 1.1.1. (+) შემოსავალი ლიფტების რეალიზაციიდან | E44: 43228 | F44: 353218 | G44: USD | H44: მიმდინარე | K44: 406067410/43228/1.1.1./1 | L44: 7BF69DE1-9EA3-4EAE-9713-910380F15356 | M44: Kleemann Pekini | 1.1.1. (+) შემოსავალი ლიფტების რეალიზაციიდან | სითი რეალ ისთეით (ს.კ. 406067410) - შპს | N44: B59170EC-16CC-499A-9FF7-0428DCB8F727 | O44: 04B265BA-02B2-4620-87C1-1D9CA09C8962 | Q44: gio.nikabadze@gmail.com
A45: 44182.056 | B45: ანაგი (ს.კ. 245416401) - შპს | C45: Gudauri Alpic | D45: 1.1.1. (+) შემოსავალი ლიფტების რეალიზაციიდან | E45: 43732 | F45: 81000 | G45: USD | H45: მიმდინარე | K45: 245416401/43732/1.1.1./1 | L45: 56B157A4-78FF-42DD-B032-B267792BBED8 | M45: Gudauri Alpic | 1.1.1. (+) შემოსავალი ლიფტების რეალიზაციიდან | ანაგი (ს.კ. 245416401) - შპს | N45: B59170EC-16CC-499A-9FF7-0428DCB8F727 | O45: 7DDF7E55-92EE-4E47-9E16-F1D4D3FABF60 | Q45: gio.nikabadze@gmail.com
A46: 44182.056 | B46: ანაგი (ს.კ. 245416401) - შპს | C46: Batumi Stadium | D46: 1.1.1. (+) შემოსავალი ლიფტების რეალიზაციიდან | E46: 43589 | F46: 139932.66 | G46: USD | H46: მიმდინარე | K46: 245416401/43589/1.1.1./1 | L46: 8A712C8E-EE09-4385-8E22-3C7E70676923 | M46: Batumi Stadium | 1.1.1. (+) შემოსავალი ლიფტების რეალიზაციიდან | ანაგი (ს.კ. 245416401) - შპს | N46: B59170EC-16CC-499A-9FF7-0428DCB8F727 | O46: 7DDF7E55-92EE-4E47-9E16-F1D4D3FABF60 | Q46: gio.nikabadze@gmail.com
A47: 44182.056 | B47: დეველოპერული კომპანია მც კვადრატი (ს.კ. 404474403) - შპს | C47: Gazapkhuli | D47: 1.1.2. (+) შემოსავალი ლიფტების სერვისიდან - გეგმიური | E47: 43831 | F47: 100 | G47: GEL | H47: მიმდინარე | K47: 404474403/43831/1.1.2./1 | L47: F487D937-85D8-43B1-8D4D-27757BC0BE36 | M47: Gazapkhuli | 1.1.2. (+) შემოსავალი ლიფტების სერვისიდან - გეგმიური | დეველოპერული კომპანია მც კვადრატი (ს.კ. 404474403) - შპს | N47: 12238130-9D12-4099-A48B-9EB5A085E0F8 | O47: EC22924D-9707-4BC1-9814-FD45570D704B | Q47: gio.nikabadze@gmail.com
A48: 44182.056 | B48: თერმორუმი (ს.კ. 405134448) - შპს | C48: Thermoroom | D48: 1.1.1. (+) შემოსავალი ლიფტების რეალიზაციიდან | E48: 43546 | F48: 82900 | G48: USD | H48: მიმდინარე | K48: 405134448/43546/1.1.1./1 | L48: 554B8399-3687-4503-A8C9-12E3BBDE60E9 | M48: Thermoroom | 1.1.1. (+) შემოსავალი ლიფტების რეალიზაციიდან | თერმორუმი (ს.კ. 405134448) - შპს | N48: B59170EC-16CC-499A-9FF7-0428DCB8F727 | O48: A71E107A-D0C2-4155-83C0-22DCD22BD19F | Q48: gio.nikabadze@gmail.com
A49: 44182.056 | B49: ტექნოკლიმა (ს.კ. 402009857) - შპს | C49: ENCORE Gudauri | D49: 1.1.1. (+) შემოსავალი ლიფტების რეალიზაციიდან | E49: 43711 | F49: 180540 | G49: EUR | H49: მიმდინარე | K49: 402009857/43711/1.1.1./1 | L49: 165277AE-3A0C-494C-8C92-CC3A68C15375 | M49: ENCORE Gudauri | 1.1.1. (+) შემოსავალი ლიფტების რეალიზაციიდან | ტექნოკლიმა (ს.კ. 402009857) - შპს | N49: B59170EC-16CC-499A-9FF7-0428DCB8F727 | O49: 967D325E-9818-4D9E-8716-3D66A117AF42 | Q49: gio.nikabadze@gmail.com
A50: 44182.056 | B50: ჯი-ემ-თი სასტუმროები (ს.კ. 203842333) - შპს | C50: MOXY HVAC | D50: 1.2.1. (+) შემოსავალი MEP დანადგარების რეალიზაციიდან | E50: 43124 | F50: 416156.43 | G50: USD | H50: მიმდინარე | K50: 203842333/43124/1.2.1./1 | L50: C78D3D45-B3FB-4533-AE2E-53D8A5FA6C34 | M50: MOXY HVAC | 1.2.1. (+) შემოსავალი MEP დანადგარების რეალიზაციიდან | ჯი-ემ-თი სასტუმროები (ს.კ. 203842333) - შპს | N50: FEA4B88F-633F-4422-B3D6-250792A2DA80 | O50: 9E3145B1-F47E-49C3-BF51-BCB9055ABC20 | Q50: gio.nikabadze@gmail.com
A51: 44182.056 | B51: 1920 (ს.კ. 400247899) - შპს | C51: Paster Hostel | D51: 1.1.1. (+) შემოსავალი ლიფტების რეალიზაციიდან | E51: 43571 | F51: 36200 | G51: USD | H51: მიმდინარე | K51: 400247899/43571/1.1.1./1 | L51: 59251EDF-2EEC-4871-ADAA-D7901FD7C84E | M51: Paster Hostel | 1.1.1. (+) შემოსავალი ლიფტების რეალიზაციიდან | 1920 (ს.კ. 400247899) - შპს | N51: B59170EC-16CC-499A-9FF7-0428DCB8F727 | O51: 30D1E20E-3889-4EAC-883A-6509ABFFA5D7 | Q51: gio.nikabadze@gmail.com
A52: 44182.056 | B52: გოჩა ჩხაიძე (ს.კ. 65002012107) - ფიზ. პირი | C52: Kaklebi | D52: 1.1.1. (+) შემოსავალი ლიფტების რეალიზაციიდან | E52: 43566 | F52: 37760 | G52: USD | H52: მიმდინარე | K52: 65002012107/43566/1.1.1./1 | L52: BCE7664A-F047-41AD-8D93-756E595D21F6 | M52: Kaklebi | 1.1.1. (+) შემოსავალი ლიფტების რეალიზაციიდან | გოჩა ჩხაიძე (ს.კ. 65002012107) - ფიზ. პირი | N52: B59170EC-16CC-499A-9FF7-0428DCB8F727 | O52: B658F42E-3F0A-44A3-B4ED-A7B4C1D8DEAE | Q52: gio.nikabadze@gmail.com
A53: 44182.056 | B53: სვირი + (ს.კ. 212916932) - შპს | C53: 156-ე საჯარო სკოლა | D53: 1.1.1. (+) შემოსავალი ლიფტების რეალიზაციიდან | E53: 43861 | F53: 8900 | G53: USD | H53: მიმდინარე | K53: 212916932/43861/1.1.1./1 | L53: 6E5F6760-7CEF-41CD-B373-B0F3B4EABCCA | M53: 156-ე საჯარო სკოლა | 1.1.1. (+) შემოსავალი ლიფტების რეალიზაციიდან | სვირი + (ს.კ. 212916932) - შპს | N53: B59170EC-16CC-499A-9FF7-0428DCB8F727 | O53: E0680301-116E-4D99-93F4-7C694EC80172 | Q53: gio.nikabadze@gmail.com
... A66: 44182.057 | B66: Dar Building (ს.კ. 445420875) - შპს | C66: OFFICE Dar Building | D66: 1.1.1. (+) შემოსავალი ლიფტების რეალიზაციიდან | E66: 44170 | F66: 20800 | G66: USD | H66: მიმდინარე | K66: 445420875/44170/1.1.1./1 | L66: E3FEF6DB-0C48-4832-A5CF-868EF7B591A4 | M66: OFFICE Dar Building | 1.1.1. (+) შემოსავალი ლიფტების რეალიზაციიდან | Dar Building (ს.კ. 445420875) - შპს | N66: B59170EC-16CC-499A-9FF7-0428DCB8F727 | O66: 7BF4A039-29BC-44AC-A87D-E8832394B94E | Q66: gio.nikabadze@gmail.com
A67: 44182.057 | B67: ანაგი (ს.კ. 245416401) - შპს | C67: Archi Digomi | D67: 1.1.1. (+) შემოსავალი ლიფტების რეალიზაციიდან | E67: 43955 | F67: 107760 | G67: USD | H67: მიმდინარე | J67: 1 6 30 1132 3 | K67: 245416401/43955/1.1.1./1 | L67: A68BEF97-923B-4D3C-8A08-9CF9311578B7 | M67: Archi Digomi | 1.1.1. (+) შემოსავალი ლიფტების რეალიზაციიდან | ანაგი (ს.კ. 245416401) - შპს | N67: B59170EC-16CC-499A-9FF7-0428DCB8F727 | O67: 7DDF7E55-92EE-4E47-9E16-F1D4D3FABF60 | Q67: gio.nikabadze@gmail.com
A68: 44182.057 | B68: Spanish Retail Georgia (ს.კ. 404404774) - შპს | C68: Zara City Mall | D68: 1.1.2. (+) შემოსავალი ლიფტების სერვისიდან - გეგმიური | E68: 43800 | F68: 1800 | G68: GEL | H68: მიმდინარე | K68: 404404774/43800/1.1.2./1 | L68: 5D93EA98-C1B5-460B-B2FB-C526651B3F64 | M68: Zara City Mall | 1.1.2. (+) შემოსავალი ლიფტების სერვისიდან - გეგმიური | Spanish Retail Georgia (ს.კ. 404404774) - შპს | N68: 12238130-9D12-4099-A48B-9EB5A085E0F8 | O68: 6DF25574-2F03-43D0-AEC4-2CD26A4A0C3A | Q68: gio.nikabadze@gmail.com
A69: 44182.057 | B69: გალერია ჰოტელ მენეჯმენტი (ს.კ. 404567508) - შპს | C69: Galleria Hotel | D69: 1.1.2. (+) შემოსავალი ლიფტების სერვისიდან - გეგმიური | E69: 43617 | F69: 300 | G69: USD | H69: მიმდინარე | K69: 404567508/43617/1.1.2./1 | L69: 7A62FB55-149C-4A13-B506-1117D0761263 | M69: Galleria Hotel | 1.1.2. (+) შემოსავალი ლიფტების სერვისიდან - გეგმიური | გალერია ჰოტელ მენეჯმენტი (ს.კ. 404567508) - შპს | N69: 12238130-9D12-4099-A48B-9EB5A085E0F8 | O69: 75C62470-4093-4FB3-8DB7-F700FEC2C222 | Q69: gio.nikabadze@gmail.com
A70: 44182.057 | B70: ერა პალასი (ს.კ. 245619807) - შპს | C70: Era Palace | D70: 1.1.2. (+) შემოსავალი ლიფტების სერვისიდან - გეგმიური | E70: 43586 | F70: 200 | G70: GEL | H70: მიმდინარე | K70: 245619807/43586/1.1.2./1 | L70: 75411B5D-3913-49E0-B5A6-48ED0D4EEBB6 | M70: Era Palace | 1.1.2. (+) შემოსავალი ლიფტების სერვისიდან - გეგმიური | ერა პალასი (ს.კ. 245619807) - შპს | N70: 12238130-9D12-4099-A48B-9EB5A085E0F8 | O70: 71A96223-5CD1-4DA9-9617-A85A565B4669 | Q70: gio.nikabadze@gmail.com
A71: 44182.057 | B71: თბილი სახლი (ს.კ. 204976179) - შპს | C71: Muzeums | D71: 1.1.2. (+) შემოსავალი ლიფტების სერვისიდან - გეგმიური | E71: 43497 | F71: 750 | G71: GEL | H71: მიმდინარე | K71: 204976179/43497/1.1.2./1 | L71: 9D27243C-D81D-4430-90C4-5F8CCBF5809F | M71: Muzeums | 1.1.2. (+) შემოსავალი ლიფტების სერვისიდან - გეგმიური | თბილი სახლი (ს.კ. 204976179) - შპს | N71: 12238130-9D12-4099-A48B-9EB5A085E0F8 | O71: 726D9023-53A2-435E-8A5B-8BCEA9625E08 | Q71: gio.nikabadze@gmail.com
A72: 44182.057 | B72: იუნიქს ქონსთრაქშენ კომპანი (ს.კ. 405133822) - შპს | C72: UNIX Ipolit Ivanov | D72: 1.1.2. (+) შემოსავალი ლიფტების სერვისიდან - გეგმიური | E72: 43539 | F72: 1500 | G72: GEL | H72: მიმდინარე | K72: 405133822/43539/1.1.2./1 | L72: 4C7A7F0C-187C-4D2B-857D-A522EE632F24 | M72: UNIX Ipolit Ivanov | 1.1.2. (+) შემოსავალი ლიფტების სერვისიდან - გეგმიური | იუნიქს ქონსთრაქშენ კომპანი (ს.კ. 405133822) - შპს | N72: 12238130-9D12-4099-A48B-9EB5A085E0F8 | O72: B4968862-3843-414D-9E73-1A7611618B41 | Q72: gio.nikabadze@gmail.com
A73: 44182.057 | B73: პიქსელ მენეჯმენტი (ს.კ. 404862314) - შპს | C73: PIXEL | D73: 1.1.2. (+) შემოსავალი ლიფტების სერვისიდან - გეგმიური | E73: 43435 | F73: 1645 | G73: USD | H73: მიმდინარე | K73: 404862314/43435/1.1.2./1 | L73: 5485535C-2F61-456A-9548-E6F7EE885A7B | M73: PIXEL | 1.1.2. (+) შემოსავალი ლიფტების სერვისიდან - გეგმიური | პიქსელ მენეჯმენტი (ს.კ. 404862314) - შპს | N73: 12238130-9D12-4099-A48B-9EB5A085E0F8 | O73: 42A1D3CC-F7CD-4EC1-A425-6E261EB22EBC | Q73: gio.nikabadze@gmail.com
A74: 44182.057 | B74: დავუდ (ს.კ. 404438417) - სს | C74: Khetagurov Office | D74: 1.1.2. (+) შემოსავალი ლიფტების სერვისიდან - გეგმიური | E74: 43462 | F74: 1000 | G74: GEL | H74: მიმდინარე | K74: 404438417/43462/1.1.2./1 | L74: 1937421D-0C5D-47B3-84E7-F06B2CECE212 | M74: Khetagurov Office | 1.1.2. (+) შემოსავალი ლიფტების სერვისიდან - გეგმიური | დავუდ (ს.კ. 404438417) - სს | N74: 12238130-9D12-4099-A48B-9EB5A085E0F8 | O74: 059C7B48-86B5-4FB3-AF87-564E29C595E9 | Q74: gio.nikabadze@gmail.com
A75: 44182.057 | B75: თბილი სახლი (ს.კ. 204976179) - შპს | C75: Galleria Tbilisi | D75: 1.1.2. (+) შემოსავალი ლიფტების სერვისიდან - გეგმიური | E75: 43862 | F75: 1 | G75: GEL | H75: მიმდინარე | J75: 1 6 31 4 1 | K75: 204976179/43862/1.1.2./1 | L75: 0ABCF801-1738-4393-BF70-87C1FA8C9F0D | M75: Galleria Tbilisi | 1.1.2. (+) შემოსავალი ლიფტების სერვისიდან - გეგმიური | თბილი სახლი (ს.კ. 204976179) - შპს | N75: 12238130-9D12-4099-A48B-9EB5A085E0F8 | O75: 726D9023-53A2-435E-8A5B-8BCEA9625E08 | Q75: gio.nikabadze@gmail.com
A76: 44182.057 | B76: თბილისი ცენტრალი (ს.კ. 205129653) - სს | C76: Tbilisi Central HVAC Service | D76: 1.2.2. (+) შემოსავალი MEP დანადგარების სერვისიდან - გეგმიური | E76: 44075 | F76: 1 | G76: GEL | H76: მიმდინარე | J76: 1 6 31 1371 | K76: 205129653/44075/1.2.2./1 | L76: F2EB27A3-4AED-4096-AF24-4B7A9C4512A7 | M76: Tbilisi Central HVAC Service | 1.2.2. (+) შემოსავალი MEP დანადგარების სერვისიდან - გეგმიური | თბილისი ცენტრალი (ს.კ. 205129653) - სს | N76: 31562B13-85C8-472E-8D02-01D802D635C1 | O76: 3D0B2E19-A7F7-45A1-A329-05C7D5F99C8A | Q76: gio.nikabadze@gmail.com
A77: 44182.057 | B77: ნინო კირცხალია (ს.კ. 01031005362) - ფიზ. პირი | C77: Mziuri | D77: 1.1.2. (+) შემოსავალი ლიფტების სერვისიდან - გეგმიური | E77: 43831 | F77: 1 | G77: GEL | H77: მიმდინარე | K77: 01031005362/43831/1.1.2./1 | L77: 7D93AE81-A3AA-4EF2-A79C-0DE309E1B402 | M77: Mziuri | 1.1.2. (+) შემოსავალი ლიფტების სერვისიდან - გეგმიური | ნინო კირცხალია (ს.კ. 01031005362) - ფიზ. პირი | N77: 12238130-9D12-4099-A48B-9EB5A085E0F8 | O77: A5C53B51-103C-4B24-B833-6653108CDE4E | Q77: gio.nikabadze@gmail.com
A78: 44182.057 | B78: ორბი ჯგუფი ბათუმი (ს.კ. 445468798) - შპს | C78: Orbi Other | D78: 1.1.2. (+) შემოსავალი ლიფტების სერვისიდან - გეგმიური | E78: 43831 | F78: 1 | G78: GEL | H78: მიმდინარე | K78: 445468798/43831/1.1.2./1 | L78: DCE1FBA2-AC1D-4481-B551-0D2215188884 | M78: Orbi Other | 1.1.2. (+) შემოსავალი ლიფტების სერვისიდან - გეგმიური | ორბი ჯგუფი ბათუმი (ს.კ. 445468798) - შპს | N78: 12238130-9D12-4099-A48B-9EB5A085E0F8 | O78: E284E0FD-A2B7-4D93-8E91-006FF0A8A4CE | Q78: gio.nikabadze@gmail.com
A79: 44182.057 | B79: ნირან პროპერტის დეველოპმენტი (ს.კ. 204564729) - შპს | C79: Bagebi | D79: 1.1.1. (+) შემოსავალი ლიფტების რეალიზაციიდან | E79: 43122 | F79: 132998 | G79: USD | H79: მიმდინარე | K79: 204564729/43122/1.1.1./1 | L79: DA0DFA6D-FB59-42CC-A78F-D211EFD8F169 | M79: Bagebi | 1.1.1. (+) შემოსავალი ლიფტების რეალიზაციიდან | ნირან პროპერტის დეველოპმენტი (ს.კ. 204564729) - შპს | N79: B59170EC-16CC-499A-9FF7-0428DCB8F727 | O79: ADBD14C7-72E2-4703-84A5-B47EC0ACB641 | Q79: gio.nikabadze@gmail.com
A80: 44182.057 | B80: ეიჩ ენდ ემ ჰენეს ენდ მაურიც ჯორჯია (ს.კ. 405164192) - შპს | C80: H&M | D80: 1.1.2. (+) შემოსავალი ლიფტების სერვისიდან - გეგმიური | E80: 43831 | F80: 1 | G80: GEL | H80: მიმდინარე | K80: 405164192/43831/1.1.2./1 | L80: BF531404-15D2-4F83-B5B6-88709B6ADBF6 | M80: H&M | 1.1.2. (+) შემოსავალი ლიფტების სერვისიდან - გეგმიური | ეიჩ ენდ ემ ჰენეს ენდ მაურიც ჯორჯია (ს.კ. 405164192) - შპს | N80: 12238130-9D12-4099-A48B-9EB5A085E0F8 | O80: 5569F396-B588-4816-B115-348127388797 | Q80: gio.nikabadze@gmail.com
A81: 44182.057 | B81: ჯი ემ ემ (ს.კ. 405115174) - შპს | C81: Marshal Gelovanis 52 | D81: 1.1.2. (+) შემოსავალი ლიფტების სერვისიდან - გეგმიური | E81: 43831 | F81: 1 | G81: GEL | H81: მიმდინარე | K81: 405115174/43831/1.1.2./1 | L81: 96631073-7C4A-4C6C-B52A-4318B544C05B | M81: Marshal Gelovanis 52 | 1.1.2. (+) შემოსავალი ლიფტების სერვისიდან - გეგმიური | ჯი ემ ემ (ს.კ. 405115174) - შპს | N81: 12238130-9D12-4099-A48B-9EB5A085E0F8 | O81: E6DBF0EF-BE8A-403C-B757-246FDF95B244 | Q81: gio.nikabadze@gmail.com
A82: 44182.057 | B82: ოლსერვისგრუპ (ს.კ. 406233552) - შპს | C82: Marshal Gelovani 52 | D82: 1.1.2. (+) შემოსავალი ლიფტების სერვისიდან - გეგმიური | E82: 43466 | F82: 1200 | G82: GEL | H82: მიმდინარე | K82: 406233552/43466/1.1.2./1 | L82: 46C2E29A-C8A7-4F32-BAC6-1FA5D9731A7D | M82: Marshal Gelovani 52 | 1.1.2. (+) შემოსავალი ლიფტების სერვისიდან - გეგმიური | ოლსერვისგრუპ (ს.კ. 406233552) - შპს | N82: 12238130-9D12-4099-A48B-9EB5A085E0F8 | O82: C08C6F90-5808-41D5-A1CC-2A1CCFAF531B | Q82: gio.nikabadze@gmail.com
A83: 44182.057 | B83: ოლსერვისჯგუფი (ს.კ. 406269041) - შპს | C83: Marshal Gelovani 52 | D83: 1.1.2. (+) შემოსავალი ლიფტების სერვისიდან - გეგმიური | E83: 43471 | F83: 10 | G83: GEL | H83: მიმდინარე | K83: 406269041/43471/1.1.2./1 | L83: 4DE1AF55-BD4D-49EA-9CC2-7254972C4832 | M83: Marshal Gelovani 52 | 1.1.2. (+) შემოსავალი ლიფტების სერვისიდან - გეგმიური | ოლსერვისჯგუფი (ს.კ. 406269041) - შპს | N83: 12238130-9D12-4099-A48B-9EB5A085E0F8 | O83: F830C37E-1BED-416F-996D-C3C709C5F339 | Q83: gio.nikabadze@gmail.com
A84: 44182.057 | B84: არქი საბურთალო (ს.კ. 405176982) - შპს | C84: Archi Jikia Block C | D84: 1.1.1. (+) შემოსავალი ლიფტების რეალიზაციიდან | E84: 44170 | F84: 136600 | G84: USD | H84: მიმდინარე | J84: 1 6 30 1453 | K84: 405176982/44170/1.1.1./1 | L84: 7F8895E0-BD86-4959-A763-AD1CD0F7FC77 | M84: Archi Jikia Block C | 1.1.1. (+) შემოსავალი ლიფტების რეალიზაციიდან | არქი საბურთალო (ს.კ. 405176982) - შპს | N84: B59170EC-16CC-499A-9FF7-0428DCB8F727 | O84: 25CECFAB-615A-4A1E-AC57-B18B8A92799B | Q84: gio.nikabadze@gmail.com
A85: 44182.057 | B85: შატო მუხრანი (ს.კ. 205000381) - სს | C85: Shato Mukhrani Gen-Set 2020 | D85: 1.2.1. (+) შემოსავალი MEP დანადგარების რეალიზაციიდან | E85: 43990 | F85: 55680 | G85: EUR | H85: მიმდინარე | K85: 205000381/43990/1.2.1./1 | L85: 798DCBA8-C0CF-4CAA-83E5-397FD911AAF0 | M85: Shato Mukhrani Gen-Set 2020 | 1.2.1. (+) შემოსავალი MEP დანადგარების რეალიზაციიდან | შატო მუხრანი (ს.კ. 205000381) - სს | N85: FEA4B88F-633F-4422-B3D6-250792A2DA80 | O85: 0E3C8876-D73B-417A-A61E-5FD08F98EDCB | Q85: gio.nikabadze@gmail.com
A86: 44182.057 | B86: ენსოლი (ს.კ. 205236190) - შპს | C86: Galleria Tbilisi | D86: 1.1.2. (+) შემოსავალი ლიფტების სერვისიდან - გეგმიური | E86: 43497 | F86: 3500 | G86: USD | H86: მიმდინარე | K86: 205236190/43497/1.1.2./1 | L86: 1BF0C1A7-EC4F-48F6-B5F1-6257BAB8D882 | M86: Galleria Tbilisi | 1.1.2. (+) შემოსავალი ლიფტების სერვისიდან - გეგმიური | ენსოლი (ს.კ. 205236190) - შპს | N86: 12238130-9D12-4099-A48B-9EB5A085E0F8 | O86: E13FA661-3B3D-437A-A26D-FB16D4C0D1C1 | Q86: gio.nikabadze@gmail.com
A87: 44182.057 | B87: დომუსი (ს.კ. 404908864) - შპს | C87: Domus | D87: 1.1.2. (+) შემოსავალი ლიფტების სერვისიდან - გეგმიური | E87: 43146 | F87: 1400 | G87: USD | H87: მიმდინარე | K87: 404908864/43146/1.1.2./1 | L87: 4E9E5103-4BE9-4B72-838F-7CCF0A771578 | M87: Domus | 1.1.2. (+) შემოსავალი ლიფტების სერვისიდან - გეგმიური | დომუსი (ს.კ. 404908864) - შპს | N87: 12238130-9D12-4099-A48B-9EB5A085E0F8 | O87: B6B26BE3-174A-4141-A509-B6EE28D4677B | Q87: gio.nikabadze@gmail.com
A88: 44182.057 | B88: როვშან მამადოვი (ს.კ. 67008001418) - ფიზ. პირი | C88: Rovshan Mamadovi | D88: 1.2.1. (+) შემოსავალი MEP დანადგარების რეალიზაციიდან | E88: 43999 | F88: 8214 | G88: USD | H88: მიმდინარე | K88: 67008001418/43999/1.2.1./1 | L88: 97C6ECBA-DA0F-4E2C-B8DB-26993DFCE122 | M88: Rovshan Mamadovi | 1.2.1. (+) შემოსავალი MEP დანადგარების რეალიზაციიდან | როვშან მამადოვი (ს.კ. 67008001418) - ფიზ. პირი | N88: FEA4B88F-633F-4422-B3D6-250792A2DA80 | O88: 3E3BB97B-230C-48D5-B6EF-41C9AE93AE61 | Q88: gio.nikabadze@gmail.com
A89: 44182.057 | B89: თბილი სახლი (ს.კ. 204976179) - შპს | C89: Sapatrulo | D89: 1.1.2. (+) შემოსავალი ლიფტების სერვისიდან - გეგმიური | E89: 43497 | F89: 250 | G89: GEL | H89: მიმდინარე | K89: 204976179/43497/1.1.2./1 | L89: 8BDDF5BD-4A6B-4C8E-942A-C62E20BCD667 | M89: Sapatrulo | 1.1.2. (+) შემოსავალი ლიფტების სერვისიდან - გეგმიური | თბილი სახლი (ს.კ. 204976179) - შპს | N89: 12238130-9D12-4099-A48B-9EB5A085E0F8 | O89: 726D9023-53A2-435E-8A5B-8BCEA9625E08 | Q89: gio.nikabadze@gmail.com
A90: 44182.057 | B90: თბილი სახლი (ს.კ. 204976179) - შპს | C90: Erovnuli | D90: 1.1.2. (+) შემოსავალი ლიფტების სერვისიდან - გეგმიური | E90: 43497 | F90: 500 | G90: GEL | H90: მიმდინარე | K90: 204976179/43497/1.1.2./1 | L90: ED933289-CEA4-446C-99AC-B1B310C1ECB5 | M90: Erovnuli | 1.1.2. (+) შემოსავალი ლიფტების სერვისიდან - გეგმიური | თბილი სახლი (ს.კ. 204976179) - შპს | N90: 12238130-9D12-4099-A48B-9EB5A085E0F8 | O90: 726D9023-53A2-435E-8A5B-8BCEA9625E08 | Q90: gio.nikabadze@gmail.com
A91: 44182.057 | B91: ერა პალასი (ს.კ. 245619807) - შპს | C91: Gonio | D91: 1.1.2. (+) შემოსავალი ლიფტების სერვისიდან - გეგმიური | E91: 43617 | F91: 300 | G91: GEL | H91: მიმდინარე | K91: 245619807/43617/1.1.2./1 | L91: 3D3A6BA2-FC37-4C7B-9979-9C6C932BA9BF | M91: Gonio | 1.1.2. (+) შემოსავალი ლიფტების სერვისიდან - გეგმიური | ერა პალასი (ს.კ. 245619807) - შპს | N91: 12238130-9D12-4099-A48B-9EB5A085E0F8 | O91: 71A96223-5CD1-4DA9-9617-A85A565B4669 | Q91: gio.nikabadze@gmail.com
A92: 44182.057 | B92: მოდუსი (ს.კ. 245565669) - შპს | C92: Modus batumi | D92: 1.1.2. (+) შემოსავალი ლიფტების სერვისიდან - გეგმიური | E92: 43592 | F92: 400 | G92: GEL | H92: მიმდინარე | K92: 245565669/43592/1.1.2./1 | L92: 07BBF564-E19D-46EA-8A32-44F28241B4B1 | M92: Modus batumi | 1.1.2. (+) შემოსავალი ლიფტების სერვისიდან - გეგმიური | მოდუსი (ს.კ. 245565669) - შპს | N92: 12238130-9D12-4099-A48B-9EB5A085E0F8 | O92: 9729C88B-F3C5-441A-8782-0656302A37F2 | Q92: gio.nikabadze@gmail.com
A93: 44182.057 | B93: ი. აბაშიძე 70 (ს.კ. ICE001082) - ამხანაგობა | C93: Abashidze 70 | D93: 1.1.2. (+) შემოსავალი ლიფტების სერვისიდან - გეგმიური | E93: 44013 | F93: 3000 | G93: GEL | H93: მიმდინარე | K93: ICE001082/44013/1.1.2./1 | L93: AFEF3A3A-0240-4773-9C5F-B7AC3C14711D | M93: Abashidze 70 | 1.1.2. (+) შემოსავალი ლიფტების სერვისიდან - გეგმიური | ი. აბაშიძე 70 (ს.კ. ICE001082) - ამხანაგობა | N93: 12238130-9D12-4099-A48B-9EB5A085E0F8 | O93: 3D0E73E0-0C40-467D-922F-74E3D4746FBD | Q93: gio.nikabadze@gmail.com
A94: 44182.057 | B94: დელისი 2020 (ს.კ. ICE001083) - ამხანაგობა | C94: Epic gazapkhuli | D94: 1.1.2. (+) შემოსავალი ლიფტების სერვისიდან - გეგმიური | E94: 44014 | F94: 500 | G94: GEL | H94: მიმდინარე | K94: ICE001083/44014/1.1.2./1 | L94: F132898D-4C52-4676-8689-21E7C2709157 | M94: Epic gazapkhuli | 1.1.2. (+) შემოსავალი ლიფტების სერვისიდან - გეგმიური | დელისი 2020 (ს.კ. ICE001083) - ამხანაგობა | N94: 12238130-9D12-4099-A48B-9EB5A085E0F8 | O94: E18CBC98-9D65-4F4A-ADC0-B7350770D6F8 | Q94: gio.nikabadze@gmail.com
A95: 44182.057 | B95: ბაგები (ს.კ. 405330262) - შპს | C95: Epic Bagebi | D95: 1.1.1. (+) შემოსავალი ლიფტების რეალიზაციიდან | E95: 44013 | F95: 48000 | G95: USD | H95: მიმდინარე | J95: 1 6 30 1471 | K95: 405330262/44013/1.1.1./1 | L95: 6F71BE16-57C6-4634-B19B-DAD451C7CB11 | M95: Epic Bagebi | 1.1.1. (+) შემოსავალი ლიფტების რეალიზაციიდან | ბაგები (ს.კ. 405330262) - შპს | N95: B59170EC-16CC-499A-9FF7-0428DCB8F727 | O95: C270A903-5EB0-4E5A-8448-B4A637D5211F | Q95: gio.nikabadze@gmail.com
A96: 44182.057 | B96: მეპერსი (ს.კ. 402121887) - შპს | C96: Hilton Garden Inn Pipes 2 | D96: 1.2.1. (+) შემოსავალი MEP დანადგარების რეალიზაციიდან | E96: 43983 | F96: 4580.94 | G96: USD | H96: მიმდინარე | K96: 402121887/43983/1.2.1./1 | L96: 53D78126-348D-47EC-8E18-ACA366D918B3 | M96: Hilton Garden Inn Pipes 2 | 1.2.1. (+) შემოსავალი MEP დანადგარების რეალიზაციიდან | მეპერსი (ს.კ. 402121887) - შპს | N96: FEA4B88F-633F-4422-B3D6-250792A2DA80 | O96: 43EABC78-AF64-4C14-9FEF-C7E6A1B6F07E | Q96: gio.nikabadze@gmail.com
A97: 44182.057 | B97: თეგეტა მოტორსი (ს.კ. 202177205) - შპს | C97: Tegeta Batumi | D97: 1.1.2. (+) შემოსავალი ლიფტების სერვისიდან - გეგმიური | E97: 44013 | F97: 1 | G97: GEL | H97: მიმდინარე | K97: 202177205/44013/1.1.2./1 | L97: 065B3CAD-864E-4949-AE0A-9170B8973736 | M97: Tegeta Batumi | 1.1.2. (+) შემოსავალი ლიფტების სერვისიდან - გეგმიური | თეგეტა მოტორსი (ს.კ. 202177205) - შპს | N97: 12238130-9D12-4099-A48B-9EB5A085E0F8 | O97: 5A21C207-4868-4EA6-9B48-5D0F743D5535 | Q97: gio.nikabadze@gmail.com
A98: 44182.057 | B98: საქ სამეცნიერო-საგანმანათ. კომპ ქსელების ასოციაცია გრენა (ს.კ. 204931654) - ასოციაცია | C98: Grena MEP 1 | D98: 1.2.1. (+) შემოსავალი MEP დანადგარების რეალიზაციიდან | E98: 44004 | F98: 9885 | G98: GEL | H98: მიმდინარე | K98: 204931654/44004/1.2.1./1 | L98: 67800432-96FF-489A-983A-99BD3F4C4954 | M98: Grena MEP 1 | 1.2.1. (+) შემოსავალი MEP დანადგარების რეალიზაციიდან | საქ სამეცნიერო-საგანმანათ. კომპ ქსელების ასოციაცია გრენა (ს.კ. 204931654) - ასოციაცია | N98: FEA4B88F-633F-4422-B3D6-250792A2DA80 | O98: 43A2E6CF-382D-45D9-9C82-D074B7CA8474 | Q98: gio.nikabadze@gmail.com
A99: 44182.057 | B99: ახალშენი 2016 (ს.კ. 405136758) - შპს | C99: Khiliani | D99: 1.1.2. (+) შემოსავალი ლიფტების სერვისიდან - გეგმიური | E99: 43891 | F99: 1 | G99: GEL | H99: მიმდინარე | K99: 405136758/43891/1.1.2./1 | L99: AB270374-C6A2-4223-A667-ED4DD185CC7F | M99: Khiliani | 1.1.2. (+) შემოსავალი ლიფტების სერვისიდან - გეგმიური | ახალშენი 2016 (ს.კ. 405136758) - შპს | N99: 12238130-9D12-4099-A48B-9EB5A085E0F8 | O99: 04FB28EA-5501-4B01-BA1D-C2955C0E1213 | Q99: gio.nikabadze@gmail.com
A100: 44182.057 | B100: ფალიაშვილის 63 (ს.კ. ICE000034) - ამხანაგობა | C100: Domus Paliashvilis 63 | D100: 1.1.2. (+) შემოსავალი ლიფტების სერვისიდან - გეგმიური | E100: 44019 | F100: 1 | G100: GEL | H100: მიმდინარე | K100: ICE000034/44019/1.1.2./1 | L100: D1923AD8-5716-4970-9AD0-37642D2C4B69 | M100: Domus Paliashvilis 63 | 1.1.2. (+) შემოსავალი ლიფტების სერვისიდან - გეგმიური | ფალიაშვილის 63 (ს.კ. ICE000034) - ამხანაგობა | N100: 12238130-9D12-4099-A48B-9EB5A085E0F8 | O100: 7F0A41E4-FA68-43E7-A979-126560D14B58 | Q100: gio.nikabadze@gmail.com
A101: 44182.057 | B101: ინდეკო (ს.კ. 202376133) - შპს | C101: Indeko - shartava 39 | D101: 1.1.2. (+) შემოსავალი ლიფტების სერვისიდან - გეგმიური | E101: 43102 | F101: 1 | G101: GEL | H101: მიმდინარე | K101: 202376133/43102/1.1.2./1 | L101: 36DA9AC9-FD85-4E9B-B6AF-0CFCDD8E7D93 | M101: Indeko - shartava 39 | 1.1.2. (+) შემოსავალი ლიფტების სერვისიდან - გეგმიური | ინდეკო (ს.კ. 202376133) - შპს | N101: 12238130-9D12-4099-A48B-9EB5A085E0F8 | O101: 8E8E99BE-75FC-49EC-9D89-960E30E7CB06 | Q101: gio.nikabadze@gmail.com
A102: 44182.057 | B102: დომუს სერვისი (ს.კ. 405311336) - შპს | C102: Domus | D102: 1.1.2. (+) შემოსავალი ლიფტების სერვისიდან - გეგმიური | E102: 43647 | F102: 1 | G102: USD | H102: მიმდინარე | K102: 405311336/43647/1.1.2./1 | L102: 576EC610-01F5-4D9B-9A18-3AE87057BAE9 | M102: Domus | 1.1.2. (+) შემოსავალი ლიფტების სერვისიდან - გეგმიური | დომუს სერვისი (ს.კ. 405311336) - შპს | N102: 12238130-9D12-4099-A48B-9EB5A085E0F8 | O102: 9B2B30F8-1FC4-427E-8478-DB1B57B48DDA | Q102: gio.nikabadze@gmail.com
A103: 44182.057 | B103: იუნიქს ქონსთრაქშენ კომპანი (ს.კ. 405133822) - შპს | C103: UNIX Marselle | D103: 1.1.2. (+) შემოსავალი ლიფტების სერვისიდან - გეგმიური | E103: 44013 | F103: 1 | G103: GEL | H103: მიმდინარე | K103: 405133822/44013/1.1.2./1 | L103: 91EE07CF-9713-420D-A132-7AEFD9A5F054 | M103: UNIX Marselle | 1.1.2. (+) შემოსავალი ლიფტების სერვისიდან - გეგმიური | იუნიქს ქონსთრაქშენ კომპანი (ს.კ. 405133822) - შპს | N103: 12238130-9D12-4099-A48B-9EB5A085E0F8 | O103: B4968862-3843-414D-9E73-1A7611618B41 | Q103: gio.nikabadze@gmail.com
A104: 44182.057 | B104: ბიზნეს ცენტრი დელისი (ს.კ. 204854014) - სს | C104: Delisi | D104: 1.1.2. (+) შემოსავალი ლიფტების სერვისიდან - გეგმიური | E104: 43831 | F104: 1 | G104: GEL | H104: მიმდინარე | K104: 204854014/43831/1.1.2./1 | L104: C01D4ADB-B292-4EAB-9036-EE74F4FB870D | M104: Delisi | 1.1.2. (+) შემოსავალი ლიფტების სერვისიდან - გეგმიური | ბიზნეს ცენტრი დელისი (ს.კ. 204854014) - სს | N104: 12238130-9D12-4099-A48B-9EB5A085E0F8 | O104: 62F6C15C-8FCC-4A60-B37E-8A3DE9D20A48 | Q104: gio.nikabadze@gmail.com
A105: 44182.057 | B105: მოდუსი (ს.კ. 245565669) - შპს | C105: Modus Kakhety HW | D105: 1.1.2. (+) შემოსავალი ლიფტების სერვისიდან - გეგმიური | E105: 43586 | F105: 1 | G105: GEL | H105: მიმდინარე | J105: 1 6 30 642 2 | K105: 245565669/43586/1.1.2./1 | L105: 2A0A1CC3-2FD5-4F5A-BF97-52EE5BDDE144 | M105: Modus Kakhety HW | 1.1.2. (+) შემოსავალი ლიფტების სერვისიდან - გეგმიური | მოდუსი (ს.კ. 245565669) - შპს | N105: 12238130-9D12-4099-A48B-9EB5A085E0F8 | O105: 9729C88B-F3C5-441A-8782-0656302A37F2 | Q105: gio.nikabadze@gmail.com
A106: 44182.057 | B106: BD Property (ს.კ. 404390967) - შპს | C106: Tbilisi Gardens | D106: 1.1.2. (+) შემოსავალი ლიფტების სერვისიდან - გეგმიური | E106: 43466 | F106: 1 | G106: USD | H106: მიმდინარე | K106: 404390967/43466/1.1.2./1 | L106: D3F209CC-BD48-4729-87EA-24F29DD15FF4 | M106: Tbilisi Gardens | 1.1.2. (+) შემოსავალი ლიფტების სერვისიდან - გეგმიური | BD Property (ს.კ. 404390967) - შპს | N106: 12238130-9D12-4099-A48B-9EB5A085E0F8 | O106: 97275D0F-23EB-47CD-8A0F-C93649EE6164 | Q106: gio.nikabadze@gmail.com
A107: 44182.057 | B107: გელა ხომერიკი (ს.კ. 33001011813) - ფიზ. პირი | C107: Kbuleti Str. - Khomeriki | D107: 1.1.2. (+) შემოსავალი ლიფტების სერვისიდან - გეგმიური | E107: 43132 | F107: 1 | G107: GEL | H107: მიმდინარე | K107: 33001011813/43132/1.1.2./1 | L107: 0172DB76-BF07-40C8-8007-921476501A04 | M107: Kbuleti Str. - Khomeriki | 1.1.2. (+) შემოსავალი ლიფტების სერვისიდან - გეგმიური | გელა ხომერიკი (ს.კ. 33001011813) - ფიზ. პირი | N107: 12238130-9D12-4099-A48B-9EB5A085E0F8 | O107: D92736A6-D9AA-4539-B5F8-0F34FACD5367 | Q107: gio.nikabadze@gmail.com
A108: 44182.057 | B108: თბილისი პალასი (ს.კ. 405253381) - შპს | C108: Tbilisi Palace | D108: 1.1.2. (+) შემოსავალი ლიფტების სერვისიდან - გეგმიური | E108: 43957 | F108: 1 | G108: GEL | H108: მიმდინარე | K108: 405253381/43957/1.1.2./1 | L108: 1322892A-5957-4D09-88EC-FC474E90B292 | M108: Tbilisi Palace | 1.1.2. (+) შემოსავალი ლიფტების სერვისიდან - გეგმიური | თბილისი პალასი (ს.კ. 405253381) - შპს | N108: 12238130-9D12-4099-A48B-9EB5A085E0F8 | O108: 3F5B4217-38D4-4FB8-B3F3-E856A10FFF06 | Q108: gio.nikabadze@gmail.com
A109: 44182.057 | B109: მოდუსი (ს.კ. 245565669) - შპს | C109: Modus Agladze | D109: 1.1.2. (+) შემოსავალი ლიფტების სერვისიდან - გეგმიური | E109: 43633 | F109: 1 | G109: GEL | H109: მიმდინარე | K109: 245565669/43633/1.1.2./1 | L109: 7F33E521-91AC-45E6-BEDC-038FF8B6F75A | M109: Modus Agladze | 1.1.2. (+) შემოსავალი ლიფტების სერვისიდან - გეგმიური | მოდუსი (ს.კ. 245565669) - შპს | N109: 12238130-9D12-4099-A48B-9EB5A085E0F8 | O109: 9729C88B-F3C5-441A-8782-0656302A37F2 | Q109: gio.nikabadze@gmail.com
A110: 44182.057 | B110: ნიუ თაიმ (ს.კ. 445440577) - შპს | C110: New Time | D110: 1.1.2. (+) შემოსავალი ლიფტების სერვისიდან - გეგმიური | E110: 43311 | F110: 1 | G110: USD | H110: მიმდინარე | K110: 445440577/43311/1.1.2./1 | L110: 7E7F4F08-6722-4720-ADA7-30669A9837B9 | M110: New Time | 1.1.2. (+) შემოსავალი ლიფტების სერვისიდან - გეგმიური | ნიუ თაიმ (ს.კ. 445440577) - შპს | N110: 12238130-9D12-4099-A48B-9EB5A085E0F8 | O110: EEF69DEA-9E1B-41C3-B563-3922DCE0A9BD | Q110: gio.nikabadze@gmail.com
A111: 44182.057 | B111: ორბი ჯგუფი ბათუმი (ს.კ. 445468798) - შპს | C111: ORBI Office Lift | D111: 1.1.2. (+) შემოსავალი ლიფტების სერვისიდან - გეგმიური | E111: 43788 | F111: 1 | G111: USD | H111: მიმდინარე | K111: 445468798/43788/1.1.2./1 | L111: 5564FE9D-DA57-4C23-B925-E2D095D97D24 | M111: ORBI Office Lift | 1.1.2. (+) შემოსავალი ლიფტების სერვისიდან - გეგმიური | ორბი ჯგუფი ბათუმი (ს.კ. 445468798) - შპს | N111: 12238130-9D12-4099-A48B-9EB5A085E0F8 | O111: E284E0FD-A2B7-4D93-8E91-006FF0A8A4CE | Q111: gio.nikabadze@gmail.com
A112: 44182.057 | B112: რედ-კო მენეჯმენტ გრუპი (ს.კ. 405198986) - შპს | C112: Redco 1 | D112: 1.1.2. (+) შემოსავალი ლიფტების სერვისიდან - გეგმიური | E112: 43879 | F112: 1 | G112: USD | H112: მიმდინარე | K112: 405198986/43879/1.1.2./1 | L112: A7C8AABE-B230-4454-A8DA-93EE74161089 | M112: Redco 1 | 1.1.2. (+) შემოსავალი ლიფტების სერვისიდან - გეგმიური | რედ-კო მენეჯმენტ გრუპი (ს.კ. 405198986) - შპს | N112: 12238130-9D12-4099-A48B-9EB5A085E0F8 | O112: 19F602E5-A978-4128-B38E-2D3540A8F675 | Q112: gio.nikabadze@gmail.com
...

Sheet Projects
A1: Timestamp | B1: კონტრაგენტი : | C1: პროექტის დასახელება : | D1: შემოსავლის კოდი : | E1: თარიღი : | F1: თანხა : | G1: ვალუტა : | H1: პროექტის სტატუსი : | I1: თანამშრომელი : | J1: ORIS 1630 : | K1: კონტრაქტის # - | L1: პროექტი_GUID/ | M1: პროექტი// | N1: შემოსავლის კოდი_GUID | O1: კონტრაგენტი_GUID | P1: თანამშრომელი_GUID | Q1: Collateral | R1: Deleted | S1: Name1 | T1: კონტრაგენტის ORIS ID | U1: {=if(A:A<>"",if(ROW(A:A)=1,"ნომერი","ICE"&row(A:A)-1),"")} -> ნომერი
A2: 44342.728 | B2: ოლიმპ ჯორჯია (ს.კ. 405231011) - შპს | C2: Biota Park | D2: 1.1.1. (+) შემოსავალი ლიფტების რეალიზაციიდან | E2: 43767 | F2: 350000 | G2: USD | H2: მიმდინარე | J2: 1 6 30 1270 | K2: 405231011/43767/1.1.1./1 | L2: 26A47FBE-6B71-4D89-B27B-4629DEEA1D34 | M2: Biota Park | 1.1.1. (+) შემოსავალი ლიფტების რეალიზაციიდან | ოლიმპ ჯორჯია (ს.კ. 405231011) - შპს | N2: B59170EC-16CC-499A-9FF7-0428DCB8F727 | O2: 6DECD64D-60DA-49AE-A9B3-49D7E02F2D62 | Q2: gio.nikabadze@gmail.com | S2: {=if(A2:A1450<>"",left(M2:M1450,iferror(search("(+)",M2:M1450),search("(-)",M2:M1450))-2)&" "&MID(M2:M1450,SEARCH("|",M2:M1450),1)&" "&left(B2:B1450,SEARCH("(ს.კ.",B2:B1450)-1)&" "&MID(M2:M1450,SEARCH("|",M2:M1450),1)&" "&TEXT(F2:F1450,"#,##0.00")&" "&G2:G1450&" "&MID(M2:M1450,SEARCH("|",M2:M1450),1)&" "&TEXT(E2:E1450,"DD.MM.YYYY"),"")} -> Biota Park | 1.1.1. | ოლიმპ ჯორჯია | 350,000.00 USD | 29.10.2019 | T2: =IFERROR(__xludf.DUMMYFUNCTION("ArrayFormula(if( A2:A1450<>"""", vlookup(O2:O1450, QUERY(IMPORTRANGE(""1BB2vegyweFMhmEGshLTiUL8CE4mOZ6zsta5ECrU9TU0"",""Counteragents""&""!A:Z""),CONCATENATE(""Select Col"",MATCH(""კონტრაგენტი_GUID/"",IMPORTRANGE(""1a0yHMlSrZV71Un45oznplcEPzNjsl78Qko9uBFT"&"PIUA"",""Counteragents!1:1""),0),"", Col"",MATCH(""ORIS ID :"",IMPORTRANGE(""1a0yHMlSrZV71Un45oznplcEPzNjsl78Qko9uBFTPIUA"",""Counteragents!1:1""),0))),2,FALSE),""""))"),1270.0) -> 1270 | U2: ICE1
A3: 44342.729 | B3: ინდეკო (ს.კ. 202376133) - შპს | C3: Chakhrukhadze | D3: 1.1.1. (+) შემოსავალი ლიფტების რეალიზაციიდან | E3: 43762 | F3: 23100 | G3: USD | H3: მიმდინარე | J3: 1 6 30 541 4 | K3: 202376133/43762/1.1.1./1 | L3: BFCA9047-3C75-4EEB-9FE8-82617FFD3965 | M3: Chakhrukhadze | 1.1.1. (+) შემოსავალი ლიფტების რეალიზაციიდან | ინდეკო (ს.კ. 202376133) - შპს | N3: B59170EC-16CC-499A-9FF7-0428DCB8F727 | O3: 8E8E99BE-75FC-49EC-9D89-960E30E7CB06 | Q3: gio.nikabadze@gmail.com | S3: Chakhrukhadze | 1.1.1. | ინდეკო | 23,100.00 USD | 24.10.2019 | T3: =IFERROR(__xludf.DUMMYFUNCTION("""COMPUTED_VALUE"""),541.0) -> 541 | U3: ICE2
A4: 44342.729 | B4: ბეტა ჯგუფი (ს.კ. 405171996) - შპს | C4: Med. University | D4: 1.1.1. (+) შემოსავალი ლიფტების რეალიზაციიდან | E4: 43767 | F4: 42500 | G4: USD | H4: მიმდინარე | K4: 405171996/43767/1.1.1./1 | L4: 00664103-FB2D-4EA7-A2B7-28064D745999 | M4: Med. University | 1.1.1. (+) შემოსავალი ლიფტების რეალიზაციიდან | ბეტა ჯგუფი (ს.კ. 405171996) - შპს | N4: B59170EC-16CC-499A-9FF7-0428DCB8F727 | O4: 3029E0C5-9337-4596-87DB-0A677D44A180 | Q4: gio.nikabadze@gmail.com | S4: Med. University | 1.1.1. | ბეტა ჯგუფი | 42,500.00 USD | 29.10.2019 | T4: =IFERROR(__xludf.DUMMYFUNCTION("""COMPUTED_VALUE"""),1257.0) -> 1257 | U4: ICE3
A5: 44342.729 | B5: გიოკაპიტალი (ს.კ. 406155841) - შპს | C5: Varketili | D5: 1.1.1. (+) შემოსავალი ლიფტების რეალიზაციიდან | E5: 43724 | F5: 48500 | G5: USD | H5: მიმდინარე | J5: 1 6 30 1252 | K5: 406155841/43724/1.1.1./1 | L5: 80851DA9-84C4-4C2C-95FE-D6A0282F7B22 | M5: Varketili | 1.1.1. (+) შემოსავალი ლიფტების რეალიზაციიდან | გიოკაპიტალი (ს.კ. 406155841) - შპს | N5: B59170EC-16CC-499A-9FF7-0428DCB8F727 | O5: 97BEEA92-7829-4A09-8B1C-D0FE871340D4 | Q5: gio.nikabadze@gmail.com | S5: Varketili | 1.1.1. | გიოკაპიტალი | 48,500.00 USD | 16.09.2019 | T5: =IFERROR(__xludf.DUMMYFUNCTION("""COMPUTED_VALUE"""),1252.0) -> 1252 | U5: ICE4
A6: 44342.729 | B6: რედ-კო (ს.კ. 405148415) - შპს | C6: Gudauri Redco Parking | D6: 1.1.1. (+) შემოსავალი ლიფტების რეალიზაციიდან | E6: 43734 | F6: 28000 | G6: USD | H6: მიმდინარე | K6: 405148415/43734/1.1.1./1 | L6: 2E1DDD27-332A-4E4A-B571-52B4DE3B8E04 | M6: Gudauri Redco Parking | 1.1.1. (+) შემოსავალი ლიფტების რეალიზაციიდან | რედ-კო (ს.კ. 405148415) - შპს | N6: B59170EC-16CC-499A-9FF7-0428DCB8F727 | O6: DA9D440B-CACD-4076-8B91-BFFCA46814B6 | Q6: gio.nikabadze@gmail.com | S6: Gudauri Redco Parking | 1.1.1. | რედ-კო | 28,000.00 USD | 26.09.2019 | T6: =IFERROR(__xludf.DUMMYFUNCTION("""COMPUTED_VALUE"""),917.0) -> 917 | U6: ICE5
A7: 44342.729 | B7: მაია კვიჭიძე (ს.კ. 01008011243) - ფიზ. პირი | C7: Ortachala | D7: 1.1.1. (+) შემოსავალი ლიფტების რეალიზაციიდან | E7: 43672 | F7: 24000 | G7: USD | H7: მიმდინარე | K7: 01008011243/43672/1.1.1./1 | L7: 83FEC832-A4EA-4380-B5E9-85BEEECE8FA4 | M7: Ortachala | 1.1.1. (+) შემოსავალი ლიფტების რეალიზაციიდან | მაია კვიჭიძე (ს.კ. 01008011243) - ფიზ. პირი | N7: B59170EC-16CC-499A-9FF7-0428DCB8F727 | O7: D5136DB7-C17A-4DDB-9797-D1B10612D28C | Q7: gio.nikabadze@gmail.com | S7: Ortachala | 1.1.1. | მაია კვიჭიძე | 24,000.00 USD | 26.07.2019 | T7: =IFERROR(__xludf.DUMMYFUNCTION("""COMPUTED_VALUE"""),1207.0) -> 1207 | U7: ICE6
A8: 44342.729 | B8: მოდუსი (ს.კ. 245565669) - შპს | C8: Modus Agladze | D8: 1.1.1. (+) შემოსავალი ლიფტების რეალიზაციიდან | E8: 43633 | F8: 32000 | G8: USD | H8: მიმდინარე | K8: 245565669/43633/1.1.1./1 | L8: ABDEF9CC-F0E1-4950-B30C-D46A8A8A912C | M8: Modus Agladze | 1.1.1. (+) შემოსავალი ლიფტების რეალიზაციიდან | მოდუსი (ს.კ. 245565669) - შპს | N8: B59170EC-16CC-499A-9FF7-0428DCB8F727 | O8: 9729C88B-F3C5-441A-8782-0656302A37F2 | Q8: gio.nikabadze@gmail.com | S8: Modus Agladze | 1.1.1. | მოდუსი | 32,000.00 USD | 17.06.2019 | T8: =IFERROR(__xludf.DUMMYFUNCTION("""COMPUTED_VALUE"""),642.0) -> 642 | U8: ICE7
A9: 44342.729 | B9: ჰომბეი (ს.კ. 405255815) - შპს | C9: Crystal Bakuriani | D9: 1.1.1. (+) შემოსავალი ლიფტების რეალიზაციიდან | E9: 43608 | F9: 104500 | G9: USD | H9: მიმდინარე | K9: 405255815/43608/1.1.1./1 | L9: 230FCB1B-1310-4C49-9D2C-9CD5F9A792A3 | M9: Crystal Bakuriani | 1.1.1. (+) შემოსავალი ლიფტების რეალიზაციიდან | ჰომბეი (ს.კ. 405255815) - შპს | N9: B59170EC-16CC-499A-9FF7-0428DCB8F727 | O9: AAFC235A-2BBF-4CEC-A2AE-F1AEBABC12E4 | Q9: gio.nikabadze@gmail.com | S9: Crystal Bakuriani | 1.1.1. | ჰომბეი | 104,500.00 USD | 23.05.2019 | T9: =IFERROR(__xludf.DUMMYFUNCTION("""COMPUTED_VALUE"""),1173.0) -> 1173 | U9: ICE8
A10: 44342.729 | B10: ანა აბუსერიძე (ს.კ. 61001051501) - ფიზ. პირი | C10: Abuseridze - Batumi | D10: 1.1.1. (+) შემოსავალი ლიფტების რეალიზაციიდან | E10: 43622 | F10: 31000 | G10: USD | H10: მიმდინარე | J10: 1 6 30 1179 | K10: 61001051501/43622/1.1.1./1 | L10: 4E89F135-A0AD-4622-97BD-7B68EF6062F8 | M10: Abuseridze - Batumi | 1.1.1. (+) შემოსავალი ლიფტების რეალიზაციიდან | ანა აბუსერიძე (ს.კ. 61001051501) - ფიზ. პირი | N10: B59170EC-16CC-499A-9FF7-0428DCB8F727 | O10: 15F35EBB-5A28-4C1B-B7CC-45FF3F31D4D6 | Q10: gio.nikabadze@gmail.com | S10: Abuseridze - Batumi | 1.1.1. | ანა აბუსერიძე | 31,000.00 USD | 06.06.2019 | T10: =IFERROR(__xludf.DUMMYFUNCTION("""COMPUTED_VALUE"""),1179.0) -> 1179 | U10: ICE9
A11: 44342.729 | B11: იუნიქს ქონსთრაქშენ კომპანი (ს.კ. 405133822) - შპს | C11: UNIX Marselle | D11: 1.1.1. (+) შემოსავალი ლიფტების რეალიზაციიდან | E11: 43607 | F11: 340000 | G11: USD | H11: მიმდინარე | K11: 405133822/43607/1.1.1./1 | L11: CFFC1C06-B78B-45A0-8A02-37A23706EAFC | M11: UNIX Marselle | 1.1.1. (+) შემოსავალი ლიფტების რეალიზაციიდან | იუნიქს ქონსთრაქშენ კომპანი (ს.კ. 405133822) - შპს | N11: B59170EC-16CC-499A-9FF7-0428DCB8F727 | O11: B4968862-3843-414D-9E73-1A7611618B41 | Q11: gio.nikabadze@gmail.com | S11: UNIX Marselle | 1.1.1. | იუნიქს ქონსთრაქშენ კომპანი | 340,000.00 USD | 22.05.2019 | T11: =IFERROR(__xludf.DUMMYFUNCTION("""COMPUTED_VALUE"""),902.0) -> 902 | U11: ICE10
A12: 44342.729 | B12: თბილისი პალასი (ს.კ. 405253381) - შპს | C12: Tbilisi Palace | D12: 1.1.1. (+) შემოსავალი ლიფტების რეალიზაციიდან | E12: 43460 | F12: 160000 | G12: USD | H12: მიმდინარე | K12: 405253381/43460/1.1.1./1 | L12: 125722B7-4DB0-4817-B1A4-DBA0B1B893D4 | M12: Tbilisi Palace | 1.1.1. (+) შემოსავალი ლიფტების რეალიზაციიდან | თბილისი პალასი (ს.კ. 405253381) - შპს | N12: B59170EC-16CC-499A-9FF7-0428DCB8F727 | O12: 3F5B4217-38D4-4FB8-B3F3-E856A10FFF06 | Q12: gio.nikabadze@gmail.com | S12: Tbilisi Palace | 1.1.1. | თბილისი პალასი | 160,000.00 USD | 26.12.2018 | T12: =IFERROR(__xludf.DUMMYFUNCTION("""COMPUTED_VALUE"""),1034.0) -> 1034 | U12: ICE11
A13: 44342.729 | B13: თეგეტა მოტორსი (ს.კ. 202177205) - შპს | C13: Tegeta Batumi | D13: 1.1.1. (+) შემოსავალი ლიფტების რეალიზაციიდან | E13: 43479 | F13: 28650 | G13: USD | H13: მიმდინარე | K13: 202177205/43479/1.1.1./1 | L13: 255604D7-5424-4548-9CAA-ECFF960BB6AE | M13: Tegeta Batumi | 1.1.1. (+) შემოსავალი ლიფტების რეალიზაციიდან | თეგეტა მოტორსი (ს.კ. 202177205) - შპს | N13: B59170EC-16CC-499A-9FF7-0428DCB8F727 | O13: 5A21C207-4868-4EA6-9B48-5D0F743D5535 | Q13: gio.nikabadze@gmail.com | S13: Tegeta Batumi | 1.1.1. | თეგეტა მოტორსი | 28,650.00 USD | 14.01.2019 | T13: =IFERROR(__xludf.DUMMYFUNCTION("""COMPUTED_VALUE"""),93.0) -> 93 | U13: ICE12
A14: 44342.729 | B14: Dar Building (ს.კ. 445420875) - შპს | C14: DAR TOWER | D14: 1.1.1. (+) შემოსავალი ლიფტების რეალიზაციიდან | E14: 43363 | F14: 1046340 | G14: USD | H14: მიმდინარე | J14: 1 6 30 853 1 | K14: 445420875/43363/1.1.1./1 | L14: A4EE54E2-C9BC-44F8-8554-44B9037B38D2 | M14: DAR TOWER | 1.1.1. (+) შემოსავალი ლიფტების რეალიზაციიდან | Dar Building (ს.კ. 445420875) - შპს | N14: B59170EC-16CC-499A-9FF7-0428DCB8F727 | O14: 7BF4A039-29BC-44AC-A87D-E8832394B94E | Q14: gio.nikabadze@gmail.com | S14: DAR TOWER | 1.1.1. | Dar Building | 1,046,340.00 USD | 20.09.2018 | T14: =IFERROR(__xludf.DUMMYFUNCTION("""COMPUTED_VALUE"""),853.0) -> 853 | U14: ICE13
A15: 44342.729 | B15: ბათბილდინგი (ს.კ. 445509334) - შპს | C15: BAT Tower | D15: 1.1.1. (+) შემოსავალი ლიფტების რეალიზაციიდან | E15: 43461 | F15: 73000 | G15: USD | H15: მიმდინარე | J15: 1 6 30 1039 | K15: 445509334/43461/1.1.1./1 | L15: A7AFCD4C-CA26-464C-8F1B-E9A5240DCB0F | M15: BAT Tower | 1.1.1. (+) შემოსავალი ლიფტების რეალიზაციიდან | ბათბილდინგი (ს.კ. 445509334) - შპს | N15: B59170EC-16CC-499A-9FF7-0428DCB8F727 | O15: DAE7B000-963F-42D9-AA35-8F3F2F8A3716 | Q15: gio.nikabadze@gmail.com | S15: BAT Tower | 1.1.1. | ბათბილდინგი | 73,000.00 USD | 27.12.2018 | T15: =IFERROR(__xludf.DUMMYFUNCTION("""COMPUTED_VALUE"""),1039.0) -> 1039 | U15: ICE14
A16: 44342.729 | B16: რუმი (ს.კ. 445481853) - შპს | C16: Rumi - batumi | D16: 1.1.1. (+) შემოსავალი ლიფტების რეალიზაციიდან | E16: 43816 | F16: 117370 | G16: USD | H16: მიმდინარე | J16: 1 6 30 1335 | K16: 445481853/43816/1.1.1./1 | L16: E95274D6-921C-43D1-B7C4-4F99A71C4005 | M16: Rumi - batumi | 1.1.1. (+) შემოსავალი ლიფტების რეალიზაციიდან | რუმი (ს.კ. 445481853) - შპს | N16: B59170EC-16CC-499A-9FF7-0428DCB8F727 | O16: BFABDF11-34C8-4815-A840-47DD5AAB9F4F | Q16: gio.nikabadze@gmail.com | S16: Rumi - batumi | 1.1.1. | რუმი | 117,370.00 USD | 17.12.2019 | T16: =IFERROR(__xludf.DUMMYFUNCTION("""COMPUTED_VALUE"""),1335.0) -> 1335 | U16: ICE15
A17: 44342.729 | B17: ფალიაშვილის 63 (ს.კ. ICE000034) - ამხანაგობა | C17: Domus Paliashviliს 63 | D17: 1.1.1. (+) შემოსავალი ლიფტების რეალიზაციიდან | E17: 42948 | F17: 97000 | G17: GEL | H17: მიმდინარე | K17: ICE000034/42948/1.1.1./1 | L17: C897938C-00C4-4220-BAF1-CA29F3237D16 | M17: Domus Paliashviliს 63 | 1.1.1. (+) შემოსავალი ლიფტების რეალიზაციიდან | ფალიაშვილის 63 (ს.კ. ICE000034) - ამხანაგობა | N17: B59170EC-16CC-499A-9FF7-0428DCB8F727 | O17: 7F0A41E4-FA68-43E7-A979-126560D14B58 | Q17: gio.nikabadze@gmail.com | S17: Domus Paliashviliს 63 | 1.1.1. | ფალიაშვილის 63 | 97,000.00 GEL | 01.08.2017 | T17: =IFERROR(__xludf.DUMMYFUNCTION("""COMPUTED_VALUE"""),863.0) -> 863 | U17: ICE16
A18: 44342.729 | B18: ეკომეტრი (ს.კ. 404464030) - შპს | C18: Gelovani 52 | D18: 1.1.1. (+) შემოსავალი ლიფტების რეალიზაციიდან | E18: 42923 | F18: 161000 | G18: USD | H18: მიმდინარე | K18: 404464030/42923/1.1.1./1 | L18: 196F7BB2-781C-4FF2-BAEE-C30045DA8E1E | M18: Gelovani 52 | 1.1.1. (+) შემოსავალი ლიფტების რეალიზაციიდან | ეკომეტრი (ს.კ. 404464030) - შპს | N18: B59170EC-16CC-499A-9FF7-0428DCB8F727 | O18: B25EF46E-8022-4949-A1EB-E8A1256C7A3B | Q18: gio.nikabadze@gmail.com | S18: Gelovani 52 | 1.1.1. | ეკომეტრი | 161,000.00 USD | 07.07.2017 | T18: =IFERROR(__xludf.DUMMYFUNCTION("""COMPUTED_VALUE"""),710.0) -> 710 | U18: ICE17
A19: 44342.729 | B19: ჩემპიონი 2 (ს.კ. 248416432) - შპს | C19: Chempioni | D19: 1.1.1. (+) შემოსავალი ლიფტების რეალიზაციიდან | E19: 42536 | F19: 23924 | G19: USD | H19: მიმდინარე | K19: 248416432/42536/1.1.1./1 | L19: 42197EB0-C73A-4679-8D11-1DD3BAC96135 | M19: Chempioni | 1.1.1. (+) შემოსავალი ლიფტების რეალიზაციიდან | ჩემპიონი 2 (ს.კ. 248416432) - შპს | N19: B59170EC-16CC-499A-9FF7-0428DCB8F727 | O19: 967EE73E-8B77-4A8F-9FD3-AA36FF0ECB17 | Q19: gio.nikabadze@gmail.com | S19: Chempioni | 1.1.1. | ჩემპიონი 2 | 23,924.00 USD | 15.06.2016 | T19: =IFERROR(__xludf.DUMMYFUNCTION("""COMPUTED_VALUE"""),599.0) -> 599 | U19: ICE18
A20: 44342.729 | B20: ნიუ თაიმ (ს.კ. 445440577) - შპს | C20: New Time | D20: 1.1.1. (+) შემოსავალი ლიფტების რეალიზაციიდან | E20: 42885 | F20: 150000 | G20: USD | H20: მიმდინარე | K20: 445440577/42885/1.1.1./1 | L20: 7A83BC1F-C807-436E-9390-775B1D423BFD | M20: New Time | 1.1.1. (+) შემოსავალი ლიფტების რეალიზაციიდან | ნიუ თაიმ (ს.კ. 445440577) - შპს | N20: B59170EC-16CC-499A-9FF7-0428DCB8F727 | O20: EEF69DEA-9E1B-41C3-B563-3922DCE0A9BD | Q20: gio.nikabadze@gmail.com | S20: New Time | 1.1.1. | ნიუ თაიმ | 150,000.00 USD | 30.05.2017 | T20: =IFERROR(__xludf.DUMMYFUNCTION("""COMPUTED_VALUE"""),693.0) -> 693 | U20: ICE19
A21: 44342.729 | B21: ელტური-2008 (ს.კ. 248434038) - შპს | C21: Green Cape | D21: 1.1.1. (+) შემოსავალი ლიფტების რეალიზაციიდან | E21: 43460 | F21: 70360 | G21: USD | H21: მიმდინარე | K21: 248434038/43460/1.1.1./1 | L21: D9285AF5-11A4-4764-B11B-745E9DAF1D34 | M21: Green Cape | 1.1.1. (+) შემოსავალი ლიფტების რეალიზაციიდან | ელტური-2008 (ს.კ. 248434038) - შპს | N21: B59170EC-16CC-499A-9FF7-0428DCB8F727 | O21: 0A7F5182-3B4F-4292-8569-FC31854BA5B4 | Q21: gio.nikabadze@gmail.com | S21: Green Cape | 1.1.1. | ელტური-2008 | 70,360.00 USD | 26.12.2018 | T21: =IFERROR(__xludf.DUMMYFUNCTION("""COMPUTED_VALUE"""),1038.0) -> 1038 | U21: ICE20
A22: 44342.729 | B22: ინდეკო (ს.კ. 202376133) - შპს | C22: Indeko - shartava 39 | D22: 1.1.1. (+) შემოსავალი ლიფტების რეალიზაციიდან | E22: 43460 | F22: 155520 | G22: USD | H22: მიმდინარე | K22: 202376133/42345/1.1.1./1 | L22: C5E1547A-8529-495B-974D-92544D0F1C66 | M22: Indeko - shartava 39 | 1.1.1. (+) შემოსავალი ლიფტების რეალიზაციიდან | ინდეკო (ს.კ. 202376133) - შპს | N22: B59170EC-16CC-499A-9FF7-0428DCB8F727 | O22: 8E8E99BE-75FC-49EC-9D89-960E30E7CB06 | Q22: gio.nikabadze@gmail.com | S22: Indeko - shartava 39 | 1.1.1. | ინდეკო | 155,520.00 USD | 26.12.2018 | T22: =IFERROR(__xludf.DUMMYFUNCTION("""COMPUTED_VALUE"""),541.0) -> 541 | U22: ICE21
A23: 44342.729 | B23: რედ-კო (ს.კ. 405148415) - შპს | C23: Redco 1 | D23: 1.1.1. (+) შემოსავალი ლიფტების რეალიზაციიდან | E23: 43248 | F23: 370000 | G23: USD | H23: მიმდინარე | J23: 1 6 30 917 2 | K23: 405148415/43248/1.1.1./1 | L23: D421D947-C097-4870-8EF1-C7F724377248 | M23: Redco 1 | 1.1.1. (+) შემოსავალი ლიფტების რეალიზაციიდან | რედ-კო (ს.კ. 405148415) - შპს | N23: B59170EC-16CC-499A-9FF7-0428DCB8F727 | O23: DA9D440B-CACD-4076-8B91-BFFCA46814B6 | Q23: gio.nikabadze@gmail.com | S23: Redco 1 | 1.1.1. | რედ-კო | 370,000.00 USD | 28.05.2018 | T23: =IFERROR(__xludf.DUMMYFUNCTION("""COMPUTED_VALUE"""),917.0) -> 917 | U23: ICE22
A24: 44342.729 | B24: ბიზნეს ცენტრი დელისი (ს.კ. 204854014) - სს | C24: Delisi | D24: 1.1.1. (+) შემოსავალი ლიფტების რეალიზაციიდან | E24: 42598 | F24: 53454 | G24: USD | H24: მიმდინარე | K24: 204854014/42598/1.1.1./1 | L24: 2496A0E0-1118-49DC-8A82-539003DC1B23 | M24: Delisi | 1.1.1. (+) შემოსავალი ლიფტების რეალიზაციიდან | ბიზნეს ცენტრი დელისი (ს.კ. 204854014) - სს | N24: B59170EC-16CC-499A-9FF7-0428DCB8F727 | O24: 62F6C15C-8FCC-4A60-B37E-8A3DE9D20A48 | Q24: gio.nikabadze@gmail.com | S24: Delisi | 1.1.1. | ბიზნეს ცენტრი დელისი | 53,454.00 USD | 16.08.2016 | T24: =IFERROR(__xludf.DUMMYFUNCTION("""COMPUTED_VALUE"""),620.0) -> 620 | U24: ICE23
A25: 44342.729 | B25: შველა (ს.კ. 448396021) - შპს | C25: Shvela | D25: 1.1.1. (+) შემოსავალი ლიფტების რეალიზაციიდან | E25: 42536 | F25: 50206 | G25: USD | H25: მიმდინარე | K25: 448396021/42536/1.1.1./1 | L25: 1C2CAB23-3967-41F9-AC61-62415AE0373C | M25: Shvela | 1.1.1. (+) შემოსავალი ლიფტების რეალიზაციიდან | შველა (ს.კ. 448396021) - შპს | N25: B59170EC-16CC-499A-9FF7-0428DCB8F727 | O25: A5C44F5D-1F9C-4BC1-BD39-C8B2E88BC49A | Q25: gio.nikabadze@gmail.com | S25: Shvela | 1.1.1. | შველა | 50,206.00 USD | 15.06.2016 | T25: =IFERROR(__xludf.DUMMYFUNCTION("""COMPUTED_VALUE"""),595.0) -> 595 | U25: ICE24
A26: 44342.729 | B26: ბკ კაპიტალი (ს.კ. 205057123) - შპს | C26: Moxy Zaabruken Hotel 1 | D26: 1.1.1. (+) შემოსავალი ლიფტების რეალიზაციიდან | E26: 42647 | F26: 157608.67 | G26: USD | H26: მიმდინარე | K26: 205057123/42647/1.1.1./1 | L26: 202843CA-C5C3-4057-8040-234B6C369B5E | M26: Moxy Zaabruken Hotel | 1.1.1. (+) შემოსავალი ლიფტების რეალიზაციიდან | ბკ კაპიტალი (ს.კ. 205057123) - შპს | N26: B59170EC-16CC-499A-9FF7-0428DCB8F727 | O26: D57E2878-F57C-4B96-B89E-A8B81F35634A | Q26: gio.nikabadze@gmail.com | S26: Moxy Zaabruken Hotel | 1.1.1. | ბკ კაპიტალი | 157,608.67 USD | 04.10.2016 | T26: =IFERROR(__xludf.DUMMYFUNCTION("""COMPUTED_VALUE"""),665.0) -> 665 | U26: ICE25
A27: 44342.729 | B27: ინჟინერთა ჯგუფი (ს.კ. 400101457) - შპს | C27: Tbilisi Gardens | D27: 1.1.1. (+) შემოსავალი ლიფტების რეალიზაციიდან | E27: 42723 | F27: 325000 | G27: USD | H27: მიმდინარე | K27: 400101457/42723/1.1.1./1 | L27: 8C8C52A5-1A7C-485F-9AC8-043862EF3D55 | M27: Tbilisi Gardens | 1.1.1. (+) შემოსავალი ლიფტების რეალიზაციიდან | ინჟინერთა ჯგუფი (ს.კ. 400101457) - შპს | N27: B59170EC-16CC-499A-9FF7-0428DCB8F727 | O27: 2ED6F730-5337-4222-94F9-284E801BCE61 | Q27: gio.nikabadze@gmail.com | S27: Tbilisi Gardens | 1.1.1. | ინჟინერთა ჯგუფი | 325,000.00 USD | 19.12.2016 | T27: =IFERROR(__xludf.DUMMYFUNCTION("""COMPUTED_VALUE"""),650.0) -> 650 | U27: ICE26
A28: 44342.729 | B28: მოდუსი (ს.კ. 245565669) - შპს | C28: Modus Kakhety HW | D28: 1.1.1. (+) შემოსავალი ლიფტების რეალიზაციიდან | E28: 42641 | F28: 25000 | G28: USD | H28: მიმდინარე | K28: 245565669/42641/1.1.1./1 | L28: BFD4409A-7F01-4C7C-9F40-73A80C2E63A6 | M28: Modus Kakhety HW | 1.1.1. (+) შემოსავალი ლიფტების რეალიზაციიდან | მოდუსი (ს.კ. 245565669) - შპს | N28: B59170EC-16CC-499A-9FF7-0428DCB8F727 | O28: 9729C88B-F3C5-441A-8782-0656302A37F2 | Q28: gio.nikabadze@gmail.com | S28: Modus Kakhety HW | 1.1.1. | მოდუსი | 25,000.00 USD | 28.09.2016 | T28: =IFERROR(__xludf.DUMMYFUNCTION("""COMPUTED_VALUE"""),642.0) -> 642 | U28: ICE27
A29: 44342.729 | B29: სითი დეველოპმენტ (ს.კ. 404481324) - შპს | C29: Kbuleti Str. - Khomeriki | D29: 1.1.1. (+) შემოსავალი ლიფტების რეალიზაციიდან | E29: 42485 | F29: 36577 | G29: USD | H29: მიმდინარე | K29: 404481324/42485/1.1.1./1 | L29: A53105CE-1BDB-4625-B775-A01DA1F6C8AD | M29: Kbuleti Str. - Khomeriki | 1.1.1. (+) შემოსავალი ლიფტების რეალიზაციიდან | სითი დეველოპმენტ (ს.კ. 404481324) - შპს | N29: B59170EC-16CC-499A-9FF7-0428DCB8F727 | O29: 57A60218-744B-4922-BF21-F9C52A01DAF6 | Q29: gio.nikabadze@gmail.com | S29: Kbuleti Str. - Khomeriki | 1.1.1. | სითი დეველოპმენტ | 36,577.00 USD | 25.04.2016 | T29: =IFERROR(__xludf.DUMMYFUNCTION("""COMPUTED_VALUE"""),570.0) -> 570 | U29: ICE28
A30: 44342.729 | B30: დომუს დეველოპმენტ (ს.კ. 205210261) - შპს | C30: Domus | D30: 1.1.1. (+) შემოსავალი ლიფტების რეალიზაციიდან | E30: 42355 | F30: 527700 | G30: USD | H30: მიმდინარე | K30: 205210261/42355/1.1.1./1 | L30: F154242F-E028-49D8-B7BE-42EB31281CD5 | M30: Domus | 1.1.1. (+) შემოსავალი ლიფტების რეალიზაციიდან | დომუს დეველოპმენტ (ს.კ. 205210261) - შპს | N30: B59170EC-16CC-499A-9FF7-0428DCB8F727 | O30: A3C5943B-D1C3-4CB2-946C-86BF678B6183 | Q30: gio.nikabadze@gmail.com | S30: Domus | 1.1.1. | დომუს დეველოპმენტ | 527,700.00 USD | 17.12.2015 | T30: =IFERROR(__xludf.DUMMYFUNCTION("""COMPUTED_VALUE"""),462.0) -> 462 | U30: ICE29
A31: 44342.729 | B31: ირაკლი კაციტაძე (ს.კ. 01008004604) - ფიზ. პირი | C31: Paliashvili 23 | D31: 1.1.2. (+) შემოსავალი ლიფტების სერვისიდან - გეგმიური | E31: 43831 | F31: 1 | G31: GEL | H31: მიმდინარე | J31: 1 6 31 1380 | K31: 01008004604/43831/1.1.2./1 | L31: 6D999F5B-2199-4578-A47D-FDC2DF179273 | M31: Paliashvili 23 | 1.1.2. (+) შემოსავალი ლიფტების სერვისიდან - გეგმიური | ირაკლი კაციტაძე (ს.კ. 01008004604) - ფიზ. პირი | N31: 12238130-9D12-4099-A48B-9EB5A085E0F8 | O31: 9AE0C821-91FF-44A4-90E6-F71F98BC044C | Q31: gio.nikabadze@gmail.com | S31: Paliashvili 23 | 1.1.2. | ირაკლი კაციტაძე | 1.00 GEL | 01.01.2020 | T31: =IFERROR(__xludf.DUMMYFUNCTION("""COMPUTED_VALUE"""),1380.0) -> 1380 | U31: ICE30
A32: 44342.729 | B32: ბკ კაპიტალი (ს.კ. 205057123) - შპს | C32: Moxy Zabruken Restaurant | D32: 1.1.1. (+) შემოსავალი ლიფტების რეალიზაციიდან | E32: 43742 | F32: 78804.33 | G32: USD | H32: მიმდინარე | K32: 205057123/43742/1.1.1./1 | L32: 5E543EA8-4A6A-4F8C-9F72-071B61F85EEB | M32: Moxy Zabruken Restaurant | 1.1.1. (+) შემოსავალი ლიფტების რეალიზაციიდან | ბკ კაპიტალი (ს.კ. 205057123) - შპს | N32: B59170EC-16CC-499A-9FF7-0428DCB8F727 | O32: D57E2878-F57C-4B96-B89E-A8B81F35634A | Q32: gio.nikabadze@gmail.com | S32: Moxy Zabruken Restaurant | 1.1.1. | ბკ კაპიტალი | 78,804.33 USD | 04.10.2019 | T32: =IFERROR(__xludf.DUMMYFUNCTION("""COMPUTED_VALUE"""),665.0) -> 665 | U32: ICE31
A33: 44342.729 | B33: ორბი ჯგუფი ბათუმი (ს.კ. 445468798) - შპს | C33: TWIN TOWER | D33: 1.1.1. (+) შემოსავალი ლიფტების რეალიზაციიდან | E33: 43059 | F33: 3273908 | G33: USD | H33: მიმდინარე | J33: 1 6 30 773 1 | K33: 445468798/43059/1.1.1./1 | L33: C35D9FF1-3A09-4634-9BFA-87C709266063 | M33: TWIN TOWER | 1.1.1. (+) შემოსავალი ლიფტების რეალიზაციიდან | ორბი ჯგუფი ბათუმი (ს.კ. 445468798) - შპს | N33: B59170EC-16CC-499A-9FF7-0428DCB8F727 | O33: E284E0FD-A2B7-4D93-8E91-006FF0A8A4CE | Q33: gio.nikabadze@gmail.com | S33: TWIN TOWER | 1.1.1. | ორბი ჯგუფი ბათუმი | 3,273,908.00 USD | 20.11.2017 | T33: =IFERROR(__xludf.DUMMYFUNCTION("""COMPUTED_VALUE"""),773.0) -> 773 | U33: ICE32
A34: 44342.729 | B34: აი ჯი დეველოფმენტ ჯორჯია (ს.კ. 404851503) - შპს | C34: City Mall | D34: 1.1.1. (+) შემოსავალი ლიფტების რეალიზაციიდან | E34: 43354 | F34: 1194345 | G34: USD | H34: მიმდინარე | J34: 1 6 30 971 | K34: 404851503/43354/1.1.1./1 | L34: EA15EDA6-F906-4932-87BA-DDB8898D4EBC | M34: City Mall | 1.1.1. (+) შემოსავალი ლიფტების რეალიზაციიდან | აი ჯი დეველოფმენტ ჯორჯია (ს.კ. 404851503) - შპს | N34: B59170EC-16CC-499A-9FF7-0428DCB8F727 | O34: DDFBBDF4-5DA2-4BD2-918A-77AAF121BF72 | Q34: gio.nikabadze@gmail.com | S34: City Mall | 1.1.1. | აი ჯი დეველოფმენტ ჯორჯია | 1,194,345.00 USD | 11.09.2018 | T34: =IFERROR(__xludf.DUMMYFUNCTION("""COMPUTED_VALUE"""),971.0) -> 971 | U34: ICE33
A35: 44342.729 | B35: რენთინგ ბიენბი (ს.კ. 404564244) - სს | C35: Renting BNB | D35: 1.1.1. (+) შემოსავალი ლიფტების რეალიზაციიდან | E35: 43886 | F35: 26000 | G35: USD | H35: მიმდინარე | J35: 1 6 30 1429 | K35: 404564244/43886/1.1.1./1 | L35: 55F53FA9-CDDE-4FBA-91A1-FEAFA51B29A0 | M35: Renting BNB | 1.1.1. (+) შემოსავალი ლიფტების რეალიზაციიდან | რენთინგ ბიენბი (ს.კ. 404564244) - სს | N35: B59170EC-16CC-499A-9FF7-0428DCB8F727 | O35: 9B349A17-7CE1-4232-98C6-02C565C3642C | Q35: gio.nikabadze@gmail.com | S35: Renting BNB | 1.1.1. | რენთინგ ბიენბი | 26,000.00 USD | 25.02.2020 | T35: =IFERROR(__xludf.DUMMYFUNCTION("""COMPUTED_VALUE"""),1429.0) -> 1429 | U35: ICE34
A36: 44342.729 | B36: ტრანსმშენი (ს.კ. 212274812) - სს | C36: Aeroporti | D36: 1.1.1. (+) შემოსავალი ლიფტების რეალიზაციიდან | E36: 43699 | F36: 20000 | G36: USD | H36: მიმდინარე | K36: 212274812/43699/1.1.1./1 | L36: 44F2F4A0-908E-42D1-B73F-04859CACCB08 | M36: Aeroporti | 1.1.1. (+) შემოსავალი ლიფტების რეალიზაციიდან | ტრანსმშენი (ს.კ. 212274812) - სს | N36: B59170EC-16CC-499A-9FF7-0428DCB8F727 | O36: 9B21D54A-56D8-405D-95E2-A05872C7C1E9 | Q36: gio.nikabadze@gmail.com | S36: Aeroporti | 1.1.1. | ტრანსმშენი | 20,000.00 USD | 22.08.2019 | T36: =IFERROR(__xludf.DUMMYFUNCTION("""COMPUTED_VALUE"""),1235.0) -> 1235 | U36: ICE35
A37: 44342.729 | B37: ბეტა ჯგუფი (ს.კ. 405171996) - შპს | C37: Dividers Med Uni | D37: 1.1.1. (+) შემოსავალი ლიფტების რეალიზაციიდან | E37: 43477 | F37: 11000 | G37: GEL | H37: მიმდინარე | K37: 405171996/43477/1.1.1./1 | L37: 2F958FC8-AC98-416D-BEAC-E4C6006FCCB3 | M37: Dividers Med Uni | 1.1.1. (+) შემოსავალი ლიფტების რეალიზაციიდან | ბეტა ჯგუფი (ს.კ. 405171996) - შპს | N37: B59170EC-16CC-499A-9FF7-0428DCB8F727 | O37: 3029E0C5-9337-4596-87DB-0A677D44A180 | Q37: gio.nikabadze@gmail.com | S37: Dividers Med Uni | 1.1.1. | ბეტა ჯგუფი | 11,000.00 GEL | 12.01.2019 | T37: =IFERROR(__xludf.DUMMYFUNCTION("""COMPUTED_VALUE"""),1257.0) -> 1257 | U37: ICE36
A38: 44342.729 | B38: ლუდსახარში ორი კათხა (ს.კ. 406283338) - შპს | C38: Brewery 1 (300KG) | D38: 1.1.1. (+) შემოსავალი ლიფტების რეალიზაციიდან | E38: 43896 | F38: 10610 | G38: USD | H38: მიმდინარე | K38: 406283338/43896/1.1.1./1 | L38: 4DB7E760-9ECD-4426-BB50-E293E58D2B02 | M38: Brewery 1 (300KG) | 1.1.1. (+) შემოსავალი ლიფტების რეალიზაციიდან | ლუდსახარში ორი კათხა (ს.კ. 406283338) - შპს | N38: B59170EC-16CC-499A-9FF7-0428DCB8F727 | O38: 1C2A10A9-FA2F-437B-8C70-F109D1C009EE | Q38: gio.nikabadze@gmail.com | S38: Brewery 1 (300KG) | 1.1.1. | ლუდსახარში ორი კათხა | 10,610.00 USD | 06.03.2020 | T38: =IFERROR(__xludf.DUMMYFUNCTION("""COMPUTED_VALUE"""),1381.0) -> 1381 | U38: ICE37
A39: 44342.729 | B39: ახალშენი 2016 (ს.კ. 405136758) - შპს | C39: Khiliani | D39: 1.1.1. (+) შემოსავალი ლიფტების რეალიზაციიდან | E39: 43677 | F39: 26400 | G39: USD | H39: მიმდინარე | K39: 405136758/43677/1.1.1./1 | L39: E136ACFA-DBED-49EE-B224-24513754542C | M39: Khiliani | 1.1.1. (+) შემოსავალი ლიფტების რეალიზაციიდან | ახალშენი 2016 (ს.კ. 405136758) - შპს | N39: B59170EC-16CC-499A-9FF7-0428DCB8F727 | O39: 04FB28EA-5501-4B01-BA1D-C2955C0E1213 | Q39: gio.nikabadze@gmail.com | S39: Khiliani | 1.1.1. | ახალშენი 2016 | 26,400.00 USD | 31.07.2019 | T39: =IFERROR(__xludf.DUMMYFUNCTION("""COMPUTED_VALUE"""),1208.0) -> 1208 | U39: ICE38
A40: 44342.729 | B40: ორბი ჯგუფი ბათუმი (ს.კ. 445468798) - შპს | C40: ORBI Office Lift | D40: 1.1.1. (+) შემოსავალი ლიფტების რეალიზაციიდან | E40: 43788 | F40: 30000 | G40: USD | H40: მიმდინარე | K40: 445468798/43788/1.1.1./1 | L40: 5B0BA252-1105-4374-8654-430AE04E8A64 | M40: ORBI Office Lift | 1.1.1. (+) შემოსავალი ლიფტების რეალიზაციიდან | ორბი ჯგუფი ბათუმი (ს.კ. 445468798) - შპს | N40: B59170EC-16CC-499A-9FF7-0428DCB8F727 | O40: E284E0FD-A2B7-4D93-8E91-006FF0A8A4CE | Q40: gio.nikabadze@gmail.com | S40: ORBI Office Lift | 1.1.1. | ორბი ჯგუფი ბათუმი | 30,000.00 USD | 19.11.2019 | T40: =IFERROR(__xludf.DUMMYFUNCTION("""COMPUTED_VALUE"""),773.0) -> 773 | U40: ICE39
A41: 44342.729 | B41: ბეტა ჯგუფი (ს.კ. 405171996) - შპს | C41: IBIS Perovi | D41: 1.1.1. (+) შემოსავალი ლიფტების რეალიზაციიდან | E41: 43719 | F41: 83750 | G41: USD | H41: მიმდინარე | J41: 1 6 30 1257 1 | K41: 405171996/43719/1.1.1./1 | L41: 3619FEF3-250F-43C1-93C3-B77FEADECC84 | M41: IBIS Perovi | 1.1.1. (+) შემოსავალი ლიფტების რეალიზაციიდან | ბეტა ჯგუფი (ს.კ. 405171996) - შპს | N41: B59170EC-16CC-499A-9FF7-0428DCB8F727 | O41: 3029E0C5-9337-4596-87DB-0A677D44A180 | Q41: gio.nikabadze@gmail.com | S41: IBIS Perovi | 1.1.1. | ბეტა ჯგუფი | 83,750.00 USD | 11.09.2019 | T41: =IFERROR(__xludf.DUMMYFUNCTION("""COMPUTED_VALUE"""),1257.0) -> 1257 | U41: ICE40
A42: 44342.729 | B42: კანოპუსი (ს.კ. 405229881) - შპს | C42: Sololaki | D42: 1.1.1. (+) შემოსავალი ლიფტების რეალიზაციიდან | E42: 43769 | F42: 24000 | G42: USD | H42: მიმდინარე | K42: 405229881/43769/1.1.1./1 | L42: 0159D5F2-86A6-4D6F-87C4-D563AB9AA860 | M42: Sololaki | 1.1.1. (+) შემოსავალი ლიფტების რეალიზაციიდან | კანოპუსი (ს.კ. 405229881) - შპს | N42: B59170EC-16CC-499A-9FF7-0428DCB8F727 | O42: F43C8D9B-B556-4114-B404-AEEFA8C31B20 | Q42: gio.nikabadze@gmail.com | S42: Sololaki | 1.1.1. | კანოპუსი | 24,000.00 USD | 31.10.2019 | T42: =IFERROR(__xludf.DUMMYFUNCTION("""COMPUTED_VALUE"""),1276.0) -> 1276 | U42: ICE41
A43: 44342.73 | B43: ბეტა ჯგუფი (ს.კ. 405171996) - შპს | C43: IBIS Perov Dumbwaiter | D43: 1.1.1. (+) შემოსავალი ლიფტების რეალიზაციიდან | E43: 43804 | F43: 16300 | G43: USD | H43: მიმდინარე | K43: 405171996/43804/1.1.1./1 | L43: B9668B49-46F2-4E2F-B183-F802279CAA6C | M43: IBIS Perov Dumbwaiter | 1.1.1. (+) შემოსავალი ლიფტების რეალიზაციიდან | ბეტა ჯგუფი (ს.კ. 405171996) - შპს | N43: B59170EC-16CC-499A-9FF7-0428DCB8F727 | O43: 3029E0C5-9337-4596-87DB-0A677D44A180 | Q43: gio.nikabadze@gmail.com | S43: IBIS Perov Dumbwaiter | 1.1.1. | ბეტა ჯგუფი | 16,300.00 USD | 05.12.2019 | T43: =IFERROR(__xludf.DUMMYFUNCTION("""COMPUTED_VALUE"""),1257.0) -> 1257 | U43: ICE42
A44: 44342.73 | B44: სითი რეალ ისთეით (ს.კ. 406067410) - შპს | C44: Kleemann Pekini | D44: 1.1.1. (+) შემოსავალი ლიფტების რეალიზაციიდან | E44: 43228 | F44: 353218 | G44: USD | H44: მიმდინარე | K44: 406067410/43228/1.1.1./1 | L44: 7BF69DE1-9EA3-4EAE-9713-910380F15356 | M44: Kleemann Pekini | 1.1.1. (+) შემოსავალი ლიფტების რეალიზაციიდან | სითი რეალ ისთეით (ს.კ. 406067410) - შპს | N44: B59170EC-16CC-499A-9FF7-0428DCB8F727 | O44: 04B265BA-02B2-4620-87C1-1D9CA09C8962 | Q44: gio.nikabadze@gmail.com | S44: Kleemann Pekini | 1.1.1. | სითი რეალ ისთეით | 353,218.00 USD | 08.05.2018 | T44: =IFERROR(__xludf.DUMMYFUNCTION("""COMPUTED_VALUE"""),892.0) -> 892 | U44: ICE43
A45: 44342.73 | B45: ანაგი (ს.კ. 245416401) - შპს | C45: Gudauri Alpic | D45: 1.1.1. (+) შემოსავალი ლიფტების რეალიზაციიდან | E45: 43732 | F45: 81000 | G45: USD | H45: მიმდინარე | K45: 245416401/43732/1.1.1./1 | L45: 56B157A4-78FF-42DD-B032-B267792BBED8 | M45: Gudauri Alpic | 1.1.1. (+) შემოსავალი ლიფტების რეალიზაციიდან | ანაგი (ს.კ. 245416401) - შპს | N45: B59170EC-16CC-499A-9FF7-0428DCB8F727 | O45: 7DDF7E55-92EE-4E47-9E16-F1D4D3FABF60 | Q45: gio.nikabadze@gmail.com | S45: Gudauri Alpic | 1.1.1. | ანაგი | 81,000.00 USD | 24.09.2019 | T45: =IFERROR(__xludf.DUMMYFUNCTION("""COMPUTED_VALUE"""),1132.0) -> 1132 | U45: ICE44
A46: 44342.73 | B46: ანაგი (ს.კ. 245416401) - შპს | C46: Batumi Stadium | D46: 1.1.1. (+) შემოსავალი ლიფტების რეალიზაციიდან | E46: 43589 | F46: 139932.66 | G46: USD | H46: მიმდინარე | K46: 245416401/43589/1.1.1./1 | L46: 8A712C8E-EE09-4385-8E22-3C7E70676923 | M46: Batumi Stadium | 1.1.1. (+) შემოსავალი ლიფტების რეალიზაციიდან | ანაგი (ს.კ. 245416401) - შპს | N46: B59170EC-16CC-499A-9FF7-0428DCB8F727 | O46: 7DDF7E55-92EE-4E47-9E16-F1D4D3FABF60 | Q46: gio.nikabadze@gmail.com | S46: Batumi Stadium | 1.1.1. | ანაგი | 139,932.66 USD | 04.05.2019 | T46: =IFERROR(__xludf.DUMMYFUNCTION("""COMPUTED_VALUE"""),1132.0) -> 1132 | U46: ICE45
A47: 44342.73 | B47: დეველოპერული კომპანია მც კვადრატი (ს.კ. 404474403) - შპს | C47: Gazapkhuli | D47: 1.1.2. (+) შემოსავალი ლიფტების სერვისიდან - გეგმიური | E47: 43831 | F47: 100 | G47: GEL | H47: მიმდინარე | K47: 404474403/43831/1.1.2./1 | L47: F487D937-85D8-43B1-8D4D-27757BC0BE36 | M47: Gazapkhuli | 1.1.2. (+) შემოსავალი ლიფტების სერვისიდან - გეგმიური | დეველოპერული კომპანია მც კვადრატი (ს.კ. 404474403) - შპს | N47: 12238130-9D12-4099-A48B-9EB5A085E0F8 | O47: EC22924D-9707-4BC1-9814-FD45570D704B | Q47: gio.nikabadze@gmail.com | S47: Gazapkhuli | 1.1.2. | დეველოპერული კომპანია მც კვადრატი | 100.00 GEL | 01.01.2020 | U47: ICE46
A48: 44342.73 | B48: თერმორუმი (ს.კ. 405134448) - შპს | C48: Thermoroom | D48: 1.1.1. (+) შემოსავალი ლიფტების რეალიზაციიდან | E48: 43546 | F48: 82900 | G48: USD | H48: მიმდინარე | K48: 405134448/43546/1.1.1./1 | L48: 554B8399-3687-4503-A8C9-12E3BBDE60E9 | M48: Thermoroom | 1.1.1. (+) შემოსავალი ლიფტების რეალიზაციიდან | თერმორუმი (ს.კ. 405134448) - შპს | N48: B59170EC-16CC-499A-9FF7-0428DCB8F727 | O48: A71E107A-D0C2-4155-83C0-22DCD22BD19F | Q48: gio.nikabadze@gmail.com | S48: Thermoroom | 1.1.1. | თერმორუმი | 82,900.00 USD | 22.03.2019 | T48: =IFERROR(__xludf.DUMMYFUNCTION("""COMPUTED_VALUE"""),585.0) -> 585 | U48: ICE47
A49: 44342.73 | B49: ტექნოკლიმა (ს.კ. 402009857) - შპს | C49: ENCORE Gudauri | D49: 1.1.1. (+) შემოსავალი ლიფტების რეალიზაციიდან | E49: 43711 | F49: 180540 | G49: EUR | H49: მიმდინარე | K49: 402009857/43711/1.1.1./1 | L49: 165277AE-3A0C-494C-8C92-CC3A68C15375 | M49: ENCORE Gudauri | 1.1.1. (+) შემოსავალი ლიფტების რეალიზაციიდან | ტექნოკლიმა (ს.კ. 402009857) - შპს | N49: B59170EC-16CC-499A-9FF7-0428DCB8F727 | O49: 967D325E-9818-4D9E-8716-3D66A117AF42 | Q49: gio.nikabadze@gmail.com | S49: ENCORE Gudauri | 1.1.1. | ტექნოკლიმა | 180,540.00 EUR | 03.09.2019 | T49: =IFERROR(__xludf.DUMMYFUNCTION("""COMPUTED_VALUE"""),506.0) -> 506 | U49: ICE48
A50: 44342.73 | B50: ჯი-ემ-თი სასტუმროები (ს.კ. 203842333) - შპს | C50: MOXY HVAC | D50: 1.2.1. (+) შემოსავალი MEP დანადგარების რეალიზაციიდან | E50: 43124 | F50: 416156.43 | G50: USD | H50: მიმდინარე | K50: 203842333/43124/1.2.1./1 | L50: C78D3D45-B3FB-4533-AE2E-53D8A5FA6C34 | M50: MOXY HVAC | 1.2.1. (+) შემოსავალი MEP დანადგარების რეალიზაციიდან | ჯი-ემ-თი სასტუმროები (ს.კ. 203842333) - შპს | N50: FEA4B88F-633F-4422-B3D6-250792A2DA80 | O50: 9E3145B1-F47E-49C3-BF51-BCB9055ABC20 | Q50: gio.nikabadze@gmail.com | S50: MOXY HVAC | 1.2.1. | ჯი-ემ-თი სასტუმროები | 416,156.43 USD | 24.01.2018 | T50: =IFERROR(__xludf.DUMMYFUNCTION("""COMPUTED_VALUE"""),571.0) -> 571 | U50: ICE49
A51: 44342.73 | B51: 1920 (ს.კ. 400247899) - შპს | C51: Paster Hostel | D51: 1.1.1. (+) შემოსავალი ლიფტების რეალიზაციიდან | E51: 43571 | F51: 36200 | G51: USD | H51: მიმდინარე | K51: 400247899/43571/1.1.1./1 | L51: 59251EDF-2EEC-4871-ADAA-D7901FD7C84E | M51: Paster Hostel | 1.1.1. (+) შემოსავალი ლიფტების რეალიზაციიდან | 1920 (ს.კ. 400247899) - შპს | N51: B59170EC-16CC-499A-9FF7-0428DCB8F727 | O51: 30D1E20E-3889-4EAC-883A-6509ABFFA5D7 | Q51: gio.nikabadze@gmail.com | S51: Paster Hostel | 1.1.1. | 1920 | 36,200.00 USD | 16.04.2019 | T51: =IFERROR(__xludf.DUMMYFUNCTION("""COMPUTED_VALUE"""),1108.0) -> 1108 | U51: ICE50
A52: 44342.73 | B52: გოჩა ჩხაიძე (ს.კ. 65002012107) - ფიზ. პირი | C52: Kaklebi | D52: 1.1.1. (+) შემოსავალი ლიფტების რეალიზაციიდან | E52: 43566 | F52: 37760 | G52: USD | H52: მიმდინარე | K52: 65002012107/43566/1.1.1./1 | L52: BCE7664A-F047-41AD-8D93-756E595D21F6 | M52: Kaklebi | 1.1.1. (+) შემოსავალი ლიფტების რეალიზაციიდან | გოჩა ჩხაიძე (ს.კ. 65002012107) - ფიზ. პირი | N52: B59170EC-16CC-499A-9FF7-0428DCB8F727 | O52: B658F42E-3F0A-44A3-B4ED-A7B4C1D8DEAE | Q52: gio.nikabadze@gmail.com | S52: Kaklebi | 1.1.1. | გოჩა ჩხაიძე | 37,760.00 USD | 11.04.2019 | T52: =IFERROR(__xludf.DUMMYFUNCTION("""COMPUTED_VALUE"""),1114.0) -> 1114 | U52: ICE51
A53: 44342.73 | B53: სვირი + (ს.კ. 212916932) - შპს | C53: 156-ე საჯარო სკოლა | D53: 1.1.1. (+) შემოსავალი ლიფტების რეალიზაციიდან | E53: 43861 | F53: 8900 | G53: USD | H53: მიმდინარე | K53: 212916932/43861/1.1.1./1 | L53: 6E5F6760-7CEF-41CD-B373-B0F3B4EABCCA | M53: 156-ე საჯარო სკოლა | 1.1.1. (+) შემოსავალი ლიფტების რეალიზაციიდან | სვირი + (ს.კ. 212916932) - შპს | N53: B59170EC-16CC-499A-9FF7-0428DCB8F727 | O53: E0680301-116E-4D99-93F4-7C694EC80172 | Q53: gio.nikabadze@gmail.com | S53: 156-ე საჯარო სკოლა | 1.1.1. | სვირი + | 8,900.00 USD | 31.01.2020 | T53: =IFERROR(__xludf.DUMMYFUNCTION("""COMPUTED_VALUE"""),1350.0) -> 1350 | U53: ICE52
A54: 44342.73 | B54: ორბი ჯგუფი (ს.კ. 245621849) - შპს | C54: Beach Tower | D54: 1.1.1. (+) შემოსავალი ლიფტების რეალიზაციიდან | E54: 43348 | F54: 650000 | G54: USD | H54: მიმდინარე | K54: 245621849/43348/1.1.1./1 | L54: A4E19F43-E4DA-4585-8CAE-4CC3E97F5AF8 | M54: Beach Tower | 1.1.1. (+) შემოსავალი ლიფტების რეალიზაციიდან | ორბი ჯგუფი (ს.კ. 245621849) - შპს | N54: B59170EC-16CC-499A-9FF7-0428DCB8F727 | O54: 90293CD0-6262-4F6E-9B52-E8D909232966 | Q54: gio.nikabadze@gmail.com | S54: Beach Tower | 1.1.1. | ორბი ჯგუფი | 650,000.00 USD | 05.09.2018 | T54: =IFERROR(__xludf.DUMMYFUNCTION("""COMPUTED_VALUE"""),998.0) -> 998 | U54: ICE53
A55: 44342.73 | B55: მეპერსი (ს.კ. 402121887) - შპს | C55: Modus PU Duct | D55: 1.2.1. (+) შემოსავალი MEP დანადგარების რეალიზაციიდან | E55: 43595 | F55: 109423.76 | G55: GEL | H55: მიმდინარე | K55: 402121887/43595/1.2.1./1 | L55: A9B6FEBD-3A47-4DFB-ACC0-BE284A1FE961 | M55: Modus PU Duct | 1.2.1. (+) შემოსავალი MEP დანადგარების რეალიზაციიდან | მეპერსი (ს.კ. 402121887) - შპს | N55: FEA4B88F-633F-4422-B3D6-250792A2DA80 | O55: 43EABC78-AF64-4C14-9FEF-C7E6A1B6F07E | Q55: gio.nikabadze@gmail.com | S55: Modus PU Duct | 1.2.1. | მეპერსი | 109,423.76 GEL | 10.05.2019 | T55: =IFERROR(__xludf.DUMMYFUNCTION("""COMPUTED_VALUE"""),1148.0) -> 1148 | U55: ICE54
A56: 44342.73 | B56: მეპერსი (ს.კ. 402121887) - შპს | C56: Modus VRV | D56: 1.2.1. (+) შემოსავალი MEP დანადგარების რეალიზაციიდან | E56: 43602 | F56: 11810 | G56: USD | H56: მიმდინარე | K56: 402121887/43602/1.2.1./1 | L56: FD1EDF0D-38F3-4DAD-BD01-A54531CAD071 | M56: Modus VRV | 1.2.1. (+) შემოსავალი MEP დანადგარების რეალიზაციიდან | მეპერსი (ს.კ. 402121887) - შპს | N56: FEA4B88F-633F-4422-B3D6-250792A2DA80 | O56: 43EABC78-AF64-4C14-9FEF-C7E6A1B6F07E | Q56: gio.nikabadze@gmail.com | S56: Modus VRV | 1.2.1. | მეპერსი | 11,810.00 USD | 17.05.2019 | T56: =IFERROR(__xludf.DUMMYFUNCTION("""COMPUTED_VALUE"""),1148.0) -> 1148 | U56: ICE55
A57: 44342.73 | B57: მეპერსი (ს.კ. 402121887) - შპს | C57: Ramada Melikishvili | D57: 1.2.1. (+) შემოსავალი MEP დანადგარების რეალიზაციიდან | E57: 43633 | F57: =319728.97-7068.01 -> 312660.96 | G57: USD | H57: მიმდინარე | K57: 402121887/43633/1.2.1./1 | L57: 9A0748F1-7447-4E99-B52A-C299B2BE2267 | M57: Ramada Melikishvili | 1.2.1. (+) შემოსავალი MEP დანადგარების რეალიზაციიდან | მეპერსი (ს.კ. 402121887) - შპს | N57: FEA4B88F-633F-4422-B3D6-250792A2DA80 | O57: 43EABC78-AF64-4C14-9FEF-C7E6A1B6F07E | Q57: gio.nikabadze@gmail.com | S57: Ramada Melikishvili | 1.2.1. | მეპერსი | 312,660.96 USD | 17.06.2019 | T57: =IFERROR(__xludf.DUMMYFUNCTION("""COMPUTED_VALUE"""),1148.0) -> 1148 | U57: ICE56
A58: 44342.73 | B58: მეპერსი (ს.კ. 402121887) - შპს | C58: Ramada Melikishvili Additional | D58: 1.2.1. (+) შემოსავალი MEP დანადგარების რეალიზაციიდან | E58: 43693 | F58: 11636.28 | G58: USD | H58: მიმდინარე | K58: 402121887/43693/1.2.1./1 | L58: 300E878A-B016-48B5-A930-E3EDEEFB0FED | M58: Ramada Melikishvili Additional | 1.2.1. (+) შემოსავალი MEP დანადგარების რეალიზაციიდან | მეპერსი (ს.კ. 402121887) - შპს | N58: FEA4B88F-633F-4422-B3D6-250792A2DA80 | O58: 43EABC78-AF64-4C14-9FEF-C7E6A1B6F07E | Q58: gio.nikabadze@gmail.com | S58: Ramada Melikishvili Additional | 1.2.1. | მეპერსი | 11,636.28 USD | 16.08.2019 | T58: =IFERROR(__xludf.DUMMYFUNCTION("""COMPUTED_VALUE"""),1148.0) -> 1148 | U58: ICE57
A59: 44342.73 | B59: მეპერსი (ს.კ. 402121887) - შპს | C59: Hilton Garden Mockup | D59: 1.2.1. (+) შემოსავალი MEP დანადგარების რეალიზაციიდან | E59: 43597 | F59: 2872.57 | G59: USD | H59: მიმდინარე | K59: 402121887/43597/1.2.1./1 | L59: B866CCA1-4F5C-4C49-9517-CD64763AD8CC | M59: Hilton Garden Mockup | 1.2.1. (+) შემოსავალი MEP დანადგარების რეალიზაციიდან | მეპერსი (ს.კ. 402121887) - შპს | N59: FEA4B88F-633F-4422-B3D6-250792A2DA80 | O59: 43EABC78-AF64-4C14-9FEF-C7E6A1B6F07E | Q59: gio.nikabadze@gmail.com | S59: Hilton Garden Mockup | 1.2.1. | მეპერსი | 2,872.57 USD | 12.05.2019 | T59: =IFERROR(__xludf.DUMMYFUNCTION("""COMPUTED_VALUE"""),1148.0) -> 1148 | U59: ICE58
A60: 44342.73 | B60: მეპერსი (ს.კ. 402121887) - შპს | C60: Kempinski Mockup | D60: 1.2.1. (+) შემოსავალი MEP დანადგარების რეალიზაციიდან | E60: 43759 | F60: 2245.13 | G60: USD | H60: მიმდინარე | K60: 402121887/43759/1.2.1./1 | L60: 3A44DBA7-152B-4C3D-8A70-C51193549F07 | M60: Kempinski Mockup | 1.2.1. (+) შემოსავალი MEP დანადგარების რეალიზაციიდან | მეპერსი (ს.კ. 402121887) - შპს | N60: FEA4B88F-633F-4422-B3D6-250792A2DA80 | O60: 43EABC78-AF64-4C14-9FEF-C7E6A1B6F07E | Q60: gio.nikabadze@gmail.com | S60: Kempinski Mockup | 1.2.1. | მეპერსი | 2,245.13 USD | 21.10.2019 | T60: =IFERROR(__xludf.DUMMYFUNCTION("""COMPUTED_VALUE"""),1148.0) -> 1148 | U60: ICE59
A61: 44342.73 | B61: მეპერსი (ს.კ. 402121887) - შპს | C61: Copper Pipes Stock | D61: 1.2.1. (+) შემოსავალი MEP დანადგარების რეალიზაციიდან | E61: 43882 | F61: 7201.2 | G61: GEL | H61: მიმდინარე | K61: 402121887/43882/1.2.1./1 | L61: 89441EC7-27A5-4210-91F3-96BB35383900 | M61: Copper Pipes Stock | 1.2.1. (+) შემოსავალი MEP დანადგარების რეალიზაციიდან | მეპერსი (ს.კ. 402121887) - შპს | N61: FEA4B88F-633F-4422-B3D6-250792A2DA80 | O61: 43EABC78-AF64-4C14-9FEF-C7E6A1B6F07E | Q61: gio.nikabadze@gmail.com | S61: Copper Pipes Stock | 1.2.1. | მეპერსი | 7,201.20 GEL | 21.02.2020 | T61: =IFERROR(__xludf.DUMMYFUNCTION("""COMPUTED_VALUE"""),1148.0) -> 1148 | U61: ICE60
A62: 44342.73 | B62: მეპერსი (ს.კ. 402121887) - შპს | C62: Valves Med. University | D62: 1.2.1. (+) შემოსავალი MEP დანადგარების რეალიზაციიდან | E62: 43815 | F62: 881.46 | G62: EUR | H62: მიმდინარე | K62: 402121887/43815/1.2.1./1 | L62: F4A2EDEE-7E84-4F30-91BA-5752286BD0A1 | M62: Valves Med. University | 1.2.1. (+) შემოსავალი MEP დანადგარების რეალიზაციიდან | მეპერსი (ს.კ. 402121887) - შპს | N62: FEA4B88F-633F-4422-B3D6-250792A2DA80 | O62: 43EABC78-AF64-4C14-9FEF-C7E6A1B6F07E | Q62: gio.nikabadze@gmail.com | S62: Valves Med. University | 1.2.1. | მეპერსი | 881.46 EUR | 16.12.2019 | T62: =IFERROR(__xludf.DUMMYFUNCTION("""COMPUTED_VALUE"""),1148.0) -> 1148 | U62: ICE61
A63: 44342.73 | B63: მეპერსი (ს.კ. 402121887) - შპს | C63: Orbi Bakuriani VRV | D63: 1.2.1. (+) შემოსავალი MEP დანადგარების რეალიზაციიდან | E63: 43894 | F63: 87484.25 | G63: USD | H63: მიმდინარე | K63: 402121887/43894/1.2.1./1 | L63: 740B928C-4173-4A00-8523-A29D1C596ECC | M63: Orbi Bakuriani VRV | 1.2.1. (+) შემოსავალი MEP დანადგარების რეალიზაციიდან | მეპერსი (ს.კ. 402121887) - შპს | N63: FEA4B88F-633F-4422-B3D6-250792A2DA80 | O63: 43EABC78-AF64-4C14-9FEF-C7E6A1B6F07E | Q63: gio.nikabadze@gmail.com | S63: Orbi Bakuriani VRV | 1.2.1. | მეპერსი | 87,484.25 USD | 04.03.2020 | T63: =IFERROR(__xludf.DUMMYFUNCTION("""COMPUTED_VALUE"""),1148.0) -> 1148 | U63: ICE62
A64: 44342.73 | B64: მეპერსი (ს.კ. 402121887) - შპს | C64: Hilton Garden Inn VRV 1 | D64: 1.2.1. (+) შემოსავალი MEP დანადგარების რეალიზაციიდან | E64: 43900 | F64: 56818.84 | G64: USD | H64: მიმდინარე | J64: 1 6 30 1148 | K64: 402121887/43900/1.2.1./1 | L64: 68E42D82-BE50-4F66-82A4-CDC4DEB322C3 | M64: Hilton Garden Inn VRV 1 | 1.2.1. (+) შემოსავალი MEP დანადგარების რეალიზაციიდან | მეპერსი (ს.კ. 402121887) - შპს | N64: FEA4B88F-633F-4422-B3D6-250792A2DA80 | O64: 43EABC78-AF64-4C14-9FEF-C7E6A1B6F07E | Q64: gio.nikabadze@gmail.com | S64: Hilton Garden Inn VRV 1 | 1.2.1. | მეპერსი | 56,818.84 USD | 10.03.2020 | T64: =IFERROR(__xludf.DUMMYFUNCTION("""COMPUTED_VALUE"""),1148.0) -> 1148 | U64: ICE63
A65: 44342.73 | B65: მეპერსი (ს.კ. 402121887) - შპს | C65: Hilton Garden Inn PIPES | D65: 1.2.1. (+) შემოსავალი MEP დანადგარების რეალიზაციიდან | E65: 43903 | F65: 8684.86 | G65: USD | H65: მიმდინარე | K65: 402121887/43903/1.2.1./1 | L65: 4723017E-EF0C-427F-BE8D-95A49C03170F | M65: Hilton Garden Inn PIPES | 1.2.1. (+) შემოსავალი MEP დანადგარების რეალიზაციიდან | მეპერსი (ს.კ. 402121887) - შპს | N65: FEA4B88F-633F-4422-B3D6-250792A2DA80 | O65: 43EABC78-AF64-4C14-9FEF-C7E6A1B6F07E | Q65: gio.nikabadze@gmail.com | S65: Hilton Garden Inn PIPES | 1.2.1. | მეპერსი | 8,684.86 USD | 13.03.2020 | T65: =IFERROR(__xludf.DUMMYFUNCTION("""COMPUTED_VALUE"""),1148.0) -> 1148 | U65: ICE64
A66: 44342.73 | B66: Dar Building (ს.კ. 445420875) - შპს | C66: OFFICE Dar Building | D66: 1.1.1. (+) შემოსავალი ლიფტების რეალიზაციიდან | E66: 44170 | F66: 20800 | G66: USD | H66: მიმდინარე | K66: 445420875/44170/1.1.1./1 | L66: E3FEF6DB-0C48-4832-A5CF-868EF7B591A4 | M66: OFFICE Dar Building | 1.1.1. (+) შემოსავალი ლიფტების რეალიზაციიდან | Dar Building (ს.კ. 445420875) - შპს | N66: B59170EC-16CC-499A-9FF7-0428DCB8F727 | O66: 7BF4A039-29BC-44AC-A87D-E8832394B94E | Q66: gio.nikabadze@gmail.com | S66: OFFICE Dar Building | 1.1.1. | Dar Building | 20,800.00 USD | 05.12.2020 | T66: =IFERROR(__xludf.DUMMYFUNCTION("""COMPUTED_VALUE"""),853.0) -> 853 | U66: ICE65
A67: 44342.73 | B67: ანაგი (ს.კ. 245416401) - შპს | C67: Archi Digomi | D67: 1.1.1. (+) შემოსავალი ლიფტების რეალიზაციიდან | E67: 43955 | F67: 107760 | G67: USD | H67: მიმდინარე | J67: 1 6 30 1132 3 | K67: 245416401/43955/1.1.1./1 | L67: A68BEF97-923B-4D3C-8A08-9CF9311578B7 | M67: Archi Digomi | 1.1.1. (+) შემოსავალი ლიფტების რეალიზაციიდან | ანაგი (ს.კ. 245416401) - შპს | N67: B59170EC-16CC-499A-9FF7-0428DCB8F727 | O67: 7DDF7E55-92EE-4E47-9E16-F1D4D3FABF60 | Q67: gio.nikabadze@gmail.com | S67: Archi Digomi | 1.1.1. | ანაგი | 107,760.00 USD | 04.05.2020 | T67: =IFERROR(__xludf.DUMMYFUNCTION("""COMPUTED_VALUE"""),1132.0) -> 1132 | U67: ICE66
A68: 44342.73 | B68: Spanish Retail Georgia (ს.კ. 404404774) - შპს | C68: Zara City Mall | D68: 1.1.2. (+) შემოსავალი ლიფტების სერვისიდან - გეგმიური | E68: 43800 | F68: 1800 | G68: GEL | H68: მიმდინარე | K68: 404404774/43800/1.1.2./1 | L68: 5D93EA98-C1B5-460B-B2FB-C526651B3F64 | M68: Zara City Mall | 1.1.2. (+) შემოსავალი ლიფტების სერვისიდან - გეგმიური | Spanish Retail Georgia (ს.კ. 404404774) - შპს | N68: 12238130-9D12-4099-A48B-9EB5A085E0F8 | O68: 6DF25574-2F03-43D0-AEC4-2CD26A4A0C3A | Q68: gio.nikabadze@gmail.com | S68: Zara City Mall | 1.1.2. | Spanish Retail Georgia | 1,800.00 GEL | 01.12.2019 | T68: =IFERROR(__xludf.DUMMYFUNCTION("""COMPUTED_VALUE"""),666.0) -> 666 | U68: ICE67
A69: 44342.73 | B69: გალერია ჰოტელ მენეჯმენტი (ს.კ. 404567508) - შპს | C69: Galleria Hotel | D69: 1.1.2. (+) შემოსავალი ლიფტების სერვისიდან - გეგმიური | E69: 43617 | F69: 300 | G69: USD | H69: მიმდინარე | J69: 1 6 31 1221 | K69: 404567508/43617/1.1.2./1 | L69: 7A62FB55-149C-4A13-B506-1117D0761263 | M69: Galleria Hotel | 1.1.2. (+) შემოსავალი ლიფტების სერვისიდან - გეგმიური | გალერია ჰოტელ მენეჯმენტი (ს.კ. 404567508) - შპს | N69: 12238130-9D12-4099-A48B-9EB5A085E0F8 | O69: 75C62470-4093-4FB3-8DB7-F700FEC2C222 | Q69: gio.nikabadze@gmail.com | S69: Galleria Hotel | 1.1.2. | გალერია ჰოტელ მენეჯმენტი | 300.00 USD | 01.06.2019 | T69: =IFERROR(__xludf.DUMMYFUNCTION("""COMPUTED_VALUE"""),1221.0) -> 1221 | U69: ICE68
A70: 44342.73 | B70: ერა პალასი (ს.კ. 245619807) - შპს | C70: Era Palace | D70: 1.1.2. (+) შემოსავალი ლიფტების სერვისიდან - გეგმიური | E70: 43586 | F70: 200 | G70: GEL | H70: მიმდინარე | K70: 245619807/43586/1.1.2./1 | L70: 75411B5D-3913-49E0-B5A6-48ED0D4EEBB6 | M70: Era Palace | 1.1.2. (+) შემოსავალი ლიფტების სერვისიდან - გეგმიური | ერა პალასი (ს.კ. 245619807) - შპს | N70: 12238130-9D12-4099-A48B-9EB5A085E0F8 | O70: 71A96223-5CD1-4DA9-9617-A85A565B4669 | Q70: gio.nikabadze@gmail.com | S70: Era Palace | 1.1.2. | ერა პალასი | 200.00 GEL | 01.05.2019 | T70: =IFERROR(__xludf.DUMMYFUNCTION("""COMPUTED_VALUE"""),145.0) -> 145 | U70: ICE69
A71: 44342.73 | B71: თბილი სახლი (ს.კ. 204976179) - შპს | C71: Muzeums | D71: 1.1.2. (+) შემოსავალი ლიფტების სერვისიდან - გეგმიური | E71: 43497 | F71: 750 | G71: GEL | H71: მიმდინარე | K71: 204976179/43497/1.1.2./1 | L71: 9D27243C-D81D-4430-90C4-5F8CCBF5809F | M71: Muzeums | 1.1.2. (+) შემოსავალი ლიფტების სერვისიდან - გეგმიური | თბილი სახლი (ს.კ. 204976179) - შპს | N71: 12238130-9D12-4099-A48B-9EB5A085E0F8 | O71: 726D9023-53A2-435E-8A5B-8BCEA9625E08 | Q71: gio.nikabadze@gmail.com | S71: Muzeums | 1.1.2. | თბილი სახლი | 750.00 GEL | 01.02.2019 | T71: =IFERROR(__xludf.DUMMYFUNCTION("""COMPUTED_VALUE"""),4.0) -> 4 | U71: ICE70
A72: 44342.73 | B72: იუნიქს ქონსთრაქშენ კომპანი (ს.კ. 405133822) - შპს | C72: UNIX Ipolit Ivanov | D72: 1.1.2. (+) შემოსავალი ლიფტების სერვისიდან - გეგმიური | E72: 43539 | F72: 1500 | G72: GEL | H72: მიმდინარე | J72: 1 6 31 902 | K72: 405133822/43539/1.1.2./1 | L72: 4C7A7F0C-187C-4D2B-857D-A522EE632F24 | M72: UNIX Ipolit Ivanov | 1.1.2. (+) შემოსავალი ლიფტების სერვისიდან - გეგმიური | იუნიქს ქონსთრაქშენ კომპანი (ს.კ. 405133822) - შპს | N72: 12238130-9D12-4099-A48B-9EB5A085E0F8 | O72: B4968862-3843-414D-9E73-1A7611618B41 | Q72: gio.nikabadze@gmail.com | S72: UNIX Ipolit Ivanov | 1.1.2. | იუნიქს ქონსთრაქშენ კომპანი | 1,500.00 GEL | 15.03.2019 | T72: =IFERROR(__xludf.DUMMYFUNCTION("""COMPUTED_VALUE"""),902.0) -> 902 | U72: ICE71
A73: 44342.73 | B73: პიქსელ მენეჯმენტი (ს.კ. 404862314) - შპს | C73: PIXEL | D73: 1.1.2. (+) შემოსავალი ლიფტების სერვისიდან - გეგმიური | E73: 43435 | F73: 1645 | G73: USD | H73: მიმდინარე | J73: 1 6 31 1044 | K73: 404862314/43435/1.1.2./1 | L73: 5485535C-2F61-456A-9548-E6F7EE885A7B | M73: PIXEL | 1.1.2. (+) შემოსავალი ლიფტების სერვისიდან - გეგმიური | პიქსელ მენეჯმენტი (ს.კ. 404862314) - შპს | N73: 12238130-9D12-4099-A48B-9EB5A085E0F8 | O73: 42A1D3CC-F7CD-4EC1-A425-6E261EB22EBC | Q73: gio.nikabadze@gmail.com | S73: PIXEL | 1.1.2. | პიქსელ მენეჯმენტი | 1,645.00 USD | 01.12.2018 | T73: =IFERROR(__xludf.DUMMYFUNCTION("""COMPUTED_VALUE"""),1044.0) -> 1044 | U73: ICE72
A74: 44342.73 | B74: დავუდ (ს.კ. 404438417) - სს | C74: Khetagurov Office | D74: 1.1.2. (+) შემოსავალი ლიფტების სერვისიდან - გეგმიური | E74: 43462 | F74: 1000 | G74: GEL | H74: მიმდინარე | J74: 1 6 31 1059 | K74: 404438417/43462/1.1.2./1 | L74: 1937421D-0C5D-47B3-84E7-F06B2CECE212 | M74: Khetagurov Office | 1.1.2. (+) შემოსავალი ლიფტების სერვისიდან - გეგმიური | დავუდ (ს.კ. 404438417) - სს | N74: 12238130-9D12-4099-A48B-9EB5A085E0F8 | O74: 059C7B48-86B5-4FB3-AF87-564E29C595E9 | Q74: gio.nikabadze@gmail.com | S74: Khetagurov Office | 1.1.2. | დავუდ | 1,000.00 GEL | 28.12.2018 | T74: =IFERROR(__xludf.DUMMYFUNCTION("""COMPUTED_VALUE"""),1059.0) -> 1059 | U74: ICE73
A75: 44342.73 | B75: თბილი სახლი (ს.კ. 204976179) - შპს | C75: Galleria Tbilisi | D75: 1.1.2. (+) შემოსავალი ლიფტების სერვისიდან - გეგმიური | E75: 43862 | F75: 1 | G75: USD | H75: მიმდინარე | J75: 1 6 31 4 1 | K75: 204976179/43862/1.1.2./1 | L75: 0ABCF801-1738-4393-BF70-87C1FA8C9F0D | M75: Galleria Tbilisi | 1.1.2. (+) შემოსავალი ლიფტების სერვისიდან - გეგმიური | თბილი სახლი (ს.კ. 204976179) - შპს | N75: 12238130-9D12-4099-A48B-9EB5A085E0F8 | O75: 726D9023-53A2-435E-8A5B-8BCEA9625E08 | Q75: gio.nikabadze@gmail.com | S75: Galleria Tbilisi | 1.1.2. | თბილი სახლი | 1.00 USD | 01.02.2020 | T75: =IFERROR(__xludf.DUMMYFUNCTION("""COMPUTED_VALUE"""),4.0) -> 4 | U75: ICE74
A76: 44342.73 | B76: თბილისი ცენტრალი (ს.კ. 205129653) - სს | C76: Tbilisi Central HVAC Service | D76: 1.2.2. (+) შემოსავალი MEP დანადგარების სერვისიდან - გეგმიური | E76: 44075 | F76: 1 | G76: GEL | H76: მიმდინარე | J76: 1 6 31 1371 | K76: 205129653/44075/1.2.2./1 | L76: F2EB27A3-4AED-4096-AF24-4B7A9C4512A7 | M76: Tbilisi Central HVAC Service | 1.2.2. (+) შემოსავალი MEP დანადგარების სერვისიდან - გეგმიური | თბილისი ცენტრალი (ს.კ. 205129653) - სს | N76: 31562B13-85C8-472E-8D02-01D802D635C1 | O76: 3D0B2E19-A7F7-45A1-A329-05C7D5F99C8A | Q76: gio.nikabadze@gmail.com | S76: Tbilisi Central HVAC Service | 1.2.2. | თბილისი ცენტრალი | 1.00 GEL | 01.09.2020 | T76: =IFERROR(__xludf.DUMMYFUNCTION("""COMPUTED_VALUE"""),1371.0) -> 1371 | U76: ICE75
A77: 44342.73 | B77: ნინო კირცხალია (ს.კ. 01031005362) - ფიზ. პირი | C77: Mziuri | D77: 1.1.2. (+) შემოსავალი ლიფტების სერვისიდან - გეგმიური | E77: 43831 | F77: 1 | G77: GEL | H77: მიმდინარე | K77: 01031005362/43831/1.1.2./1 | L77: 7D93AE81-A3AA-4EF2-A79C-0DE309E1B402 | M77: Mziuri | 1.1.2. (+) შემოსავალი ლიფტების სერვისიდან - გეგმიური | ნინო კირცხალია (ს.კ. 01031005362) - ფიზ. პირი | N77: 12238130-9D12-4099-A48B-9EB5A085E0F8 | O77: A5C53B51-103C-4B24-B833-6653108CDE4E | Q77: gio.nikabadze@gmail.com | S77: Mziuri | 1.1.2. | ნინო კირცხალია | 1.00 GEL | 01.01.2020 | U77: ICE76
A78: 44342.73 | B78: ორბი ჯგუფი ბათუმი (ს.კ. 445468798) - შპს | C78: Orbi Other | D78: 1.1.2. (+) შემოსავალი ლიფტების სერვისიდან - გეგმიური | E78: 43831 | F78: 1 | G78: GEL | H78: მიმდინარე | K78: 445468798/43831/1.1.2./1 | L78: DCE1FBA2-AC1D-4481-B551-0D2215188884 | M78: Orbi Other | 1.1.2. (+) შემოსავალი ლიფტების სერვისიდან - გეგმიური | ორბი ჯგუფი ბათუმი (ს.კ. 445468798) - შპს | N78: 12238130-9D12-4099-A48B-9EB5A085E0F8 | O78: E284E0FD-A2B7-4D93-8E91-006FF0A8A4CE | Q78: gio.nikabadze@gmail.com | S78: Orbi Other | 1.1.2. | ორბი ჯგუფი ბათუმი | 1.00 GEL | 01.01.2020 | T78: =IFERROR(__xludf.DUMMYFUNCTION("""COMPUTED_VALUE"""),773.0) -> 773 | U78: ICE77
A79: 44342.73 | B79: ნირან პროპერტის დეველოპმენტი (ს.კ. 204564729) - შპს | C79: Bagebi | D79: 1.1.1. (+) შემოსავალი ლიფტების რეალიზაციიდან | E79: 43122 | F79: 132998 | G79: USD | H79: მიმდინარე | K79: 204564729/43122/1.1.1./1 | L79: DA0DFA6D-FB59-42CC-A78F-D211EFD8F169 | M79: Bagebi | 1.1.1. (+) შემოსავალი ლიფტების რეალიზაციიდან | ნირან პროპერტის დეველოპმენტი (ს.კ. 204564729) - შპს | N79: B59170EC-16CC-499A-9FF7-0428DCB8F727 | O79: ADBD14C7-72E2-4703-84A5-B47EC0ACB641 | Q79: gio.nikabadze@gmail.com | S79: Bagebi | 1.1.1. | ნირან პროპერტის დეველოპმენტი | 132,998.00 USD | 22.01.2018 | T79: =IFERROR(__xludf.DUMMYFUNCTION("""COMPUTED_VALUE"""),189.0) -> 189 | U79: ICE78
A80: 44342.73 | B80: ეიჩ ენდ ემ ჰენეს ენდ მაურიც ჯორჯია (ს.კ. 405164192) - შპს | C80: H&M | D80: 1.1.2. (+) შემოსავალი ლიფტების სერვისიდან - გეგმიური | E80: 43831 | F80: 1 | G80: USD | H80: მიმდინარე | K80: 405164192/43831/1.1.2./1 | L80: BF531404-15D2-4F83-B5B6-88709B6ADBF6 | M80: H&M | 1.1.2. (+) შემოსავალი ლიფტების სერვისიდან - გეგმიური | ეიჩ ენდ ემ ჰენეს ენდ მაურიც ჯორჯია (ს.კ. 405164192) - შპს | N80: 12238130-9D12-4099-A48B-9EB5A085E0F8 | O80: 5569F396-B588-4816-B115-348127388797 | Q80: gio.nikabadze@gmail.com | S80: H&M | 1.1.2. | ეიჩ ენდ ემ ჰენეს ენდ მაურიც ჯორჯია | 1.00 USD | 01.01.2020 | T80: =IFERROR(__xludf.DUMMYFUNCTION("""COMPUTED_VALUE"""),1314.0) -> 1314 | U80: ICE79
A81: 44342.73 | B81: ჯი ემ ემ (ს.კ. 405115174) - შპს | C81: Marshal Gelovanis 52 | D81: 1.1.2. (+) შემოსავალი ლიფტების სერვისიდან - გეგმიური | E81: 43831 | F81: 1 | G81: GEL | H81: მიმდინარე | K81: 405115174/43831/1.1.2./1 | L81: 96631073-7C4A-4C6C-B52A-4318B544C05B | M81: Marshal Gelovanis 52 | 1.1.2. (+) შემოსავალი ლიფტების სერვისიდან - გეგმიური | ჯი ემ ემ (ს.კ. 405115174) - შპს | N81: 12238130-9D12-4099-A48B-9EB5A085E0F8 | O81: E6DBF0EF-BE8A-403C-B757-246FDF95B244 | Q81: gio.nikabadze@gmail.com | S81: Marshal Gelovanis 52 | 1.1.2. | ჯი ემ ემ | 1.00 GEL | 01.01.2020 | T81: =IFERROR(__xludf.DUMMYFUNCTION("""COMPUTED_VALUE"""),1382.0) -> 1382 | U81: ICE80
A82: 44342.73 | B82: ოლსერვისგრუპ (ს.კ. 406233552) - შპს | C82: Marshal Gelovani 52 | D82: 1.1.2. (+) შემოსავალი ლიფტების სერვისიდან - გეგმიური | E82: 43466 | F82: 1200 | G82: GEL | H82: მიმდინარე | K82: 406233552/43466/1.1.2./1 | L82: 46C2E29A-C8A7-4F32-BAC6-1FA5D9731A7D | M82: Marshal Gelovani 52 | 1.1.2. (+) შემოსავალი ლიფტების სერვისიდან - გეგმიური | ოლსერვისგრუპ (ს.კ. 406233552) - შპს | N82: 12238130-9D12-4099-A48B-9EB5A085E0F8 | O82: C08C6F90-5808-41D5-A1CC-2A1CCFAF531B | Q82: gio.nikabadze@gmail.com | S82: Marshal Gelovani 52 | 1.1.2. | ოლსერვისგრუპ | 1,200.00 GEL | 01.01.2019 | T82: =IFERROR(__xludf.DUMMYFUNCTION("""COMPUTED_VALUE"""),1184.0) -> 1184 | U82: ICE81
A83: 44342.731 | B83: ოლსერვისჯგუფი (ს.კ. 406269041) - შპს | C83: Marshal Gelovani 52 | D83: 1.1.2. (+) შემოსავალი ლიფტების სერვისიდან - გეგმიური | E83: 43471 | F83: 10 | G83: GEL | H83: მიმდინარე | K83: 406269041/43471/1.1.2./1 | L83: 4DE1AF55-BD4D-49EA-9CC2-7254972C4832 | M83: Marshal Gelovani 52 | 1.1.2. (+) შემოსავალი ლიფტების სერვისიდან - გეგმიური | ოლსერვისჯგუფი (ს.კ. 406269041) - შპს | N83: 12238130-9D12-4099-A48B-9EB5A085E0F8 | O83: F830C37E-1BED-416F-996D-C3C709C5F339 | Q83: gio.nikabadze@gmail.com | S83: Marshal Gelovani 52 | 1.1.2. | ოლსერვისჯგუფი | 10.00 GEL | 06.01.2019 | T83: =IFERROR(__xludf.DUMMYFUNCTION("""COMPUTED_VALUE"""),1066.0) -> 1066 | U83: ICE82
A84: 44342.731 | B84: არქი საბურთალო (ს.კ. 405176982) - შპს | C84: Archi Jikia Block C | D84: 1.1.1. (+) შემოსავალი ლიფტების რეალიზაციიდან | E84: 44170 | F84: 136600 | G84: USD | H84: მიმდინარე | J84: 1 6 30 1453 | K84: 405176982/44170/1.1.1./1 | L84: 7F8895E0-BD86-4959-A763-AD1CD0F7FC77 | M84: Archi Jikia Block C | 1.1.1. (+) შემოსავალი ლიფტების რეალიზაციიდან | არქი საბურთალო (ს.კ. 405176982) - შპს | N84: B59170EC-16CC-499A-9FF7-0428DCB8F727 | O84: 25CECFAB-615A-4A1E-AC57-B18B8A92799B | Q84: gio.nikabadze@gmail.com | S84: Archi Jikia Block C | 1.1.1. | არქი საბურთალო | 136,600.00 USD | 05.12.2020 | T84: =IFERROR(__xludf.DUMMYFUNCTION("""COMPUTED_VALUE"""),1453.0) -> 1453 | U84: ICE83
A85: 44342.731 | B85: შატო მუხრანი (ს.კ. 205000381) - სს | C85: Shato Mukhrani Gen-Set 2020 | D85: 1.2.1. (+) შემოსავალი MEP დანადგარების რეალიზაციიდან | E85: 43990 | F85: 55680 | G85: EUR | H85: მიმდინარე | K85: 205000381/43990/1.2.1./1 | L85: 798DCBA8-C0CF-4CAA-83E5-397FD911AAF0 | M85: Shato Mukhrani Gen-Set 2020 | 1.2.1. (+) შემოსავალი MEP დანადგარების რეალიზაციიდან | შატო მუხრანი (ს.კ. 205000381) - სს | N85: FEA4B88F-633F-4422-B3D6-250792A2DA80 | O85: 0E3C8876-D73B-417A-A61E-5FD08F98EDCB | Q85: gio.nikabadze@gmail.com | S85: Shato Mukhrani Gen-Set 2020 | 1.2.1. | შატო მუხრანი | 55,680.00 EUR | 08.06.2020 | T85: =IFERROR(__xludf.DUMMYFUNCTION("""COMPUTED_VALUE"""),415.0) -> 415 | U85: ICE84
A86: 44342.731 | B86: ენსოლი (ს.კ. 205236190) - შპს | C86: Galleria Tbilisi | D86: 1.1.2. (+) შემოსავალი ლიფტების სერვისიდან - გეგმიური | E86: 43497 | F86: 3500 | G86: USD | H86: მიმდინარე | K86: 205236190/43497/1.1.2./1 | L86: 1BF0C1A7-EC4F-48F6-B5F1-6257BAB8D882 | M86: Galleria Tbilisi | 1.1.2. (+) შემოსავალი ლიფტების სერვისიდან - გეგმიური | ენსოლი (ს.კ. 205236190) - შპს | N86: 12238130-9D12-4099-A48B-9EB5A085E0F8 | O86: E13FA661-3B3D-437A-A26D-FB16D4C0D1C1 | Q86: gio.nikabadze@gmail.com | S86: Galleria Tbilisi | 1.1.2. | ენსოლი | 3,500.00 USD | 01.02.2019 | T86: =IFERROR(__xludf.DUMMYFUNCTION("""COMPUTED_VALUE"""),979.0) -> 979 | U86: ICE85
A87: 44342.731 | B87: დომუსი (ს.კ. 404908864) - შპს | C87: Domus | D87: 1.1.2. (+) შემოსავალი ლიფტების სერვისიდან - გეგმიური | E87: 43146 | F87: 1400 | G87: USD | H87: მიმდინარე | K87: 404908864/43146/1.1.2./1 | L87: 4E9E5103-4BE9-4B72-838F-7CCF0A771578 | M87: Domus | 1.1.2. (+) შემოსავალი ლიფტების სერვისიდან - გეგმიური | დომუსი (ს.კ. 404908864) - შპს | N87: 12238130-9D12-4099-A48B-9EB5A085E0F8 | O87: B6B26BE3-174A-4141-A509-B6EE28D4677B | Q87: gio.nikabadze@gmail.com | S87: Domus | 1.1.2. | დომუსი | 1,400.00 USD | 15.02.2018 | T87: =IFERROR(__xludf.DUMMYFUNCTION("""COMPUTED_VALUE"""),546.0) -> 546 | U87: ICE86
A88: 44342.731 | B88: როვშან მამადოვი (ს.კ. 67008001418) - ფიზ. პირი | C88: Rovshan Mamadovi | D88: 1.2.1. (+) შემოსავალი MEP დანადგარების რეალიზაციიდან | E88: 43999 | F88: 8214 | G88: USD | H88: მიმდინარე | K88: 67008001418/43999/1.2.1./1 | L88: 97C6ECBA-DA0F-4E2C-B8DB-26993DFCE122 | M88: Rovshan Mamadovi | 1.2.1. (+) შემოსავალი MEP დანადგარების რეალიზაციიდან | როვშან მამადოვი (ს.კ. 67008001418) - ფიზ. პირი | N88: FEA4B88F-633F-4422-B3D6-250792A2DA80 | O88: 3E3BB97B-230C-48D5-B6EF-41C9AE93AE61 | Q88: gio.nikabadze@gmail.com | S88: Rovshan Mamadovi | 1.2.1. | როვშან მამადოვი | 8,214.00 USD | 17.06.2020 | T88: =IFERROR(__xludf.DUMMYFUNCTION("""COMPUTED_VALUE"""),1462.0) -> 1462 | U88: ICE87
A89: 44342.731 | B89: თბილი სახლი (ს.კ. 204976179) - შპს | C89: Sapatrulo | D89: 1.1.2. (+) შემოსავალი ლიფტების სერვისიდან - გეგმიური | E89: 43497 | F89: 250 | G89: GEL | H89: მიმდინარე | K89: 204976179/43497/1.1.2./1 | L89: 8BDDF5BD-4A6B-4C8E-942A-C62E20BCD667 | M89: Sapatrulo | 1.1.2. (+) შემოსავალი ლიფტების სერვისიდან - გეგმიური | თბილი სახლი (ს.კ. 204976179) - შპს | N89: 12238130-9D12-4099-A48B-9EB5A085E0F8 | O89: 726D9023-53A2-435E-8A5B-8BCEA9625E08 | Q89: gio.nikabadze@gmail.com | S89: Sapatrulo | 1.1.2. | თბილი სახლი | 250.00 GEL | 01.02.2019 | T89: =IFERROR(__xludf.DUMMYFUNCTION("""COMPUTED_VALUE"""),4.0) -> 4 | U89: ICE88
A90: 44342.731 | B90: თბილი სახლი (ს.კ. 204976179) - შპს | C90: Erovnuli | D90: 1.1.2. (+) შემოსავალი ლიფტების სერვისიდან - გეგმიური | E90: 43497 | F90: 500 | G90: GEL | H90: მიმდინარე | K90: 204976179/43497/1.1.2./1 | L90: ED933289-CEA4-446C-99AC-B1B310C1ECB5 | M90: Erovnuli | 1.1.2. (+) შემოსავალი ლიფტების სერვისიდან - გეგმიური | თბილი სახლი (ს.კ. 204976179) - შპს | N90: 12238130-9D12-4099-A48B-9EB5A085E0F8 | O90: 726D9023-53A2-435E-8A5B-8BCEA9625E08 | Q90: gio.nikabadze@gmail.com | S90: Erovnuli | 1.1.2. | თბილი სახლი | 500.00 GEL | 01.02.2019 | T90: =IFERROR(__xludf.DUMMYFUNCTION("""COMPUTED_VALUE"""),4.0) -> 4 | U90: ICE89
A91: 44342.731 | B91: ერა პალასი (ს.კ. 245619807) - შპს | C91: Gonio | D91: 1.1.2. (+) შემოსავალი ლიფტების სერვისიდან - გეგმიური | E91: 43617 | F91: 300 | G91: GEL | H91: მიმდინარე | K91: 245619807/43617/1.1.2./1 | L91: 3D3A6BA2-FC37-4C7B-9979-9C6C932BA9BF | M91: Gonio | 1.1.2. (+) შემოსავალი ლიფტების სერვისიდან - გეგმიური | ერა პალასი (ს.კ. 245619807) - შპს | N91: 12238130-9D12-4099-A48B-9EB5A085E0F8 | O91: 71A96223-5CD1-4DA9-9617-A85A565B4669 | Q91: gio.nikabadze@gmail.com | S91: Gonio | 1.1.2. | ერა პალასი | 300.00 GEL | 01.06.2019 | T91: =IFERROR(__xludf.DUMMYFUNCTION("""COMPUTED_VALUE"""),145.0) -> 145 | U91: ICE90
A92: 44342.731 | B92: მოდუსი (ს.კ. 245565669) - შპს | C92: Modus batumi | D92: 1.1.2. (+) შემოსავალი ლიფტების სერვისიდან - გეგმიური | E92: 43592 | F92: 400 | G92: GEL | H92: მიმდინარე | K92: 245565669/43592/1.1.2./1 | L92: 07BBF564-E19D-46EA-8A32-44F28241B4B1 | M92: Modus batumi | 1.1.2. (+) შემოსავალი ლიფტების სერვისიდან - გეგმიური | მოდუსი (ს.კ. 245565669) - შპს | N92: 12238130-9D12-4099-A48B-9EB5A085E0F8 | O92: 9729C88B-F3C5-441A-8782-0656302A37F2 | Q92: gio.nikabadze@gmail.com | S92: Modus batumi | 1.1.2. | მოდუსი | 400.00 GEL | 07.05.2019 | T92: =IFERROR(__xludf.DUMMYFUNCTION("""COMPUTED_VALUE"""),642.0) -> 642 | U92: ICE91
A93: 44342.731 | B93: ი. აბაშიძე 70 (ს.კ. ICE001082) - ამხანაგობა | C93: Abashidze 70 | D93: 1.1.2. (+) შემოსავალი ლიფტების სერვისიდან - გეგმიური | E93: 44013 | F93: 3000 | G93: GEL | H93: მიმდინარე | J93: 1 6 31 1485 | K93: ICE001082/44013/1.1.2./1 | L93: AFEF3A3A-0240-4773-9C5F-B7AC3C14711D | M93: Abashidze 70 | 1.1.2. (+) შემოსავალი ლიფტების სერვისიდან - გეგმიური | ი. აბაშიძე 70 (ს.კ. ICE001082) - ამხანაგობა | N93: 12238130-9D12-4099-A48B-9EB5A085E0F8 | O93: 3D0E73E0-0C40-467D-922F-74E3D4746FBD | Q93: gio.nikabadze@gmail.com | S93: Abashidze 70 | 1.1.2. | ი. აბაშიძე 70 | 3,000.00 GEL | 01.07.2020 | T93: =IFERROR(__xludf.DUMMYFUNCTION("""COMPUTED_VALUE"""),1485.0) -> 1485 | U93: ICE92
A94: 44342.731 | B94: დელისი 2020 (ს.კ. ICE001083) - ამხანაგობა | C94: Epic gazapkhuli | D94: 1.1.2. (+) შემოსავალი ლიფტების სერვისიდან - გეგმიური | E94: 44014 | F94: 500 | G94: GEL | H94: მიმდინარე | J94: 1 6 31 1470 | K94: ICE001083/44014/1.1.2./1 | L94: F132898D-4C52-4676-8689-21E7C2709157 | M94: Epic gazapkhuli | 1.1.2. (+) შემოსავალი ლიფტების სერვისიდან - გეგმიური | დელისი 2020 (ს.კ. ICE001083) - ამხანაგობა | N94: 12238130-9D12-4099-A48B-9EB5A085E0F8 | O94: E18CBC98-9D65-4F4A-ADC0-B7350770D6F8 | Q94: gio.nikabadze@gmail.com | S94: Epic gazapkhuli | 1.1.2. | დელისი 2020 | 500.00 GEL | 02.07.2020 | T94: =IFERROR(__xludf.DUMMYFUNCTION("""COMPUTED_VALUE"""),1470.0) -> 1470 | U94: ICE93
A95: 44342.731 | B95: ბაგები (ს.კ. 405330262) - შპს | C95: Epic Bagebi | D95: 1.1.1. (+) შემოსავალი ლიფტების რეალიზაციიდან | E95: 44013 | F95: 64790 | G95: USD | H95: მიმდინარე | J95: 1 6 30 1471 | K95: 405330262/44013/1.1.1./1 | L95: 6F71BE16-57C6-4634-B19B-DAD451C7CB11 | M95: Epic Bagebi | 1.1.1. (+) შემოსავალი ლიფტების რეალიზაციიდან | ბაგები (ს.კ. 405330262) - შპს | N95: B59170EC-16CC-499A-9FF7-0428DCB8F727 | O95: C270A903-5EB0-4E5A-8448-B4A637D5211F | Q95: gio.nikabadze@gmail.com | S95: Epic Bagebi | 1.1.1. | ბაგები | 64,790.00 USD | 01.07.2020 | T95: =IFERROR(__xludf.DUMMYFUNCTION("""COMPUTED_VALUE"""),1471.0) -> 1471 | U95: ICE94
A96: 44342.731 | B96: მეპერსი (ს.კ. 402121887) - შპს | C96: Hilton Garden Inn Pipes 2 | D96: 1.2.1. (+) შემოსავალი MEP დანადგარების რეალიზაციიდან | E96: 43983 | F96: 4580.94 | G96: USD | H96: მიმდინარე | K96: 402121887/43983/1.2.1./1 | L96: 53D78126-348D-47EC-8E18-ACA366D918B3 | M96: Hilton Garden Inn Pipes 2 | 1.2.1. (+) შემოსავალი MEP დანადგარების რეალიზაციიდან | მეპერსი (ს.კ. 402121887) - შპს | N96: FEA4B88F-633F-4422-B3D6-250792A2DA80 | O96: 43EABC78-AF64-4C14-9FEF-C7E6A1B6F07E | Q96: gio.nikabadze@gmail.com | S96: Hilton Garden Inn Pipes 2 | 1.2.1. | მეპერსი | 4,580.94 USD | 01.06.2020 | T96: =IFERROR(__xludf.DUMMYFUNCTION("""COMPUTED_VALUE"""),1148.0) -> 1148 | U96: ICE95
A97: 44342.731 | B97: თეგეტა მოტორსი (ს.კ. 202177205) - შპს | C97: Tegeta Batumi | D97: 1.1.2. (+) შემოსავალი ლიფტების სერვისიდან - გეგმიური | E97: 44013 | F97: 1 | G97: GEL | H97: მიმდინარე | K97: 202177205/44013/1.1.2./1 | L97: 065B3CAD-864E-4949-AE0A-9170B8973736 | M97: Tegeta Batumi | 1.1.2. (+) შემოსავალი ლიფტების სერვისიდან - გეგმიური | თეგეტა მოტორსი (ს.კ. 202177205) - შპს | N97: 12238130-9D12-4099-A48B-9EB5A085E0F8 | O97: 5A21C207-4868-4EA6-9B48-5D0F743D5535 | Q97: gio.nikabadze@gmail.com | S97: Tegeta Batumi | 1.1.2. | თეგეტა მოტორსი | 1.00 GEL | 01.07.2020 | T97: =IFERROR(__xludf.DUMMYFUNCTION("""COMPUTED_VALUE"""),93.0) -> 93 | U97: ICE96
A98: 44342.731 | B98: საქ სამეცნიერო-საგანმანათ. კომპ ქსელების ასოციაცია გრენა (ს.კ. 204931654) - ასოციაცია | C98: Grena MEP 1 | D98: 1.2.1. (+) შემოსავალი MEP დანადგარების რეალიზაციიდან | E98: 44004 | F98: 9885 | G98: GEL | H98: მიმდინარე | K98: 204931654/44004/1.2.1./1 | L98: 67800432-96FF-489A-983A-99BD3F4C4954 | M98: Grena MEP 1 | 1.2.1. (+) შემოსავალი MEP დანადგარების რეალიზაციიდან | საქ სამეცნიერო-საგანმანათ. კომპ ქსელების ასოციაცია გრენა (ს.კ. 204931654) - ასოციაცია | N98: FEA4B88F-633F-4422-B3D6-250792A2DA80 | O98: 43A2E6CF-382D-45D9-9C82-D074B7CA8474 | Q98: gio.nikabadze@gmail.com | S98: Grena MEP 1 | 1.2.1. | საქ სამეცნიერო-საგანმანათ. კომპ ქსელების ასოციაცია გრენა | 9,885.00 GEL | 22.06.2020 | T98: =IFERROR(__xludf.DUMMYFUNCTION("""COMPUTED_VALUE"""),1459.0) -> 1459 | U98: ICE97
A99: 44342.731 | B99: ახალშენი 2016 (ს.კ. 405136758) - შპს | C99: Khiliani | D99: 1.1.2. (+) შემოსავალი ლიფტების სერვისიდან - გეგმიური | E99: 43891 | F99: 1 | G99: GEL | H99: მიმდინარე | K99: 405136758/43891/1.1.2./1 | L99: AB270374-C6A2-4223-A667-ED4DD185CC7F | M99: Khiliani | 1.1.2. (+) შემოსავალი ლიფტების სერვისიდან - გეგმიური | ახალშენი 2016 (ს.კ. 405136758) - შპს | N99: 12238130-9D12-4099-A48B-9EB5A085E0F8 | O99: 04FB28EA-5501-4B01-BA1D-C2955C0E1213 | Q99: gio.nikabadze@gmail.com | S99: Khiliani | 1.1.2. | ახალშენი 2016 | 1.00 GEL | 01.03.2020 | T99: =IFERROR(__xludf.DUMMYFUNCTION("""COMPUTED_VALUE"""),1208.0) -> 1208 | U99: ICE98
A100: 44342.731 | B100: ფალიაშვილის 63 (ს.კ. ICE000034) - ამხანაგობა | C100: Domus Paliashvilis 63 | D100: 1.1.2. (+) შემოსავალი ლიფტების სერვისიდან - გეგმიური | E100: 44019 | F100: 1 | G100: GEL | H100: მიმდინარე | J100: 1 6 31 863 | K100: ICE000034/44019/1.1.2./1 | L100: D1923AD8-5716-4970-9AD0-37642D2C4B69 | M100: Domus Paliashvilis 63 | 1.1.2. (+) შემოსავალი ლიფტების სერვისიდან - გეგმიური | ფალიაშვილის 63 (ს.კ. ICE000034) - ამხანაგობა | N100: 12238130-9D12-4099-A48B-9EB5A085E0F8 | O100: 7F0A41E4-FA68-43E7-A979-126560D14B58 | Q100: gio.nikabadze@gmail.com | S100: Domus Paliashvilis 63 | 1.1.2. | ფალიაშვილის 63 | 1.00 GEL | 07.07.2020 | T100: =IFERROR(__xludf.DUMMYFUNCTION("""COMPUTED_VALUE"""),863.0) -> 863 | U100: ICE99
...

Sheet Pivot Table 1
E1: Income Docs | F1: CF_Income
E2: =IFERROR(__xludf.DUMMYFUNCTION("IFERROR(index(query(IMPORTRANGE(""1NDlqCtTmX6RSsROpyHMIN-WbErF8iWbqHj88gYBfL_Q"",""Incomes!A:Y""),""Select sum(Col5) where Col16 = '""&VLOOKUP(B2,{Projects!S:S,Projects!L:L},2,false)&""'"",0),2),0)"),0.0) -> 0 | H2: =D2-E2 -> 120 | I2: =IFERROR(__xludf.DUMMYFUNCTION("ifna(query(IMPORTRANGE(""1NDlqCtTmX6RSsROpyHMIN-WbErF8iWbqHj88gYBfL_Q"",""Incomes!A:Y""),""Select Col25 where Col16 = '""&VLOOKUP(B2,{Projects!S:S,Projects!L:L},2,false)&""'"",0),0)"),0.0) -> 0
E3: =IFERROR(__xludf.DUMMYFUNCTION("IFERROR(index(query(IMPORTRANGE(""1NDlqCtTmX6RSsROpyHMIN-WbErF8iWbqHj88gYBfL_Q"",""Incomes!A:Y""),""Select sum(Col5) where Col16 = '""&VLOOKUP(B3,{Projects!S:S,Projects!L:L},2,false)&""'"",0),2),0)"),23100.0) -> 23100 | H3: =D3-E3 -> 0 | I3: =IFERROR(__xludf.DUMMYFUNCTION("ifna(transpose(query(IMPORTRANGE(""1NDlqCtTmX6RSsROpyHMIN-WbErF8iWbqHj88gYBfL_Q"",""Incomes!A:Y""),""Select Col25 where Col16 = '""&VLOOKUP(B3,{Projects!S:S,Projects!L:L},2,false)&""'"",0)),"""")"),"https://drive.google.com/file/d/1LYETNmjS6zVIZBGE88tluHrlTqP7pB4d/view") -> https://drive.google.com/file/d/1LYETNmjS6zVIZBGE88tluHrlTqP7pB4d/view
E4: =IFERROR(__xludf.DUMMYFUNCTION("IFERROR(index(query(IMPORTRANGE(""1NDlqCtTmX6RSsROpyHMIN-WbErF8iWbqHj88gYBfL_Q"",""Incomes!A:Y""),""Select sum(Col5) where Col16 = '""&VLOOKUP(B4,{Projects!S:S,Projects!L:L},2,false)&""'"",0),2),0)"),0.0) -> 0 | H4: =D4-E4 -> 1 | I4: =IFERROR(__xludf.DUMMYFUNCTION("ifna(transpose(query(IMPORTRANGE(""1NDlqCtTmX6RSsROpyHMIN-WbErF8iWbqHj88gYBfL_Q"",""Incomes!A:Y""),""Select Col25 where Col16 = '""&VLOOKUP(B4,{Projects!S:S,Projects!L:L},2,false)&""'"",0)),"""")"),"")
E5: =IFERROR(__xludf.DUMMYFUNCTION("IFERROR(index(query(IMPORTRANGE(""1NDlqCtTmX6RSsROpyHMIN-WbErF8iWbqHj88gYBfL_Q"",""Incomes!A:Y""),""Select sum(Col5) where Col16 = '""&VLOOKUP(B5,{Projects!S:S,Projects!L:L},2,false)&""'"",0),2),0)"),155520.0) -> 155520 | H5: =D5-E5 -> 0 | I5: =IFERROR(__xludf.DUMMYFUNCTION("ifna(transpose(query(IMPORTRANGE(""1NDlqCtTmX6RSsROpyHMIN-WbErF8iWbqHj88gYBfL_Q"",""Incomes!A:Y""),""Select Col25 where Col16 = '""&VLOOKUP(B5,{Projects!S:S,Projects!L:L},2,false)&""'"",0)),"""")"),"https://drive.google.com/file/d/1qeuaKubIR1SQ05XZJsliaHwS28sKjpu3/view") -> https://drive.google.com/file/d/1qeuaKubIR1SQ05XZJsliaHwS28sKjpu3/view
E6: =IFERROR(__xludf.DUMMYFUNCTION("IFERROR(index(query(IMPORTRANGE(""1NDlqCtTmX6RSsROpyHMIN-WbErF8iWbqHj88gYBfL_Q"",""Incomes!A:Y""),""Select sum(Col5) where Col16 = '""&VLOOKUP(B6,{Projects!S:S,Projects!L:L},2,false)&""'"",0),2),0)"),1.0) -> 1 | H6: =D6-E6 -> 0 | I6: =IFERROR(__xludf.DUMMYFUNCTION("ifna(transpose(query(IMPORTRANGE(""1NDlqCtTmX6RSsROpyHMIN-WbErF8iWbqHj88gYBfL_Q"",""Incomes!A:Y""),""Select Col25 where Col16 = '""&VLOOKUP(B6,{Projects!S:S,Projects!L:L},2,false)&""'"",0)),"""")"),"https://drive.google.com/open?id=1W56u6YNbSTCc5sQjPZ9j8_vXkFeYeVho") -> https://drive.google.com/open?id=1W56u6YNbSTCc5sQjPZ9j8_vXkFeYeVho
E7: =IFERROR(__xludf.DUMMYFUNCTION("IFERROR(index(query(IMPORTRANGE(""1NDlqCtTmX6RSsROpyHMIN-WbErF8iWbqHj88gYBfL_Q"",""Incomes!A:Y""),""Select sum(Col5) where Col16 = '""&VLOOKUP(B7,{Projects!S:S,Projects!L:L},2,false)&""'"",0),2),0)"),0.0) -> 0 | H7: =D7-E7 -> 15000 | I7: =IFERROR(__xludf.DUMMYFUNCTION("ifna(transpose(query(IMPORTRANGE(""1NDlqCtTmX6RSsROpyHMIN-WbErF8iWbqHj88gYBfL_Q"",""Incomes!A:Y""),""Select Col25 where Col16 = '""&VLOOKUP(B7,{Projects!S:S,Projects!L:L},2,false)&""'"",0)),"""")"),"")
E8: =IFERROR(__xludf.DUMMYFUNCTION("IFERROR(index(query(IMPORTRANGE(""1NDlqCtTmX6RSsROpyHMIN-WbErF8iWbqHj88gYBfL_Q"",""Incomes!A:Y""),""Select sum(Col5) where Col16 = '""&VLOOKUP(B8,{Projects!S:S,Projects!L:L},2,false)&""'"",0),2),0)"),291990.0) -> 291990 | H8: =D8-E8 -> 0 | I8: =IFERROR(__xludf.DUMMYFUNCTION("ifna(transpose(query(IMPORTRANGE(""1NDlqCtTmX6RSsROpyHMIN-WbErF8iWbqHj88gYBfL_Q"",""Incomes!A:Y""),""Select Col25 where Col16 = '""&VLOOKUP(B8,{Projects!S:S,Projects!L:L},2,false)&""'"",0)),"""")"),"https://drive.google.com/open?id=1gsGgurCsW7yVlG0_XRaUFCUVfE1j_IxP") -> https://drive.google.com/open?id=1gsGgurCsW7yVlG0_XRaUFCUVfE1j_IxP | J8: =IFERROR(__xludf.DUMMYFUNCTION("""COMPUTED_VALUE"""),"https://drive.google.com/open?id=17Uk7dIz0VBDs7FRg4UIvRbDaq0hfdb0X") -> https://drive.google.com/open?id=17Uk7dIz0VBDs7FRg4UIvRbDaq0hfdb0X
E9: =IFERROR(__xludf.DUMMYFUNCTION("IFERROR(index(query(IMPORTRANGE(""1NDlqCtTmX6RSsROpyHMIN-WbErF8iWbqHj88gYBfL_Q"",""Incomes!A:Y""),""Select sum(Col5) where Col16 = '""&VLOOKUP(B9,{Projects!S:S,Projects!L:L},2,false)&""'"",0),2),0)"),0.0) -> 0 | H9: =D9-E9 -> 5806 | I9: =IFERROR(__xludf.DUMMYFUNCTION("ifna(transpose(query(IMPORTRANGE(""1NDlqCtTmX6RSsROpyHMIN-WbErF8iWbqHj88gYBfL_Q"",""Incomes!A:Y""),""Select Col25 where Col16 = '""&VLOOKUP(B9,{Projects!S:S,Projects!L:L},2,false)&""'"",0)),"""")"),"")
E10: =IFERROR(__xludf.DUMMYFUNCTION("IFERROR(index(query(IMPORTRANGE(""1NDlqCtTmX6RSsROpyHMIN-WbErF8iWbqHj88gYBfL_Q"",""Incomes!A:Y""),""Select sum(Col5) where Col16 = '""&VLOOKUP(B10,{Projects!S:S,Projects!L:L},2,false)&""'"",0),2),0)"),0.0) -> 0 | H10: =D10-E10 -> 1800000 | I10: =IFERROR(__xludf.DUMMYFUNCTION("ifna(transpose(query(IMPORTRANGE(""1NDlqCtTmX6RSsROpyHMIN-WbErF8iWbqHj88gYBfL_Q"",""Incomes!A:Y""),""Select Col25 where Col16 = '""&VLOOKUP(B10,{Projects!S:S,Projects!L:L},2,false)&""'"",0)),"""")"),"")
E11: =IFERROR(__xludf.DUMMYFUNCTION("IFERROR(index(query(IMPORTRANGE(""1NDlqCtTmX6RSsROpyHMIN-WbErF8iWbqHj88gYBfL_Q"",""Incomes!A:Y""),""Select sum(Col5) where Col16 = '""&VLOOKUP(B11,{Projects!S:S,Projects!L:L},2,false)&""'"",0),2),0)"),0.0) -> 0 | H11: =D11-E11 -> 444536.2 | I11: =IFERROR(__xludf.DUMMYFUNCTION("ifna(transpose(query(IMPORTRANGE(""1NDlqCtTmX6RSsROpyHMIN-WbErF8iWbqHj88gYBfL_Q"",""Incomes!A:Y""),""Select Col25 where Col16 = '""&VLOOKUP(B11,{Projects!S:S,Projects!L:L},2,false)&""'"",0)),"""")"),"")
E12: =IFERROR(__xludf.DUMMYFUNCTION("IFERROR(index(query(IMPORTRANGE(""1NDlqCtTmX6RSsROpyHMIN-WbErF8iWbqHj88gYBfL_Q"",""Incomes!A:Y""),""Select sum(Col5) where Col16 = '""&VLOOKUP(B12,{Projects!S:S,Projects!L:L},2,false)&""'"",0),2),0)"),0.0) -> 0 | H12: =D12-E12 -> 9300 | I12: =IFERROR(__xludf.DUMMYFUNCTION("ifna(transpose(query(IMPORTRANGE(""1NDlqCtTmX6RSsROpyHMIN-WbErF8iWbqHj88gYBfL_Q"",""Incomes!A:Y""),""Select Col25 where Col16 = '""&VLOOKUP(B12,{Projects!S:S,Projects!L:L},2,false)&""'"",0)),"""")"),"")
E13: =IFERROR(__xludf.DUMMYFUNCTION("IFERROR(index(query(IMPORTRANGE(""1NDlqCtTmX6RSsROpyHMIN-WbErF8iWbqHj88gYBfL_Q"",""Incomes!A:Y""),""Select sum(Col5) where Col16 = '""&VLOOKUP(B13,{Projects!S:S,Projects!L:L},2,false)&""'"",0),2),0)"),0.0) -> 0 | H13: =D13-E13 -> 2200 | I13: =IFERROR(__xludf.DUMMYFUNCTION("ifna(transpose(query(IMPORTRANGE(""1NDlqCtTmX6RSsROpyHMIN-WbErF8iWbqHj88gYBfL_Q"",""Incomes!A:Y""),""Select Col25 where Col16 = '""&VLOOKUP(B13,{Projects!S:S,Projects!L:L},2,false)&""'"",0)),"""")"),"")
E14: =IFERROR(__xludf.DUMMYFUNCTION("IFERROR(index(query(IMPORTRANGE(""1NDlqCtTmX6RSsROpyHMIN-WbErF8iWbqHj88gYBfL_Q"",""Incomes!A:Y""),""Select sum(Col5) where Col16 = '""&VLOOKUP(B14,{Projects!S:S,Projects!L:L},2,false)&""'"",0),2),0)"),92506.45) -> 92506.45 | H14: =D14-E14 -> 99 | I14: =IFERROR(__xludf.DUMMYFUNCTION("ifna(transpose(query(IMPORTRANGE(""1NDlqCtTmX6RSsROpyHMIN-WbErF8iWbqHj88gYBfL_Q"",""Incomes!A:Y""),""Select Col25 where Col16 = '""&VLOOKUP(B14,{Projects!S:S,Projects!L:L},2,false)&""'"",0)),"""")"),"https://drive.google.com/open?id=1u7Zotf3kL-m-w9DxHv-tAa04AiBg5Bcg") -> https://drive.google.com/open?id=1u7Zotf3kL-m-w9DxHv-tAa04AiBg5Bcg
E15: =IFERROR(__xludf.DUMMYFUNCTION("IFERROR(index(query(IMPORTRANGE(""1NDlqCtTmX6RSsROpyHMIN-WbErF8iWbqHj88gYBfL_Q"",""Incomes!A:Y""),""Select sum(Col5) where Col16 = '""&VLOOKUP(B15,{Projects!S:S,Projects!L:L},2,false)&""'"",0),2),0)"),0.0) -> 0 | H15: =D15-E15 -> 1875 | I15: =IFERROR(__xludf.DUMMYFUNCTION("ifna(transpose(query(IMPORTRANGE(""1NDlqCtTmX6RSsROpyHMIN-WbErF8iWbqHj88gYBfL_Q"",""Incomes!A:Y""),""Select Col25 where Col16 = '""&VLOOKUP(B15,{Projects!S:S,Projects!L:L},2,false)&""'"",0)),"""")"),"")
E16: =IFERROR(__xludf.DUMMYFUNCTION("IFERROR(index(query(IMPORTRANGE(""1NDlqCtTmX6RSsROpyHMIN-WbErF8iWbqHj88gYBfL_Q"",""Incomes!A:Y""),""Select sum(Col5) where Col16 = '""&VLOOKUP(B16,{Projects!S:S,Projects!L:L},2,false)&""'"",0),2),0)"),6682.0) -> 6682 | H16: =D16-E16 -> 1909 | I16: =IFERROR(__xludf.DUMMYFUNCTION("ifna(transpose(query(IMPORTRANGE(""1NDlqCtTmX6RSsROpyHMIN-WbErF8iWbqHj88gYBfL_Q"",""Incomes!A:Y""),""Select Col25 where Col16 = '""&VLOOKUP(B16,{Projects!S:S,Projects!L:L},2,false)&""'"",0)),"""")"),"")
E17: =IFERROR(__xludf.DUMMYFUNCTION("IFERROR(index(query(IMPORTRANGE(""1NDlqCtTmX6RSsROpyHMIN-WbErF8iWbqHj88gYBfL_Q"",""Incomes!A:Y""),""Select sum(Col5) where Col16 = '""&VLOOKUP(B17,{Projects!S:S,Projects!L:L},2,false)&""'"",0),2),0)"),0.0) -> 0 | H17: =D17-E17 -> 15120 | I17: =IFERROR(__xludf.DUMMYFUNCTION("ifna(transpose(query(IMPORTRANGE(""1NDlqCtTmX6RSsROpyHMIN-WbErF8iWbqHj88gYBfL_Q"",""Incomes!A:Y""),""Select Col25 where Col16 = '""&VLOOKUP(B17,{Projects!S:S,Projects!L:L},2,false)&""'"",0)),"""")"),"")
E18: =IFERROR(__xludf.DUMMYFUNCTION("IFERROR(index(query(IMPORTRANGE(""1NDlqCtTmX6RSsROpyHMIN-WbErF8iWbqHj88gYBfL_Q"",""Incomes!A:Y""),""Select sum(Col5) where Col16 = '""&VLOOKUP(B18,{Projects!S:S,Projects!L:L},2,false)&""'"",0),2),0)"),0.0) -> 0 | H18: =D18-E18 -> 109707 | I18: =IFERROR(__xludf.DUMMYFUNCTION("ifna(transpose(query(IMPORTRANGE(""1NDlqCtTmX6RSsROpyHMIN-WbErF8iWbqHj88gYBfL_Q"",""Incomes!A:Y""),""Select Col25 where Col16 = '""&VLOOKUP(B18,{Projects!S:S,Projects!L:L},2,false)&""'"",0)),"""")"),"")
E19: =IFERROR(__xludf.DUMMYFUNCTION("IFERROR(index(query(IMPORTRANGE(""1NDlqCtTmX6RSsROpyHMIN-WbErF8iWbqHj88gYBfL_Q"",""Incomes!A:Y""),""Select sum(Col5) where Col16 = '""&VLOOKUP(B19,{Projects!S:S,Projects!L:L},2,false)&""'"",0),2),0)"),0.0) -> 0 | H19: =D19-E19 -> 1320 | I19: =IFERROR(__xludf.DUMMYFUNCTION("ifna(transpose(query(IMPORTRANGE(""1NDlqCtTmX6RSsROpyHMIN-WbErF8iWbqHj88gYBfL_Q"",""Incomes!A:Y""),""Select Col25 where Col16 = '""&VLOOKUP(B19,{Projects!S:S,Projects!L:L},2,false)&""'"",0)),"""")"),"")
E20: =IFERROR(__xludf.DUMMYFUNCTION("IFERROR(index(query(IMPORTRANGE(""1NDlqCtTmX6RSsROpyHMIN-WbErF8iWbqHj88gYBfL_Q"",""Incomes!A:Y""),""Select sum(Col5) where Col16 = '""&VLOOKUP(B20,{Projects!S:S,Projects!L:L},2,false)&""'"",0),2),0)"),0.0) -> 0 | H20: =D20-E20 -> 51668 | I20: =IFERROR(__xludf.DUMMYFUNCTION("ifna(transpose(query(IMPORTRANGE(""1NDlqCtTmX6RSsROpyHMIN-WbErF8iWbqHj88gYBfL_Q"",""Incomes!A:Y""),""Select Col25 where Col16 = '""&VLOOKUP(B20,{Projects!S:S,Projects!L:L},2,false)&""'"",0)),"""")"),"")

Sheet Sheet7
A1: Beach Tower | 1.1.2. | ორბი ჯგუფი | 1.00 USD | 05.09.2018 | B1: 1 6 31 998 | F1: MTZ Service | 1.1.2. | მტზ კომპანი | 600.00 USD | 01.02.2025 | G1: 1 6 31 2487
A2: Porta Apartments 4003 | 1.2.1. | ბურაქ ქონსტრაქშენ | 14,591.00 USD | 20.05.2024 | B2: 1 6 30 2504 | F2: Cafe Central Oth | 1.1.3. | კაფე ცენტრალი | 170.00 GEL | 09.06.2024 | G2: 1 6 31 2559
A3: Porta Apartments 2906 | 1.2.1. | ბურაქ ქონსტრაქშენ | 9,407.00 USD | 20.05.2024 | B3: 1 6 30 2504 | F3: Bagebi Service | 1.1.3. | ეკატერინე ელისაბედაშვილი | 1,500.00 GEL | 21.03.2025 | G3: 1 6 31 2200
A4: Simetria Lisi 1 Unit | 1.1.1. | მეპერსი | 2,000.00 USD | 01.06.2024 | B4: 1 6 30 1148 | F4: Crown Plaza | 1.2.1. | ემ სი ქონსთრაქშენ | 693,840.00 EUR | 05.11.2024 | G4: 1 6 30 2625
A5: Nutsubidze | 1.1.1. | სფერა | 549,980.00 USD | 11.08.2023 | B5: 1 6 30 1559 | F5: DAR TOWER | 1.1.3. | Dar Building | 1,214.00 USD | 22.02.2021 | G5: 1 6 31 853
A6: Khabazi Kobuleti | 1.1.1. | ვახტანგი ხაბაზი | 29,700.00 USD | 04.12.2023 | B6: 1 6 30 2347 | F6: Archi Isani C Block | 1.1.2. | არქი მეინთენენს | 200.00 USD | 01.02.2025 | G6: 1 6 31 2687
A7: Radisson Batumi Reabilitation | 1.1.3. | არგო მენეჯმენტი | 50,000.00 USD | 01.10.2023 | B7: 1 6 30 2307
A8: Kvareli Residence | 1.1.1. | მეპერსი | 2,000.00 USD | 01.12.2023 | B8: 1 6 30 1148
A9: Kbuleti Str. - Khomeriki | 1.1.2. | გელა ხომერიკი | 1.00 GEL | 01.02.2018 | B9: 1 6 31 882
A10: LUX | 1.1.1. | მეპერსი | 19,160.00 USD | 01.09.2024 | B10: 1 6 30 1148
A11: Sunrise Shartava | 1.1.2. | სანრაიზ დეველოპმენტი | 600.00 USD | 01.10.2023 | B11: 1 6 30 1514
A12: Batumi Cafe Central | 1.1.2. | კაფე ცენტრალი | 300.00 GEL | 01.07.2024 | B12: 1 6 31 2559
A13: Goderdzi EP | 1.1.1. | ხიდი 2006 | 23,860.00 USD | 07.08.2024 | B13: 1 6 30 2571
A14: Jgenti Warehouse | 1.1.2. | ემ ელ სი ლოჯისტიკს | 1.00 GEL | 01.05.2022 | B14: 1 6 31 1713
A15: Basis Bank | 1.1.1. | მეპერსი | 5,000.00 USD | 01.02.2024 | B15: 1 6 30 1148
A16: Ambassador Goderdzi | 1.2.1. | ამბასადორი ბათუმი | 43,449.10 USD | 02.12.2024 | B16: 1 6 30 2589 2
A17: Tegeta Chiller | 1.2.1. | თეგეტა მოტორსი | 257,240.00 EUR | 26.06.2024 | B17: 1 6 30 90
A18: Tegeta AHU | 1.2.1. | თეგეტა მოტორსი | 164,800.00 EUR | 16.07.2024 | B18: 1 6 30 90
... A47: Mziuri Gardens Service | 1.1.2. | მზიური რეზორტ | 1,440.00 USD | 01.01.2024 | B47: 1 6 31 1703

Sheet Sheet4
A1: Timestamp | B1: კონტრაგენტი : | C1: პროექტის დასახელება : | D1: შემოსავლის კოდი : | E1: თარიღი : | F1: თანხა : | G1: ვალუტა : | H1: პროექტის სტატუსი : | I1: თანამშრომელი : | J1: ORIS 1630 : | K1: კონტრაქტის # - | L1: პროექტი_GUID/ | M1: პროექტი// | N1: შემოსავლის კოდი_GUID | O1: კონტრაგენტი_GUID | P1: თანამშრომელი_GUID | Q1: Collateral | R1: Deleted | S1: Name1 | T1: კონტრაგენტის ORIS ID | U1: ნომერი
A2: 44342.736 | B2: ბალტიის ბიზნეს განვითარება (ს.კ. 400098078 ) - შპს | C2: Redisson Red VRV | D2: 1.2.1. (+) შემოსავალი MEP დანადგარების რეალიზაციიდან | E2: 44291 | F2: 227761 | G2: USD | H2: მიმდინარე | K2: 400098078 /44291/1.2.1./1 | L2: 8C35AE1C-A6AB-42B6-9EE6-4FA33CE10E1E | M2: Redisson Red VRV | 1.2.1. (+) შემოსავალი MEP დანადგარების რეალიზაციიდან | ბალტიის ბიზნეს განვითარება (ს.კ. 400098078 ) - შპს | N2: FEA4B88F-633F-4422-B3D6-250792A2DA80 | O2: 683C3DF5-4CB1-4571-B08C-7154A4496822 | Q2: gio.nikabadze@gmail.com | S2: Redisson Red VRV | 1.2.1. | ბალტიის ბიზნეს განვითარება | 227,761.00 USD | 05.04.2021 | T2: 1591 | U2: ICE248
A3: 44342.736 | B3: პალადა (ს.კ. 205180472) - შპს | C3: Samkharauli SOS | D3: 1.2.1. (+) შემოსავალი MEP დანადგარების რეალიზაციიდან | E3: 44287 | F3: 271416.96 | G3: GEL | H3: მიმდინარე | J3: 1 6 30 504 | K3: 205180472/44287/1.2.1./1 | L3: 4B566549-74E9-41C8-8391-72C2AD451C7B | M3: Samkharauli SOS | 1.2.1. (+) შემოსავალი MEP დანადგარების რეალიზაციიდან | პალადა (ს.კ. 205180472) - შპს | N3: FEA4B88F-633F-4422-B3D6-250792A2DA80 | O3: 31D45C00-CEC1-4C42-8E96-8127B22496EB | Q3: gio.nikabadze@gmail.com | S3: Samkharauli SOS | 1.2.1. | პალადა | 271,416.96 GEL | 01.04.2021 | T3: 504 | U3: ICE256
A4: 44342.736 | B4: მეპერსი (ს.კ. 402121887) - შპს | C4: HIEX | D4: 1.2.1. (+) შემოსავალი MEP დანადგარების რეალიზაციიდან | E4: 44256 | F4: 701000 | G4: USD | H4: მიმდინარე | K4: 402121887/44256/1.2.1./1 | L4: B6E0A204-58B5-494C-916D-CF90B1FC158B | M4: HIEX | 1.2.1. (+) შემოსავალი MEP დანადგარების რეალიზაციიდან | მეპერსი (ს.კ. 402121887) - შპს | N4: FEA4B88F-633F-4422-B3D6-250792A2DA80 | O4: 43EABC78-AF64-4C14-9FEF-C7E6A1B6F07E | Q4: gio.nikabadze@gmail.com | S4: HIEX | 1.2.1. | მეპერსი | 701,000.00 USD | 01.03.2021 | T4: 1148 | U4: ICE258
A5: 44413.723 | B5: ანაგი (ს.კ. 245416401) - შპს | C5: Mziuri Office | D5: 1.1.1. (+) შემოსავალი ლიფტების რეალიზაციიდან | E5: 44392 | F5: 62500 | G5: USD | H5: მიმდინარე | J5: 1 6 30 1132 5 | K5: 245416401/44392/1.1.1./1 | L5: 68E60BFC-794B-4930-8623-83A6EAEC4EEB | M5: Mziuri Office | 1.1.1. (+) შემოსავალი ლიფტების რეალიზაციიდან | ანაგი (ს.კ. 245416401) - შპს | N5: B59170EC-16CC-499A-9FF7-0428DCB8F727 | O5: 7DDF7E55-92EE-4E47-9E16-F1D4D3FABF60 | Q5: gio.nikabadze@gmail.com | S5: Mziuri Office | 1.1.1. | ანაგი | 62,500.00 USD | 15.07.2021 | T5: 1132 | U5: ICE287
A6: 44413.741 | B6: მზიური რეზორტ (ს.კ. 404462256) - შპს | C6: Mziuri Garden | D6: 1.1.1. (+) შემოსავალი ლიფტების რეალიზაციიდან | E6: 44398 | F6: 664800 | G6: USD | H6: მიმდინარე | J6: 1 6 30 1703 | K6: 404462256/44398/1.1.1./1 | L6: 72A4E017-677E-4C04-8946-3A941DA81F07 | M6: Mziuri Garden | 1.1.1. (+) შემოსავალი ლიფტების რეალიზაციიდან | მზიური რეზორტ (ს.კ. 404462256) - შპს | N6: B59170EC-16CC-499A-9FF7-0428DCB8F727 | O6: 933470D5-D1F0-4CB0-8738-317256F1B307 | Q6: gio.nikabadze@gmail.com | S6: Mziuri Garden | 1.1.1. | მზიური რეზორტ | 664,800.00 USD | 21.07.2021 | U6: ICE288
A7: 44419.663 | B7: გრინ დეველოპმენტი (ს.კ. 204452412) - შპს | C7: Lisi Green | D7: 1.1.1. (+) შემოსავალი ლიფტების რეალიზაციიდან | E7: 44414 | F7: 55690 | G7: USD | H7: მიმდინარე | J7: 1 6 30 1697 | K7: 204452412/44414/1.1.1./1 | L7: 05075E08-C469-4344-970E-4AF1BE573411 | M7: Lisi Green | 1.1.1. (+) შემოსავალი ლიფტების რეალიზაციიდან | გრინ დეველოპმენტი (ს.კ. 204452412) - შპს | N7: B59170EC-16CC-499A-9FF7-0428DCB8F727 | O7: 25CDD3DB-B92D-4066-8363-867726289059 | Q7: gio.nikabadze@gmail.com | S7: Lisi Green | 1.1.1. | გრინ დეველოპმენტი | 55,690.00 USD | 06.08.2021 | U7: ICE290
A8: 44475.723 | B8: ანაგი (ს.კ. 245416401) - შპს | C8: Makhata | D8: 1.1.1. (+) შემოსავალი ლიფტების რეალიზაციიდან | E8: 44474 | F8: 1158300 | G8: USD | H8: მიმდინარე | I8: გიორგი გუნაშვილი (ს.კ. 01005042868) - ფიზ. პირი | J8: 1 6 30 1132 6 | K8: 245416401/44474/1.1.1./1 | L8: F3E662E0-2276-4959-AEF7-FAA08D2B5257 | M8: Makhata | 1.1.1. (+) შემოსავალი ლიფტების რეალიზაციიდან | ანაგი (ს.კ. 245416401) - შპს | N8: B59170EC-16CC-499A-9FF7-0428DCB8F727 | O8: 7DDF7E55-92EE-4E47-9E16-F1D4D3FABF60 | Q8: gio.nikabadze@gmail.com | S8: Makhata | 1.1.1. | ანაგი | 1,158,300.00 USD | 05.10.2021 | T8: 1132 | U8: ICE300
A9: 44558.619 | B9: პრემიუმ ჯგუფი (ს.კ. 445522907) - შპს | C9: Premium Group | D9: 1.1.1. (+) შემოსავალი ლიფტების რეალიზაციიდან | E9: 44554 | F9: 400000 | G9: USD | H9: მიმდინარე | J9: 1 6 30 1820 | K9: 445522907/44554/1.1.1./1 | L9: CA21A428-93AA-4FDF-980E-486EC36530FC | M9: Premium Group | 1.1.1. (+) შემოსავალი ლიფტების რეალიზაციიდან | პრემიუმ ჯგუფი (ს.კ. 445522907) - შპს | N9: B59170EC-16CC-499A-9FF7-0428DCB8F727 | O9: C1B734D0-6642-4B4C-AD22-ABF60C8F299C | Q9: gio.nikabadze@gmail.com | S9: Premium Group | 1.1.1. | პრემიუმ ჯგუფი | 400,000.00 USD | 24.12.2021 | U9: ICE311
A10: 44575.584 | B10: ორბი ჯგუფი (ს.კ. 245621849) - შპს | C10: Sea Tower | D10: 1.1.1. (+) შემოსავალი ლიფტების რეალიზაციიდან | E10: 44293 | F10: 429922 | G10: USD | H10: მიმდინარე | K10: 245621849/44293/1.1.1./1 | L10: FDCA881B-9BEC-41C6-80D0-19AC10CDCC8D | M10: Sea Tower | 1.1.1. (+) შემოსავალი ლიფტების რეალიზაციიდან | ორბი ჯგუფი (ს.კ. 245621849) - შპს | N10: B59170EC-16CC-499A-9FF7-0428DCB8F727 | O10: 90293CD0-6262-4F6E-9B52-E8D909232966 | Q10: gio.nikabadze@gmail.com | S10: Sea Tower | 1.1.1. | ორბი ჯგუფი | 429,922.00 USD | 07.04.2021 | T10: 998 | U10: ICE313
A11: 44615.733 | B11: კაპიტალ გრუპი (ს.კ. 405296255) - შპს | C11: SAKCABELI | D11: 1.2.1. (+) შემოსავალი MEP დანადგარების რეალიზაციიდან | E11: 44614 | F11: 60000 | G11: USD | H11: მიმდინარე | I11: დავით ნადირაძე (ს.კ. 01001014120) - ფიზ. პირი | J11: 1 6 30 1847 | K11: 405296255/44614/1.2.1./1 | L11: A19E9D26-09AD-4255-819B-9373E4343D2E | M11: SAKCABELI | 1.2.1. (+) შემოსავალი MEP დანადგარების რეალიზაციიდან | კაპიტალ გრუპი (ს.კ. 405296255) - შპს | N11: FEA4B88F-633F-4422-B3D6-250792A2DA80 | O11: 77AF1960-EC8C-4658-B33E-8D26E449F36A | P11: C309CB7C-404D-431A-A8FB-29671DCA0C49 | Q11: gio.nikabadze@gmail.com | S11: SAKCABELI | 1.2.1. | კაპიტალ გრუპი | 60,000.00 USD | 22.02.2022 | U11: ICE317
A12: 44637.608 | B12: ორბი ჯგუფი ბათუმი (ს.კ. 445468798) - შპს | C12: Orbi City D2 block | D12: 1.1.1. (+) შემოსავალი ლიფტების რეალიზაციიდან | E12: 44546 | F12: 1161507 | G12: USD | H12: მიმდინარე | J12: 1 6 30 773 7 | K12: 445468798/44546/1.1.1./1 | L12: A14A73A4-6449-4ED8-96BB-94AE30C5A311 | M12: Orbi City D2 block | 1.1.1. (+) შემოსავალი ლიფტების რეალიზაციიდან | ორბი ჯგუფი ბათუმი (ს.კ. 445468798) - შპს | N12: B59170EC-16CC-499A-9FF7-0428DCB8F727 | O12: E284E0FD-A2B7-4D93-8E91-006FF0A8A4CE | Q12: gio.nikabadze@gmail.com | S12: Orbi City D2 block | 1.1.1. | ორბი ჯგუფი ბათუმი | 1,161,507.00 USD | 16.12.2021 | T12: 773 | U12: ICE320
A13: 44637.661 | B13: ორბი ჯგუფი ბათუმი (ს.კ. 445468798) - შპს | C13: Orbi city D1 block | D13: 1.1.1. (+) შემოსავალი ლიფტების რეალიზაციიდან | E13: 44424 | F13: 1161507.8 | G13: USD | H13: მიმდინარე | J13: 1 6 30 773 5 | K13: 445468798/44496/1.1.1./1 | L13: 07AEFB68-2673-4B70-A963-413918AF6741 | M13: Orbi city D1 block | 1.1.1. (+) შემოსავალი ლიფტების რეალიზაციიდან | ორბი ჯგუფი ბათუმი (ს.კ. 445468798) - შპს | N13: B59170EC-16CC-499A-9FF7-0428DCB8F727 | O13: E284E0FD-A2B7-4D93-8E91-006FF0A8A4CE | Q13: gio.nikabadze@gmail.com | S13: Orbi city D1 block | 1.1.1. | ორბი ჯგუფი ბათუმი | 1,161,507.82 USD | 16.08.2021 | T13: 773 | U13: ICE321
A14: 44648.536 | B14: ალიანსი თბილისი (ს.კ. 405144703) - შპს | C14: Alliance Highline | D14: 1.1.1. (+) შემოსავალი ლიფტების რეალიზაციიდან | E14: 44582 | F14: 2281058 | G14: USD | H14: მიმდინარე | K14: 405144703/44582/1.1.1./1 | L14: DC975886-9BF9-42C8-AFBE-87695AA01262 | M14: Alliance Highline | 1.1.1. (+) შემოსავალი ლიფტების რეალიზაციიდან | ალიანსი თბილისი (ს.კ. 405144703) - შპს | N14: B59170EC-16CC-499A-9FF7-0428DCB8F727 | O14: 73F7A185-024C-4137-BCF6-0AF1157D6600 | Q14: gio.nikabadze@gmail.com | S14: Alliance Highline | 1.1.1. | ალიანსი თბილისი | 2,281,058.00 USD | 21.01.2022 | U14: ICE326
A15: 44700.51 | B15: ლაიქ ჰაუსი (ს.კ. 445478563) - შპს | C15: Holiday Inn | D15: 1.1.1. (+) შემოსავალი ლიფტების რეალიზაციიდან | E15: 44602 | F15: 372497 | G15: USD | H15: მიმდინარე | K15: 445478563/44602/1.1.1./1 | L15: 2702712B-A1E7-43FA-8C75-F84D4BD6D43F | M15: Holiday Inn | 1.1.1. (+) შემოსავალი ლიფტების რეალიზაციიდან | ლაიქ ჰაუსი (ს.კ. 445478563) - შპს | N15: B59170EC-16CC-499A-9FF7-0428DCB8F727 | O15: E5065FFE-1CD4-4C87-A053-0558ECFC9B1D | Q15: gio.nikabadze@gmail.com | S15: Holiday Inn | 1.1.1. | ლაიქ ჰაუსი | 372,497.00 USD | 10.02.2022 | U15: ICE354
A16: 44712.735 | B16: ნუცუბიძე (ს.კ. 405387861) - შპს | C16: Park Home Saburtalo | D16: 1.1.1. (+) შემოსავალი ლიფტების რეალიზაციიდან | E16: 44701 | F16: 626280 | G16: USD | H16: მიმდინარე | K16: 405387861/44701/1.1.1./1 | L16: 016A3ACC-14B7-48A0-A8C1-C5485BD40EDD | M16: Park Home Saburtalo | 1.1.1. (+) შემოსავალი ლიფტების რეალიზაციიდან | ნუცუბიძე (ს.კ. 405387861) - შპს | N16: B59170EC-16CC-499A-9FF7-0428DCB8F727 | O16: 272FF8D3-4909-409A-99B0-E2C8CA3BB9AF | Q16: gio.nikabadze@gmail.com | S16: Park Home Saburtalo | 1.1.1. | ნუცუბიძე | 626,280.00 USD | 20.05.2022 | U16: ICE355
A17: 44761.722 | B17: ეიჩ გრუპ კონსტრაქშენ (ს.კ. 445510411) - შპს | C17: 7th sky | D17: 1.1.1. (+) შემოსავალი ლიფტების რეალიზაციიდან | E17: 44755 | F17: 1266280 | G17: USD | H17: მიმდინარე | K17: ICE001124/44755/1.1.1./3GTVRO | L17: 7fdd6160-db67-4d95-a4fc-7ae6ccc0c50a | M17: 7th sky | 1.1.1. (+) შემოსავალი ლიფტების რეალიზაციიდან | ეიჩ გრუპ კონსტრაქშენ (ს.კ. 445510411) - შპს | N17: B59170EC-16CC-499A-9FF7-0428DCB8F727 | O17: FD75B701-F0B0-4EFD-934E-9BC3480483AE | Q17: gio.nikabadze@gmail.com | S17: 7th sky | 1.1.1. | ეიჩ გრუპ კონსტრაქშენ | 1,266,280.00 USD | 13.07.2022 | U17: ICE359
A18: 44762 | B18: მეპერსი (ს.კ. 402121887) - შპს | C18: ALLIANCE HIGHLINES CHILLERS | D18: 1.2.1. (+) შემოსავალი MEP დანადგარების რეალიზაციიდან | E18: 44727 | F18: 273570 | G18: EUR | H18: მიმდინარე | K18: ICE000118/44727/1.2.1./QVXXKU | L18: b00cd68e-053a-4994-80e0-dad77e2461da | M18: ALLIANCE HIGHLINES CHILLERS | 1.2.1. (+) შემოსავალი MEP დანადგარების რეალიზაციიდან | მეპერსი (ს.კ. 402121887) - შპს | N18: FEA4B88F-633F-4422-B3D6-250792A2DA80 | O18: 43EABC78-AF64-4C14-9FEF-C7E6A1B6F07E | Q18: shorena.jijiashvili1980@gmail.com | S18: ALLIANCE HIGHLINES CHILLERS | 1.2.1. | მეპერსი | 273,570.00 EUR | 15.06.2022 | T18: 1148 | U18: ICE360
A19: 44774.588 | B19: ბაგრატიონი რეზიდენსი (ს.კ. 445572568) - შპს | C19: Bagrationi | D19: 1.1.1. (+) შემოსავალი ლიფტების რეალიზაციიდან | E19: 44737 | F19: 450470 | G19: USD | H19: მიმდინარე | K19: ICE001880/44737/1.1.1./2T1HQF | L19: 9518b3a0-051a-4732-b24d-e59f121af873 | M19: Bagrationi | 1.1.1. (+) შემოსავალი ლიფტების რეალიზაციიდან | ბაგრატიონი რეზიდენსი (ს.კ. 445572568) - შპს | N19: B59170EC-16CC-499A-9FF7-0428DCB8F727 | O19: 58fa8342-2181-4246-af05-590de2ef9e8d | Q19: shorena.jijiashvili1980@gmail.com | S19: Bagrationi | 1.1.1. | ბაგრატიონი რეზიდენსი | 450,470.00 USD | 25.06.2022 | U19: ICE371
A20: 44778.74 | B20: ალიანსი ფრივილიჯი (ს.კ. 412718466) - შპს | C20: Alliance Previlige | D20: 1.1.1. (+) შემოსავალი ლიფტების რეალიზაციიდან | E20: 44774 | F20: 600000 | G20: USD | H20: მიმდინარე | K20: ICE001882/44774/1.1.1./AYODT5 | L20: 70a35471-a9c1-45d1-bfaf-a8c98abeaed7 | M20: Alliance Previlige | 1.1.1. (+) შემოსავალი ლიფტების რეალიზაციიდან | ალიანსი ფრივილიჯი (ს.კ. 412718466) - შპს | N20: B59170EC-16CC-499A-9FF7-0428DCB8F727 | O20: dbbb87c7-d197-4838-8a24-faf3e22917cc | Q20: shorena.jijiashvili1980@gmail.com | S20: Alliance Previlige | 1.1.1. | ალიანსი ფრივილიჯი | 600,000.00 USD | 01.08.2022 | U20: ICE373
