Workbook

Sheet Orders
A1: Date | B1: Sum | C1: ID_14 | D1: Comment | E1: Description | F1: IBAN | G1: Collateral | H1: Code | I1: Counteragent | J1: Project | K1: Job Type | L1: Income Tax | M1: Job | N1: Record GUID | O1: Timestamp | P1: User
A2: 46142.458 | B2: 25000 | C2: f3ce6e_a3_beadc9 | F2: 2 | G2: nikaelevator@gmail.com | H2: 1.1.1.5. (+) ლიფტების ჩაბარება | I2: ზ-გრუპ (ს.კ. 400017245) - შპს | J2: ZYGMA | 1.1.1. | ზ-გრუპ | 524,300.00 USD | 10.03.2025 | L2: FALSE | N2: 9b744368-f75c-456d-9a8e-9bdf1ba21169 | O2: 45744.657 | P2: nikaelevator@gmail.com
A3: 46142.458 | B3: 962 | C3: 5007c8_f0_b26d52 | F3: DummyIBAN | G3: nikaelevator@gmail.com | H3: 2.1.1.9. (-) ლიფტების მონტაჟის ბონუსები | I3: Budget Dummy (ს.კ. ICE002065) - შპს | J3: ZYGMA | 1.1.1. | ზ-გრუპ | 524,300.00 USD | 10.03.2025 | L3: FALSE | N3: 3447cfc3-e66b-443c-b7f2-82e9f0f949dd | O3: 45744.657 | P3: nikaelevator@gmail.com
A4: 46127.458 | B4: 25000 | C4: b83db5_84_b38688 | F4: 2 | G4: nikaelevator@gmail.com | H4: 1.1.1.4. (+) ლიფტების მონტაჟის პროგრესის ავანსი | I4: ზ-გრუპ (ს.კ. 400017245) - შპს | J4: ZYGMA | 1.1.1. | ზ-გრუპ | 524,300.00 USD | 10.03.2025 | L4: FALSE | N4: d97adbef-875b-4fb1-8e16-522e9cda263a | O4: 45744.657 | P4: nikaelevator@gmail.com
A5: 46127.458 | B5: 21200 | C5: fc79e7_85_8e7110 | F5: DummyIBAN | G5: nikaelevator@gmail.com | H5: 2.1.1.3. (-) ლიფტების მონტაჟის ღირებულება | I5: Budget Dummy (ს.კ. ICE002065) - შპს | J5: ZYGMA | 1.1.1. | ზ-გრუპ | 524,300.00 USD | 10.03.2025 | L5: TRUE | N5: 81759988-8d22-4a12-ad6d-94d4049106ab | O5: 45744.657 | P5: nikaelevator@gmail.com
A6: 46127.458 | B6: 1590 | C6: a6622d_06_a1a791 | F6: DummyIBAN | G6: nikaelevator@gmail.com | H6: 2.1.1.6. (-) ლიფტების მონტაჟის დამხმარე მასალები | I6: Budget Dummy (ს.კ. ICE002065) - შპს | J6: ZYGMA | 1.1.1. | ზ-გრუპ | 524,300.00 USD | 10.03.2025 | L6: FALSE | N6: 33461393-89c8-4877-9702-0ffa90130fb1 | O6: 45744.657 | P6: nikaelevator@gmail.com
A7: 46097.458 | B7: 22000 | C7: b9aaa8_9e_9285dc | F7: DummyIBAN | G7: nikaelevator@gmail.com | H7: 2.1.1.3. (-) ლიფტების მონტაჟის ღირებულება | I7: Budget Dummy (ს.კ. ICE002065) - შპს | J7: ZYGMA | 1.1.1. | ზ-გრუპ | 524,300.00 USD | 10.03.2025 | L7: TRUE | N7: b40bae34-6cd0-4dfb-bb52-929411b0f0da | O7: 45744.657 | P7: nikaelevator@gmail.com
A8: 46097.458 | B8: 1600 | C8: ba3047_8b_9b6889 | F8: DummyIBAN | G8: nikaelevator@gmail.com | H8: 2.1.1.6. (-) ლიფტების მონტაჟის დამხმარე მასალები | I8: Budget Dummy (ს.კ. ICE002065) - შპს | J8: ZYGMA | 1.1.1. | ზ-გრუპ | 524,300.00 USD | 10.03.2025 | L8: FALSE | N8: aa2fe372-6fa5-416f-8e39-71b791155e41 | O8: 45744.657 | P8: nikaelevator@gmail.com
A9: 46067.5 | B9: 22000 | C9: 777dd5_69_ba96e1 | F9: DummyIBAN | G9: nikaelevator@gmail.com | H9: 2.1.1.3. (-) ლიფტების მონტაჟის ღირებულება | I9: Budget Dummy (ს.კ. ICE002065) - შპს | J9: ZYGMA | 1.1.1. | ზ-გრუპ | 524,300.00 USD | 10.03.2025 | L9: TRUE | N9: cd17e642-3548-46e4-a2c7-b71991f829eb | O9: 45744.657 | P9: nikaelevator@gmail.com
A10: 46067.5 | B10: 1600 | C10: 67707d_5a_be6e2a | F10: DummyIBAN | G10: nikaelevator@gmail.com | H10: 2.1.1.6. (-) ლიფტების მონტაჟის დამხმარე მასალები | I10: Budget Dummy (ს.კ. ICE002065) - შპს | J10: ZYGMA | 1.1.1. | ზ-გრუპ | 524,300.00 USD | 10.03.2025 | L10: FALSE | N10: 751c23df-ddf7-4035-bfc5-7de5a0378a58 | O10: 45744.657 | P10: nikaelevator@gmail.com
A11: 46037.5 | B11: 222000 | C11: a3a1a2_f5_be4ae3 | F11: 2 | G11: nikaelevator@gmail.com | H11: 1.1.1.3. (+) ლიფტების საბაჟოზე შემოსვლის ან დასაწყობების ავანსი | I11: ზ-გრუპ (ს.კ. 400017245) - შპს | J11: ZYGMA | 1.1.1. | ზ-გრუპ | 524,300.00 USD | 10.03.2025 | L11: FALSE | N11: 0cf5880f-c4ef-447d-9952-3d8b37283c52 | O11: 45744.657 | P11: nikaelevator@gmail.com
A12: 46037.5 | B12: 36800 | C12: 3197b7_5d_9c197e | F12: DummyIBAN | G12: nikaelevator@gmail.com | H12: 2.1.1.2. (-) ლიფტების ტრანსპორტირება | I12: Budget Dummy (ს.კ. ICE002065) - შპს | J12: ZYGMA | 1.1.1. | ზ-გრუპ | 524,300.00 USD | 10.03.2025 | L12: FALSE | N12: aea3a925-c419-445a-be02-29db9c84a7a3 | O12: 45744.657 | P12: nikaelevator@gmail.com
A13: 46033.5 | B13: 6615 | C13: 5eecbc_3a_9cc4c3 | F13: 2 | G13: nikaelevator@gmail.com | H13: 1.1.1.5. (+) ლიფტების ჩაბარება | I13: ნამი 2024 (ს.კ. 405720019) - შპს | J13: Nami | 1.1.1. | ნამი 2024 | 66,150.00 USD | 16.04.2025 | L13: FALSE | N13: b49bc77e-fcce-4d9b-81f5-941bb5fea34f | O13: 45763.699 | P13: nikaelevator@gmail.com
A14: 46033.5 | B14: 1875 | C14: 1e93d0_c4_a2b384 | F14: DummyIBAN | G14: nikaelevator@gmail.com | H14: 2.1.1.3. (-) ლიფტების მონტაჟის ღირებულება | I14: Budget Dummy (ს.კ. ICE002065) - შპს | J14: Nami | 1.1.1. | ნამი 2024 | 66,150.00 USD | 16.04.2025 | L14: TRUE | N14: 1b8c55a4-acd0-4b17-97da-9bdd1b2d7110 | O14: 45763.699 | P14: nikaelevator@gmail.com
A15: 46033.5 | B15: 413 | C15: 4de8d0_53_942ef8 | F15: DummyIBAN | G15: nikaelevator@gmail.com | H15: 2.1.1.6. (-) ლიფტების მონტაჟის დამხმარე მასალები | I15: Budget Dummy (ს.კ. ICE002065) - შპს | J15: Nami | 1.1.1. | ნამი 2024 | 66,150.00 USD | 16.04.2025 | L15: FALSE | N15: 708f82ba-b595-4092-9128-e4202256bd96 | O15: 45763.699 | P15: nikaelevator@gmail.com
A16: 46033.5 | B16: 647 | C16: 06940e_84_a4d6f3 | F16: GE20BG0000000129248100 | G16: nikaelevator@gmail.com | H16: 2.1.1.9. (-) ლიფტების მონტაჟის ბონუსები | I16: ნიკოლოზ ოთარაშვილი (ს.კ. 01026015799) - ფიზ. პირი | J16: Nami | 1.1.1. | ნამი 2024 | 66,150.00 USD | 16.04.2025 | L16: TRUE | N16: 7204c4cc-8e50-4a12-8898-664aa4fc69b6 | O16: 45763.699 | P16: nikaelevator@gmail.com
A17: 46023.5 | B17: 100 | C17: 3fd2b0_15_b1bf7e | E17: ბონუსი | F17: GE29BG0000000450982000 | G17: gio.nikabadze@gmail.com | H17: 3.2.1. (-) ოფისის იჯარის ხარჯი | I17: გიორგი ბახტაძე (ს.კ. 01024067298) - ფიზ. პირი | J17: Batumi Office Rent MEPPERS | 1.3.2. | მეპერსი | 2,700.00 USD | 15.08.2024 | L17: TRUE | N17: 60ee7912-968b-4aa9-b27d-a522eb3beeac | O17: 45671.698 | P17: gio.nikabadze@gmail.com
A18: 46023.5 | B18: 170 | C18: 5b57b2_7d_b1d45c | E18: ბონუსი | F18: GE29BG0000000450982000 | G18: gio.nikabadze@gmail.com | H18: 3.2.1. (-) ოფისის იჯარის ხარჯი | I18: გიორგი ბახტაძე (ს.კ. 01024067298) - ფიზ. პირი | J18: Batumi Office Rent CASA | 1.3.2. | კაზა დი ბათუმი | 500.00 USD | 15.08.2024 | L18: TRUE | N18: 055d090b-f632-4907-8fe8-fd402520c372 | O18: 45671.698 | P18: gio.nikabadze@gmail.com
A19: 46023.5 | B19: 100 | C19: 86f954_6b_816c74 | E19: ბონუსი | F19: GE22BG0000000343713900 | G19: gio.nikabadze@gmail.com | H19: 3.2.1. (-) ოფისის იჯარის ხარჯი | I19: პაატა დვალიშვილი (ს.კ. 01001011731) - ფიზ. პირი | J19: Batumi Office Rent MEPPERS | 1.3.2. | მეპერსი | 2,700.00 USD | 15.08.2024 | L19: TRUE | N19: d745d1c5-2d8b-4b7f-ba0d-33a3a918e7fe | O19: 45671.698 | P19: gio.nikabadze@gmail.com
A20: 46023.5 | B20: 170 | C20: 01c4d3_05_a5dce3 | E20: ბონუსი | F20: GE22BG0000000343713900 | G20: gio.nikabadze@gmail.com | H20: 3.2.1. (-) ოფისის იჯარის ხარჯი | I20: პაატა დვალიშვილი (ს.კ. 01001011731) - ფიზ. პირი | J20: Batumi Office Rent CASA | 1.3.2. | კაზა დი ბათუმი | 500.00 USD | 15.08.2024 | L20: TRUE | N20: 25b83317-c049-4640-8a8c-1baa7fccf63e | O20: 45671.698 | P20: gio.nikabadze@gmail.com
A21: 46023.5 | B21: 480 | C21: e3b011_7d_9b3279 | E21: ბონუსი | F21: GE29BG0000000450982000 | G21: gio.nikabadze@gmail.com | H21: 3.2.1. (-) ოფისის იჯარის ხარჯი | I21: გიორგი ბახტაძე (ს.კ. 01024067298) - ფიზ. პირი | L21: TRUE | N21: b5a82b12-9f72-4ea9-845b-1705bb6f3de6 | O21: 45671.698 | P21: gio.nikabadze@gmail.com
A22: 46023.5 | B22: 480 | C22: e05daf_4b_b0621d | E22: ბონუსი | F22: GE22BG0000000343713900 | G22: gio.nikabadze@gmail.com | H22: 3.2.1. (-) ოფისის იჯარის ხარჯი | I22: პაატა დვალიშვილი (ს.კ. 01001011731) - ფიზ. პირი | L22: TRUE | N22: 7f075687-e2a1-4b06-80b1-5f7cbd3a693c | O22: 45671.698 | P22: gio.nikabadze@gmail.com
A23: 46018.5 | B23: 1875 | C23: ba9b1d_ea_9e8480 | F23: DummyIBAN | G23: nikaelevator@gmail.com | H23: 2.1.1.3. (-) ლიფტების მონტაჟის ღირებულება | I23: Budget Dummy (ს.კ. ICE002065) - შპს | J23: Nami | 1.1.1. | ნამი 2024 | 66,150.00 USD | 16.04.2025 | L23: TRUE | N23: 844c0d67-92c7-4366-8db4-6ee2b261927f | O23: 45763.699 | P23: nikaelevator@gmail.com
A24: 46018.5 | B24: 413 | C24: 8b3401_e6_8e103b | F24: DummyIBAN | G24: nikaelevator@gmail.com | H24: 2.1.1.6. (-) ლიფტების მონტაჟის დამხმარე მასალები | I24: Budget Dummy (ს.კ. ICE002065) - შპს | J24: Nami | 1.1.1. | ნამი 2024 | 66,150.00 USD | 16.04.2025 | L24: FALSE | N24: 3003b8f2-3452-4ea0-b10c-8589e1a72d67 | O24: 45763.699 | P24: nikaelevator@gmail.com
A25: 46017.5 | B25: 11753 | C25: 05ad6a_4e_a08415 | F25: 2 | G25: dito.sichinava@gmail.com | H25: 1.1.1.5. (+) ლიფტების ჩაბარება | I25: გრანდე ჯგუფი (ს.კ. 404557127) - შპს | J25: Grande Krtsanisi D & E BlocK | 1.1.1. | გრანდე ჯგუფი | 235,060.00 USD | 13.05.2025 | L25: FALSE | N25: 725a2223-5790-4682-88db-8c436cc9f6a7 | O25: 45792.717 | P25: dito.sichinava@gmail.com
A26: 46017.5 | B26: 8650 | C26: bbc0d6_2b_9e0231 | F26: 2 | G26: dito.sichinava@gmail.com | H26: 2.1.1.4. (-) ლიფტების მონტაჟის დამხმარე შრომა | I26: Budget Dummy (ს.კ. ICE002065) - შპს | J26: Grande Krtsanisi D & E BlocK | 1.1.1. | გრანდე ჯგუფი | 235,060.00 USD | 13.05.2025 | L26: TRUE | N26: eaedf8ee-3318-4e4e-a086-490ee8a2e5ef | O26: 45792.717 | P26: dito.sichinava@gmail.com
A27: 46017.5 | B27: 1865 | C27: b851ba_6e_93ab84 | F27: 2 | G27: dito.sichinava@gmail.com | H27: 2.1.1.8. (-) ლიფტების მონტაჟის გაუთვალისწინებელი ხარჯი | I27: Budget Dummy (ს.კ. ICE002065) - შპს | J27: Grande Krtsanisi D & E BlocK | 1.1.1. | გრანდე ჯგუფი | 235,060.00 USD | 13.05.2025 | L27: FALSE | N27: 0d3c6c5f-b41e-46e6-8a8f-9d6b99e7aa93 | O27: 45792.717 | P27: dito.sichinava@gmail.com
A28: 46017.5 | B28: 862 | C28: f82938_9e_8df609 | F28: 2 | G28: dito.sichinava@gmail.com | H28: 2.1.1.9. (-) ლიფტების მონტაჟის ბონუსები | I28: Budget Dummy (ს.კ. ICE002065) - შპს | J28: Grande Krtsanisi D & E BlocK | 1.1.1. | გრანდე ჯგუფი | 235,060.00 USD | 13.05.2025 | L28: FALSE | N28: 8341843c-2e26-42a2-a8b1-7dbc5c8e51eb | O28: 45792.717 | P28: dito.sichinava@gmail.com
A29: 46000.5 | B29: 10060 | C29: 92165f_b2_83d248 | F29: GE21TB1000000036500001 | G29: dito.sichinava@gmail.com | H29: 1.1.1.5. (+) ლიფტების ჩაბარება | I29: ანაგი (ს.კ. 245416401) - შპს | J29: Social Houses Batumi | 1.1.1. | ანაგი | 201,200.00 USD | 28.02.2025 | L29: FALSE | N29: 5f09288d-0927-4cf7-a634-1f47e60c1544 | O29: 45743.605 | P29: t.tsintsadze2006@gmail.com
A30: 46000.5 | B30: 11040 | C30: e963d7_29_a0891d | F30: DummyIBAN | G30: dito.sichinava@gmail.com | H30: 2.1.1.3. (-) ლიფტების მონტაჟის ღირებულება | I30: Budget Dummy (ს.კ. ICE002065) - შპს | J30: Social Houses Batumi | 1.1.1. | ანაგი | 201,200.00 USD | 28.02.2025 | L30: TRUE | N30: 024ba79c-b4d1-4289-b0f1-39a1eb8ec37a | O30: 45743.605 | P30: t.tsintsadze2006@gmail.com
A31: 46000.5 | B31: 1382.6667 | C31: c8e43c_4c_a2d15a | F31: DummyIBAN | G31: dito.sichinava@gmail.com | H31: 2.1.1.4. (-) ლიფტების მონტაჟის დამხმარე შრომა | I31: Budget Dummy (ს.კ. ICE002065) - შპს | J31: Social Houses Batumi | 1.1.1. | ანაგი | 201,200.00 USD | 28.02.2025 | L31: FALSE | N31: 0671d69e-97e6-400b-8a6c-91179de336ce | O31: 45743.605 | P31: t.tsintsadze2006@gmail.com
A32: 46000.5 | B32: 2163 | C32: 2327e6_2f_bd5852 | F32: DummyIBAN | G32: dito.sichinava@gmail.com | H32: 2.1.1.9. (-) ლიფტების მონტაჟის ბონუსები | I32: Budget Dummy (ს.კ. ICE002065) - შპს | J32: Social Houses Batumi | 1.1.1. | ანაგი | 201,200.00 USD | 28.02.2025 | L32: FALSE | N32: 9acb8fd3-518e-4467-9c6b-395c77c12512 | O32: 45743.605 | P32: t.tsintsadze2006@gmail.com
A33: 46000.5 | B33: 900 | C33: 77589a_ee_95d789 | F33: GE26TB7457645064300069 | G33: dito.sichinava@gmail.com | H33: 2.1.1.11. (-) ლიფტების პროექტის მომსახურების ბონუსები | I33: თეა ურიდია (ს.კ. 62001030230) - ფიზ. პირი | J33: Social Houses Batumi | 1.1.1. | ანაგი | 201,200.00 USD | 28.02.2025 | L33: TRUE | N33: e2a7c21b-a255-4bf8-92c5-42e8e3f60faa | O33: 45743.605 | P33: t.tsintsadze2006@gmail.com
A34: 45992.5 | B34: 100 | C34: 3fd2b0_15_b1bf7e | E34: ბონუსი | F34: GE29BG0000000450982000 | G34: gio.nikabadze@gmail.com | H34: 3.2.1. (-) ოფისის იჯარის ხარჯი | I34: გიორგი ბახტაძე (ს.კ. 01024067298) - ფიზ. პირი | J34: Batumi Office Rent MEPPERS | 1.3.2. | მეპერსი | 300.00 USD | 15.08.2024 | L34: TRUE | N34: 733f616d-1456-4815-a7d4-7c16f93c013a | O34: 45671.698 | P34: gio.nikabadze@gmail.com
A35: 45992.5 | B35: 170 | C35: 5b57b2_7d_b1d45c | E35: ბონუსი | F35: GE29BG0000000450982000 | G35: gio.nikabadze@gmail.com | H35: 3.2.1. (-) ოფისის იჯარის ხარჯი | I35: გიორგი ბახტაძე (ს.კ. 01024067298) - ფიზ. პირი | J35: Batumi Office Rent CASA | 1.3.2. | კაზა დი ბათუმი | 500.00 USD | 15.08.2024 | L35: TRUE | N35: 6e42a7cc-6dbd-4c63-9d71-17088dbdc1d7 | O35: 45671.698 | P35: gio.nikabadze@gmail.com
A36: 45992.5 | B36: 100 | C36: 86f954_6b_816c74 | E36: ბონუსი | F36: GE22BG0000000343713900 | G36: gio.nikabadze@gmail.com | H36: 3.2.1. (-) ოფისის იჯარის ხარჯი | I36: პაატა დვალიშვილი (ს.კ. 01001011731) - ფიზ. პირი | J36: Batumi Office Rent MEPPERS | 1.3.2. | მეპერსი | 300.00 USD | 15.08.2024 | L36: TRUE | N36: 8612cafa-9488-4f3f-a112-47db131b3577 | O36: 45671.698 | P36: gio.nikabadze@gmail.com
A37: 45992.5 | B37: 170 | C37: 01c4d3_05_a5dce3 | E37: ბონუსი | F37: GE22BG0000000343713900 | G37: gio.nikabadze@gmail.com | H37: 3.2.1. (-) ოფისის იჯარის ხარჯი | I37: პაატა დვალიშვილი (ს.კ. 01001011731) - ფიზ. პირი | J37: Batumi Office Rent CASA | 1.3.2. | კაზა დი ბათუმი | 500.00 USD | 15.08.2024 | L37: TRUE | N37: b3851181-d5ab-4433-af33-3b37e0934b72 | O37: 45671.698 | P37: gio.nikabadze@gmail.com
A38: 45992.5 | B38: 480 | C38: e3b011_7d_9b3279 | E38: ბონუსი | F38: GE29BG0000000450982000 | G38: gio.nikabadze@gmail.com | H38: 3.2.1. (-) ოფისის იჯარის ხარჯი | I38: გიორგი ბახტაძე (ს.კ. 01024067298) - ფიზ. პირი | L38: TRUE | N38: c0497842-1d5e-4a4a-bc5c-5c6723856a26 | O38: 45671.698 | P38: gio.nikabadze@gmail.com
A39: 45992.5 | B39: 480 | C39: e05daf_4b_b0621d | E39: ბონუსი | F39: GE22BG0000000343713900 | G39: gio.nikabadze@gmail.com | H39: 3.2.1. (-) ოფისის იჯარის ხარჯი | I39: პაატა დვალიშვილი (ს.კ. 01001011731) - ფიზ. პირი | L39: TRUE | N39: 59d2752a-ac26-4a2e-ae05-1ae2194bb41f | O39: 45671.698 | P39: gio.nikabadze@gmail.com
A40: 45991.5 | B40: 1334 | C40: 35a808_50_90b5ae | F40: 111 | G40: dito.sichinava@gmail.com | H40: 1.1.1.5. (+) ლიფტების ჩაბარება | I40: საკენი ბიოგრაფი (ს.კ. 404651015) - შპს | J40: SaKeni | 1.1.1. | საკენი ბიოგრაფი | 26,680.00 USD | 21.05.2025 | L40: FALSE | N40: 9280da5b-03dd-4ff6-8a4b-d4f456ceccff | O40: 45807.582 | P40: dito.sichinava@gmail.com
A41: 45991.5 | B41: 1600 | C41: 56e434_a9_9c8392 | F41: 333 | G41: dito.sichinava@gmail.com | H41: 2.1.1.3. (-) ლიფტების მონტაჟის ღირებულება | I41: Budget Dummy (ს.კ. ICE002065) - შპს | J41: SaKeni | 1.1.1. | საკენი ბიოგრაფი | 26,680.00 USD | 21.05.2025 | L41: FALSE | N41: e977df02-abf6-416e-ae69-97de6a8f12b7 | O41: 45807.582 | P41: dito.sichinava@gmail.com
A42: 45991.5 | B42: 421 | C42: 856b9a_55_bd6642 | F42: 333 | G42: dito.sichinava@gmail.com | H42: 2.1.1.6. (-) ლიფტების მონტაჟის დამხმარე მასალები | I42: Budget Dummy (ს.კ. ICE002065) - შპს | J42: SaKeni | 1.1.1. | საკენი ბიოგრაფი | 26,680.00 USD | 21.05.2025 | L42: FALSE | N42: 1dd9a4c2-0c46-4f38-9a3c-f4c81ca703c0 | O42: 45807.582 | P42: dito.sichinava@gmail.com
A43: 45991.5 | B43: 500 | C43: 9118c1_76_bd6cdb | F43: GE20BG0000000129248100 | G43: dito.sichinava@gmail.com | H43: 2.1.1.9. (-) ლიფტების მონტაჟის ბონუსები | I43: ნიკოლოზ ოთარაშვილი (ს.კ. 01026015799) - ფიზ. პირი | J43: SaKeni | 1.1.1. | საკენი ბიოგრაფი | 26,680.00 USD | 21.05.2025 | L43: TRUE | N43: b8782313-b25b-4b0c-8309-9b7195ff767c | O43: 45807.582 | P43: dito.sichinava@gmail.com
A44: 45991.5 | B44: 1500 | C44: 22c54f_95_894bc9 | F44: 4444 | G44: dito.sichinava@gmail.com | H44: 6.3. (-) გარანტიის/აკრედიტივის % | I44: საქართველოს ბანკი (ს.კ. 204378869) - სს | J44: SaKeni | 1.1.1. | საკენი ბიოგრაფი | 26,680.00 USD | 21.05.2025 | L44: FALSE | N44: e1b5c94f-455f-4aa1-9484-c645b9c3b744 | O44: 45807.582 | P44: dito.sichinava@gmail.com
A45: 45988.5 | B45: 1875 | C45: 6672c7_17_9d5ea3 | F45: DummyIBAN | G45: nikaelevator@gmail.com | H45: 2.1.1.3. (-) ლიფტების მონტაჟის ღირებულება | I45: Budget Dummy (ს.კ. ICE002065) - შპს | J45: Nami | 1.1.1. | ნამი 2024 | 66,150.00 USD | 16.04.2025 | L45: FALSE | N45: 3f87ef47-6c74-4049-aefe-96b8fa55d694 | O45: 45763.699 | P45: nikaelevator@gmail.com
A46: 45988.5 | B46: 413 | C46: d5d075_37_a47876 | F46: DummyIBAN | G46: nikaelevator@gmail.com | H46: 2.1.1.6. (-) ლიფტების მონტაჟის დამხმარე მასალები | I46: Budget Dummy (ს.კ. ICE002065) - შპს | J46: Nami | 1.1.1. | ნამი 2024 | 66,150.00 USD | 16.04.2025 | L46: TRUE | N46: 08f94056-af80-440c-b175-300489804f7a | O46: 45763.699 | P46: nikaelevator@gmail.com
A47: 45988.5 | B47: 4701 | C47: 2861e3_06_bb0146 | F47: GE40BG0000000606119819 | G47: dito.sichinava@gmail.com | H47: 1.1.1.5. (+) ლიფტების ჩაბარება | I47: ტოკიო ჰოტელ (ს.კ. 402229423) - შპს | J47: Uznadze Office | 1.1.1. | ტოკიო ჰოტელ | 94,000.00 USD | 01.05.2025 | L47: FALSE | N47: 3710df57-477c-43b4-aa6b-9938f0f46339 | O47: 45807.582 | P47: dito.sichinava@gmail.com
A48: 45988.5 | B48: 4100 | C48: 48c375_8f_9053d9 | F48: DummyIBAN | G48: dito.sichinava@gmail.com | H48: 2.1.1.3. (-) ლიფტების მონტაჟის ღირებულება | I48: Budget Dummy (ს.კ. ICE002065) - შპს | J48: Uznadze Office | 1.1.1. | ტოკიო ჰოტელ | 94,000.00 USD | 01.05.2025 | L48: FALSE | N48: 88b0049e-f3fd-4035-9bf9-9137beb317a0 | O48: 45807.582 | P48: dito.sichinava@gmail.com
A49: 45988.5 | B49: 654 | C49: 86baa6_0e_ae1be2 | F49: DummyIBAN | G49: dito.sichinava@gmail.com | H49: 2.1.1.6. (-) ლიფტების მონტაჟის დამხმარე მასალები | I49: Budget Dummy (ს.კ. ICE002065) - შპს | J49: Uznadze Office | 1.1.1. | ტოკიო ჰოტელ | 94,000.00 USD | 01.05.2025 | L49: FALSE | N49: adf83297-b7fe-409b-90d4-4db7132a796b | O49: 45807.582 | P49: dito.sichinava@gmail.com
A50: 45988.5 | B50: 1000 | C50: 43230e_01_b7174c | F50: GE20BG0000000129248100 | G50: dito.sichinava@gmail.com | H50: 2.1.1.9. (-) ლიფტების მონტაჟის ბონუსები | I50: ნიკოლოზ ოთარაშვილი (ს.კ. 01026015799) - ფიზ. პირი | J50: Uznadze Office | 1.1.1. | ტოკიო ჰოტელ | 94,000.00 USD | 01.05.2025 | L50: TRUE | N50: 2948f0cd-2176-4ffe-8e28-0e2a4f4bc373 | O50: 45807.582 | P50: dito.sichinava@gmail.com
A51: 45987.5 | B51: 8650 | C51: d96de0_92_abf3f5 | F51: 2 | G51: dito.sichinava@gmail.com | H51: 2.1.1.4. (-) ლიფტების მონტაჟის დამხმარე შრომა | I51: Budget Dummy (ს.კ. ICE002065) - შპს | J51: Grande Krtsanisi D & E BlocK | 1.1.1. | გრანდე ჯგუფი | 235,060.00 USD | 13.05.2025 | L51: TRUE | N51: 02104f12-becd-460f-8138-434fd85847af | O51: 45792.717 | P51: dito.sichinava@gmail.com
A52: 45987.5 | B52: 1865 | C52: 2400f1_64_adcf46 | F52: 2 | G52: dito.sichinava@gmail.com | H52: 2.1.1.8. (-) ლიფტების მონტაჟის გაუთვალისწინებელი ხარჯი | I52: Budget Dummy (ს.კ. ICE002065) - შპს | J52: Grande Krtsanisi D & E BlocK | 1.1.1. | გრანდე ჯგუფი | 235,060.00 USD | 13.05.2025 | L52: FALSE | N52: 96d9d466-573b-4b33-8cd3-869695f09a33 | O52: 45792.717 | P52: dito.sichinava@gmail.com
A53: 45979.5 | B53: 2500 | C53: 5edcfb_a5_8e7e92 | F53: 1 | G53: dito.sichinava@gmail.com | H53: 1.1.1.5. (+) ლიფტების ჩაბარება | I53: მშენებელი 2004 (ს.კ. 205023277) - შპს | J53: Grishashvili | 1.1.1. | მშენებელი 2004 | 50,000.00 USD | 22.05.2025 | L53: FALSE | N53: beced08e-d266-4c81-9a07-fff484ba8aa8 | O53: 45799.757 | P53: dito.sichinava@gmail.com
A54: 45979.5 | B54: 240 | C54: d81c89_b9_a6a534 | F54: 1 | G54: dito.sichinava@gmail.com | H54: 2.1.1.9. (-) ლიფტების მონტაჟის ბონუსები | I54: Budget Dummy (ს.კ. ICE002065) - შპს | J54: Grishashvili | 1.1.1. | მშენებელი 2004 | 50,000.00 USD | 22.05.2025 | L54: FALSE | N54: d92533b5-e4fe-4e43-b037-b412f231abdc | O54: 45799.757 | P54: dito.sichinava@gmail.com
A55: 45973 | B55: 1200 | C55: d3ae8b_05_91e423 | E55: მანიტოთი მომსახურების თირებულება Arsenal | F55: GE36TB7971245064300011 | G55: nikaelevator@gmail.com | H55: 2.1.1.2. (-) ლიფტების ტრანსპორტირება | I55: შოთა ღვინიაშვილი (ს.კ. 31001021836) - მცირე მეწარმე | J55: Arsenal | 1.1.1. | არსენალ რეზიდენსი | 195,270.00 USD | 07.03.2024 | L55: FALSE | N55: 5965cc37-f975-424f-9d31-12735ff3c1f1 | O55: 45677.568 | P55: nikaelevator@gmail.com
A56: 45970.5 | B56: 11040 | C56: 0dd2e1_5c_94bd09 | F56: DummyIBAN | G56: dito.sichinava@gmail.com | H56: 2.1.1.3. (-) ლიფტების მონტაჟის ღირებულება | I56: Budget Dummy (ს.კ. ICE002065) - შპს | J56: Social Houses Batumi | 1.1.1. | ანაგი | 201,200.00 USD | 28.02.2025 | L56: TRUE | N56: c1d7eec7-b6db-4510-aec0-9a966ffcad0b | O56: 45743.605 | P56: t.tsintsadze2006@gmail.com
A57: 45970.5 | B57: 1382.6667 | C57: 660ff5_d3_a06ac3 | F57: DummyIBAN | G57: dito.sichinava@gmail.com | H57: 2.1.1.4. (-) ლიფტების მონტაჟის დამხმარე შრომა | I57: Budget Dummy (ს.კ. ICE002065) - შპს | J57: Social Houses Batumi | 1.1.1. | ანაგი | 201,200.00 USD | 28.02.2025 | L57: FALSE | N57: 1b6f0aa9-df43-4531-b98b-b47b1d59cca6 | O57: 45743.605 | P57: t.tsintsadze2006@gmail.com
A58: 45969.5 | B58: 11656 | C58: 5125d3_30_b26814 | F58: 4 | G58: nikaelevator@gmail.com | H58: 1.1.1.5. (+) ლიფტების ჩაბარება | I58: იდეა ქონსთრაქშენი (ს.კ. 405545030) - შპს | J58: Panorama | 1.1.1. | იდეა ქონსთრაქშენი | 233,110.00 USD | 26.02.2025 | L58: FALSE | N58: 17eec147-b40f-4d79-9c57-35987d7a55c5 | O58: 45715.527 | P58: nikaelevator@gmail.com
A59: 45969.5 | B59: 9000 | C59: 3b8912_0b_97bc45 | F59: DummyIBAN | G59: nikaelevator@gmail.com | H59: 2.1.1.3. (-) ლიფტების მონტაჟის ღირებულება | I59: Budget Dummy (ს.კ. ICE002065) - შპს | J59: Panorama | 1.1.1. | იდეა ქონსთრაქშენი | 233,110.00 USD | 26.02.2025 | L59: TRUE | N59: 94aeb6f3-2be9-4188-99bf-a2694a46dc18 | O59: 45715.527 | P59: nikaelevator@gmail.com
A60: 45969.5 | B60: 1138.6667 | C60: 2d759f_37_aad8a8 | F60: DummyIBAN | G60: nikaelevator@gmail.com | H60: 2.1.1.6. (-) ლიფტების მონტაჟის დამხმარე მასალები | I60: Budget Dummy (ს.კ. ICE002065) - შპს | J60: Panorama | 1.1.1. | იდეა ქონსთრაქშენი | 233,110.00 USD | 26.02.2025 | L60: FALSE | N60: 7e30ab1d-b874-4370-82b6-d2ed896fad30 | O60: 45715.527 | P60: nikaelevator@gmail.com
A61: 45969.5 | B61: 962 | C61: 8f1ab5_e6_8374c7 | F61: DummyIBAN | G61: nikaelevator@gmail.com | H61: 2.1.1.9. (-) ლიფტების მონტაჟის ბონუსები | I61: Budget Dummy (ს.კ. ICE002065) - შპს | J61: Panorama | 1.1.1. | იდეა ქონსთრაქშენი | 233,110.00 USD | 26.02.2025 | L61: FALSE | N61: 82bd88e5-232a-49e3-8bc4-c5d47b38ef9e | O61: 45715.527 | P61: nikaelevator@gmail.com
A62: 45964.5 | B62: 5000 | C62: ca41ee_e1_97b745 | F62: 1 | G62: dito.sichinava@gmail.com | H62: 1.1.1.4. (+) ლიფტების მონტაჟის პროგრესის ავანსი | I62: მშენებელი 2004 (ს.კ. 205023277) - შპს | J62: Grishashvili | 1.1.1. | მშენებელი 2004 | 50,000.00 USD | 22.05.2025 | L62: FALSE | N62: a80e88a0-f5c3-4b3e-9e5f-ae630c523842 | O62: 45799.757 | P62: dito.sichinava@gmail.com
A63: 45964.5 | B63: 3400 | C63: 8c2db4_2d_8c53d1 | F63: 1 | G63: dito.sichinava@gmail.com | H63: 2.1.1.3. (-) ლიფტების მონტაჟის ღირებულება | I63: Budget Dummy (ს.კ. ICE002065) - შპს | J63: Grishashvili | 1.1.1. | მშენებელი 2004 | 50,000.00 USD | 22.05.2025 | L63: TRUE | N63: 77e812b6-2265-42fb-97e2-81ba5ba717a3 | O63: 45799.757 | P63: dito.sichinava@gmail.com
A64: 45964.5 | B64: 661 | C64: 42e8bb_a1_99b52f | F64: 1 | G64: dito.sichinava@gmail.com | H64: 2.1.1.8. (-) ლიფტების მონტაჟის გაუთვალისწინებელი ხარჯი | I64: Budget Dummy (ს.კ. ICE002065) - შპს | J64: Grishashvili | 1.1.1. | მშენებელი 2004 | 50,000.00 USD | 22.05.2025 | L64: FALSE | N64: 1d23c4ff-49b7-4152-bd9f-42bc25d57552 | O64: 45799.757 | P64: dito.sichinava@gmail.com
A65: 45962.458 | B65: 100 | C65: 3fd2b0_15_b1bf7e | E65: ბონუსი | F65: GE29BG0000000450982000 | G65: gio.nikabadze@gmail.com | H65: 3.2.1. (-) ოფისის იჯარის ხარჯი | I65: გიორგი ბახტაძე (ს.კ. 01024067298) - ფიზ. პირი | J65: Batumi Office Rent MEPPERS | 1.3.2. | მეპერსი | 300.00 USD | 15.08.2024 | L65: TRUE | N65: b7e0c2c5-8f2e-44a4-b6db-5020822e009e | O65: 45671.698 | P65: gio.nikabadze@gmail.com
A66: 45962.458 | B66: 170 | C66: 5b57b2_7d_b1d45c | E66: ბონუსი | F66: GE29BG0000000450982000 | G66: gio.nikabadze@gmail.com | H66: 3.2.1. (-) ოფისის იჯარის ხარჯი | I66: გიორგი ბახტაძე (ს.კ. 01024067298) - ფიზ. პირი | J66: Batumi Office Rent CASA | 1.3.2. | კაზა დი ბათუმი | 500.00 USD | 15.08.2024 | L66: TRUE | N66: 327293fb-5cfd-4151-85da-00a855a7a280 | O66: 45671.698 | P66: gio.nikabadze@gmail.com
A67: 45962.458 | B67: 100 | C67: 86f954_6b_816c74 | E67: ბონუსი | F67: GE22BG0000000343713900 | G67: gio.nikabadze@gmail.com | H67: 3.2.1. (-) ოფისის იჯარის ხარჯი | I67: პაატა დვალიშვილი (ს.კ. 01001011731) - ფიზ. პირი | J67: Batumi Office Rent MEPPERS | 1.3.2. | მეპერსი | 300.00 USD | 15.08.2024 | L67: TRUE | N67: a554ab41-5f91-4c8c-8ca0-93f47d90b226 | O67: 45671.698 | P67: gio.nikabadze@gmail.com
A68: 45962.458 | B68: 170 | C68: 01c4d3_05_a5dce3 | E68: ბონუსი | F68: GE22BG0000000343713900 | G68: gio.nikabadze@gmail.com | H68: 3.2.1. (-) ოფისის იჯარის ხარჯი | I68: პაატა დვალიშვილი (ს.კ. 01001011731) - ფიზ. პირი | J68: Batumi Office Rent CASA | 1.3.2. | კაზა დი ბათუმი | 500.00 USD | 15.08.2024 | L68: TRUE | N68: b5399c6b-d89e-4832-861e-7948bae73bb8 | O68: 45671.698 | P68: gio.nikabadze@gmail.com
A69: 45962.458 | B69: 480 | C69: e3b011_7d_9b3279 | E69: ბონუსი | F69: GE29BG0000000450982000 | G69: gio.nikabadze@gmail.com | H69: 3.2.1. (-) ოფისის იჯარის ხარჯი | I69: გიორგი ბახტაძე (ს.კ. 01024067298) - ფიზ. პირი | L69: TRUE | N69: ac2a1b3a-7193-402e-9340-21a3e8a8d35a | O69: 45671.698 | P69: gio.nikabadze@gmail.com
A70: 45962.458 | B70: 480 | C70: e05daf_4b_b0621d | E70: ბონუსი | F70: GE22BG0000000343713900 | G70: gio.nikabadze@gmail.com | H70: 3.2.1. (-) ოფისის იჯარის ხარჯი | I70: პაატა დვალიშვილი (ს.კ. 01001011731) - ფიზ. პირი | L70: TRUE | N70: c464235a-5919-4e67-ab59-92deb9b3e860 | O70: 45671.698 | P70: gio.nikabadze@gmail.com
A71: 45962.458 | B71: 203000 | C71: a9a9f9_2d_b659e6 | F71: 2 | G71: nikaelevator@gmail.com | H71: 1.1.1.2. (+) ლიფტების საქარხნო მზაობის ავანსი | I71: ზ-გრუპ (ს.კ. 400017245) - შპს | J71: ZYGMA | 1.1.1. | ზ-გრუპ | 524,300.00 USD | 10.03.2025 | L71: FALSE | N71: a3f0e279-7237-4cd7-9755-34867242ffc6 | O71: 45744.657 | P71: nikaelevator@gmail.com
A72: 45962.458 | B72: 208000 | C72: 1b448f_e0_818416 | F72: KZ4983201D0200436001 | G72: nikaelevator@gmail.com | H72: 2.1.1.1. (-) ლიფტების საქარხნო თვითღირებულება | I72: OTIS KAZAKHSTAN (ს.კ. 0) - უცხოური საწარმო | J72: ZYGMA | 1.1.1. | ზ-გრუპ | 524,300.00 USD | 10.03.2025 | L72: FALSE | N72: eb51e6b6-12bb-4058-9815-d2b85ee42aba | O72: 45744.657 | P72: nikaelevator@gmail.com
A73: 45960 | B73: 630 | C73: 03f387_32_83f33d | D73: მხოლოდ 630$ ჩაერიცხა კონცელიძეს | E73: ლიფტის მექანიკური მონტაჟის საფასური Basis BanK L0001 | F73: GE85BG0000000528248088 | G73: nikaelevator@gmail.com | H73: 2.1.1.3. (-) ლიფტების მონტაჟის ღირებულება | I73: ირაკლი კონცელიძე (ს.კ. 61004061086) - მცირე მეწარმე | J73: Basis BanK | 1.1.1. | მეპერსი | 5,000.00 USD | 01.02.2024 | K73: იჯარა | L73: FALSE | M73: L0001 | N73: f4f76729-01ad-4960-9d94-7a9fe1023882 | O73: 45667.06 | P73: nikaelevator@gmail.com
A74: 45958.458 | B74: 13230 | C74: dac879_b2_bcbd7f | F74: 2 | G74: nikaelevator@gmail.com | H74: 1.1.1.3. (+) ლიფტების საბაჟოზე შემოსვლის ან დასაწყობების ავანსი | I74: ნამი 2024 (ს.კ. 405720019) - შპს | J74: Nami | 1.1.1. | ნამი 2024 | 66,150.00 USD | 16.04.2025 | L74: FALSE | N74: cd22846b-6510-4c47-b665-218f961ac16c | O74: 45763.699 | P74: nikaelevator@gmail.com
A75: 45958.458 | B75: 12450 | C75: 24f41d_2a_a9cff2 | F75: DummyIBAN | G75: nikaelevator@gmail.com | H75: 2.1.1.2. (-) ლიფტების ტრანსპორტირება | I75: Budget Dummy (ს.კ. ICE002065) - შპს | J75: Nami | 1.1.1. | ნამი 2024 | 66,150.00 USD | 16.04.2025 | L75: FALSE | N75: f639993f-dd0b-484e-b913-7191a0a9ecf2 | O75: 45763.699 | P75: nikaelevator@gmail.com
A76: 45958.458 | B76: 9402 | C76: 52607e_3d_b82859 | F76: GE40BG0000000606119819 | G76: dito.sichinava@gmail.com | H76: 1.1.1.4. (+) ლიფტების მონტაჟის პროგრესის ავანსი | I76: ტოკიო ჰოტელ (ს.კ. 402229423) - შპს | J76: Uznadze Office | 1.1.1. | ტოკიო ჰოტელ | 94,000.00 USD | 01.05.2025 | L76: FALSE | N76: 265bd52d-cfaa-4990-839a-ff5187372d34 | O76: 45807.582 | P76: dito.sichinava@gmail.com
A77: 45958.458 | B77: 4100 | C77: c25732_51_b891b7 | F77: DummyIBAN | G77: dito.sichinava@gmail.com | H77: 2.1.1.3. (-) ლიფტების მონტაჟის ღირებულება | I77: Budget Dummy (ს.კ. ICE002065) - შპს | J77: Uznadze Office | 1.1.1. | ტოკიო ჰოტელ | 94,000.00 USD | 01.05.2025 | L77: FALSE | N77: da8cf36e-10b6-400a-a4a3-2ca6f5f76e10 | O77: 45807.582 | P77: dito.sichinava@gmail.com
A78: 45958.458 | B78: 654 | C78: eb7c48_51_ac2e16 | F78: DummyIBAN | G78: dito.sichinava@gmail.com | H78: 2.1.1.6. (-) ლიფტების მონტაჟის დამხმარე მასალები | I78: Budget Dummy (ს.კ. ICE002065) - შპს | J78: Uznadze Office | 1.1.1. | ტოკიო ჰოტელ | 94,000.00 USD | 01.05.2025 | L78: FALSE | N78: 318f5db2-0085-4334-b8c3-21928a0cf6b5 | O78: 45807.582 | P78: dito.sichinava@gmail.com
A79: 45957.458 | B79: 35259 | C79: 1f23e0_cf_a2d215 | F79: 2 | G79: dito.sichinava@gmail.com | H79: 1.1.1.3. (+) ლიფტების საბაჟოზე შემოსვლის ან დასაწყობების ავანსი | I79: გრანდე ჯგუფი (ს.კ. 404557127) - შპს | J79: Grande Krtsanisi D & E BlocK | 1.1.1. | გრანდე ჯგუფი | 235,060.00 USD | 13.05.2025 | L79: FALSE | N79: f9bd9584-52de-460b-a144-755c3d17074a | O79: 45792.717 | P79: dito.sichinava@gmail.com
A80: 45957.458 | B80: 15400 | C80: a3bbc5_4f_9b77c7 | F80: 2 | G80: dito.sichinava@gmail.com | H80: 2.1.1.3. (-) ლიფტების მონტაჟის ღირებულება | I80: Budget Dummy (ს.კ. ICE002065) - შპს | J80: Grande Krtsanisi D & E BlocK | 1.1.1. | გრანდე ჯგუფი | 235,060.00 USD | 13.05.2025 | L80: FALSE | N80: 2de528df-3de8-407c-a838-b62bbb777ab0 | O80: 45792.717 | P80: dito.sichinava@gmail.com
A81: 45955.458 | B81: 10060 | C81: b1bfab_2c_996082 | F81: GE21TB1000000036500001 | G81: dito.sichinava@gmail.com | H81: 1.1.1.4. (+) ლიფტების მონტაჟის პროგრესის ავანსი | I81: ანაგი (ს.კ. 245416401) - შპს | J81: Social Houses Batumi | 1.1.1. | ანაგი | 201,200.00 USD | 28.02.2025 | L81: FALSE | N81: 4c09dd8d-789d-404c-a3d8-ce3963add26e | O81: 45743.605 | P81: t.tsintsadze2006@gmail.com
A82: 45954.458 | B82: 9000 | C82: e7a388_9f_91d054 | F82: DummyIBAN | G82: nikaelevator@gmail.com | H82: 2.1.1.3. (-) ლიფტების მონტაჟის ღირებულება | I82: Budget Dummy (ს.კ. ICE002065) - შპს | J82: Panorama | 1.1.1. | იდეა ქონსთრაქშენი | 233,110.00 USD | 26.02.2025 | L82: TRUE | N82: a24ba360-bc30-47c5-bbd9-4a1b27ba93fa | O82: 45715.527 | P82: nikaelevator@gmail.com
A83: 45954.458 | B83: 1138.6667 | C83: 993716_ac_9159ba | F83: DummyIBAN | G83: nikaelevator@gmail.com | H83: 2.1.1.6. (-) ლიფტების მონტაჟის დამხმარე მასალები | I83: Budget Dummy (ს.კ. ICE002065) - შპს | J83: Panorama | 1.1.1. | იდეა ქონსთრაქშენი | 233,110.00 USD | 26.02.2025 | L83: FALSE | N83: 960a2230-2af8-4f87-a4e9-091a27a6ff0a | O83: 45715.527 | P83: nikaelevator@gmail.com
A84: 45942.458 | B84: 1334 | C84: 50f0f7_ac_9616f8 | F84: 111 | G84: dito.sichinava@gmail.com | H84: 1.1.1.4. (+) ლიფტების მონტაჟის პროგრესის ავანსი | I84: საკენი ბიოგრაფი (ს.კ. 404651015) - შპს | J84: SaKeni | 1.1.1. | საკენი ბიოგრაფი | 26,680.00 USD | 21.05.2025 | L84: FALSE | N84: 0667bd0c-3f69-4bd0-b236-590e11ebbbef | O84: 45807.582 | P84: dito.sichinava@gmail.com
A85: 45941.458 | B85: 2350 | C85: cdf6f4_f5_964395 | F85: GE92BG0000000285549500 | G85: nikaelevator@gmail.com | H85: 1.1.1.5. (+) ლიფტების ჩაბარება | I85: მპ დეველოპმენტი (ს.კ. 404960217) - შპს | J85: Telavi Mall | 1.1.1. | მპ დეველოპმენტი | 47,000.00 USD | 31.01.2025 | L85: FALSE | N85: 883dfffb-df3e-4af4-8c3f-ab822f4fc61b | O85: 45729.54 | P85: nikaelevator@gmail.com
A86: 45941.458 | B86: 1300 | C86: cab4cd_7d_864fdb | F86: DummyIBAN | G86: nikaelevator@gmail.com | H86: 2.1.1.3. (-) ლიფტების მონტაჟის ღირებულება | I86: Budget Dummy (ს.კ. ICE002065) - შპს | J86: Telavi Mall | 1.1.1. | მპ დეველოპმენტი | 47,000.00 USD | 31.01.2025 | L86: TRUE | N86: ba98c8af-5941-44f8-8346-777785e6ae92 | O86: 45729.54 | P86: nikaelevator@gmail.com
A87: 45941.458 | B87: 418 | C87: ec00a8_c4_b298b0 | F87: DummyIBAN | G87: nikaelevator@gmail.com | H87: 2.1.1.6. (-) ლიფტების მონტაჟის დამხმარე მასალები | I87: Budget Dummy (ს.კ. ICE002065) - შპს | J87: Telavi Mall | 1.1.1. | მპ დეველოპმენტი | 47,000.00 USD | 31.01.2025 | L87: FALSE | N87: 9d3dcd2b-f496-40b2-a9e4-698198027a62 | O87: 45729.54 | P87: nikaelevator@gmail.com
A88: 45941.458 | B88: 431 | C88: 46e4e5_b6_895db2 | F88: DummyIBAN | G88: nikaelevator@gmail.com | H88: 2.1.1.9. (-) ლიფტების მონტაჟის ბონუსები | I88: Budget Dummy (ს.კ. ICE002065) - შპს | J88: Telavi Mall | 1.1.1. | მპ დეველოპმენტი | 47,000.00 USD | 31.01.2025 | L88: FALSE | N88: 8593fabb-1ed1-4428-817a-5dd1bc8593f4 | O88: 45729.54 | P88: nikaelevator@gmail.com
A89: 45940.458 | B89: 11040 | C89: bda45f_d7_88c4b7 | F89: DummyIBAN | G89: dito.sichinava@gmail.com | H89: 2.1.1.3. (-) ლიფტების მონტაჟის ღირებულება | I89: Budget Dummy (ს.კ. ICE002065) - შპს | J89: Social Houses Batumi | 1.1.1. | ანაგი | 201,200.00 USD | 28.02.2025 | L89: TRUE | N89: 7803cd5e-e8e8-4738-b24c-8b9a318fe3bb | O89: 45743.605 | P89: t.tsintsadze2006@gmail.com
A90: 45940.458 | B90: 1382.6667 | C90: 9fa741_33_945418 | F90: DummyIBAN | G90: dito.sichinava@gmail.com | H90: 2.1.1.4. (-) ლიფტების მონტაჟის დამხმარე შრომა | I90: Budget Dummy (ს.კ. ICE002065) - შპს | J90: Social Houses Batumi | 1.1.1. | ანაგი | 201,200.00 USD | 28.02.2025 | L90: FALSE | N90: d1230a95-153f-4ba5-93b0-6c711fb7223c | O90: 45743.605 | P90: t.tsintsadze2006@gmail.com
A91: 45934.458 | B91: 7500 | C91: 26c27b_d9_afe7e4 | F91: 1 | G91: dito.sichinava@gmail.com | H91: 1.1.1.3. (+) ლიფტების საბაჟოზე შემოსვლის ან დასაწყობების ავანსი | I91: მშენებელი 2004 (ს.კ. 205023277) - შპს | J91: Grishashvili | 1.1.1. | მშენებელი 2004 | 50,000.00 USD | 22.05.2025 | L91: FALSE | N91: 9240495b-4ddd-46ac-99a7-f311d0225016 | O91: 45799.757 | P91: dito.sichinava@gmail.com
A92: 45931.458 | B92: 100 | C92: 3fd2b0_15_b1bf7e | E92: ბონუსი | F92: GE29BG0000000450982000 | G92: gio.nikabadze@gmail.com | H92: 3.2.1. (-) ოფისის იჯარის ხარჯი | I92: გიორგი ბახტაძე (ს.კ. 01024067298) - ფიზ. პირი | J92: Batumi Office Rent MEPPERS | 1.3.2. | მეპერსი | 300.00 USD | 15.08.2024 | L92: TRUE | N92: ed61db77-396d-43b2-8a81-90db0c8dab5f | O92: 45671.698 | P92: gio.nikabadze@gmail.com
A93: 45931.458 | B93: 170 | C93: 5b57b2_7d_b1d45c | E93: ბონუსი | F93: GE29BG0000000450982000 | G93: gio.nikabadze@gmail.com | H93: 3.2.1. (-) ოფისის იჯარის ხარჯი | I93: გიორგი ბახტაძე (ს.კ. 01024067298) - ფიზ. პირი | J93: Batumi Office Rent CASA | 1.3.2. | კაზა დი ბათუმი | 500.00 USD | 15.08.2024 | L93: TRUE | N93: e9a94c53-91d7-4bb9-ae35-ba74218fa029 | O93: 45671.698 | P93: gio.nikabadze@gmail.com
A94: 45931.458 | B94: 100 | C94: 86f954_6b_816c74 | E94: ბონუსი | F94: GE22BG0000000343713900 | G94: gio.nikabadze@gmail.com | H94: 3.2.1. (-) ოფისის იჯარის ხარჯი | I94: პაატა დვალიშვილი (ს.კ. 01001011731) - ფიზ. პირი | J94: Batumi Office Rent MEPPERS | 1.3.2. | მეპერსი | 300.00 USD | 15.08.2024 | L94: TRUE | N94: 31a77c48-9c8f-4501-b9dc-834000e69ac1 | O94: 45671.698 | P94: gio.nikabadze@gmail.com
A95: 45931.458 | B95: 170 | C95: 01c4d3_05_a5dce3 | E95: ბონუსი | F95: GE22BG0000000343713900 | G95: gio.nikabadze@gmail.com | H95: 3.2.1. (-) ოფისის იჯარის ხარჯი | I95: პაატა დვალიშვილი (ს.კ. 01001011731) - ფიზ. პირი | J95: Batumi Office Rent CASA | 1.3.2. | კაზა დი ბათუმი | 500.00 USD | 15.08.2024 | L95: TRUE | N95: ae9debcd-4020-4082-8071-5791878e70c4 | O95: 45671.698 | P95: gio.nikabadze@gmail.com
A96: 45931.458 | B96: 480 | C96: e3b011_7d_9b3279 | E96: ბონუსი | F96: GE29BG0000000450982000 | G96: gio.nikabadze@gmail.com | H96: 3.2.1. (-) ოფისის იჯარის ხარჯი | I96: გიორგი ბახტაძე (ს.კ. 01024067298) - ფიზ. პირი | L96: TRUE | N96: 7807f102-cd44-4828-8d3c-43a35df85060 | O96: 45671.698 | P96: gio.nikabadze@gmail.com
A97: 45931.458 | B97: 480 | C97: e05daf_4b_b0621d | E97: ბონუსი | F97: GE22BG0000000343713900 | G97: gio.nikabadze@gmail.com | H97: 3.2.1. (-) ოფისის იჯარის ხარჯი | I97: პაატა დვალიშვილი (ს.კ. 01001011731) - ფიზ. პირი | L97: TRUE | N97: 3705f386-3bcf-4fe2-ba18-1ac99b5179f7 | O97: 45671.698 | P97: gio.nikabadze@gmail.com
A98: 45928.458 | B98: 6670 | C98: 207bbe_31_a69cfc | F98: 111 | G98: dito.sichinava@gmail.com | H98: 1.1.1.3. (+) ლიფტების საბაჟოზე შემოსვლის ან დასაწყობების ავანსი | I98: საკენი ბიოგრაფი (ს.კ. 404651015) - შპს | J98: SaKeni | 1.1.1. | საკენი ბიოგრაფი | 26,680.00 USD | 21.05.2025 | L98: FALSE | N98: 6250710d-895e-4a8a-aea6-a051a6e6fe1e | O98: 45807.582 | P98: dito.sichinava@gmail.com
A99: 45928.458 | B99: 4100 | C99: 7530d8_6a_8466c1 | F99: 333 | G99: dito.sichinava@gmail.com | H99: 2.1.1.2. (-) ლიფტების ტრანსპორტირება | I99: Budget Dummy (ს.კ. ICE002065) - შპს | J99: SaKeni | 1.1.1. | საკენი ბიოგრაფი | 26,680.00 USD | 21.05.2025 | L99: FALSE | N99: e4e1b984-efdb-4387-9de5-55e6fae38921 | O99: 45807.582 | P99: dito.sichinava@gmail.com
A100: 45928.458 | B100: 14103 | C100: 943032_a4_8a0df7 | F100: GE40BG0000000606119819 | G100: dito.sichinava@gmail.com | H100: 1.1.1.3. (+) ლიფტების საბაჟოზე შემოსვლის ან დასაწყობების ავანსი | I100: ტოკიო ჰოტელ (ს.კ. 402229423) - შპს | J100: Uznadze Office | 1.1.1. | ტოკიო ჰოტელ | 94,000.00 USD | 01.05.2025 | L100: FALSE | N100: b78de480-b28b-4224-b342-ceacea8be193 | O100: 45807.582 | P100: dito.sichinava@gmail.com
...

Sheet Sheet1
A1: paymentId | B1: effectiveDate | C1: accrual | D1: order | E1: comment | F1: recordUuid | G1: userEmail
A2: f3ce6e_a3_beadc9 | B2: 46142 | D2: 25000 | F2: 9b744368-f75c-456d-9a8e-9bdf1ba21169 | G2: nikaelevator@gmail.com | H2: {=MATCH(A2&B2,Sheet2!$A$2:$A$6970&Sheet2!$B$2:$B$6970,0)} -> 5509 | I2: {=ISNUMBER(B2:B8118)} -> TRUE
A3: 5007c8_f0_b26d52 | B3: 46142 | D3: 962 | F3: 3447cfc3-e66b-443c-b7f2-82e9f0f949dd | G3: nikaelevator@gmail.com | H3: {=MATCH(A3&B3,Sheet2!$A$2:$A$6970&Sheet2!$B$2:$B$6970,0)} -> 5518 | I3: TRUE
A4: b83db5_84_b38688 | B4: 46127 | D4: 25000 | F4: d97adbef-875b-4fb1-8e16-522e9cda263a | G4: nikaelevator@gmail.com | H4: {=MATCH(A4&B4,Sheet2!$A$2:$A$6970&Sheet2!$B$2:$B$6970,0)} -> 5508 | I4: TRUE
A5: fc79e7_85_8e7110 | B5: 46127 | D5: 21200 | F5: 81759988-8d22-4a12-ad6d-94d4049106ab | G5: nikaelevator@gmail.com | H5: {=MATCH(A5&B5,Sheet2!$A$2:$A$6970&Sheet2!$B$2:$B$6970,0)} -> 5514 | I5: TRUE
A6: a6622d_06_a1a791 | B6: 46127 | D6: 1590 | F6: 33461393-89c8-4877-9702-0ffa90130fb1 | G6: nikaelevator@gmail.com | H6: {=MATCH(A6&B6,Sheet2!$A$2:$A$6970&Sheet2!$B$2:$B$6970,0)} -> 5517 | I6: TRUE
A7: b9aaa8_9e_9285dc | B7: 46097 | D7: 22000 | F7: b40bae34-6cd0-4dfb-bb52-929411b0f0da | G7: nikaelevator@gmail.com | H7: {=MATCH(A7&B7,Sheet2!$A$2:$A$6970&Sheet2!$B$2:$B$6970,0)} -> 5513 | I7: TRUE
A8: ba3047_8b_9b6889 | B8: 46097 | D8: 1600 | F8: aa2fe372-6fa5-416f-8e39-71b791155e41 | G8: nikaelevator@gmail.com | H8: {=MATCH(A8&B8,Sheet2!$A$2:$A$6970&Sheet2!$B$2:$B$6970,0)} -> 5516 | I8: TRUE
A9: 777dd5_69_ba96e1 | B9: 46067 | D9: 22000 | F9: cd17e642-3548-46e4-a2c7-b71991f829eb | G9: nikaelevator@gmail.com | H9: {=MATCH(A9&B9,Sheet2!$A$2:$A$6970&Sheet2!$B$2:$B$6970,0)} -> 5512 | I9: TRUE
A10: 67707d_5a_be6e2a | B10: 46067 | D10: 1600 | F10: 751c23df-ddf7-4035-bfc5-7de5a0378a58 | G10: nikaelevator@gmail.com | H10: {=MATCH(A10&B10,Sheet2!$A$2:$A$6970&Sheet2!$B$2:$B$6970,0)} -> 5515 | I10: TRUE
A11: a3a1a2_f5_be4ae3 | B11: 46037 | D11: 222000 | F11: 0cf5880f-c4ef-447d-9952-3d8b37283c52 | G11: nikaelevator@gmail.com | H11: {=MATCH(A11&B11,Sheet2!$A$2:$A$6970&Sheet2!$B$2:$B$6970,0)} -> 5507 | I11: TRUE
A12: 3197b7_5d_9c197e | B12: 46037 | D12: 36800 | F12: aea3a925-c419-445a-be02-29db9c84a7a3 | G12: nikaelevator@gmail.com | H12: {=MATCH(A12&B12,Sheet2!$A$2:$A$6970&Sheet2!$B$2:$B$6970,0)} -> 5511 | I12: TRUE
A13: 5eecbc_3a_9cc4c3 | B13: 46033 | D13: 6615 | F13: b49bc77e-fcce-4d9b-81f5-941bb5fea34f | G13: nikaelevator@gmail.com | H13: {=MATCH(A13&B13,Sheet2!$A$2:$A$6970&Sheet2!$B$2:$B$6970,0)} -> 5628 | I13: TRUE
A14: 1e93d0_c4_a2b384 | B14: 46033 | D14: 1875 | F14: 1b8c55a4-acd0-4b17-97da-9bdd1b2d7110 | G14: nikaelevator@gmail.com | H14: {=MATCH(A14&B14,Sheet2!$A$2:$A$6970&Sheet2!$B$2:$B$6970,0)} -> 5634 | I14: TRUE
... A72: 1b448f_e0_818416 | B72: 45962 | D72: 208000 | F72: eb51e6b6-12bb-4058-9815-d2b85ee42aba | G72: nikaelevator@gmail.com | H72: {=MATCH(A72&B72,Sheet2!$A$2:$A$6970&Sheet2!$B$2:$B$6970,0)} -> 5510 | I72: TRUE
A73: 03f387_32_83f33d | B73: 45960 | D73: 630 | E73: მხოლოდ 630$ ჩაერიცხა კონცელიძეს | F73: f4f76729-01ad-4960-9d94-7a9fe1023882 | G73: nikaelevator@gmail.com | H73: {=MATCH(A73&B73,Sheet2!$A$2:$A$6970&Sheet2!$B$2:$B$6970,0)} -> #N/A | I73: TRUE
A74: dac879_b2_bcbd7f | B74: 45958 | D74: 13230 | F74: cd22846b-6510-4c47-b665-218f961ac16c | G74: nikaelevator@gmail.com | H74: {=MATCH(A74&B74,Sheet2!$A$2:$A$6970&Sheet2!$B$2:$B$6970,0)} -> 5627 | I74: TRUE
A75: 24f41d_2a_a9cff2 | B75: 45958 | D75: 12450 | F75: f639993f-dd0b-484e-b913-7191a0a9ecf2 | G75: nikaelevator@gmail.com | H75: {=MATCH(A75&B75,Sheet2!$A$2:$A$6970&Sheet2!$B$2:$B$6970,0)} -> 5631 | I75: TRUE
A76: 52607e_3d_b82859 | B76: 45958 | D76: 9402 | F76: 265bd52d-cfaa-4990-839a-ff5187372d34 | G76: dito.sichinava@gmail.com | H76: {=MATCH(A76&B76,Sheet2!$A$2:$A$6970&Sheet2!$B$2:$B$6970,0)} -> 5923 | I76: TRUE
A77: c25732_51_b891b7 | B77: 45958 | D77: 4100 | F77: da8cf36e-10b6-400a-a4a3-2ca6f5f76e10 | G77: dito.sichinava@gmail.com | H77: {=MATCH(A77&B77,Sheet2!$A$2:$A$6970&Sheet2!$B$2:$B$6970,0)} -> 5928 | I77: TRUE
A78: eb7c48_51_ac2e16 | B78: 45958 | D78: 654 | F78: 318f5db2-0085-4334-b8c3-21928a0cf6b5 | G78: dito.sichinava@gmail.com | H78: {=MATCH(A78&B78,Sheet2!$A$2:$A$6970&Sheet2!$B$2:$B$6970,0)} -> 5930 | I78: TRUE
A79: 1f23e0_cf_a2d215 | B79: 45957 | D79: 35259 | F79: f9bd9584-52de-460b-a144-755c3d17074a | G79: dito.sichinava@gmail.com | H79: {=MATCH(A79&B79,Sheet2!$A$2:$A$6970&Sheet2!$B$2:$B$6970,0)} -> 5823 | I79: TRUE
A80: a3bbc5_4f_9b77c7 | B80: 45957 | D80: 15400 | F80: 2de528df-3de8-407c-a838-b62bbb777ab0 | G80: dito.sichinava@gmail.com | H80: {=MATCH(A80&B80,Sheet2!$A$2:$A$6970&Sheet2!$B$2:$B$6970,0)} -> 5827 | I80: TRUE
A81: b1bfab_2c_996082 | B81: 45955 | D81: 10060 | F81: 4c09dd8d-789d-404c-a3d8-ce3963add26e | G81: t.tsintsadze2006@gmail.com | H81: {=MATCH(A81&B81,Sheet2!$A$2:$A$6970&Sheet2!$B$2:$B$6970,0)} -> 5488 | I81: TRUE
A82: e7a388_9f_91d054 | B82: 45954 | D82: 9000 | F82: a24ba360-bc30-47c5-bbd9-4a1b27ba93fa | G82: nikaelevator@gmail.com | H82: {=MATCH(A82&B82,Sheet2!$A$2:$A$6970&Sheet2!$B$2:$B$6970,0)} -> 5295 | I82: TRUE
A83: 993716_ac_9159ba | B83: 45954 | D83: 1138.6667 | F83: 960a2230-2af8-4f87-a4e9-091a27a6ff0a | G83: nikaelevator@gmail.com | H83: {=MATCH(A83&B83,Sheet2!$A$2:$A$6970&Sheet2!$B$2:$B$6970,0)} -> 5298 | I83: TRUE
A84: 50f0f7_ac_9616f8 | B84: 45942 | D84: 1334 | F84: 0667bd0c-3f69-4bd0-b236-590e11ebbbef | G84: dito.sichinava@gmail.com | H84: {=MATCH(A84&B84,Sheet2!$A$2:$A$6970&Sheet2!$B$2:$B$6970,0)} -> 5910 | I84: TRUE
A85: cdf6f4_f5_964395 | B85: 45941 | D85: 2350 | F85: 883dfffb-df3e-4af4-8c3f-ab822f4fc61b | G85: nikaelevator@gmail.com | H85: {=MATCH(A85&B85,Sheet2!$A$2:$A$6970&Sheet2!$B$2:$B$6970,0)} -> 5388 | I85: TRUE
... A105: 93582a_91_bd23aa | B105: 45924 | D105: 1138.6667 | F105: 39a53714-d031-4b46-9cdd-da1ac8b0e20f | G105: nikaelevator@gmail.com | H105: {=MATCH(A105&B105,Sheet2!$A$2:$A$6970&Sheet2!$B$2:$B$6970,0)} -> 5297 | I105: TRUE
A106: f0e746_dc_8f772e | B106: 45915 | D106: 953.8 | E106: მანქანა #4 | F106: 225b0d63-2fe0-44cf-918b-020ec918bad0 | G106: gio.nikabadze@gmail.com | H106: {=MATCH(A106&B106,Sheet2!$A$2:$A$6970&Sheet2!$B$2:$B$6970,0)} -> 4012 | I106: TRUE
A107: 3204ba_8e_a03b4d | B107: 45912 | D107: 9200 | F107: 9c7856e3-2178-476b-b295-6506e84d07cd | G107: nikaelevator@gmail.com | H107: {=MATCH(A107&B107,Sheet2!$A$2:$A$6970&Sheet2!$B$2:$B$6970,0)} -> 5306 | I107: TRUE
A108: 9d9b5e_80_96bbe4 | B108: 45912 | D108: 3500 | F108: 8a367363-587f-4c65-ad34-221cd1e6a456 | G108: nikaelevator@gmail.com | H108: {=MATCH(A108&B108,Sheet2!$A$2:$A$6970&Sheet2!$B$2:$B$6970,0)} -> 5311 | I108: TRUE
A109: cd2134_89_9c02ef | B109: 45912 | D109: 500 | F109: 80fc9dbc-b3e2-4c9c-ab44-76161c483d36 | G109: nikaelevator@gmail.com | H109: {=MATCH(A109&B109,Sheet2!$A$2:$A$6970&Sheet2!$B$2:$B$6970,0)} -> 5313 | I109: TRUE
A110: 88a1c5_cf_849d34 | B110: 45912 | D110: 829 | F110: eb9743d0-95dc-4773-9e4c-17e8dff0dfd3 | G110: nikaelevator@gmail.com | H110: {=MATCH(A110&B110,Sheet2!$A$2:$A$6970&Sheet2!$B$2:$B$6970,0)} -> 5315 | I110: TRUE
A111: 8993e6_9f_b16e46 | B111: 45912 | D111: 431 | F111: a255e0e7-0a9a-4ecb-9649-db07f6412be1 | G111: nikaelevator@gmail.com | H111: {=MATCH(A111&B111,Sheet2!$A$2:$A$6970&Sheet2!$B$2:$B$6970,0)} -> 5316 | I111: TRUE
A112: d35a7d_48_a5b35c | B112: 45910 | D112: 50300 | F112: ec9fb7ba-a491-4850-bc9e-6ab6b8ab5ad6 | G112: t.tsintsadze2006@gmail.com | H112: {=MATCH(A112&B112,Sheet2!$A$2:$A$6970&Sheet2!$B$2:$B$6970,0)} -> 5487 | I112: TRUE
A113: 53fb3e_b8_85c957 | B113: 45910 | D113: 18850 | F113: b0b44bdb-8f32-4105-8968-1d30d28becd5 | G113: t.tsintsadze2006@gmail.com | H113: {=MATCH(A113&B113,Sheet2!$A$2:$A$6970&Sheet2!$B$2:$B$6970,0)} -> 5491 | I113: TRUE
A114: 996ba1_b6_ac0529 | B114: 45910 | D114: 1667 | F114: 7e0c7e94-8425-4508-874d-41e6843dc5b4 | G114: t.tsintsadze2006@gmail.com | H114: {=MATCH(A114&B114,Sheet2!$A$2:$A$6970&Sheet2!$B$2:$B$6970,0)} -> 5498 | I114: TRUE
A115: 3fd2b0_15_b1bf7e | B115: 45901 | D115: 100 | F115: 739caa67-d422-47b0-8e22-09a4e31ef129 | G115: gio.nikabadze@gmail.com | H115: {=MATCH(A115&B115,Sheet2!$A$2:$A$6970&Sheet2!$B$2:$B$6970,0)} -> 4550 | I115: TRUE
A116: 5b57b2_7d_b1d45c | B116: 45901 | D116: 170 | F116: bcf8616a-d921-4989-8b5c-de9d4874647b | G116: gio.nikabadze@gmail.com | H116: {=MATCH(A116&B116,Sheet2!$A$2:$A$6970&Sheet2!$B$2:$B$6970,0)} -> 4551 | I116: TRUE
A117: 86f954_6b_816c74 | B117: 45901 | D117: 100 | F117: a343071c-c402-442c-a090-b1ec0aef4e11 | G117: gio.nikabadze@gmail.com | H117: {=MATCH(A117&B117,Sheet2!$A$2:$A$6970&Sheet2!$B$2:$B$6970,0)} -> 4552 | I117: TRUE
A118: 01c4d3_05_a5dce3 | B118: 45901 | D118: 170 | F118: 77d3f4ac-93de-4598-ba94-5aafdc1352a0 | G118: gio.nikabadze@gmail.com | H118: {=MATCH(A118&B118,Sheet2!$A$2:$A$6970&Sheet2!$B$2:$B$6970,0)} -> 4553 | I118: TRUE
... A123: 9afd1c_3c_bdc271 | B123: 45894 | D123: 12500 | F123: 98673939-710c-4f28-b90e-67cdae8a4afb | G123: nikaelevator@gmail.com | H123: {=MATCH(A123&B123,Sheet2!$A$2:$A$6970&Sheet2!$B$2:$B$6970,0)} -> 5293 | I123: TRUE
A124: f0e746_dc_8f772e | B124: 45884 | D124: 949 | E124: მანქანა #4 | F124: 08444caa-6d36-49ba-a062-1c5c618098e0 | G124: gio.nikabadze@gmail.com | H124: {=MATCH(A124&B124,Sheet2!$A$2:$A$6970&Sheet2!$B$2:$B$6970,0)} -> 4011 | I124: TRUE
A125: 2e076f_31_9f8d41 | B125: 45882 | D125: 3500 | F125: 05247a24-d927-41c7-8938-297ce4853e3b | G125: nikaelevator@gmail.com | H125: {=MATCH(A125&B125,Sheet2!$A$2:$A$6970&Sheet2!$B$2:$B$6970,0)} -> 5310 | I125: TRUE
A126: bd11b1_b1_af0e14 | B126: 45882 | D126: 500 | F126: 04dc466f-26d4-4483-bf42-f57beed4e00d | G126: nikaelevator@gmail.com | H126: {=MATCH(A126&B126,Sheet2!$A$2:$A$6970&Sheet2!$B$2:$B$6970,0)} -> 5312 | I126: TRUE
A127: 9a48a1_6e_9eb68c | B127: 45882 | D127: 829 | F127: 3ae76166-bd64-4c04-827c-192e540a891f | G127: nikaelevator@gmail.com | H127: {=MATCH(A127&B127,Sheet2!$A$2:$A$6970&Sheet2!$B$2:$B$6970,0)} -> 5314 | I127: TRUE
A128: c21079_a4_bee167 | B128: 45882 | D128: 70518 | F128: c56c0c67-9346-4681-be1d-bfe433a67ad0 | G128: dito.sichinava@gmail.com | H128: {=MATCH(A128&B128,Sheet2!$A$2:$A$6970&Sheet2!$B$2:$B$6970,0)} -> 5822 | I128: TRUE
A129: b1a9a3_9a_9742ba | B129: 45882 | D129: 58250 | F129: 2025ba76-a030-4daf-a3f9-eeda9a13db31 | G129: dito.sichinava@gmail.com | H129: {=MATCH(A129&B129,Sheet2!$A$2:$A$6970&Sheet2!$B$2:$B$6970,0)} -> 5826 | I129: TRUE
A130: fbaa5c_24_a3afaf | B130: 45881 | D130: 11750 | F130: 87a58cef-06fb-4d2f-b66d-06d778ae3a17 | G130: nikaelevator@gmail.com | H130: {=MATCH(A130&B130,Sheet2!$A$2:$A$6970&Sheet2!$B$2:$B$6970,0)} -> 5386 | I130: TRUE
A131: 903792_6f_91a67c | B131: 45881 | D131: 8200 | F131: e35616c9-b82a-40c1-8ae3-884a0f2fa781 | G131: nikaelevator@gmail.com | H131: {=MATCH(A131&B131,Sheet2!$A$2:$A$6970&Sheet2!$B$2:$B$6970,0)} -> 5391 | I131: TRUE
A132: ce7848_f7_96b96d | B132: 45880 | D132: 62000 | F132: b99e3595-5617-481f-bd40-2fecabf915b6 | G132: t.tsintsadze2006@gmail.com | H132: {=MATCH(A132&B132,Sheet2!$A$2:$A$6970&Sheet2!$B$2:$B$6970,0)} -> 4844 | I132: TRUE
A133: 1009fb_e6_9e3b00 | B133: 45880 | D133: 962 | F133: aa8447b6-097f-475a-882c-1e4d42b3793c | G133: t.tsintsadze2006@gmail.com | H133: {=MATCH(A133&B133,Sheet2!$A$2:$A$6970&Sheet2!$B$2:$B$6970,0)} -> 4849 | I133: TRUE
A134: 212ec2_a4_865118 | B134: 45880 | D134: 17700 | F134: dd920cbb-8283-4bc3-a949-bdaff8ec7c1e | G134: t.tsintsadze2006@gmail.com | H134: {=MATCH(A134&B134,Sheet2!$A$2:$A$6970&Sheet2!$B$2:$B$6970,0)} -> 4853 | I134: TRUE
A135: 7e5dcd_86_9b86c9 | B135: 45874 | D135: 17500 | F135: 857c1730-56fb-4ca3-a4c7-72a534762064 | G135: dito.sichinava@gmail.com | H135: {=MATCH(A135&B135,Sheet2!$A$2:$A$6970&Sheet2!$B$2:$B$6970,0)} -> 5869 | I135: TRUE
A136: 8fa476_3a_bca703 | B136: 45874 | D136: 12250 | F136: ef82d667-1ea3-41cc-bb9c-31b817ce8a4c | G136: dito.sichinava@gmail.com | H136: {=MATCH(A136&B136,Sheet2!$A$2:$A$6970&Sheet2!$B$2:$B$6970,0)} -> 5874 | I136: TRUE
... A146: c2c311_b6_8a1638 | B146: 45868 | D146: 23152 | F146: b241201a-df33-4114-88b8-831b82e3f050 | G146: nikaelevator@gmail.com | H146: {=MATCH(A146&B146,Sheet2!$A$2:$A$6970&Sheet2!$B$2:$B$6970,0)} -> 5626 | I146: TRUE
A147: f0e746_dc_8f772e | B147: 45867 | D147: 953.8 | E147: QQ336QV ბათუმის ლიფტები | F147: 22bf817a-d9a8-48c1-8f81-31f7d6112cd2 | G147: gio.nikabadze@gmail.com | H147: {=MATCH(A147&B147,Sheet2!$A$2:$A$6970&Sheet2!$B$2:$B$6970,0)} -> 3990 | I147: TRUE
A148: 659bce_3a_8b1c65 | B148: 45865 | D148: 250 | E148: ზეთის შეცვლა კამრი | F148: 90674757-52a7-4263-b83d-a2a6b12d6b50 | G148: dito.sichinava@gmail.com | H148: {=MATCH(A148&B148,Sheet2!$A$2:$A$6970&Sheet2!$B$2:$B$6970,0)} -> 6246 | I148: TRUE
A149: 5aa1b4_1a_922ace | B149: 45864 | D149: 1200 | E149: რელსების გაწმენდა 3 კაცი * 9 დღე *80₾ | F149: 59072f26-7c22-4b34-8338-db17ce6d4036 | G149: dito.sichinava@gmail.com | H149: {=MATCH(A149&B149,Sheet2!$A$2:$A$6970&Sheet2!$B$2:$B$6970,0)} -> 6243 | I149: TRUE
A150: c34390_12_93f512 | B150: 45864 | D150: 1200 | E150: რელსების გაწმენდა 3 კაცი * 9 დღე *80₾ | F150: b7c8eb5e-51bf-4248-93fb-5827f5832f8d | G150: dito.sichinava@gmail.com | H150: {=MATCH(A150&B150,Sheet2!$A$2:$A$6970&Sheet2!$B$2:$B$6970,0)} -> 6244 | I150: TRUE
A151: c69e7e_82_815150 | B151: 45864 | D151: 600 | E151: [22:01, 25/07/2025] David Nadiradze: ბესო გამოყლეებულს ჩაურიცხე ყვარლის სასტუმროს პროექტზე დაზიანებული ვრფ-გარე ბლოკის შეკეთების 600 ლარი | F151: 112e06db-5dd0-47a3-b64e-f4ebc9426e8b | G151: dito.sichinava@gmail.com | H151: {=MATCH(A151&B151,Sheet2!$A$2:$A$6970&Sheet2!$B$2:$B$6970,0)} -> 6245 | I151: TRUE
A152: 5ae613_9a_a4197a | B152: 45863 | D152: 1530 | E152: ალექსეის პირველი ბინა | F152: c933b70f-acac-4cf4-868a-2095810da826 | G152: dito.sichinava@gmail.com | H152: {=MATCH(A152&B152,Sheet2!$A$2:$A$6970&Sheet2!$B$2:$B$6970,0)} -> 6224 | I152: TRUE
A153: 4fc1a7_00_857c53 | B153: 45863 | D153: 720 | F153: e0be3505-b86d-48cf-bcc3-c24b4ae3d42b | G153: nikaelevator@gmail.com | H153: {=MATCH(A153&B153,Sheet2!$A$2:$A$6970&Sheet2!$B$2:$B$6970,0)} -> #N/A | I153: TRUE
A154: f0cdec_57_9726f8 | B154: 45863 | D154: 215.997 | F154: 79f770ae-8bd0-4ca8-9c04-40e82df2b47d | G154: nikaelevator@gmail.com | H154: {=MATCH(A154&B154,Sheet2!$A$2:$A$6970&Sheet2!$B$2:$B$6970,0)} -> 6225 | I154: TRUE
A155: 2eec3c_88_977f94 | B155: 45863 | D155: 2000 | F155: b18c6b8a-d621-47be-9026-9a5f7f172418 | G155: dito.sichinava@gmail.com | H155: {=MATCH(A155&B155,Sheet2!$A$2:$A$6970&Sheet2!$B$2:$B$6970,0)} -> 6227 | I155: TRUE
A156: 110836_84_aa8d02 | B156: 45863 | D156: 1000 | F156: c1a6de14-9978-48f6-929a-ff2698bacd20 | G156: dito.sichinava@gmail.com | H156: {=MATCH(A156&B156,Sheet2!$A$2:$A$6970&Sheet2!$B$2:$B$6970,0)} -> 6228 | I156: TRUE
A157: debd17_0d_ab9df5 | B157: 45863 | D157: 500 | F157: 9c5edfce-b9db-42ec-ab46-95efe41295b4 | G157: dito.sichinava@gmail.com | H157: {=MATCH(A157&B157,Sheet2!$A$2:$A$6970&Sheet2!$B$2:$B$6970,0)} -> 6229 | I157: TRUE
A158: 2de726_a6_a94436 | B158: 45863 | D158: 14900 | F158: 816e4630-ff36-4dcd-97fb-d6a830f628ce | G158: dito.sichinava@gmail.com | H158: {=MATCH(A158&B158,Sheet2!$A$2:$A$6970&Sheet2!$B$2:$B$6970,0)} -> 6231 | I158: TRUE
A159: bb8a8b_d6_bad9ea | B159: 45863 | D159: 1900 | F159: 59724c94-763f-4314-893a-ac68d0193ed9 | G159: dito.sichinava@gmail.com | H159: {=MATCH(A159&B159,Sheet2!$A$2:$A$6970&Sheet2!$B$2:$B$6970,0)} -> 6235 | I159: TRUE
A160: 4dadae_77_9db68a | B160: 45863 | D160: 1000 | F160: 0a78d095-ea83-492e-b336-c0186b9352fa | G160: dito.sichinava@gmail.com | H160: {=MATCH(A160&B160,Sheet2!$A$2:$A$6970&Sheet2!$B$2:$B$6970,0)} -> 6238 | I160: TRUE
A161: a8e493_76_89534b | B161: 45863 | D161: 1500 | F161: 4c80fce9-c33a-4dc0-b63a-e59793b0b1e5 | G161: dito.sichinava@gmail.com | H161: {=MATCH(A161&B161,Sheet2!$A$2:$A$6970&Sheet2!$B$2:$B$6970,0)} -> 6239 | I161: TRUE
A162: aa7f18_ac_968132 | B162: 45863 | D162: 1000 | F162: 33500f2b-ec30-440a-a2a7-df54ba66ac02 | G162: dito.sichinava@gmail.com | H162: {=MATCH(A162&B162,Sheet2!$A$2:$A$6970&Sheet2!$B$2:$B$6970,0)} -> 6240 | I162: TRUE
A163: e6a9bb_99_8efaea | B163: 45863 | D163: 4000 | F163: f2f8e247-85fc-4699-8849-2d159bb129be | G163: dito.sichinava@gmail.com | H163: {=MATCH(A163&B163,Sheet2!$A$2:$A$6970&Sheet2!$B$2:$B$6970,0)} -> 6241 | I163: TRUE
A164: 67839e_f4_b4ff59 | B164: 45862 | D164: 1960 | E164: ბოლო ხელფასი რახან გავუშვით | F164: 95616d34-3564-41f6-94d6-f156708bbd88 | G164: dito.sichinava@gmail.com | H164: {=MATCH(A164&B164,Sheet2!$A$2:$A$6970&Sheet2!$B$2:$B$6970,0)} -> 6206 | I164: TRUE
A165: d2b30c_d3_a42b15 | B165: 45862 | D165: 500 | F165: 81d55a39-f507-4af4-b441-44e7cfccb078 | G165: nikaelevator@gmail.com | H165: {=MATCH(A165&B165,Sheet2!$A$2:$A$6970&Sheet2!$B$2:$B$6970,0)} -> 6207 | I165: TRUE
A166: 786ff2_ec_907a0b | B166: 45862 | D166: 300 | E166: ხარაჩოს დაშლა აწყობის ღირებულება (ხარაჩოს მოიტანს მეპერსი) | F166: d28eda21-b802-49ed-8283-4d9d5d0a8377 | G166: nikaelevator@gmail.com | H166: {=MATCH(A166&B166,Sheet2!$A$2:$A$6970&Sheet2!$B$2:$B$6970,0)} -> 6208 | I166: TRUE
A167: a23aa9_29_8e510c | B167: 45862 | D167: 2940 | F167: 6af12829-e7ac-452f-8dde-0f5dc10be8fc | G167: nikaelevator@gmail.com | H167: {=MATCH(A167&B167,Sheet2!$A$2:$A$6970&Sheet2!$B$2:$B$6970,0)} -> 6209 | I167: TRUE
A168: 25e8de_ac_b3e9ca | B168: 45862 | D168: 245 | F168: 4b689afb-aaa2-4702-ac92-f227d09aa8d4 | G168: nikaelevator@gmail.com | H168: {=MATCH(A168&B168,Sheet2!$A$2:$A$6970&Sheet2!$B$2:$B$6970,0)} -> 6210 | I168: TRUE
A169: 6920d7_cb_8b82bf | B169: 45862 | D169: 1960 | F169: fba10b2b-ab10-4884-a1af-52104acf5cae | G169: nikaelevator@gmail.com | H169: {=MATCH(A169&B169,Sheet2!$A$2:$A$6970&Sheet2!$B$2:$B$6970,0)} -> 6211 | I169: TRUE
A170: 298bf5_62_aa64eb | B170: 45862 | D170: 490 | F170: b7a0c290-31bb-435a-bb3e-deb22405d2cb | G170: nikaelevator@gmail.com | H170: {=MATCH(A170&B170,Sheet2!$A$2:$A$6970&Sheet2!$B$2:$B$6970,0)} -> 6212 | I170: TRUE
A171: 3dd293_2f_83bdb4 | B171: 45862 | D171: 490 | F171: 007cae07-ef22-487a-b616-2efa7a1388ad | G171: nikaelevator@gmail.com | H171: {=MATCH(A171&B171,Sheet2!$A$2:$A$6970&Sheet2!$B$2:$B$6970,0)} -> 6213 | I171: TRUE
A172: e1d559_2a_a0cbac | B172: 45862 | D172: 245 | F172: 19972544-9d57-4224-89c5-9ffc6ecfe7a3 | G172: nikaelevator@gmail.com | H172: {=MATCH(A172&B172,Sheet2!$A$2:$A$6970&Sheet2!$B$2:$B$6970,0)} -> 6214 | I172: TRUE
A173: 3b4107_bc_9bedb7 | B173: 45862 | D173: 2450 | F173: 33990085-25aa-4ec5-b725-ddd347c069f3 | G173: nikaelevator@gmail.com | H173: {=MATCH(A173&B173,Sheet2!$A$2:$A$6970&Sheet2!$B$2:$B$6970,0)} -> 6215 | I173: TRUE
A174: f4d490_cd_b41083 | B174: 45862 | D174: 980 | F174: 2b5327b0-d25a-499c-b914-c0c06eeaf5fd | G174: nikaelevator@gmail.com | H174: {=MATCH(A174&B174,Sheet2!$A$2:$A$6970&Sheet2!$B$2:$B$6970,0)} -> 6216 | I174: TRUE
A175: 2172ab_ad_9666ff | B175: 45862 | D175: 490 | F175: c472218f-98a8-402d-add9-b96d0b0c7df9 | G175: nikaelevator@gmail.com | H175: {=MATCH(A175&B175,Sheet2!$A$2:$A$6970&Sheet2!$B$2:$B$6970,0)} -> 6217 | I175: TRUE
A176: fa9ce0_0a_b54546 | B176: 45862 | D176: 980 | F176: 785bd67c-2e2b-447b-8258-134ca8aa2bb6 | G176: nikaelevator@gmail.com | H176: {=MATCH(A176&B176,Sheet2!$A$2:$A$6970&Sheet2!$B$2:$B$6970,0)} -> 6218 | I176: TRUE
A177: 287008_16_9595ea | B177: 45862 | D177: 3920 | F177: a48744c0-954f-4a67-a009-fe164866961f | G177: nikaelevator@gmail.com | H177: {=MATCH(A177&B177,Sheet2!$A$2:$A$6970&Sheet2!$B$2:$B$6970,0)} -> 6219 | I177: TRUE
A178: ac3e87_ea_ac5297 | B178: 45862 | D178: 245 | F178: 5fb165ce-bed3-4fc2-b417-e11edefad3eb | G178: nikaelevator@gmail.com | H178: {=MATCH(A178&B178,Sheet2!$A$2:$A$6970&Sheet2!$B$2:$B$6970,0)} -> 6220 | I178: TRUE
... A181: 42cf83_34_89806d | B181: 45861 | D181: 33 | F181: fcf91e64-486c-44ea-bf01-6a966a9d30dd | G181: nikaelevator@gmail.com | H181: {=MATCH(A181&B181,Sheet2!$A$2:$A$6970&Sheet2!$B$2:$B$6970,0)} -> 4799 | I181: TRUE
A182: 128964_a9_8bf226 | B182: 45861 | D182: 5500 | E182: ორბი 30 ლიფტის რელსის გასწორების საფასურის ხელფასი (თოშხუა + ანზორ გორჯელაძე) | F182: ca7fd7b1-3e57-45f4-b175-5864127537fe | G182: t.tsintsadze2006@gmail.com | H182: {=MATCH(A182&B182,Sheet2!$A$2:$A$6970&Sheet2!$B$2:$B$6970,0)} -> 6197 | I182: TRUE
A183: c017e6_77_90152a | B183: 45861 | D183: 11500 | E183: ორბი 30 ლიფტის რელსის გასწორების საფასურის ხელფასი (თოშხუა + ანზორ გორჯელაძე) | F183: 1a4b861a-53d3-45db-81c9-2a63a85b0b57 | G183: t.tsintsadze2006@gmail.com | H183: {=MATCH(A183&B183,Sheet2!$A$2:$A$6970&Sheet2!$B$2:$B$6970,0)} -> 6198 | I183: TRUE
A184: 2d5351_d6_95c577 | B184: 45861 | D184: 197.99 | F184: 2ef36a4d-ad37-47f5-88f0-8fd77e5bf807 | G184: nikaelevator@gmail.com | H184: {=MATCH(A184&B184,Sheet2!$A$2:$A$6970&Sheet2!$B$2:$B$6970,0)} -> #N/A | I184: TRUE
A185: c8b23c_70_b84b8b | B185: 45861 | D185: 198 | F185: e07542d9-3c07-4347-a08f-ad503842a02c | G185: nikaelevator@gmail.com | H185: {=MATCH(A185&B185,Sheet2!$A$2:$A$6970&Sheet2!$B$2:$B$6970,0)} -> #N/A | I185: TRUE
A186: 916cae_f8_9bdb51 | B186: 45861 | D186: 594 | F186: 01f53aa6-eb78-4ce7-a54f-e28fb99beeb5 | G186: nikaelevator@gmail.com | H186: {=MATCH(A186&B186,Sheet2!$A$2:$A$6970&Sheet2!$B$2:$B$6970,0)} -> #N/A | I186: TRUE
A187: 1c5b7f_74_b1ec04 | B187: 45861 | D187: 500 | E187: დაცლისას მუშებს | F187: 3d5e5f09-c784-4260-8f75-eef72b59d308 | G187: dito.sichinava@gmail.com | H187: {=MATCH(A187&B187,Sheet2!$A$2:$A$6970&Sheet2!$B$2:$B$6970,0)} -> 6199 | I187: TRUE
A188: ae8cf3_61_aeea7a | B188: 45861 | D188: 490 | F188: f82a9c57-e09f-466b-b369-1010337586be | G188: nikaelevator@gmail.com | H188: {=MATCH(A188&B188,Sheet2!$A$2:$A$6970&Sheet2!$B$2:$B$6970,0)} -> 6201 | I188: TRUE
A189: 1d4959_15_9ac446 | B189: 45861 | D189: 490 | F189: 7af03c5a-3158-4387-bf76-c54c9f7e34cc | G189: nikaelevator@gmail.com | H189: {=MATCH(A189&B189,Sheet2!$A$2:$A$6970&Sheet2!$B$2:$B$6970,0)} -> 6202 | I189: TRUE
A190: f52756_f1_85fd19 | B190: 45861 | D190: 490 | F190: 8b0e7afe-6d72-4243-95aa-77d5d51358be | G190: nikaelevator@gmail.com | H190: {=MATCH(A190&B190,Sheet2!$A$2:$A$6970&Sheet2!$B$2:$B$6970,0)} -> 6203 | I190: TRUE
A191: 53d3ae_11_b54afc | B191: 45861 | E191: დაკორექტირდა სართულის ღირებულება გახ | F191: bc8551d9-b24e-47e7-9922-596d80a961c9 | G191: nikaelevator@gmail.com | H191: {=MATCH(A191&B191,Sheet2!$A$2:$A$6970&Sheet2!$B$2:$B$6970,0)} -> 6204 | I191: TRUE
...

Sheet paymentsledger
A1: paymentId | B1: effectiveDate | C1: accrual | D1: order | E1: comment | F1: recordUuid | G1: userEmail
A2: f0e746_dc_8f772e | B2: 46293 | C2: 1071.3 | D2: 1071.3 | E2: დასტერი | F2: b562e038-6e5e-4e12-ba53-56a0875cba04 | G2: dito.sichinava@gmail.com
A3: 78a10b_38_a4410f | B3: 46280 | C3: 9885 | D3: 9885 | F3: e729c2d6-7d02-4fdf-b5e4-233dc24e127d | G3: dito.sichinava@gmail.com
A4: 166a1a_0c_a96f66 | B4: 46280 | C4: 24020 | D4: 24020 | F4: c8ce5212-fedb-429e-b493-1d5b2f8587aa | G4: dito.sichinava@gmail.com
A5: cd6bf6_9b_b6ad1e | B5: 46280 | C5: 4310 | D5: 4310 | E5: აქ შედის ზედამხედველობის 880$ | F5: f578b9d3-7347-46f5-b377-82bd2fc01058 | G5: dito.sichinava@gmail.com
A6: 065489_e6_8ab012 | B6: 46280 | C6: 740.8 | D6: 740.8 | F6: b2a8e04b-38d9-4590-809b-af63ebb93708 | G6: dito.sichinava@gmail.com
A7: f0e746_dc_8f772e | B7: 46262 | C7: 1071.3 | D7: 1071.3 | E7: დასტერი | F7: 773faea1-520b-4fa0-a735-df528e5e52f8 | G7: dito.sichinava@gmail.com
A8: 66b7b1_ea_97fc6e | B8: 46250 | C8: 22240 | D8: 22240 | F8: 7b1e6fa5-6fbb-4dc4-a523-a6577771a511 | G8: dito.sichinava@gmail.com
A9: f0e746_dc_8f772e | B9: 46231 | C9: 1071.3 | D9: 1071.3 | E9: დასტერი | F9: 46752a10-a86d-414b-8bf0-b1358c08b38f | G9: dito.sichinava@gmail.com
A10: f0e746_dc_8f772e | B10: 46201 | C10: 1071.3 | D10: 1071.3 | E10: დასტერი | F10: f3b17f4a-9d08-4248-a200-05d9ec505477 | G10: dito.sichinava@gmail.com
A11: 370528_7e_83c640 | B11: 46190 | C11: 34597 | D11: 34597 | F11: c879edec-4c1e-465f-83b0-ad5c370f55f3 | G11: dito.sichinava@gmail.com
A12: f0f5f4_38_81dab6 | B12: 46190 | C12: 10600 | D12: 10600 | F12: c2a05e30-7a1f-4e68-b9a4-568cd563ed2d | G12: dito.sichinava@gmail.com
A13: f0e746_dc_8f772e | B13: 46170 | C13: 1071.3 | D13: 1071.3 | E13: დასტერი | F13: 81794777-b62e-4bc4-9c47-fde1504ab8eb | G13: dito.sichinava@gmail.com
A14: 71a80d_2e_b7eed3 | B14: 46143 | C14: 1500 | D14: 1500 | E14: 5_2026 | F14: a4f12b94-a935-4376-9bf9-d22b086cd0bc | G14: dito.sichinava@gmail.com
A15: f3ce6e_a3_beadc9 | B15: 46142 | C15: 25000 | D15: 25000 | F15: 943203ba-4295-496a-81aa-c3887e77d088 | G15: nikaelevator@gmail.com
A16: 5007c8_f0_b26d52 | B16: 46142 | C16: 962 | D16: 962 | F16: 007057d2-bfc3-4479-b2b5-42505855359b | G16: dito.sichinava@gmail.com
A17: 01b09d_06_b32e00 | B17: 46142 | C17: 7700 | D17: 7700 | F17: 90285ff7-d6d3-42e3-beca-c8f17ce12af7 | G17: dito.sichinava@gmail.com
A18: 8d5919_80_8dd7af | B18: 46142 | C18: 9400 | D18: 9400 | F18: a1cded52-13d2-4d79-81bb-f082d7dcb041 | G18: dito.sichinava@gmail.com
A19: 98df19_46_bce836 | B19: 46142 | C19: 925 | D19: 925 | F19: 6d427b6f-891e-493a-bb43-8c4626ba9b2e | G19: dito.sichinava@gmail.com
A20: fafa8e_c1_96f3be | B20: 46142 | C20: 431.03448 | D20: 431.03448 | F20: f8e76eb0-097f-414c-8d58-867d424c6add | G20: dito.sichinava@gmail.com
A21: f0e746_dc_8f772e | B21: 46140 | C21: 1071.3 | D21: 1071.3 | E21: დასტერი | F21: 8aa774db-dc8f-49c5-83cd-b4bc7ede146a | G21: dito.sichinava@gmail.com
A22: 3c2808_03_b9dce5 | B22: 46137 | C22: 7025 | D22: 7025 | F22: 6e905bcc-b405-459b-829c-3648081a80b9 | G22: dito.sichinava@gmail.com
A23: e7ddc9_e9_af1bef | B23: 46130 | C23: 7750 | D23: 7750 | F23: 18b7d9c0-7fbd-4a00-aa8d-7caab85fb359 | G23: dito.sichinava@gmail.com
A24: 3868ab_e7_aafae9 | B24: 46130 | C24: 9500 | D24: 9500 | F24: 7b50e190-ddae-4c59-b57e-3c9e6527f170 | G24: dito.sichinava@gmail.com
A25: 29a975_c6_a55b6e | B25: 46130 | C25: 481 | D25: 481 | F25: 169af46b-6fa3-4df0-a443-baa7f6041441 | G25: dito.sichinava@gmail.com
A26: 89f289_69_ad84ec | B26: 46128 | C26: 3040.5 | D26: 3040.5 | F26: c5a9a601-555f-492a-8c29-21f236507f54 | G26: dito.sichinava@gmail.com
A27: b83db5_84_b38688 | B27: 46127 | C27: 25000 | D27: 25000 | F27: c667ecb5-ceb0-46b1-b32b-155f955d9dc4 | G27: nikaelevator@gmail.com
A28: fc79e7_85_8e7110 | B28: 46127 | C28: 21200 | D28: 21200 | F28: abd9ff61-5642-4a1f-a7c4-11fd0a740fcd | G28: dito.sichinava@gmail.com
A29: a6622d_06_a1a791 | B29: 46127 | C29: 1590 | D29: 1590 | F29: 46896653-214f-4bb0-a4e1-c58b3eb841ff | G29: dito.sichinava@gmail.com
A30: 71a80d_2e_b7eed3 | B30: 46113 | C30: 1500 | D30: 1500 | E30: 4_2026 | F30: 86c04ee2-1742-4fbd-bcf5-60f619fa03b0 | G30: dito.sichinava@gmail.com
A31: f7af4e_98_bf8f1f | B31: 46113 | C31: 3040.5 | D31: 3040.5 | F31: 62e920e5-b2a2-4a04-a989-8ac332828133 | G31: dito.sichinava@gmail.com
A32: 4aea25_96_802d92 | B32: 46113 | C32: 3500 | D32: 3500 | F32: 17d2ac8b-911c-4941-87a7-ce6542547e03 | G32: dito.sichinava@gmail.com
A33: bbbca2_71_a5e42f | B33: 46113 | C33: 934 | D33: 934 | F33: 11b74504-ca46-4cb3-bcf5-f6c3edba4c67 | G33: dito.sichinava@gmail.com
A34: 59c7f2_c9_a713a7 | B34: 46113 | C34: 240.38462 | D34: 240.38462 | F34: 3fa14c58-3baf-4dad-9548-536cd5ff70f5 | G34: dito.sichinava@gmail.com
A35: f0e746_dc_8f772e | B35: 46109 | C35: 1071.3 | D35: 1071.3 | E35: დასტერი | F35: c11bd946-e7a4-4a2a-842f-b9c3c4130f4b | G35: dito.sichinava@gmail.com
A36: b73629_18_900218 | B36: 46107 | C36: 7025 | D36: 7025 | F36: dc5886ca-09ef-42c2-a326-4235490d7172 | G36: dito.sichinava@gmail.com
A37: cb8906_e1_b19938 | B37: 46100 | C37: 15500 | D37: 15500 | F37: 0124426e-6c2c-4aad-8b11-bd6d667fe079 | G37: dito.sichinava@gmail.com
A38: 169b33_f8_a0ab74 | B38: 46100 | C38: 9500 | D38: 9500 | F38: 62eceab3-e5ab-4eab-93ae-e468c180dde9 | G38: dito.sichinava@gmail.com
A39: bc9624_b2_816c2d | B39: 46100 | C39: 1681 | D39: 1681 | F39: 635706bf-58ae-4b7d-806c-b1c6a0f69843 | G39: dito.sichinava@gmail.com
A40: 6a5647_35_816ec5 | B40: 46100 | C40: 81550 | D40: 81550 | F40: 5d995b21-5355-4fb6-b944-412956497729 | G40: dito.sichinava@gmail.com
A41: 00dbba_cd_9a6eb5 | B41: 46100 | C41: 95200 | D41: 95200 | F41: b47c4f92-4825-45ab-ae5c-060f9ca0def8 | G41: dito.sichinava@gmail.com
A42: b9aaa8_9e_9285dc | B42: 46097 | C42: 22000 | D42: 22000 | F42: cbe4b962-970a-4c6d-b5dd-7605778a4f38 | G42: dito.sichinava@gmail.com
A43: ba3047_8b_9b6889 | B43: 46097 | C43: 1600 | D43: 1600 | F43: cc2b214f-d996-4934-8305-3d857539197b | G43: dito.sichinava@gmail.com
A44: 74873d_c8_b803b1 | B44: 46095 | C44: 7700 | D44: 7700 | F44: dbf55dc6-3c03-41e2-bb19-36b175d9a363 | G44: dito.sichinava@gmail.com
A45: 6981fe_6f_84f2ae | B45: 46095 | C45: 6600 | D45: 6600 | F45: 6ee68d3f-6e99-483c-b2a8-b5579a1d8d97 | G45: dito.sichinava@gmail.com
A46: 71a80d_2e_b7eed3 | B46: 46082 | C46: 1500 | D46: 1500 | E46: 3_2026 | F46: 781cda23-fae5-4546-998c-9085ec3948d5 | G46: dito.sichinava@gmail.com
A47: f0e746_dc_8f772e | B47: 46081 | C47: 1071.3 | D47: 1071.3 | E47: დასტერი | F47: 3c193e28-b445-4f42-8099-2f247089f51d | G47: dito.sichinava@gmail.com
A48: 82342f_d0_ab8943 | B48: 46076 | C48: 5224 | D48: 5224 | E48: OTIS ლიფტების ხელშეკრულება | F48: ede0685c-4b89-4d41-922b-1ff29177098d | G48: dito.sichinava@gmail.com
A49: 59bbb7_91_aed694 | B49: 46076 | C49: 20854 | D49: 20854 | E49: HIDRAL ლიფტების ხელშეკრულება | F49: 335dcd87-4329-41d3-884a-6c6513b31fca | G49: dito.sichinava@gmail.com
A50: 9be482_e6_964f0c | B50: 46076 | C50: 567 | D50: 567 | E50: DELFAR ლიფტების ხელშეკრულება | F50: e146c8cc-f000-42f8-8dc4-50e5c9bc1a1c | G50: dito.sichinava@gmail.com
A51: 087e5e_1f_b3a274 | B51: 46068 | C51: 12162 | D51: 12162 | F51: db919078-6633-4a97-a54c-5562e67aebbb | G51: dito.sichinava@gmail.com
A52: b774ef_55_acf584 | B52: 46068 | C52: 6350 | D52: 6350 | F52: 46fe7c89-7c52-4ebd-ae28-2e923fbb7d5e | G52: dito.sichinava@gmail.com
A53: 777dd5_69_ba96e1 | B53: 46067 | C53: 22000 | D53: 22000 | F53: ceb1285b-83cb-4606-b92b-6428fa0cf626 | G53: dito.sichinava@gmail.com
A54: 67707d_5a_be6e2a | B54: 46067 | C54: 1600 | D54: 1600 | F54: cc701613-19a2-4be2-8405-6b65d9955db3 | G54: dito.sichinava@gmail.com
A55: 2dd8a3_bd_bd99e5 | B55: 46059 | C55: 7609 | D55: 7609 | F55: f1d1bbc5-38ef-42cc-91ce-85fc5419fe2e | G55: dito.sichinava@gmail.com
A56: d35ce3_d2_bc96e7 | B56: 46055 | C56: 38750 | D56: 38750 | F56: 66dc47c1-0a80-47ba-bd32-4d70f6967300 | G56: dito.sichinava@gmail.com
A57: ef7931_ea_812e27 | B57: 46055 | C57: 11600 | D57: 11600 | F57: f8691497-c422-44b5-8d8c-d790a3d9699c | G57: dito.sichinava@gmail.com
A58: 71a80d_2e_b7eed3 | B58: 46054 | C58: 1500 | D58: 1500 | E58: 2_2026 | F58: 540e25f8-c831-435d-bae7-6da6ec9f91ba | G58: dito.sichinava@gmail.com
A59: f0e746_dc_8f772e | B59: 46051 | C59: 1071.3 | D59: 1071.3 | E59: დასტერი | F59: 22a1b62c-11df-4787-b8b4-523fd585d2f5 | G59: dito.sichinava@gmail.com
A60: da9168_63_bca837 | B60: 46047 | C60: 21075 | D60: 21075 | F60: f3178482-bb63-4485-a71e-c0a9d6d2983c | G60: dito.sichinava@gmail.com
A61: c24aa5_9f_a13083 | B61: 46044 | C61: 15217 | D61: 15217 | F61: 18e87c36-5287-41d1-bb92-2180edd5684a | G61: dito.sichinava@gmail.com
A62: 55fae5_3d_8c11fe | B62: 46044 | C62: 14500 | D62: 14500 | F62: c6480ba1-7b54-4d86-b46d-6636fa4c93b3 | G62: dito.sichinava@gmail.com
A63: 9b78e3_5e_bdda04 | B63: 46044 | C63: 1974 | D63: 1974 | F63: 87378010-40e8-4c23-8394-315397e2c68f | G63: dito.sichinava@gmail.com
A64: 68cd13_3f_993678 | B64: 46044 | C64: 481 | D64: 481 | F64: d2a68131-8110-4a6a-81f4-b0f56a034fa9 | G64: dito.sichinava@gmail.com
A65: a3a1a2_f5_be4ae3 | B65: 46037 | C65: 222000 | D65: 222000 | F65: 9e729afc-0c3c-4b76-a359-f3128e695479 | G65: nikaelevator@gmail.com
A66: 3197b7_5d_9c197e | B66: 46037 | C66: 36800 | D66: 36800 | F66: 2ab6c05d-9c89-4080-b63c-f867494173e5 | G66: dito.sichinava@gmail.com
A67: 5eecbc_3a_9cc4c3 | B67: 46033 | C67: 6615 | D67: 6615 | F67: 4cdd6b9a-4f6e-484f-aab8-52c97dda7c29 | G67: nikaelevator@gmail.com
A68: 1e93d0_c4_a2b384 | B68: 46033 | C68: 1875 | D68: 1875 | F68: 8f6f8eba-e024-47e5-aa41-a4dbef9b6dce | G68: dito.sichinava@gmail.com
A69: 4de8d0_53_942ef8 | B69: 46033 | C69: 413 | D69: 413 | F69: e78d8627-5f25-4c04-9e41-b8d9982c4957 | G69: dito.sichinava@gmail.com
A70: 06940e_84_a4d6f3 | B70: 46033 | C70: 647 | D70: 647 | F70: 3f83ee26-b6e1-4f80-b8e0-b5d6fc001f30 | G70: nikaelevator@gmail.com
A71: 3fd2b0_15_b1bf7e | B71: 46023 | C71: 100 | D71: 100 | F71: 8635208f-faae-463b-9310-e085549f2a0f | G71: gio.nikabadze@gmail.com
... A76: e05daf_4b_b0621d | B76: 46023 | C76: 480 | D76: 480 | F76: f7d82c9f-6ffc-415f-8ee7-bfe52902cbac | G76: gio.nikabadze@gmail.com
A77: 71a80d_2e_b7eed3 | B77: 46023 | C77: 1500 | D77: 1500 | E77: 1_2026 | F77: ea43c4fb-a035-44cf-88e2-792ad2f9893f | G77: dito.sichinava@gmail.com
A78: f0e746_dc_8f772e | B78: 46020 | C78: 1071.3 | D78: 1071.3 | E78: დასტერი | F78: 9178c5d1-4877-4076-a43e-d73e6bb52284 | G78: dito.sichinava@gmail.com
A79: facec2_f1_9ca410 | B79: 46020 | C79: 38500 | D79: 38500 | F79: 5413a55b-8473-4d61-9f99-bd0faaa0a8bb | G79: dito.sichinava@gmail.com
A80: b2bf15_d2_9bb694 | B80: 46020 | C80: 21000 | D80: 21000 | F80: 826fd27c-cf1c-4757-b0c4-09b1869f6eb4 | G80: dito.sichinava@gmail.com
A81: ba9b1d_ea_9e8480 | B81: 46018 | C81: 1875 | D81: 1875 | F81: 24da66cd-5298-4795-a03f-ede7645741f2 | G81: dito.sichinava@gmail.com
A82: 8b3401_e6_8e103b | B82: 46018 | C82: 413 | D82: 413 | F82: 95fbd9d6-2bdc-4508-a8c3-3e38b387128a | G82: dito.sichinava@gmail.com
A83: 05ad6a_4e_a08415 | B83: 46017 | C83: 11753 | D83: 11753 | F83: 869d0cc5-d800-4391-8b4f-b551752be87f | G83: dito.sichinava@gmail.com
A84: bbc0d6_2b_9e0231 | B84: 46017 | C84: 8650 | D84: 8650 | F84: ad23eaf7-5329-481d-9a62-16d31f2e9fde | G84: dito.sichinava@gmail.com
A85: b851ba_6e_93ab84 | B85: 46017 | C85: 1865 | D85: 1865 | F85: f2653a21-f240-41cc-a58d-53e758bfd853 | G85: dito.sichinava@gmail.com
A86: f82938_9e_8df609 | B86: 46017 | C86: 862 | D86: 862 | F86: 56c37def-ec07-4cfb-b065-daf1058b05c9 | G86: dito.sichinava@gmail.com
A87: 954c42_b9_89d897 | B87: 46016 | C87: 15672 | D87: 15672 | E87: OTIS ლიფტების ხელშეკრულება | F87: 2f24842a-e0c2-411d-b717-a3d46bfc29ae | G87: dito.sichinava@gmail.com
A88: 1dc6f6_ac_be9472 | B88: 46016 | C88: 62562 | D88: 62562 | E88: HIDRAL ლიფტების ხელშეკრულება | F88: 79534284-f3e5-4d7a-aae1-139c782b0882 | G88: dito.sichinava@gmail.com
A89: 66518c_96_aa9e26 | B89: 46016 | C89: 1701 | D89: 1701 | E89: DELFAR ლიფტების ხელშეკრულება | F89: 3f013811-03fe-4121-b06b-9afec395abdd | G89: dito.sichinava@gmail.com
A90: 8d996e_c9_a0d705 | B90: 46014 | C90: 30434 | D90: 30434 | F90: 4520f4d6-6c23-45f9-af3a-43c2cb360a6e | G90: dito.sichinava@gmail.com
A91: 5b6aa4_cf_9ba6b8 | B91: 46014 | C91: 16700 | D91: 16700 | F91: 354f6a58-7d4b-4afa-b6ac-8d56f1d65296 | G91: dito.sichinava@gmail.com
A92: b4182e_54_87ab6a | B92: 46014 | C92: 1500 | D92: 900 | F92: cb12db82-a6f3-43c4-8fa7-aed176cc00e3 | G92: dito.sichinava@gmail.com
A93: a43d94_92_b00ece | B93: 46013 | C93: 1250 | D93: 750 | F93: f3b80e01-0e2a-41cc-8d70-0daa9eeb18ef | G93: dito.sichinava@gmail.com
A94: 23c14c_98_abf7dc | B94: 46013 | C94: 3000 | D94: 900 | F94: 7c8d45c1-a483-425e-a5d4-1520a456cf8d | G94: dito.sichinava@gmail.com
A95: c90b0f_a7_b186ba | B95: 46013 | C95: 3000 | D95: 900 | F95: e0d61404-7db4-41c0-9eec-ed776d15146c | G95: dito.sichinava@gmail.com
A96: 860541_99_acb926 | B96: 46013 | C96: 2400 | D96: 720 | F96: 0b72c14a-dd65-4a87-913d-e98043434334 | G96: dito.sichinava@gmail.com
A97: e6ca35_91_aba45e | B97: 46013 | C97: 2100 | D97: 630 | F97: 82bd2ef9-07fc-4589-9dca-8417f62c1415 | G97: dito.sichinava@gmail.com
A98: 67b425_eb_849e35 | B98: 46013 | C98: 1312.5 | D98: 1312.5 | F98: ff45f071-a36f-4c7f-a322-797b2c27bc6c | G98: dito.sichinava@gmail.com
A99: 3be85c_aa_a28cef | B99: 46013 | C99: 1312.5 | D99: 1312.5 | F99: 544950e5-0d82-4a52-bc68-2742ed085df9 | G99: dito.sichinava@gmail.com
A100: 7f105a_95_b482d9 | B100: 46013 | C100: 500 | D100: 500 | F100: fb37237d-20a9-405a-ba07-dedf84ac0148 | G100: dito.sichinava@gmail.com
A101: e302ae_97_962785 | B101: 46013 | C101: 500 | D101: 500 | F101: 1dc40bad-751d-4108-8937-80525991f322 | G101: dito.sichinava@gmail.com
... A111: 199a9d_fc_a6df21 | B111: 46011 | C111: 100 | D111: 100 | F111: ca269779-5ad2-4032-90c1-bea766611e40 | G111: dito.sichinava@gmail.com
A112: e05fe3_14_ae6ace | B112: 46010 | C112: 2000 | D112: 2000 | E112: ყვარლის სასტუმროს პროექტზე დავით ახალაძეს ჩაურიცხე 2000 ლარი, საქვაბის ჩართვა გაშვების თანხა პ.ნ- 01012011353 ანგ. GE92BG0000000042195900 | F112: f2cd62a8-e908-4127-91f4-d25f9e06c892 | G112: dito.sichinava@gmail.com
A113: fc95a2_16_bfb2ec | B113: 46010 | C113: 14000 | D113: 14000 | F113: f4395464-2d9d-45df-aefc-efea3aed410e | G113: dito.sichinava@gmail.com
...

Sheet Sheet2
A1: paymentId | B1: effectiveDate | C1: accrual | D1: order | E1: comment | F1: recordUuid | G1: userEmail
A2: e5165a_c0_9c34f0 | B2: 44515 | C2: 216624 | D2: =SUMIFs(Sheet1!D:D,Sheet1!A:A, A2,Sheet1!B:B, B2) -> 216624 | F2: 76aee41f-6e87-44c7-a98e-b0abe7d90a53 | G2: t.tsintsadze2006@gmail.com | I2: {=ISNUMBER(B2:B6970)} -> TRUE
A3: e2f304_19_88d27d | B3: 44515 | C3: 70548.3 | D3: =SUMIFs(Sheet1!D:D,Sheet1!A:A, A3,Sheet1!B:B, B3) -> 70548.3 | F3: 00f2db4b-9275-4d85-b961-89e741cc39a4 | G3: t.tsintsadze2006@gmail.com | I3: TRUE
A4: 48bc50_b1_9d1d98 | B4: 44561 | C4: 500800 | D4: =SUMIFs(Sheet1!D:D,Sheet1!A:A, A4,Sheet1!B:B, B4) -> 0 | F4: 8af4d6c6-772e-4c82-81b0-1caa293e86bf | G4: t.tsintsadze2006@gmail.com | I4: TRUE
A5: 2444ab_7d_93b08f | B5: 44573 | C5: 89323.6 | D5: =SUMIFs(Sheet1!D:D,Sheet1!A:A, A5,Sheet1!B:B, B5) -> 89323.6 | F5: 6084fd44-6467-4cb5-b18c-6c12faae47f0 | G5: t.tsintsadze2006@gmail.com | I5: TRUE
A6: 427177_39_b41c6c | B6: 44582 | C6: 77770 | D6: =SUMIFs(Sheet1!D:D,Sheet1!A:A, A6,Sheet1!B:B, B6) -> 77770 | F6: 49d27129-e214-4369-a39d-1e49b2151abe | G6: nikaelevator@gmail.com | I6: TRUE
A7: 1f42f3_6f_b98fac | B7: 44589 | C7: 602943.57 | D7: =SUMIFs(Sheet1!D:D,Sheet1!A:A, A7,Sheet1!B:B, B7) -> 602943.57 | F7: 83a3ef1c-1dc6-4c26-9d2f-d6fae1769037 | G7: nikaelevator@gmail.com | I7: TRUE
A8: d2c9a4_b9_88ccc8 | B8: 44589 | C8: 26000 | D8: =SUMIFs(Sheet1!D:D,Sheet1!A:A, A8,Sheet1!B:B, B8) -> 26000 | F8: 11464d5e-ced9-475d-91e4-3faa519b9a16 | G8: nikaelevator@gmail.com | I8: TRUE
A9: 87b8b7_2e_aa9e0f | B9: 44599 | C9: 240000 | D9: =SUMIFs(Sheet1!D:D,Sheet1!A:A, A9,Sheet1!B:B, B9) -> 240000 | F9: 335a728d-64b0-4a98-9b6d-b9c9c4a62c74 | G9: t.tsintsadze2006@gmail.com | I9: TRUE
A10: a965cd_b0_859d3c | B10: 44620 | C10: 270780 | D10: =SUMIFs(Sheet1!D:D,Sheet1!A:A, A10,Sheet1!B:B, B10) -> 270780 | F10: c3ab9e5a-4741-410a-b71b-d41fcf2c4ff6 | G10: t.tsintsadze2006@gmail.com | I10: TRUE
A11: 31b6a3_c9_87cf10 | B11: 44635 | C11: 178850 | D11: =SUMIFs(Sheet1!D:D,Sheet1!A:A, A11,Sheet1!B:B, B11) -> 178850 | F11: 5d53d2cd-694c-4b1e-959b-8f1643cec98d | G11: t.tsintsadze2006@gmail.com | I11: TRUE
A12: d2c9a4_b9_88ccc8 | B12: 44655 | C12: 11880 | D12: =SUMIFs(Sheet1!D:D,Sheet1!A:A, A12,Sheet1!B:B, B12) -> 11880 | F12: 393bfcf7-d427-45b5-856f-fe9dbaa86ef9 | G12: nikaelevator@gmail.com | I12: TRUE
A13: d2c9a4_b9_88ccc8 | B13: 44657 | C13: 18377.1 | D13: =SUMIFs(Sheet1!D:D,Sheet1!A:A, A13,Sheet1!B:B, B13) -> 18377.1 | F13: e45248e8-6f63-425e-b099-cbea20ef8bff | G13: nikaelevator@gmail.com | I13: TRUE
A14: ba7562_a3_a36397 | B14: 44665 | C14: 324936 | D14: =SUMIFs(Sheet1!D:D,Sheet1!A:A, A14,Sheet1!B:B, B14) -> 324936 | F14: 638c4ba5-b819-4d8e-ba73-64529d503ec9 | G14: t.tsintsadze2006@gmail.com | I14: TRUE
... A93: 0a6c18_7c_ae5d25 | B93: 44805 | C93: -520 | D93: =SUMIFs(Sheet1!D:D,Sheet1!A:A, A93,Sheet1!B:B, B93) -> 0 | F93: 6d1a0511-8abc-417a-b772-0f4064d5394b | G93: t.tsintsadze2006@gmail.com | I93: TRUE
A94: 90fd3b_4e_ba034e | B94: 44805 | C94: 2080 | D94: =SUMIFs(Sheet1!D:D,Sheet1!A:A, A94,Sheet1!B:B, B94) -> 0 | E94: ყაჭეიშვილი/ჰამიდა 50/50 | F94: aa916643-5f20-4a45-8034-d5fab9a8e99a | G94: t.tsintsadze2006@gmail.com | I94: TRUE
A95: 92b6d5_41_962daf | B95: 44805 | C95: 2080 | D95: =SUMIFs(Sheet1!D:D,Sheet1!A:A, A95,Sheet1!B:B, B95) -> 0 | E95: ყაჭეიშვილი/ჰამიდა 50/50 | F95: dcfb286a-6795-4b2c-932c-0ef83dd3428e | G95: t.tsintsadze2006@gmail.com | I95: TRUE
A96: 6fcf6b_4d_92f52d | B96: 44805 | C96: 1250 | D96: =SUMIFs(Sheet1!D:D,Sheet1!A:A, A96,Sheet1!B:B, B96) -> 0 | E96: თურქული ლიფტის ელექტრო მონტაჟი | F96: e12600a3-a8bb-43e4-9fc2-c74e920ec766 | G96: t.tsintsadze2006@gmail.com | I96: TRUE
A97: b94197_21_95579c | B97: 44805 | C97: 187884 | D97: =SUMIFs(Sheet1!D:D,Sheet1!A:A, A97,Sheet1!B:B, B97) -> 187884 | F97: 0e3cc00e-0983-45fb-8691-b11414ae4784 | G97: nikaelevator@gmail.com | I97: TRUE
A98: d9c6af_54_eadde1 | B98: 44816 | C98: 2100 | D98: =SUMIFs(Sheet1!D:D,Sheet1!A:A, A98,Sheet1!B:B, B98) -> 0 | F98: 2efb17a8-cc2c-4225-b569-e5c4537511ba | G98: t.tsintsadze2006@gmail.com | I98: TRUE
A99: 967b88_31_072e1c | B99: 44816 | C99: 2100 | D99: =SUMIFs(Sheet1!D:D,Sheet1!A:A, A99,Sheet1!B:B, B99) -> 0 | F99: cf56413b-dc5a-499c-bda3-df8c8e37e6b5 | G99: t.tsintsadze2006@gmail.com | I99: TRUE
A100: a0d21b_5c_cdaa53 | B100: 44816 | C100: 2100 | D100: =SUMIFs(Sheet1!D:D,Sheet1!A:A, A100,Sheet1!B:B, B100) -> 0 | F100: 66d2ddca-eefa-4c31-a35d-124ba30f7c4f | G100: t.tsintsadze2006@gmail.com | I100: TRUE
A101: 23a2ba_cb_c2b9a7 | B101: 44816 | C101: 900 | D101: =SUMIFs(Sheet1!D:D,Sheet1!A:A, A101,Sheet1!B:B, B101) -> 0 | F101: f1e045d1-85f1-4e36-8ab0-1bf59129799d | G101: t.tsintsadze2006@gmail.com | I101: TRUE
A102: af6073_47_fe697c | B102: 44816 | C102: 600 | D102: =SUMIFs(Sheet1!D:D,Sheet1!A:A, A102,Sheet1!B:B, B102) -> 0 | F102: 17ecfc82-eb6b-4b79-8c7c-84fe7857f73d | G102: t.tsintsadze2006@gmail.com | I102: TRUE
A103: 49e021_94_ee7ddb | B103: 44816 | C103: 1000 | D103: =SUMIFs(Sheet1!D:D,Sheet1!A:A, A103,Sheet1!B:B, B103) -> 0 | F103: a3b019e7-9680-4708-8bf7-cb961e2a41ab | G103: t.tsintsadze2006@gmail.com | I103: TRUE
A104: bbeab1_70_c49bc8 | B104: 44816 | C104: 4930 | D104: =SUMIFs(Sheet1!D:D,Sheet1!A:A, A104,Sheet1!B:B, B104) -> 0 | F104: 5ea9c7a2-9998-408d-a6d9-cd66c28fe3b3 | G104: t.tsintsadze2006@gmail.com | I104: TRUE
A105: e8c432_f9_fa073a | B105: 44816 | C105: 1000 | D105: =SUMIFs(Sheet1!D:D,Sheet1!A:A, A105,Sheet1!B:B, B105) -> 0 | F105: fbe36755-f1f5-4de9-acc0-24efe5072043 | G105: t.tsintsadze2006@gmail.com | I105: TRUE
A106: 279f4b_c4_83101e | B106: 44816 | C106: 1000 | D106: =SUMIFs(Sheet1!D:D,Sheet1!A:A, A106,Sheet1!B:B, B106) -> 0 | F106: 915224f3-42ad-447a-9218-231e5f504d4b | G106: t.tsintsadze2006@gmail.com | I106: TRUE
A107: 39a699_82_ac3ab8 | B107: 44816 | C107: 1000 | D107: =SUMIFs(Sheet1!D:D,Sheet1!A:A, A107,Sheet1!B:B, B107) -> 0 | F107: e7850617-f014-466b-8085-94457123b60c | G107: t.tsintsadze2006@gmail.com | I107: TRUE
A108: 85de02_c8_5c0681 | B108: 44816 | C108: 1000 | D108: =SUMIFs(Sheet1!D:D,Sheet1!A:A, A108,Sheet1!B:B, B108) -> 0 | F108: 50b9c526-f5b9-436f-9e4a-de433bb7f6cc | G108: t.tsintsadze2006@gmail.com | I108: TRUE
... A199: 39f40c_65_9bc762 | B199: 44900 | C199: 311154.59 | D199: =SUMIFs(Sheet1!D:D,Sheet1!A:A, A199,Sheet1!B:B, B199) -> 311154.59 | F199: 9108d409-9177-4e03-9e75-07476059a16e | G199: t.tsintsadze2006@gmail.com | I199: TRUE
A200: 82a0b7_55_844b1d | B200: 44917 | C200: 50 | D200: =SUMIFs(Sheet1!D:D,Sheet1!A:A, A200,Sheet1!B:B, B200) -> 0 | E200: ძველი არადეკლარირების გამო 96 გადახდა გვთხოვა თანხის დამატება + ამ შეკვეთის 1% = 5$ | F200: 627f4d34-57e8-4b01-8533-bab0cbbf1c7b | G200: nikaelevator@gmail.com | I200: TRUE
A201: d57716_c5_8173a3 | B201: 44917 | C201: 100 | D201: =SUMIFs(Sheet1!D:D,Sheet1!A:A, A201,Sheet1!B:B, B201) -> 0 | F201: c6df6ebd-033a-4d72-8558-06a0b60f26e5 | G201: nikaelevator@gmail.com | I201: TRUE
A202: 78faf6_af_ad4294 | B202: 44921 | C202: 800 | D202: =SUMIFs(Sheet1!D:D,Sheet1!A:A, A202,Sheet1!B:B, B202) -> 800 | F202: 62b119c3-fa2d-4fec-bb95-d2c3fe0e92db | G202: t.tsintsadze2006@gmail.com | I202: TRUE
A203: ef8238_04_8053f9 | B203: 44921 | C203: 750 | D203: =SUMIFs(Sheet1!D:D,Sheet1!A:A, A203,Sheet1!B:B, B203) -> 0 | F203: f73c8c75-7454-4aa5-b620-bef3ad3b7af1 | G203: t.tsintsadze2006@gmail.com | I203: TRUE
A204: cc5a7d_c1_88c1af | B204: 44921 | C204: 700 | D204: =SUMIFs(Sheet1!D:D,Sheet1!A:A, A204,Sheet1!B:B, B204) -> 700 | F204: 4ee064c8-65c6-49bc-8090-cd72ca6bced6 | G204: t.tsintsadze2006@gmail.com | I204: TRUE
A205: 0ac63d_8e_865110 | B205: 44921 | C205: 400 | D205: =SUMIFs(Sheet1!D:D,Sheet1!A:A, A205,Sheet1!B:B, B205) -> 400 | E205: 4 შახტა * 100₾ | F205: a83eeede-ac32-4d83-9a2d-b0ea365455a8 | G205: nikaelevator@gmail.com | I205: TRUE
A206: a5af2c_d9_bc9545 | B206: 44921 | C206: 300 | D206: =SUMIFs(Sheet1!D:D,Sheet1!A:A, A206,Sheet1!B:B, B206) -> 300 | E206: 3 შახტა * 100₾ | F206: b530eee4-0be4-44a5-b1c5-8b3fde7a02b7 | G206: nikaelevator@gmail.com | I206: TRUE
A207: 8f60a2_fa_86c127 | B207: 44921 | C207: 70 | D207: =SUMIFs(Sheet1!D:D,Sheet1!A:A, A207,Sheet1!B:B, B207) -> 70 | E207: 1 შახტა | F207: 4bfac12d-2632-4fae-a373-4391db510955 | G207: nikaelevator@gmail.com | I207: TRUE
A208: 67149c_44_8d4f7d | B208: 44927 | C208: 62628 | D208: =SUMIFs(Sheet1!D:D,Sheet1!A:A, A208,Sheet1!B:B, B208) -> 62628 | F208: ac4e6dcd-baf4-4bcf-99a9-a06e21475146 | G208: nikaelevator@gmail.com | I208: TRUE
A209: 198143_6e_aad72d | B209: 44930 | C209: 1280 | D209: =SUMIFs(Sheet1!D:D,Sheet1!A:A, A209,Sheet1!B:B, B209) -> 1280 | E209: იანვრის თვის იჯარა | F209: a666d351-ef16-4cd7-887a-d96a5ab15be7 | G209: t.tsintsadze2006@gmail.com | I209: TRUE
A210: ba7c2f_36_be2590 | B210: 44930 | C210: 500 | D210: =SUMIFs(Sheet1!D:D,Sheet1!A:A, A210,Sheet1!B:B, B210) -> 500 | F210: 52bac7b4-d8fe-4110-b389-dc6c4af87db4 | G210: gio.nikabadze@gmail.com | I210: TRUE
A211: 6fc0b9_e7_960cd0 | B211: 44931 | C211: 11470 | D211: =SUMIFs(Sheet1!D:D,Sheet1!A:A, A211,Sheet1!B:B, B211) -> 11470 | E211: ფრახტი | F211: 18cda351-077c-4031-a7eb-d40667a900bc | G211: nikaelevator@gmail.com | I211: TRUE
A212: d1756e_92_91caa2 | B212: 44935 | C212: 58494 | D212: =SUMIFs(Sheet1!D:D,Sheet1!A:A, A212,Sheet1!B:B, B212) -> 0 | F212: 88e88477-0708-4104-aa9d-04908c98725b | G212: t.tsintsadze2006@gmail.com | I212: TRUE
A213: c13939_a3_b06e88 | B213: 44936 | C213: 1520 | D213: =SUMIFs(Sheet1!D:D,Sheet1!A:A, A213,Sheet1!B:B, B213) -> 920 | E213: 120$ საწვავისფული | F213: a63aca44-812d-4ddb-843e-82eb9b6cdb28 | G213: t.tsintsadze2006@gmail.com | I213: TRUE
A214: 004a5f_33_942e49 | B214: 44936 | C214: 1350 | D214: =SUMIFs(Sheet1!D:D,Sheet1!A:A, A214,Sheet1!B:B, B214) -> 0 | F214: f458e9a2-5776-4c52-9513-db60c5ff0cd0 | G214: t.tsintsadze2006@gmail.com | I214: TRUE
A215: 8e9699_d1_8424fd | B215: 44936 | C215: 815 | D215: =SUMIFs(Sheet1!D:D,Sheet1!A:A, A215,Sheet1!B:B, B215) -> 0 | E215: არამას გადავურიცხე არ ვიცი რისთვის თეონამ იცის და ბახტაძემ | F215: 390478c8-af62-47ae-befd-ac60d399b811 | G215: gio.nikabadze@gmail.com | I215: TRUE
A216: 0b6064_da_a9cf73 | B216: 44936 | C216: 2700 | D216: =SUMIFs(Sheet1!D:D,Sheet1!A:A, A216,Sheet1!B:B, B216) -> 1000 | F216: 840fcb23-318c-4c07-a45d-b93e7110f1d0 | G216: t.tsintsadze2006@gmail.com | I216: TRUE
A217: 898c1d_9a_bfadc2 | B217: 44936 | C217: 200 | D217: =SUMIFs(Sheet1!D:D,Sheet1!A:A, A217,Sheet1!B:B, B217) -> 200 | F217: cf90d3b7-8026-497a-8f00-0eec2dae57a4 | G217: t.tsintsadze2006@gmail.com | I217: TRUE
A218: 162f15_78_b2d691 | B218: 44936 | C218: 200 | D218: =SUMIFs(Sheet1!D:D,Sheet1!A:A, A218,Sheet1!B:B, B218) -> 200 | F218: 17bb7543-7b96-4cfb-b260-8132ff8f444a | G218: t.tsintsadze2006@gmail.com | I218: TRUE
A219: 198143_6e_aad72d | B219: 44936 | C219: 3770 | D219: =SUMIFs(Sheet1!D:D,Sheet1!A:A, A219,Sheet1!B:B, B219) -> 3770 | E219: ახალი ბინის ორი თვის იჯარა 1400$ | F219: 6a9aa42c-c12f-4b20-b12e-7d83ac450331 | G219: t.tsintsadze2006@gmail.com | I219: TRUE
A220: c9cea2_75_85b37f | B220: 44939 | C220: -130 | D220: =SUMIFs(Sheet1!D:D,Sheet1!A:A, A220,Sheet1!B:B, B220) -> 0 | E220: გააკეთა ნოდარ ვარსიმაშვილმა | F220: 683a8f87-4243-4d1a-b2bf-b46a7bced0fe | G220: nikaelevator@gmail.com | I220: TRUE
A221: 52e668_ea_86dea8 | B221: 44939 | C221: 130 | D221: =SUMIFs(Sheet1!D:D,Sheet1!A:A, A221,Sheet1!B:B, B221) -> 130 | E221: 90% გააკეთა ტურაშვილმა | F221: 0dbf118c-4ad2-4bd3-a49f-977c4b05889d | G221: nikaelevator@gmail.com | I221: TRUE
A222: cb73aa_a0_bdf98f | B222: 44942 | C222: 930 | D222: =SUMIFs(Sheet1!D:D,Sheet1!A:A, A222,Sheet1!B:B, B222) -> 930 | F222: d705b1a2-3635-47aa-8554-923be39dcabc | G222: gio.nikabadze@gmail.com | I222: TRUE
A223: fae823_96_8aa59d | B223: 44942 | C223: 5728.94 | D223: =SUMIFs(Sheet1!D:D,Sheet1!A:A, A223,Sheet1!B:B, B223) -> 5728.94 | F223: 0966dc03-3ebe-4d3e-961f-f8853bb23bb3 | G223: gio.nikabadze@gmail.com | I223: TRUE
A224: 09cb90_0e_8521a5 | B224: 44942 | C224: 3000 | D224: =SUMIFs(Sheet1!D:D,Sheet1!A:A, A224,Sheet1!B:B, B224) -> 3000 | F224: 5cd4299d-82b9-4829-9b5a-d33276194d18 | G224: gio.nikabadze@gmail.com | I224: TRUE
A225: 88aeea_8c_a659d6 | B225: 44942 | C225: 400 | D225: =SUMIFs(Sheet1!D:D,Sheet1!A:A, A225,Sheet1!B:B, B225) -> 400 | E225: პაატას,იბრაგიმას და ნოდარის საკითხზე ლიფტის გადატანა უნდა დააბრუნოს პოპაატამ | F225: d4547743-1697-44a5-8f42-e604baa0698c | G225: gio.nikabadze@gmail.com | I225: TRUE
A226: 135e70_1c_9cc369 | B226: 44943 | C226: 195 | D226: =SUMIFs(Sheet1!D:D,Sheet1!A:A, A226,Sheet1!B:B, B226) -> 195 | F226: 6461fa0a-92be-4405-bcfa-93c30c13c683 | G226: gio.nikabadze@gmail.com | I226: TRUE
A227: 4b1341_87_ba7136 | B227: 44943 | C227: 250 | D227: =SUMIFs(Sheet1!D:D,Sheet1!A:A, A227,Sheet1!B:B, B227) -> 250 | F227: 1a14dd0a-ec09-4af2-99a4-36af3058e5d6 | G227: gio.nikabadze@gmail.com | I227: TRUE
A228: f193b0_5d_bb1cb1 | B228: 44943 | C228: 1030 | D228: =SUMIFs(Sheet1!D:D,Sheet1!A:A, A228,Sheet1!B:B, B228) -> 1030 | F228: 746f484f-7834-4cb9-a0d7-2e96ab972eba | G228: gio.nikabadze@gmail.com | I228: TRUE
A229: 264e95_ae_996aff | B229: 44943 | C229: 80 | D229: =SUMIFs(Sheet1!D:D,Sheet1!A:A, A229,Sheet1!B:B, B229) -> 80 | F229: 48c25bb0-1735-4713-b422-53d4b126c6dd | G229: gio.nikabadze@gmail.com | I229: TRUE
A230: ab04d6_30_940aa4 | B230: 44943 | C230: 196 | D230: =SUMIFs(Sheet1!D:D,Sheet1!A:A, A230,Sheet1!B:B, B230) -> 196 | F230: fb4de8ed-29ab-459d-b808-a49eb3461bc4 | G230: gio.nikabadze@gmail.com | I230: TRUE
A231: 44689f_7c_9c0a06 | B231: 44943 | C231: 1274 | D231: =SUMIFs(Sheet1!D:D,Sheet1!A:A, A231,Sheet1!B:B, B231) -> 0 | F231: a152fbaf-b2aa-4378-a5e1-2288e26ac5c7 | G231: gio.nikabadze@gmail.com | I231: TRUE
A232: 9bdbb1_90_bfb90e | B232: 44943 | C232: 50 | D232: =SUMIFs(Sheet1!D:D,Sheet1!A:A, A232,Sheet1!B:B, B232) -> 50 | F232: c6137891-d274-477f-9a4c-a57b80a2b0d2 | G232: gio.nikabadze@gmail.com | I232: TRUE
A233: a1e225_11_8710a1 | B233: 44943 | C233: 150 | D233: =SUMIFs(Sheet1!D:D,Sheet1!A:A, A233,Sheet1!B:B, B233) -> 150 | F233: 50e76086-2ed8-48c5-9712-676a6326b6a0 | G233: gio.nikabadze@gmail.com | I233: TRUE
A234: 869763_87_af7d4e | B234: 44944 | C234: 60 | D234: =SUMIFs(Sheet1!D:D,Sheet1!A:A, A234,Sheet1!B:B, B234) -> 60 | F234: 590bbb2f-ad06-472d-817f-ff7323e689cb | G234: gio.nikabadze@gmail.com | I234: TRUE
A235: 7e7d80_53_815b02 | B235: 44944 | C235: 792 | D235: =SUMIFs(Sheet1!D:D,Sheet1!A:A, A235,Sheet1!B:B, B235) -> 792 | E235: ბათუმის სერვისის მანქანა | F235: 92b8cbbf-4a44-4b54-9f38-051257ac9b00 | G235: t.tsintsadze2006@gmail.com | I235: TRUE
A236: e0ce9c_54_82211d | B236: 44944 | C236: 12 | D236: =SUMIFs(Sheet1!D:D,Sheet1!A:A, A236,Sheet1!B:B, B236) -> 12 | F236: 9e40c90d-97a9-415a-9918-c853a52ce544 | G236: gio.nikabadze@gmail.com | I236: TRUE
A237: 46693d_f6_8a0015 | B237: 44944 | C237: 204 | D237: =SUMIFs(Sheet1!D:D,Sheet1!A:A, A237,Sheet1!B:B, B237) -> 204 | F237: ec907867-6103-4172-9f66-626e2a022ce2 | G237: gio.nikabadze@gmail.com | I237: TRUE
A238: 7ea0ff_8c_a3309f | B238: 44944 | C238: 300 | D238: =SUMIFs(Sheet1!D:D,Sheet1!A:A, A238,Sheet1!B:B, B238) -> 300 | E238: ბათუმის სერვისის მანქანა | F238: fa62e90b-fa4e-45eb-801b-113fd7c947fe | G238: t.tsintsadze2006@gmail.com | I238: TRUE
A239: 0841c4_9b_9336d7 | B239: 44944 | C239: 782.5 | D239: =SUMIFs(Sheet1!D:D,Sheet1!A:A, A239,Sheet1!B:B, B239) -> 782.5 | F239: bfa28978-2888-4a7e-a9c1-d2e4568ba9c2 | G239: gio.nikabadze@gmail.com | I239: TRUE
A240: 2541ba_54_9b527c | B240: 44944 | C240: 363 | D240: =SUMIFs(Sheet1!D:D,Sheet1!A:A, A240,Sheet1!B:B, B240) -> 363 | F240: 4ec539e0-ff6a-402a-a0d1-033df6bdbfbf | G240: gio.nikabadze@gmail.com | I240: TRUE
A241: 65b156_3d_8b0a4a | B241: 44944 | C241: 30 | D241: =SUMIFs(Sheet1!D:D,Sheet1!A:A, A241,Sheet1!B:B, B241) -> 30 | F241: 84a8342c-7e10-4859-8c66-ca9fb75c8cac | G241: gio.nikabadze@gmail.com | I241: TRUE
A242: 49b657_aa_b75ba6 | B242: 44944 | C242: 600 | D242: =SUMIFs(Sheet1!D:D,Sheet1!A:A, A242,Sheet1!B:B, B242) -> 0 | F242: 4816cd09-b6cf-45c3-a779-9e50269a2ee0 | G242: gio.nikabadze@gmail.com | I242: TRUE
A243: 9e5261_e7_b3b94e | B243: 44944 | C243: 330.21 | D243: =SUMIFs(Sheet1!D:D,Sheet1!A:A, A243,Sheet1!B:B, B243) -> 330.21 | F243: 49f95f5e-acdc-40e5-a262-4e1e74393cdb | G243: gio.nikabadze@gmail.com | I243: TRUE
A244: 3af535_76_9ec723 | B244: 44944 | C244: 415 | D244: =SUMIFs(Sheet1!D:D,Sheet1!A:A, A244,Sheet1!B:B, B244) -> 415 | E244: ქანთარიას და ჩიტაიშვილის კომუნალურები | F244: d467e95e-db94-45f4-87e5-af06f2732278 | G244: t.tsintsadze2006@gmail.com | I244: TRUE
A245: 869763_87_af7d4e | B245: 44945 | C245: 500 | D245: =SUMIFs(Sheet1!D:D,Sheet1!A:A, A245,Sheet1!B:B, B245) -> 500 | F245: e3c62c8d-48ce-4529-ada7-7de12f4ded9c | G245: gio.nikabadze@gmail.com | I245: TRUE
A246: 2bfc44_01_bf7535 | B246: 44946 | C246: 24700 | D246: =SUMIFs(Sheet1!D:D,Sheet1!A:A, A246,Sheet1!B:B, B246) -> 12350 | F246: 43ea860c-0670-462d-bd98-c563763819e4 | G246: gio.nikabadze@gmail.com | I246: TRUE
A247: 37aa94_29_be51e2 | B247: 44946 | C247: 1228.8 | D247: =SUMIFs(Sheet1!D:D,Sheet1!A:A, A247,Sheet1!B:B, B247) -> 1228.8 | F247: 31e55982-bca8-4ec1-86fb-7e53e2da35e7 | G247: gio.nikabadze@gmail.com | I247: TRUE
A248: 09cb90_0e_8521a5 | B248: 44946 | C248: 3000 | D248: =SUMIFs(Sheet1!D:D,Sheet1!A:A, A248,Sheet1!B:B, B248) -> 3000 | F248: c4299225-0f61-499f-a7c2-9613f132096c | G248: gio.nikabadze@gmail.com | I248: TRUE
A249: e446e6_5c_b53171 | B249: 44946 | C249: 1832.1 | D249: =SUMIFs(Sheet1!D:D,Sheet1!A:A, A249,Sheet1!B:B, B249) -> 1832.1 | F249: fb1fd133-af68-4e6a-9f57-f3c6677e0aaf | G249: gio.nikabadze@gmail.com | I249: TRUE
A250: 7fa1d7_2d_a568a5 | B250: 44946 | C250: 30 | D250: =SUMIFs(Sheet1!D:D,Sheet1!A:A, A250,Sheet1!B:B, B250) -> 30 | F250: a80b0329-7973-4e5e-b5c2-7e778bfe30a3 | G250: gio.nikabadze@gmail.com | I250: TRUE
A251: ee8000_e6_b55d70 | B251: 44946 | C251: 600 | D251: =SUMIFs(Sheet1!D:D,Sheet1!A:A, A251,Sheet1!B:B, B251) -> 600 | F251: abf55a84-8fe7-4a74-8dec-70692057cc3f | G251: gio.nikabadze@gmail.com | I251: TRUE
A252: 0841c4_9b_9336d7 | B252: 44946 | C252: 120 | D252: =SUMIFs(Sheet1!D:D,Sheet1!A:A, A252,Sheet1!B:B, B252) -> 120 | F252: c872dc00-c6d1-4a56-9ffd-ceed3f8c459f | G252: gio.nikabadze@gmail.com | I252: TRUE
A253: b2815c_d5_ac989a | B253: 44946 | C253: 213.5 | D253: =SUMIFs(Sheet1!D:D,Sheet1!A:A, A253,Sheet1!B:B, B253) -> 213.5 | F253: 96c7b73c-5b58-49e9-9b4f-1006d0ad126b | G253: gio.nikabadze@gmail.com | I253: TRUE
A254: 869763_87_af7d4e | B254: 44946 | C254: 783 | D254: =SUMIFs(Sheet1!D:D,Sheet1!A:A, A254,Sheet1!B:B, B254) -> 783 | F254: 1543a6c8-1900-49d9-beae-b3e8416688b9 | G254: gio.nikabadze@gmail.com | I254: TRUE
A255: 3e0cf2_83_a5592b | B255: 44946 | C255: 1000 | D255: =SUMIFs(Sheet1!D:D,Sheet1!A:A, A255,Sheet1!B:B, B255) -> 0 | F255: 88aa2c42-4aa9-4c8e-8e07-ee4e0f48e464 | G255: gio.nikabadze@gmail.com | I255: TRUE
A256: 3db9a6_df_bf1db4 | B256: 44946 | C256: 490 | D256: =SUMIFs(Sheet1!D:D,Sheet1!A:A, A256,Sheet1!B:B, B256) -> 0 | F256: 2f8518b7-293b-4f03-aabf-af559412211b | G256: gio.nikabadze@gmail.com | I256: TRUE
... A267: 1430f4_4e_8ddf3e | B267: 44949 | C267: 200 | D267: =SUMIFs(Sheet1!D:D,Sheet1!A:A, A267,Sheet1!B:B, B267) -> 200 | F267: 6f42ffc5-41ee-4a1c-bf94-06ea5a8ab603 | G267: gio.nikabadze@gmail.com | I267: TRUE
A268: a3f159_ae_b9bb00 | B268: 44949 | C268: 450 | D268: =SUMIFs(Sheet1!D:D,Sheet1!A:A, A268,Sheet1!B:B, B268) -> 450 | E268: IC050EE კატალიზატორი | F268: fa926ffc-0d10-4daf-be27-e49661997143 | G268: gio.nikabadze@gmail.com | I268: TRUE
A269: 2bfc44_01_bf7535 | B269: 44949 | C269: -2080 | D269: =SUMIFs(Sheet1!D:D,Sheet1!A:A, A269,Sheet1!B:B, B269) -> -1040 | F269: 57226fe6-67f1-4318-826b-8c6e4f07d2a6 | G269: gio.nikabadze@gmail.com | I269: TRUE
A270: 46693d_f6_8a0015 | B270: 44950 | C270: 280 | D270: =SUMIFs(Sheet1!D:D,Sheet1!A:A, A270,Sheet1!B:B, B270) -> 0 | F270: 9d8171a8-71c5-4a2f-be2b-35cb7542b568 | G270: gio.nikabadze@gmail.com | I270: TRUE
A271: 943436_85_9d8a19 | B271: 44950 | C271: 360 | D271: =SUMIFs(Sheet1!D:D,Sheet1!A:A, A271,Sheet1!B:B, B271) -> 360 | F271: 4f5836cb-f3d2-4020-9807-7f7224fdead9 | G271: gio.nikabadze@gmail.com | I271: TRUE
A272: e0ce9c_54_82211d | B272: 44950 | C272: 167 | D272: =SUMIFs(Sheet1!D:D,Sheet1!A:A, A272,Sheet1!B:B, B272) -> 8 | F272: 09618641-63a5-4ee7-ab6b-490bf33275b0 | G272: gio.nikabadze@gmail.com | I272: TRUE
A273: 9d013b_0c_b5012a | B273: 44950 | C273: 9200 | D273: =SUMIFs(Sheet1!D:D,Sheet1!A:A, A273,Sheet1!B:B, B273) -> 0 | F273: 248f4c56-a14b-4d6d-a1e5-887a7a78d093 | G273: gio.nikabadze@gmail.com | I273: TRUE
A274: cb73aa_a0_bdf98f | B274: 44950 | C274: -930 | D274: =SUMIFs(Sheet1!D:D,Sheet1!A:A, A274,Sheet1!B:B, B274) -> -930 | F274: 4fa34bde-1992-4be0-aaf9-a186814dd448 | G274: gio.nikabadze@gmail.com | I274: TRUE
A275: 0841c4_9b_9336d7 | B275: 44950 | C275: 1801.5 | D275: =SUMIFs(Sheet1!D:D,Sheet1!A:A, A275,Sheet1!B:B, B275) -> 1801.5 | F275: c1535691-14ca-4969-9a33-f0dddfbaf4a7 | G275: gio.nikabadze@gmail.com | I275: TRUE
A276: e0ce9c_54_82211d | B276: 44950 | C276: 8 | D276: =SUMIFs(Sheet1!D:D,Sheet1!A:A, A276,Sheet1!B:B, B276) -> 8 | F276: eb9e37c4-c693-4dfc-969e-1159ed156a06 | G276: gio.nikabadze@gmail.com | I276: TRUE
A277: 8c41f6_69_ab850b | B277: 44950 | C277: 320 | D277: =SUMIFs(Sheet1!D:D,Sheet1!A:A, A277,Sheet1!B:B, B277) -> 320 | F277: 8382df11-bf8d-46b9-8022-3b1db1b33aa1 | G277: gio.nikabadze@gmail.com | I277: TRUE
A278: 27eb43_a4_bb02ef | B278: 44950 | C278: 167 | D278: =SUMIFs(Sheet1!D:D,Sheet1!A:A, A278,Sheet1!B:B, B278) -> 280 | F278: 3214f7cc-84e1-4c4f-93d1-5488e57f15c0 | G278: gio.nikabadze@gmail.com | I278: TRUE
...
